Workbook

Sheet LISEZMOI
A1: Vestis — Analyse FEC multi-exercices
A2: Exercices : 2024, 2025. Généré le 19/10/2026.
A4: Principe | B4: Toutes les agrégations sont des formules : modifier le référentiel, une surcharge de compte ou le type d'un journal met à jour tout le classeur. Excel recalcule à l'ouverture ; un aperçu (messagerie, téléphone) peut afficher des cellules vides.
A5: Chaîne de calcul | B5: FEC_xxxx (données) → Comptes (soldes et affectation par exercice) → Liasse (rapprochement) → PnL_annuel, PnL_mensuel, Bilan_synth, Tresorerie.
A6: Où intervenir | B6: Referentiel : colonnes C à F. Comptes : colonnes D et E (jaunes) pour une exception propre au dossier. Journaux : colonne E. Bilan_synth : taux de TVA.
A7: Couleurs | B7: Bleu = donnée saisie ou lue automatiquement ; noir = formule ; fond jaune = hypothèse ou surcharge.
A8: Signes | B8: Compte de résultat : produits positifs, charges négatives. Bilan : fournisseurs et trésorerie en négatif.
A9: Valeurs figées | B9: Onglet Tiers, et dans Controles : écritures déséquilibrées, postes ouverts, continuité. Calculés par l'application ; relancer l'application si un FEC change.
A10: Ordre de lecture | B10: 1. Controles (tout doit être OK) 2. Liasse 3. PnL_annuel 4. Cloture (qualité du résultat) 5. Bilan_synth 6. PnL_mensuel, Tresorerie, Tiers.
A11: Clôture | B11: Cloture : ce que les écritures d'inventaire apportent au résultat, provisions, comptes de régularisation, produits sans encaissement. Ecritures_cloture : liste des écritures, avec un statut et un commentaire à renseigner (colonnes jaunes) ; la synthèse se recalcule sur cette liste.
A12: Confidentialité | B12: Classeur produit localement : les fichiers n'ont été transmis à aucun serveur.

Sheet Pieces_a_demander
A1: Pièces à demander à la société
A2: Liste établie à partir de ce que révèlent les comptes. Colonnes E et F (jaunes) : suivi des demandes.
A4: Domaine | B4: Pièce | C4: Pourquoi / détail | D4: Statut | E4: Demandée le | F4: Reçue le
A5: Comptabilité | B5: FEC des 3 derniers exercices clos | C5: 2 exercice(s) clos fourni(s) | D5: Incomplet
A6: Comptabilité | B6: FEC de l'exercice en cours (situation récente) | D6: À demander
A7: Comptabilité | B7: Liasses fiscales des exercices clos | C7: 0 liasse(s) lue(s) sur 2 | D7: Incomplet
A8: Trésorerie | B8: Relevés bancaires PDF + export CSV, tous comptes, 12 derniers mois | C8: Comptes : 512000 Banque Fictive | D8: À demander
A9: Social | B9: URSSAF : attestation de vigilance et situation du compte (dettes, majorations) | C9: Espace en ligne URSSAF de la société | D9: À demander
A10: Social | B10: État mensuel des cotisations par organisme (logiciel de paie) ou récapitulatifs DSN, 12 derniers mois | C10: Base du rapprochement dû / payé | D10: À demander
A11: Fiscal | B11: Relevé du compte fiscal (espace professionnel impots.gouv) : TVA, IS, CFE, CVAE | D11: À demander
A12: Fiscal | B12: Attestation de régularité fiscale | D12: À demander
A13: Fiscal | B13: Déclarations de TVA des 12 derniers mois | C13: Rapprochement TVA déclarée / payée | D13: À demander
A14: Dette financière | B14: Contrats de prêt et tableaux d'amortissement (dont PGE), sûretés | C14: Emprunts au bilan | D14: À demander
A15: Exploitation | B15: Baux et loyers (échéances, garanties, impayés) | C15: Loyers comptabilisés | D15: À demander
A16: Exploitation | B16: État d'inventaire valorisé à la dernière clôture (par article, avec dates de dernier mouvement) | C16: Stock au bilan | D16: À demander
A17: Exploitation | B17: Balance âgée clients et fournisseurs à date (logiciel de gestion) | C17: Validation de l'ancienneté calculée par l'outil | D17: À demander
A18: Groupe | B18: Organigramme juridique, conventions de trésorerie et de refacturation intragroupe | C18: Comptes courants de groupe | D18: À demander

Sheet Controles
A1: Contrôles d'intégrité
A2: Généré le 19/10/2026 par l'application Vestis (traitement local, aucune donnée transmise).
A4: Contrôle | B4: 2024 | C4: Statut | D4: 2025 | E4: Statut | F4: Commentaire
A5: Total débit - total crédit | B5: =ROUND(SUM(FEC_2024!$I:$I)-SUM(FEC_2024!$J:$J),2) | C5: =IF(ISNUMBER(B5),IF(ABS(B5)<=1,"OK","À VOIR"),"n.d.") | D5: =ROUND(SUM(FEC_2025!$I:$I)-SUM(FEC_2025!$J:$J),2) | E5: =IF(ISNUMBER(D5),IF(ABS(D5)<=1,"OK","À VOIR"),"n.d.")
A6: Écritures déséquilibrées (journal + numéro) | B6: 0 | C6: =IF(ISNUMBER(B6),IF(ABS(B6)<=0,"OK","À VOIR"),"n.d.") | D6: 1 | E6: =IF(ISNUMBER(D6),IF(ABS(D6)<=0,"OK","À VOIR"),"n.d.") | F6: Calculé par l'application.
A7: Lignes sans date d'écriture valide | B7: 0 | C7: =IF(ISNUMBER(B7),IF(ABS(B7)<=0,"OK","À VOIR"),"n.d.") | D7: 0 | E7: =IF(ISNUMBER(D7),IF(ABS(D7)<=0,"OK","À VOIR"),"n.d.")
A8: Comptes non affectés par le référentiel | B8: 0 | C8: =IF(ISNUMBER(B8),IF(ABS(B8)<=0,"OK","À VOIR"),"n.d.") | D8: 0 | E8: =IF(ISNUMBER(D8),IF(ABS(D8)<=0,"OK","À VOIR"),"n.d.")
A9: Postes de liasse en écart (> 1 €) | B9: n.d. | C9: =IF(ISNUMBER(B9),IF(ABS(B9)<=0,"OK","À VOIR"),"n.d.") | D9: n.d. | E9: =IF(ISNUMBER(D9),IF(ABS(D9)<=0,"OK","À VOIR"),"n.d.") | F9: Un écart sur une ligne de détail dont les totaux sont OK est une différence de présentation de la liasse, pas une erreur d'affectation.
A10: Résultat net économique - résultat liasse | B10: n.d. | C10: =IF(ISNUMBER(B10),IF(ABS(B10)<=1,"OK","À VOIR"),"n.d.") | D10: n.d. | E10: =IF(ISNUMBER(D10),IF(ABS(D10)<=1,"OK","À VOIR"),"n.d.")
A11: Équilibre du bilan économique | B11: =Bilan_synth!B32 | C11: =IF(ISNUMBER(B11),IF(ABS(B11)<=1,"OK","À VOIR"),"n.d.") | D11: =Bilan_synth!C32 | E11: =IF(ISNUMBER(D11),IF(ABS(D11)<=1,"OK","À VOIR"),"n.d.")
A12: Postes ouverts (lettrage) - soldes clients et fournisseurs | B12: 0 | C12: =IF(ISNUMBER(B12),IF(ABS(B12)<=1,"OK","À VOIR"),"n.d.") | D12: 0 | E12: =IF(ISNUMBER(D12),IF(ABS(D12)<=1,"OK","À VOIR"),"n.d.") | F12: Postes ouverts = non lettrés + lettrages partiels non soldés.
A13: Continuité : à-nouveaux - clôture de l'exercice précédent (écarts cumulés) | B13: n.d. | C13: =IF(ISNUMBER(B13),IF(ABS(B13)<=1,"OK","À VOIR"),"n.d.") | D13: 0 | E13: =IF(ISNUMBER(D13),IF(ABS(D13)<=1,"OK","À VOIR"),"n.d.") | F13: Compare, par racine de compte, la balance de clôture de l'exercice précédent et le journal d'à-nouveaux. Détail ci-dessous.
A14: Écritures validées après le dépôt de la liasse (impact résultat) | B14: n.d. | C14: =IF(ISNUMBER(B14),IF(ABS(B14)<=1,"OK","À VOIR"),"n.d.") | D14: n.d. | E14: =IF(ISNUMBER(D14),IF(ABS(D14)<=1,"OK","À VOIR"),"n.d.") | F14: Compare la colonne ValidDate du FEC à la date de dépôt imprimée sur la liasse. Une écriture passée après le dépôt signifie que le FEC n'est plus celui de la déclaration. « Non mesurable » : le logiciel met la date d'export dans ValidDate. Détail ci-dessous.
A15: Écritures en double : impact sur le résultat | B15: 0 | C15: =IF(ISNUMBER(B15),IF(ABS(B15)<=1,"OK","À VOIR"),"n.d.") | D15: -12000 | E15: =IF(ISNUMBER(D15),IF(ABS(D15)<=1,"OK","À VOIR"),"n.d.") | F15: Écritures identiques (journal, date, lignes) sous des numéros différents : import répété (paie, ventes). Liste ci-dessous. Un petit montant peut être légitime (deux factures identiques le même jour).
A16: Lignes avec compte auxiliaire (CompAuxNum) | B16: 273 | C16: info | D16: 282 | E16: info | F16: 0 = tiers éclatés dans le plan de comptes (401xxx, 411xxx).
A17: Comptes tiers « DIVERS » | B17: 0 | C17: info | D17: 0 | E17: info | F17: Tiers reconstitués à partir du libellé d'écriture.
A18: Capitaux propres - moitié du capital social (négatif = seuil franchi) | B18: =Bilan_synth!B28+Bilan_synth!B29+SUMIFS(Comptes!$F$5:$F$42,Comptes!$A$5:$A$42,"101*")/2 | C18: =IF(B18>=0,"OK","À VOIR") | D18: =Bilan_synth!C28+Bilan_synth!C29+SUMIFS(Comptes!$I$5:$I$42,Comptes!$A$5:$A$42,"101*")/2 | E18: =IF(D18>=0,"OK","À VOIR") | F18: Capitaux propres devenus inférieurs à la moitié du capital social : obligation de consulter les associés dans les 4 mois suivant l'approbation des comptes (C. com. L223-42 / L225-248). À vérifier par le conseil juridique.
A20: Profil des fichiers
A21: Logiciel (saisi)
A22: Fichier FEC | B22: 999000111FEC20241231.txt | D22: 999000111FEC20251231.txt
A23: Période | B23: 01/01/2024 - 31/12/2024 | D23: 01/01/2025 - 31/12/2025
A24: Encodage | B24: UTF-8 | D24: UTF-8
A25: Séparateur | B25: tabulation | D25: tabulation
A26: Séparateur décimal | B26: virgule | D26: virgule
A27: Format des montants | B27: Débit / Crédit | D27: Débit / Crédit
A28: Nombre de colonnes | B28: 18 | D28: 18
A29: Nombre de lignes | B29: 906 | D29: 932
A30: Régime fiscal (liasse) | B30: Régime réel normal (2050-2053) (par défaut, pas de liasse) | D30: Régime réel normal (2050-2053) (par défaut, pas de liasse)
A31: Liasse | B31: non fournie | D31: non fournie
A32: Journaux | B32: AN A-NOUVEAUX, VT VENTES, AC ACHATS, BQ BANQUE, OD OD, SA OD, INV INVENTAIRE | D32: AN A-NOUVEAUX, AC ACHATS, BQ BANQUE, VT VENTES, OD OD, SA OD, INV INVENTAIRE
A34: Continuité 2024 → 2025 : aucun écart
A35: Racine | B35: Clôture 2024 | C35: À-nouveaux 2025 | D35: Écart
A36: 13 racines comparées, toutes identiques.
A38: 2025 : 1 écriture(s) en double, impact résultat -12000 €
A39: Journal | B39: Date | C39: Nb d'exemplaires | D39: N° d'écriture | E39: Libellé | F39: Montant (débit)
A40: AC | B40: 22/05/2025 | C40: 2 | D40: AC00077, AC00078 | E40: Facture Vernis et Finitions F003-2291 | F40: 14400

Sheet PnL_annuel
A1: Compte de résultat économique
A2: En euros. Produits positifs, charges négatives. Agrégats définis dans Referentiel.
A4: Agrégat | B4: 2024 | C4: % CA | D4: 2025 | E4: % CA
A5: Chiffre d'affaires | B5: =-SUMIFS(Comptes!$F$5:$F$42,Comptes!$H$5:$H$42,"CA") | C5: =IF(B$5=0,0,B5/B$5) | D5: =-SUMIFS(Comptes!$I$5:$I$42,Comptes!$K$5:$K$42,"CA") | E5: =IF(D$5=0,0,D5/D$5)
A6: Production stockée et immobilisée | B6: =-SUMIFS(Comptes!$F$5:$F$42,Comptes!$H$5:$H$42,"PRODUCTION_STOCKEE") | C6: =IF(B$5=0,0,B6/B$5) | D6: =-SUMIFS(Comptes!$I$5:$I$42,Comptes!$K$5:$K$42,"PRODUCTION_STOCKEE") | E6: =IF(D$5=0,0,D6/D$5)
A7: Subventions et autres produits d'exploitation | B7: =-SUMIFS(Comptes!$F$5:$F$42,Comptes!$H$5:$H$42,"AUTRES_PRODUITS") | C7: =IF(B$5=0,0,B7/B$5) | D7: =-SUMIFS(Comptes!$I$5:$I$42,Comptes!$K$5:$K$42,"AUTRES_PRODUITS") | E7: =IF(D$5=0,0,D7/D$5)
A8: Production | B8: =B5+B6+B7 | C8: =IF(B$5=0,0,B8/B$5) | D8: =D5+D6+D7 | E8: =IF(D$5=0,0,D8/D$5)
A9: Coûts directs (achats consommés, sous-traitance) | B9: =-SUMIFS(Comptes!$F$5:$F$42,Comptes!$H$5:$H$42,"COUTS_DIRECTS") | C9: =IF(B$5=0,0,B9/B$5) | D9: =-SUMIFS(Comptes!$I$5:$I$42,Comptes!$K$5:$K$42,"COUTS_DIRECTS") | E9: =IF(D$5=0,0,D9/D$5)
A10: Marge brute | B10: =B8+B9 | C10: =IF(B$5=0,0,B10/B$5) | D10: =D8+D9 | E10: =IF(D$5=0,0,D10/D$5)
A11: Charges externes | B11: =-SUMIFS(Comptes!$F$5:$F$42,Comptes!$H$5:$H$42,"CHARGES_EXTERNES") | C11: =IF(B$5=0,0,B11/B$5) | D11: =-SUMIFS(Comptes!$I$5:$I$42,Comptes!$K$5:$K$42,"CHARGES_EXTERNES") | E11: =IF(D$5=0,0,D11/D$5)
A12: Impôts et taxes | B12: =-SUMIFS(Comptes!$F$5:$F$42,Comptes!$H$5:$H$42,"IMPOTS_TAXES") | C12: =IF(B$5=0,0,B12/B$5) | D12: =-SUMIFS(Comptes!$I$5:$I$42,Comptes!$K$5:$K$42,"IMPOTS_TAXES") | E12: =IF(D$5=0,0,D12/D$5)
A13: Frais de personnel | B13: =-SUMIFS(Comptes!$F$5:$F$42,Comptes!$H$5:$H$42,"PERSONNEL") | C13: =IF(B$5=0,0,B13/B$5) | D13: =-SUMIFS(Comptes!$I$5:$I$42,Comptes!$K$5:$K$42,"PERSONNEL") | E13: =IF(D$5=0,0,D13/D$5)
A14: Autres charges de gestion | B14: =-SUMIFS(Comptes!$F$5:$F$42,Comptes!$H$5:$H$42,"AUTRES_CHARGES") | C14: =IF(B$5=0,0,B14/B$5) | D14: =-SUMIFS(Comptes!$I$5:$I$42,Comptes!$K$5:$K$42,"AUTRES_CHARGES") | E14: =IF(D$5=0,0,D14/D$5)
A15: EBITDA (EBE retraité) | B15: =B10+B11+B12+B13+B14 | C15: =IF(B$5=0,0,B15/B$5) | D15: =D10+D11+D12+D13+D14 | E15: =IF(D$5=0,0,D15/D$5)
A16: Dotations nettes aux amortissements et provisions | B16: =-SUMIFS(Comptes!$F$5:$F$42,Comptes!$H$5:$H$42,"DAP_NETTES") | C16: =IF(B$5=0,0,B16/B$5) | D16: =-SUMIFS(Comptes!$I$5:$I$42,Comptes!$K$5:$K$42,"DAP_NETTES") | E16: =IF(D$5=0,0,D16/D$5)
A17: Résultat d'exploitation (EBIT) | B17: =B15+B16 | C17: =IF(B$5=0,0,B17/B$5) | D17: =D15+D16 | E17: =IF(D$5=0,0,D17/D$5)
A18: Résultat financier | B18: =-SUMIFS(Comptes!$F$5:$F$42,Comptes!$H$5:$H$42,"RESULTAT_FIN") | C18: =IF(B$5=0,0,B18/B$5) | D18: =-SUMIFS(Comptes!$I$5:$I$42,Comptes!$K$5:$K$42,"RESULTAT_FIN") | E18: =IF(D$5=0,0,D18/D$5)
A19: Résultat courant avant impôt | B19: =B17+B18 | C19: =IF(B$5=0,0,B19/B$5) | D19: =D17+D18 | E19: =IF(D$5=0,0,D19/D$5)
A20: Résultat exceptionnel | B20: =-SUMIFS(Comptes!$F$5:$F$42,Comptes!$H$5:$H$42,"EXCEPTIONNEL") | C20: =IF(B$5=0,0,B20/B$5) | D20: =-SUMIFS(Comptes!$I$5:$I$42,Comptes!$K$5:$K$42,"EXCEPTIONNEL") | E20: =IF(D$5=0,0,D20/D$5)
A21: Participation des salariés | B21: =-SUMIFS(Comptes!$F$5:$F$42,Comptes!$H$5:$H$42,"PARTICIPATION") | C21: =IF(B$5=0,0,B21/B$5) | D21: =-SUMIFS(Comptes!$I$5:$I$42,Comptes!$K$5:$K$42,"PARTICIPATION") | E21: =IF(D$5=0,0,D21/D$5)
A22: Impôt sur les sociétés | B22: =-SUMIFS(Comptes!$F$5:$F$42,Comptes!$H$5:$H$42,"IS") | C22: =IF(B$5=0,0,B22/B$5) | D22: =-SUMIFS(Comptes!$I$5:$I$42,Comptes!$K$5:$K$42,"IS") | E22: =IF(D$5=0,0,D22/D$5)
A23: Résultat net | B23: =B19+B20+B21+B22 | C23: =IF(B$5=0,0,B23/B$5) | D23: =D19+D20+D21+D22 | E23: =IF(D$5=0,0,D23/D$5)
A25: Contrôle : résultat net - résultat de la liasse (HN ou 310)
A27: Variation du chiffre d'affaires
A28: 2024 → 2025 | D28: =IF(B5=0,0,D5/B5-1)

Sheet PnL_mensuel
A1: Compte de résultat économique mensuel
A2: Comptabilité brute par mois. Les écritures de clôture (en-cours, provisions, charges à payer) et leurs extournes concentrent des montants sur le premier et le dernier mois : utiliser la ligne « hors clôture » pour les tendances.
B3: 2024 | C3: 2024 | D3: 2024 | E3: 2024 | F3: 2024 | G3: 2024 | H3: 2024 | I3: 2024 | J3: 2024 | K3: 2024 | L3: 2024 | M3: 2024 | N3: 2025 | O3: 2025 | P3: 2025 | Q3: 2025 | R3: 2025 | S3: 2025 | T3: 2025 | U3: 2025 | V3: 2025 | W3: 2025 | X3: 2025 | Y3: 2025
A4: Agrégat | B4: 2024-01 | C4: 2024-02 | D4: 2024-03 | E4: 2024-04 | F4: 2024-05 | G4: 2024-06 | H4: 2024-07 | I4: 2024-08 | J4: 2024-09 | K4: 2024-10 | L4: 2024-11 | M4: 2024-12 | N4: 2025-01 | O4: 2025-02 | P4: 2025-03 | Q4: 2025-04 | R4: 2025-05 | S4: 2025-06 | T4: 2025-07 | U4: 2025-08 | V4: 2025-09 | W4: 2025-10 | X4: 2025-11 | Y4: 2025-12
A5: Chiffre d'affaires | B5: =-SUMIFS(FEC_2024!$M:$M,FEC_2024!$P:$P,"CA",FEC_2024!$N:$N,B$4) | C5: =-SUMIFS(FEC_2024!$M:$M,FEC_2024!$P:$P,"CA",FEC_2024!$N:$N,C$4) | D5: =-SUMIFS(FEC_2024!$M:$M,FEC_2024!$P:$P,"CA",FEC_2024!$N:$N,D$4) | E5: =-SUMIFS(FEC_2024!$M:$M,FEC_2024!$P:$P,"CA",FEC_2024!$N:$N,E$4) | F5: =-SUMIFS(FEC_2024!$M:$M,FEC_2024!$P:$P,"CA",FEC_2024!$N:$N,F$4) | G5: =-SUMIFS(FEC_2024!$M:$M,FEC_2024!$P:$P,"CA",FEC_2024!$N:$N,G$4) | H5: =-SUMIFS(FEC_2024!$M:$M,FEC_2024!$P:$P,"CA",FEC_2024!$N:$N,H$4) | I5: =-SUMIFS(FEC_2024!$M:$M,FEC_2024!$P:$P,"CA",FEC_2024!$N:$N,I$4) | ... M5: =-SUMIFS(FEC_2024!$M:$M,FEC_2024!$P:$P,"CA",FEC_2024!$N:$N,M$4) | N5: =-SUMIFS(FEC_2025!$M:$M,FEC_2025!$P:$P,"CA",FEC_2025!$N:$N,N$4) | O5: =-SUMIFS(FEC_2025!$M:$M,FEC_2025!$P:$P,"CA",FEC_2025!$N:$N,O$4) | P5: =-SUMIFS(FEC_2025!$M:$M,FEC_2025!$P:$P,"CA",FEC_2025!$N:$N,P$4) | Q5: =-SUMIFS(FEC_2025!$M:$M,FEC_2025!$P:$P,"CA",FEC_2025!$N:$N,Q$4) | R5: =-SUMIFS(FEC_2025!$M:$M,FEC_2025!$P:$P,"CA",FEC_2025!$N:$N,R$4) | S5: =-SUMIFS(FEC_2025!$M:$M,FEC_2025!$P:$P,"CA",FEC_2025!$N:$N,S$4) | T5: =-SUMIFS(FEC_2025!$M:$M,FEC_2025!$P:$P,"CA",FEC_2025!$N:$N,T$4) | U5: =-SUMIFS(FEC_2025!$M:$M,FEC_2025!$P:$P,"CA",FEC_2025!$N:$N,U$4) | ... Y5: =-SUMIFS(FEC_2025!$M:$M,FEC_2025!$P:$P,"CA",FEC_2025!$N:$N,Y$4)
A6: Production stockée et immobilisée | B6: =-SUMIFS(FEC_2024!$M:$M,FEC_2024!$P:$P,"PRODUCTION_STOCKEE",FEC_2024!$N:$N,B$4) | C6: =-SUMIFS(FEC_2024!$M:$M,FEC_2024!$P:$P,"PRODUCTION_STOCKEE",FEC_2024!$N:$N,C$4) | D6: =-SUMIFS(FEC_2024!$M:$M,FEC_2024!$P:$P,"PRODUCTION_STOCKEE",FEC_2024!$N:$N,D$4) | E6: =-SUMIFS(FEC_2024!$M:$M,FEC_2024!$P:$P,"PRODUCTION_STOCKEE",FEC_2024!$N:$N,E$4) | F6: =-SUMIFS(FEC_2024!$M:$M,FEC_2024!$P:$P,"PRODUCTION_STOCKEE",FEC_2024!$N:$N,F$4) | G6: =-SUMIFS(FEC_2024!$M:$M,FEC_2024!$P:$P,"PRODUCTION_STOCKEE",FEC_2024!$N:$N,G$4) | H6: =-SUMIFS(FEC_2024!$M:$M,FEC_2024!$P:$P,"PRODUCTION_STOCKEE",FEC_2024!$N:$N,H$4) | I6: =-SUMIFS(FEC_2024!$M:$M,FEC_2024!$P:$P,"PRODUCTION_STOCKEE",FEC_2024!$N:$N,I$4) | ... M6: =-SUMIFS(FEC_2024!$M:$M,FEC_2024!$P:$P,"PRODUCTION_STOCKEE",FEC_2024!$N:$N,M$4) | N6: =-SUMIFS(FEC_2025!$M:$M,FEC_2025!$P:$P,"PRODUCTION_STOCKEE",FEC_2025!$N:$N,N$4) | O6: =-SUMIFS(FEC_2025!$M:$M,FEC_2025!$P:$P,"PRODUCTION_STOCKEE",FEC_2025!$N:$N,O$4) | P6: =-SUMIFS(FEC_2025!$M:$M,FEC_2025!$P:$P,"PRODUCTION_STOCKEE",FEC_2025!$N:$N,P$4) | Q6: =-SUMIFS(FEC_2025!$M:$M,FEC_2025!$P:$P,"PRODUCTION_STOCKEE",FEC_2025!$N:$N,Q$4) | R6: =-SUMIFS(FEC_2025!$M:$M,FEC_2025!$P:$P,"PRODUCTION_STOCKEE",FEC_2025!$N:$N,R$4) | S6: =-SUMIFS(FEC_2025!$M:$M,FEC_2025!$P:$P,"PRODUCTION_STOCKEE",FEC_2025!$N:$N,S$4) | T6: =-SUMIFS(FEC_2025!$M:$M,FEC_2025!$P:$P,"PRODUCTION_STOCKEE",FEC_2025!$N:$N,T$4) | U6: =-SUMIFS(FEC_2025!$M:$M,FEC_2025!$P:$P,"PRODUCTION_STOCKEE",FEC_2025!$N:$N,U$4) | ... Y6: =-SUMIFS(FEC_2025!$M:$M,FEC_2025!$P:$P,"PRODUCTION_STOCKEE",FEC_2025!$N:$N,Y$4)
A7: Subventions et autres produits d'exploitation | B7: =-SUMIFS(FEC_2024!$M:$M,FEC_2024!$P:$P,"AUTRES_PRODUITS",FEC_2024!$N:$N,B$4) | C7: =-SUMIFS(FEC_2024!$M:$M,FEC_2024!$P:$P,"AUTRES_PRODUITS",FEC_2024!$N:$N,C$4) | D7: =-SUMIFS(FEC_2024!$M:$M,FEC_2024!$P:$P,"AUTRES_PRODUITS",FEC_2024!$N:$N,D$4) | E7: =-SUMIFS(FEC_2024!$M:$M,FEC_2024!$P:$P,"AUTRES_PRODUITS",FEC_2024!$N:$N,E$4) | F7: =-SUMIFS(FEC_2024!$M:$M,FEC_2024!$P:$P,"AUTRES_PRODUITS",FEC_2024!$N:$N,F$4) | G7: =-SUMIFS(FEC_2024!$M:$M,FEC_2024!$P:$P,"AUTRES_PRODUITS",FEC_2024!$N:$N,G$4) | H7: =-SUMIFS(FEC_2024!$M:$M,FEC_2024!$P:$P,"AUTRES_PRODUITS",FEC_2024!$N:$N,H$4) | I7: =-SUMIFS(FEC_2024!$M:$M,FEC_2024!$P:$P,"AUTRES_PRODUITS",FEC_2024!$N:$N,I$4) | ... M7: =-SUMIFS(FEC_2024!$M:$M,FEC_2024!$P:$P,"AUTRES_PRODUITS",FEC_2024!$N:$N,M$4) | N7: =-SUMIFS(FEC_2025!$M:$M,FEC_2025!$P:$P,"AUTRES_PRODUITS",FEC_2025!$N:$N,N$4) | O7: =-SUMIFS(FEC_2025!$M:$M,FEC_2025!$P:$P,"AUTRES_PRODUITS",FEC_2025!$N:$N,O$4) | P7: =-SUMIFS(FEC_2025!$M:$M,FEC_2025!$P:$P,"AUTRES_PRODUITS",FEC_2025!$N:$N,P$4) | Q7: =-SUMIFS(FEC_2025!$M:$M,FEC_2025!$P:$P,"AUTRES_PRODUITS",FEC_2025!$N:$N,Q$4) | R7: =-SUMIFS(FEC_2025!$M:$M,FEC_2025!$P:$P,"AUTRES_PRODUITS",FEC_2025!$N:$N,R$4) | S7: =-SUMIFS(FEC_2025!$M:$M,FEC_2025!$P:$P,"AUTRES_PRODUITS",FEC_2025!$N:$N,S$4) | T7: =-SUMIFS(FEC_2025!$M:$M,FEC_2025!$P:$P,"AUTRES_PRODUITS",FEC_2025!$N:$N,T$4) | U7: =-SUMIFS(FEC_2025!$M:$M,FEC_2025!$P:$P,"AUTRES_PRODUITS",FEC_2025!$N:$N,U$4) | ... Y7: =-SUMIFS(FEC_2025!$M:$M,FEC_2025!$P:$P,"AUTRES_PRODUITS",FEC_2025!$N:$N,Y$4)
A8: Production | B8: =B5+B6+B7 | C8: =C5+C6+C7 | D8: =D5+D6+D7 | E8: =E5+E6+E7 | F8: =F5+F6+F7 | G8: =G5+G6+G7 | H8: =H5+H6+H7 | I8: =I5+I6+I7 | ... Y8: =Y5+Y6+Y7
A9: Coûts directs (achats consommés, sous-traitance) | B9: =-SUMIFS(FEC_2024!$M:$M,FEC_2024!$P:$P,"COUTS_DIRECTS",FEC_2024!$N:$N,B$4) | C9: =-SUMIFS(FEC_2024!$M:$M,FEC_2024!$P:$P,"COUTS_DIRECTS",FEC_2024!$N:$N,C$4) | D9: =-SUMIFS(FEC_2024!$M:$M,FEC_2024!$P:$P,"COUTS_DIRECTS",FEC_2024!$N:$N,D$4) | E9: =-SUMIFS(FEC_2024!$M:$M,FEC_2024!$P:$P,"COUTS_DIRECTS",FEC_2024!$N:$N,E$4) | F9: =-SUMIFS(FEC_2024!$M:$M,FEC_2024!$P:$P,"COUTS_DIRECTS",FEC_2024!$N:$N,F$4) | G9: =-SUMIFS(FEC_2024!$M:$M,FEC_2024!$P:$P,"COUTS_DIRECTS",FEC_2024!$N:$N,G$4) | H9: =-SUMIFS(FEC_2024!$M:$M,FEC_2024!$P:$P,"COUTS_DIRECTS",FEC_2024!$N:$N,H$4) | I9: =-SUMIFS(FEC_2024!$M:$M,FEC_2024!$P:$P,"COUTS_DIRECTS",FEC_2024!$N:$N,I$4) | ... M9: =-SUMIFS(FEC_2024!$M:$M,FEC_2024!$P:$P,"COUTS_DIRECTS",FEC_2024!$N:$N,M$4) | N9: =-SUMIFS(FEC_2025!$M:$M,FEC_2025!$P:$P,"COUTS_DIRECTS",FEC_2025!$N:$N,N$4) | O9: =-SUMIFS(FEC_2025!$M:$M,FEC_2025!$P:$P,"COUTS_DIRECTS",FEC_2025!$N:$N,O$4) | P9: =-SUMIFS(FEC_2025!$M:$M,FEC_2025!$P:$P,"COUTS_DIRECTS",FEC_2025!$N:$N,P$4) | Q9: =-SUMIFS(FEC_2025!$M:$M,FEC_2025!$P:$P,"COUTS_DIRECTS",FEC_2025!$N:$N,Q$4) | R9: =-SUMIFS(FEC_2025!$M:$M,FEC_2025!$P:$P,"COUTS_DIRECTS",FEC_2025!$N:$N,R$4) | S9: =-SUMIFS(FEC_2025!$M:$M,FEC_2025!$P:$P,"COUTS_DIRECTS",FEC_2025!$N:$N,S$4) | T9: =-SUMIFS(FEC_2025!$M:$M,FEC_2025!$P:$P,"COUTS_DIRECTS",FEC_2025!$N:$N,T$4) | U9: =-SUMIFS(FEC_2025!$M:$M,FEC_2025!$P:$P,"COUTS_DIRECTS",FEC_2025!$N:$N,U$4) | ... Y9: =-SUMIFS(FEC_2025!$M:$M,FEC_2025!$P:$P,"COUTS_DIRECTS",FEC_2025!$N:$N,Y$4)
A10: Marge brute | B10: =B8+B9 | C10: =C8+C9 | D10: =D8+D9 | E10: =E8+E9 | F10: =F8+F9 | G10: =G8+G9 | H10: =H8+H9 | I10: =I8+I9 | ... Y10: =Y8+Y9
A11: Charges externes | B11: =-SUMIFS(FEC_2024!$M:$M,FEC_2024!$P:$P,"CHARGES_EXTERNES",FEC_2024!$N:$N,B$4) | C11: =-SUMIFS(FEC_2024!$M:$M,FEC_2024!$P:$P,"CHARGES_EXTERNES",FEC_2024!$N:$N,C$4) | D11: =-SUMIFS(FEC_2024!$M:$M,FEC_2024!$P:$P,"CHARGES_EXTERNES",FEC_2024!$N:$N,D$4) | E11: =-SUMIFS(FEC_2024!$M:$M,FEC_2024!$P:$P,"CHARGES_EXTERNES",FEC_2024!$N:$N,E$4) | F11: =-SUMIFS(FEC_2024!$M:$M,FEC_2024!$P:$P,"CHARGES_EXTERNES",FEC_2024!$N:$N,F$4) | G11: =-SUMIFS(FEC_2024!$M:$M,FEC_2024!$P:$P,"CHARGES_EXTERNES",FEC_2024!$N:$N,G$4) | H11: =-SUMIFS(FEC_2024!$M:$M,FEC_2024!$P:$P,"CHARGES_EXTERNES",FEC_2024!$N:$N,H$4) | I11: =-SUMIFS(FEC_2024!$M:$M,FEC_2024!$P:$P,"CHARGES_EXTERNES",FEC_2024!$N:$N,I$4) | ... M11: =-SUMIFS(FEC_2024!$M:$M,FEC_2024!$P:$P,"CHARGES_EXTERNES",FEC_2024!$N:$N,M$4) | N11: =-SUMIFS(FEC_2025!$M:$M,FEC_2025!$P:$P,"CHARGES_EXTERNES",FEC_2025!$N:$N,N$4) | O11: =-SUMIFS(FEC_2025!$M:$M,FEC_2025!$P:$P,"CHARGES_EXTERNES",FEC_2025!$N:$N,O$4) | P11: =-SUMIFS(FEC_2025!$M:$M,FEC_2025!$P:$P,"CHARGES_EXTERNES",FEC_2025!$N:$N,P$4) | Q11: =-SUMIFS(FEC_2025!$M:$M,FEC_2025!$P:$P,"CHARGES_EXTERNES",FEC_2025!$N:$N,Q$4) | R11: =-SUMIFS(FEC_2025!$M:$M,FEC_2025!$P:$P,"CHARGES_EXTERNES",FEC_2025!$N:$N,R$4) | S11: =-SUMIFS(FEC_2025!$M:$M,FEC_2025!$P:$P,"CHARGES_EXTERNES",FEC_2025!$N:$N,S$4) | T11: =-SUMIFS(FEC_2025!$M:$M,FEC_2025!$P:$P,"CHARGES_EXTERNES",FEC_2025!$N:$N,T$4) | U11: =-SUMIFS(FEC_2025!$M:$M,FEC_2025!$P:$P,"CHARGES_EXTERNES",FEC_2025!$N:$N,U$4) | ... Y11: =-SUMIFS(FEC_2025!$M:$M,FEC_2025!$P:$P,"CHARGES_EXTERNES",FEC_2025!$N:$N,Y$4)
A12: Impôts et taxes | B12: =-SUMIFS(FEC_2024!$M:$M,FEC_2024!$P:$P,"IMPOTS_TAXES",FEC_2024!$N:$N,B$4) | C12: =-SUMIFS(FEC_2024!$M:$M,FEC_2024!$P:$P,"IMPOTS_TAXES",FEC_2024!$N:$N,C$4) | D12: =-SUMIFS(FEC_2024!$M:$M,FEC_2024!$P:$P,"IMPOTS_TAXES",FEC_2024!$N:$N,D$4) | E12: =-SUMIFS(FEC_2024!$M:$M,FEC_2024!$P:$P,"IMPOTS_TAXES",FEC_2024!$N:$N,E$4) | F12: =-SUMIFS(FEC_2024!$M:$M,FEC_2024!$P:$P,"IMPOTS_TAXES",FEC_2024!$N:$N,F$4) | G12: =-SUMIFS(FEC_2024!$M:$M,FEC_2024!$P:$P,"IMPOTS_TAXES",FEC_2024!$N:$N,G$4) | H12: =-SUMIFS(FEC_2024!$M:$M,FEC_2024!$P:$P,"IMPOTS_TAXES",FEC_2024!$N:$N,H$4) | I12: =-SUMIFS(FEC_2024!$M:$M,FEC_2024!$P:$P,"IMPOTS_TAXES",FEC_2024!$N:$N,I$4) | ... M12: =-SUMIFS(FEC_2024!$M:$M,FEC_2024!$P:$P,"IMPOTS_TAXES",FEC_2024!$N:$N,M$4) | N12: =-SUMIFS(FEC_2025!$M:$M,FEC_2025!$P:$P,"IMPOTS_TAXES",FEC_2025!$N:$N,N$4) | O12: =-SUMIFS(FEC_2025!$M:$M,FEC_2025!$P:$P,"IMPOTS_TAXES",FEC_2025!$N:$N,O$4) | P12: =-SUMIFS(FEC_2025!$M:$M,FEC_2025!$P:$P,"IMPOTS_TAXES",FEC_2025!$N:$N,P$4) | Q12: =-SUMIFS(FEC_2025!$M:$M,FEC_2025!$P:$P,"IMPOTS_TAXES",FEC_2025!$N:$N,Q$4) | R12: =-SUMIFS(FEC_2025!$M:$M,FEC_2025!$P:$P,"IMPOTS_TAXES",FEC_2025!$N:$N,R$4) | S12: =-SUMIFS(FEC_2025!$M:$M,FEC_2025!$P:$P,"IMPOTS_TAXES",FEC_2025!$N:$N,S$4) | T12: =-SUMIFS(FEC_2025!$M:$M,FEC_2025!$P:$P,"IMPOTS_TAXES",FEC_2025!$N:$N,T$4) | U12: =-SUMIFS(FEC_2025!$M:$M,FEC_2025!$P:$P,"IMPOTS_TAXES",FEC_2025!$N:$N,U$4) | ... Y12: =-SUMIFS(FEC_2025!$M:$M,FEC_2025!$P:$P,"IMPOTS_TAXES",FEC_2025!$N:$N,Y$4)
A13: Frais de personnel | B13: =-SUMIFS(FEC_2024!$M:$M,FEC_2024!$P:$P,"PERSONNEL",FEC_2024!$N:$N,B$4) | C13: =-SUMIFS(FEC_2024!$M:$M,FEC_2024!$P:$P,"PERSONNEL",FEC_2024!$N:$N,C$4) | D13: =-SUMIFS(FEC_2024!$M:$M,FEC_2024!$P:$P,"PERSONNEL",FEC_2024!$N:$N,D$4) | E13: =-SUMIFS(FEC_2024!$M:$M,FEC_2024!$P:$P,"PERSONNEL",FEC_2024!$N:$N,E$4) | F13: =-SUMIFS(FEC_2024!$M:$M,FEC_2024!$P:$P,"PERSONNEL",FEC_2024!$N:$N,F$4) | G13: =-SUMIFS(FEC_2024!$M:$M,FEC_2024!$P:$P,"PERSONNEL",FEC_2024!$N:$N,G$4) | H13: =-SUMIFS(FEC_2024!$M:$M,FEC_2024!$P:$P,"PERSONNEL",FEC_2024!$N:$N,H$4) | I13: =-SUMIFS(FEC_2024!$M:$M,FEC_2024!$P:$P,"PERSONNEL",FEC_2024!$N:$N,I$4) | ... M13: =-SUMIFS(FEC_2024!$M:$M,FEC_2024!$P:$P,"PERSONNEL",FEC_2024!$N:$N,M$4) | N13: =-SUMIFS(FEC_2025!$M:$M,FEC_2025!$P:$P,"PERSONNEL",FEC_2025!$N:$N,N$4) | O13: =-SUMIFS(FEC_2025!$M:$M,FEC_2025!$P:$P,"PERSONNEL",FEC_2025!$N:$N,O$4) | P13: =-SUMIFS(FEC_2025!$M:$M,FEC_2025!$P:$P,"PERSONNEL",FEC_2025!$N:$N,P$4) | Q13: =-SUMIFS(FEC_2025!$M:$M,FEC_2025!$P:$P,"PERSONNEL",FEC_2025!$N:$N,Q$4) | R13: =-SUMIFS(FEC_2025!$M:$M,FEC_2025!$P:$P,"PERSONNEL",FEC_2025!$N:$N,R$4) | S13: =-SUMIFS(FEC_2025!$M:$M,FEC_2025!$P:$P,"PERSONNEL",FEC_2025!$N:$N,S$4) | T13: =-SUMIFS(FEC_2025!$M:$M,FEC_2025!$P:$P,"PERSONNEL",FEC_2025!$N:$N,T$4) | U13: =-SUMIFS(FEC_2025!$M:$M,FEC_2025!$P:$P,"PERSONNEL",FEC_2025!$N:$N,U$4) | ... Y13: =-SUMIFS(FEC_2025!$M:$M,FEC_2025!$P:$P,"PERSONNEL",FEC_2025!$N:$N,Y$4)
A14: Autres charges de gestion | B14: =-SUMIFS(FEC_2024!$M:$M,FEC_2024!$P:$P,"AUTRES_CHARGES",FEC_2024!$N:$N,B$4) | C14: =-SUMIFS(FEC_2024!$M:$M,FEC_2024!$P:$P,"AUTRES_CHARGES",FEC_2024!$N:$N,C$4) | D14: =-SUMIFS(FEC_2024!$M:$M,FEC_2024!$P:$P,"AUTRES_CHARGES",FEC_2024!$N:$N,D$4) | E14: =-SUMIFS(FEC_2024!$M:$M,FEC_2024!$P:$P,"AUTRES_CHARGES",FEC_2024!$N:$N,E$4) | F14: =-SUMIFS(FEC_2024!$M:$M,FEC_2024!$P:$P,"AUTRES_CHARGES",FEC_2024!$N:$N,F$4) | G14: =-SUMIFS(FEC_2024!$M:$M,FEC_2024!$P:$P,"AUTRES_CHARGES",FEC_2024!$N:$N,G$4) | H14: =-SUMIFS(FEC_2024!$M:$M,FEC_2024!$P:$P,"AUTRES_CHARGES",FEC_2024!$N:$N,H$4) | I14: =-SUMIFS(FEC_2024!$M:$M,FEC_2024!$P:$P,"AUTRES_CHARGES",FEC_2024!$N:$N,I$4) | ... M14: =-SUMIFS(FEC_2024!$M:$M,FEC_2024!$P:$P,"AUTRES_CHARGES",FEC_2024!$N:$N,M$4) | N14: =-SUMIFS(FEC_2025!$M:$M,FEC_2025!$P:$P,"AUTRES_CHARGES",FEC_2025!$N:$N,N$4) | O14: =-SUMIFS(FEC_2025!$M:$M,FEC_2025!$P:$P,"AUTRES_CHARGES",FEC_2025!$N:$N,O$4) | P14: =-SUMIFS(FEC_2025!$M:$M,FEC_2025!$P:$P,"AUTRES_CHARGES",FEC_2025!$N:$N,P$4) | Q14: =-SUMIFS(FEC_2025!$M:$M,FEC_2025!$P:$P,"AUTRES_CHARGES",FEC_2025!$N:$N,Q$4) | R14: =-SUMIFS(FEC_2025!$M:$M,FEC_2025!$P:$P,"AUTRES_CHARGES",FEC_2025!$N:$N,R$4) | S14: =-SUMIFS(FEC_2025!$M:$M,FEC_2025!$P:$P,"AUTRES_CHARGES",FEC_2025!$N:$N,S$4) | T14: =-SUMIFS(FEC_2025!$M:$M,FEC_2025!$P:$P,"AUTRES_CHARGES",FEC_2025!$N:$N,T$4) | U14: =-SUMIFS(FEC_2025!$M:$M,FEC_2025!$P:$P,"AUTRES_CHARGES",FEC_2025!$N:$N,U$4) | ... Y14: =-SUMIFS(FEC_2025!$M:$M,FEC_2025!$P:$P,"AUTRES_CHARGES",FEC_2025!$N:$N,Y$4)
A15: EBITDA (EBE retraité) | B15: =B10+B11+B12+B13+B14 | C15: =C10+C11+C12+C13+C14 | D15: =D10+D11+D12+D13+D14 | E15: =E10+E11+E12+E13+E14 | F15: =F10+F11+F12+F13+F14 | G15: =G10+G11+G12+G13+G14 | H15: =H10+H11+H12+H13+H14 | I15: =I10+I11+I12+I13+I14 | ... Y15: =Y10+Y11+Y12+Y13+Y14
A16: Dotations nettes aux amortissements et provisions | B16: =-SUMIFS(FEC_2024!$M:$M,FEC_2024!$P:$P,"DAP_NETTES",FEC_2024!$N:$N,B$4) | C16: =-SUMIFS(FEC_2024!$M:$M,FEC_2024!$P:$P,"DAP_NETTES",FEC_2024!$N:$N,C$4) | D16: =-SUMIFS(FEC_2024!$M:$M,FEC_2024!$P:$P,"DAP_NETTES",FEC_2024!$N:$N,D$4) | E16: =-SUMIFS(FEC_2024!$M:$M,FEC_2024!$P:$P,"DAP_NETTES",FEC_2024!$N:$N,E$4) | F16: =-SUMIFS(FEC_2024!$M:$M,FEC_2024!$P:$P,"DAP_NETTES",FEC_2024!$N:$N,F$4) | G16: =-SUMIFS(FEC_2024!$M:$M,FEC_2024!$P:$P,"DAP_NETTES",FEC_2024!$N:$N,G$4) | H16: =-SUMIFS(FEC_2024!$M:$M,FEC_2024!$P:$P,"DAP_NETTES",FEC_2024!$N:$N,H$4) | I16: =-SUMIFS(FEC_2024!$M:$M,FEC_2024!$P:$P,"DAP_NETTES",FEC_2024!$N:$N,I$4) | ... M16: =-SUMIFS(FEC_2024!$M:$M,FEC_2024!$P:$P,"DAP_NETTES",FEC_2024!$N:$N,M$4) | N16: =-SUMIFS(FEC_2025!$M:$M,FEC_2025!$P:$P,"DAP_NETTES",FEC_2025!$N:$N,N$4) | O16: =-SUMIFS(FEC_2025!$M:$M,FEC_2025!$P:$P,"DAP_NETTES",FEC_2025!$N:$N,O$4) | P16: =-SUMIFS(FEC_2025!$M:$M,FEC_2025!$P:$P,"DAP_NETTES",FEC_2025!$N:$N,P$4) | Q16: =-SUMIFS(FEC_2025!$M:$M,FEC_2025!$P:$P,"DAP_NETTES",FEC_2025!$N:$N,Q$4) | R16: =-SUMIFS(FEC_2025!$M:$M,FEC_2025!$P:$P,"DAP_NETTES",FEC_2025!$N:$N,R$4) | S16: =-SUMIFS(FEC_2025!$M:$M,FEC_2025!$P:$P,"DAP_NETTES",FEC_2025!$N:$N,S$4) | T16: =-SUMIFS(FEC_2025!$M:$M,FEC_2025!$P:$P,"DAP_NETTES",FEC_2025!$N:$N,T$4) | U16: =-SUMIFS(FEC_2025!$M:$M,FEC_2025!$P:$P,"DAP_NETTES",FEC_2025!$N:$N,U$4) | ... Y16: =-SUMIFS(FEC_2025!$M:$M,FEC_2025!$P:$P,"DAP_NETTES",FEC_2025!$N:$N,Y$4)
A17: Résultat d'exploitation (EBIT) | B17: =B15+B16 | C17: =C15+C16 | D17: =D15+D16 | E17: =E15+E16 | F17: =F15+F16 | G17: =G15+G16 | H17: =H15+H16 | I17: =I15+I16 | ... Y17: =Y15+Y16
A18: Résultat financier | B18: =-SUMIFS(FEC_2024!$M:$M,FEC_2024!$P:$P,"RESULTAT_FIN",FEC_2024!$N:$N,B$4) | C18: =-SUMIFS(FEC_2024!$M:$M,FEC_2024!$P:$P,"RESULTAT_FIN",FEC_2024!$N:$N,C$4) | D18: =-SUMIFS(FEC_2024!$M:$M,FEC_2024!$P:$P,"RESULTAT_FIN",FEC_2024!$N:$N,D$4) | E18: =-SUMIFS(FEC_2024!$M:$M,FEC_2024!$P:$P,"RESULTAT_FIN",FEC_2024!$N:$N,E$4) | F18: =-SUMIFS(FEC_2024!$M:$M,FEC_2024!$P:$P,"RESULTAT_FIN",FEC_2024!$N:$N,F$4) | G18: =-SUMIFS(FEC_2024!$M:$M,FEC_2024!$P:$P,"RESULTAT_FIN",FEC_2024!$N:$N,G$4) | H18: =-SUMIFS(FEC_2024!$M:$M,FEC_2024!$P:$P,"RESULTAT_FIN",FEC_2024!$N:$N,H$4) | I18: =-SUMIFS(FEC_2024!$M:$M,FEC_2024!$P:$P,"RESULTAT_FIN",FEC_2024!$N:$N,I$4) | ... M18: =-SUMIFS(FEC_2024!$M:$M,FEC_2024!$P:$P,"RESULTAT_FIN",FEC_2024!$N:$N,M$4) | N18: =-SUMIFS(FEC_2025!$M:$M,FEC_2025!$P:$P,"RESULTAT_FIN",FEC_2025!$N:$N,N$4) | O18: =-SUMIFS(FEC_2025!$M:$M,FEC_2025!$P:$P,"RESULTAT_FIN",FEC_2025!$N:$N,O$4) | P18: =-SUMIFS(FEC_2025!$M:$M,FEC_2025!$P:$P,"RESULTAT_FIN",FEC_2025!$N:$N,P$4) | Q18: =-SUMIFS(FEC_2025!$M:$M,FEC_2025!$P:$P,"RESULTAT_FIN",FEC_2025!$N:$N,Q$4) | R18: =-SUMIFS(FEC_2025!$M:$M,FEC_2025!$P:$P,"RESULTAT_FIN",FEC_2025!$N:$N,R$4) | S18: =-SUMIFS(FEC_2025!$M:$M,FEC_2025!$P:$P,"RESULTAT_FIN",FEC_2025!$N:$N,S$4) | T18: =-SUMIFS(FEC_2025!$M:$M,FEC_2025!$P:$P,"RESULTAT_FIN",FEC_2025!$N:$N,T$4) | U18: =-SUMIFS(FEC_2025!$M:$M,FEC_2025!$P:$P,"RESULTAT_FIN",FEC_2025!$N:$N,U$4) | ... Y18: =-SUMIFS(FEC_2025!$M:$M,FEC_2025!$P:$P,"RESULTAT_FIN",FEC_2025!$N:$N,Y$4)
A19: Résultat courant avant impôt | B19: =B17+B18 | C19: =C17+C18 | D19: =D17+D18 | E19: =E17+E18 | F19: =F17+F18 | G19: =G17+G18 | H19: =H17+H18 | I19: =I17+I18 | ... Y19: =Y17+Y18
A20: Résultat exceptionnel | B20: =-SUMIFS(FEC_2024!$M:$M,FEC_2024!$P:$P,"EXCEPTIONNEL",FEC_2024!$N:$N,B$4) | C20: =-SUMIFS(FEC_2024!$M:$M,FEC_2024!$P:$P,"EXCEPTIONNEL",FEC_2024!$N:$N,C$4) | D20: =-SUMIFS(FEC_2024!$M:$M,FEC_2024!$P:$P,"EXCEPTIONNEL",FEC_2024!$N:$N,D$4) | E20: =-SUMIFS(FEC_2024!$M:$M,FEC_2024!$P:$P,"EXCEPTIONNEL",FEC_2024!$N:$N,E$4) | F20: =-SUMIFS(FEC_2024!$M:$M,FEC_2024!$P:$P,"EXCEPTIONNEL",FEC_2024!$N:$N,F$4) | G20: =-SUMIFS(FEC_2024!$M:$M,FEC_2024!$P:$P,"EXCEPTIONNEL",FEC_2024!$N:$N,G$4) | H20: =-SUMIFS(FEC_2024!$M:$M,FEC_2024!$P:$P,"EXCEPTIONNEL",FEC_2024!$N:$N,H$4) | I20: =-SUMIFS(FEC_2024!$M:$M,FEC_2024!$P:$P,"EXCEPTIONNEL",FEC_2024!$N:$N,I$4) | ... M20: =-SUMIFS(FEC_2024!$M:$M,FEC_2024!$P:$P,"EXCEPTIONNEL",FEC_2024!$N:$N,M$4) | N20: =-SUMIFS(FEC_2025!$M:$M,FEC_2025!$P:$P,"EXCEPTIONNEL",FEC_2025!$N:$N,N$4) | O20: =-SUMIFS(FEC_2025!$M:$M,FEC_2025!$P:$P,"EXCEPTIONNEL",FEC_2025!$N:$N,O$4) | P20: =-SUMIFS(FEC_2025!$M:$M,FEC_2025!$P:$P,"EXCEPTIONNEL",FEC_2025!$N:$N,P$4) | Q20: =-SUMIFS(FEC_2025!$M:$M,FEC_2025!$P:$P,"EXCEPTIONNEL",FEC_2025!$N:$N,Q$4) | R20: =-SUMIFS(FEC_2025!$M:$M,FEC_2025!$P:$P,"EXCEPTIONNEL",FEC_2025!$N:$N,R$4) | S20: =-SUMIFS(FEC_2025!$M:$M,FEC_2025!$P:$P,"EXCEPTIONNEL",FEC_2025!$N:$N,S$4) | T20: =-SUMIFS(FEC_2025!$M:$M,FEC_2025!$P:$P,"EXCEPTIONNEL",FEC_2025!$N:$N,T$4) | U20: =-SUMIFS(FEC_2025!$M:$M,FEC_2025!$P:$P,"EXCEPTIONNEL",FEC_2025!$N:$N,U$4) | ... Y20: =-SUMIFS(FEC_2025!$M:$M,FEC_2025!$P:$P,"EXCEPTIONNEL",FEC_2025!$N:$N,Y$4)
A21: Participation des salariés | B21: =-SUMIFS(FEC_2024!$M:$M,FEC_2024!$P:$P,"PARTICIPATION",FEC_2024!$N:$N,B$4) | C21: =-SUMIFS(FEC_2024!$M:$M,FEC_2024!$P:$P,"PARTICIPATION",FEC_2024!$N:$N,C$4) | D21: =-SUMIFS(FEC_2024!$M:$M,FEC_2024!$P:$P,"PARTICIPATION",FEC_2024!$N:$N,D$4) | E21: =-SUMIFS(FEC_2024!$M:$M,FEC_2024!$P:$P,"PARTICIPATION",FEC_2024!$N:$N,E$4) | F21: =-SUMIFS(FEC_2024!$M:$M,FEC_2024!$P:$P,"PARTICIPATION",FEC_2024!$N:$N,F$4) | G21: =-SUMIFS(FEC_2024!$M:$M,FEC_2024!$P:$P,"PARTICIPATION",FEC_2024!$N:$N,G$4) | H21: =-SUMIFS(FEC_2024!$M:$M,FEC_2024!$P:$P,"PARTICIPATION",FEC_2024!$N:$N,H$4) | I21: =-SUMIFS(FEC_2024!$M:$M,FEC_2024!$P:$P,"PARTICIPATION",FEC_2024!$N:$N,I$4) | ... M21: =-SUMIFS(FEC_2024!$M:$M,FEC_2024!$P:$P,"PARTICIPATION",FEC_2024!$N:$N,M$4) | N21: =-SUMIFS(FEC_2025!$M:$M,FEC_2025!$P:$P,"PARTICIPATION",FEC_2025!$N:$N,N$4) | O21: =-SUMIFS(FEC_2025!$M:$M,FEC_2025!$P:$P,"PARTICIPATION",FEC_2025!$N:$N,O$4) | P21: =-SUMIFS(FEC_2025!$M:$M,FEC_2025!$P:$P,"PARTICIPATION",FEC_2025!$N:$N,P$4) | Q21: =-SUMIFS(FEC_2025!$M:$M,FEC_2025!$P:$P,"PARTICIPATION",FEC_2025!$N:$N,Q$4) | R21: =-SUMIFS(FEC_2025!$M:$M,FEC_2025!$P:$P,"PARTICIPATION",FEC_2025!$N:$N,R$4) | S21: =-SUMIFS(FEC_2025!$M:$M,FEC_2025!$P:$P,"PARTICIPATION",FEC_2025!$N:$N,S$4) | T21: =-SUMIFS(FEC_2025!$M:$M,FEC_2025!$P:$P,"PARTICIPATION",FEC_2025!$N:$N,T$4) | U21: =-SUMIFS(FEC_2025!$M:$M,FEC_2025!$P:$P,"PARTICIPATION",FEC_2025!$N:$N,U$4) | ... Y21: =-SUMIFS(FEC_2025!$M:$M,FEC_2025!$P:$P,"PARTICIPATION",FEC_2025!$N:$N,Y$4)
A22: Impôt sur les sociétés | B22: =-SUMIFS(FEC_2024!$M:$M,FEC_2024!$P:$P,"IS",FEC_2024!$N:$N,B$4) | C22: =-SUMIFS(FEC_2024!$M:$M,FEC_2024!$P:$P,"IS",FEC_2024!$N:$N,C$4) | D22: =-SUMIFS(FEC_2024!$M:$M,FEC_2024!$P:$P,"IS",FEC_2024!$N:$N,D$4) | E22: =-SUMIFS(FEC_2024!$M:$M,FEC_2024!$P:$P,"IS",FEC_2024!$N:$N,E$4) | F22: =-SUMIFS(FEC_2024!$M:$M,FEC_2024!$P:$P,"IS",FEC_2024!$N:$N,F$4) | G22: =-SUMIFS(FEC_2024!$M:$M,FEC_2024!$P:$P,"IS",FEC_2024!$N:$N,G$4) | H22: =-SUMIFS(FEC_2024!$M:$M,FEC_2024!$P:$P,"IS",FEC_2024!$N:$N,H$4) | I22: =-SUMIFS(FEC_2024!$M:$M,FEC_2024!$P:$P,"IS",FEC_2024!$N:$N,I$4) | ... M22: =-SUMIFS(FEC_2024!$M:$M,FEC_2024!$P:$P,"IS",FEC_2024!$N:$N,M$4) | N22: =-SUMIFS(FEC_2025!$M:$M,FEC_2025!$P:$P,"IS",FEC_2025!$N:$N,N$4) | O22: =-SUMIFS(FEC_2025!$M:$M,FEC_2025!$P:$P,"IS",FEC_2025!$N:$N,O$4) | P22: =-SUMIFS(FEC_2025!$M:$M,FEC_2025!$P:$P,"IS",FEC_2025!$N:$N,P$4) | Q22: =-SUMIFS(FEC_2025!$M:$M,FEC_2025!$P:$P,"IS",FEC_2025!$N:$N,Q$4) | R22: =-SUMIFS(FEC_2025!$M:$M,FEC_2025!$P:$P,"IS",FEC_2025!$N:$N,R$4) | S22: =-SUMIFS(FEC_2025!$M:$M,FEC_2025!$P:$P,"IS",FEC_2025!$N:$N,S$4) | T22: =-SUMIFS(FEC_2025!$M:$M,FEC_2025!$P:$P,"IS",FEC_2025!$N:$N,T$4) | U22: =-SUMIFS(FEC_2025!$M:$M,FEC_2025!$P:$P,"IS",FEC_2025!$N:$N,U$4) | ... Y22: =-SUMIFS(FEC_2025!$M:$M,FEC_2025!$P:$P,"IS",FEC_2025!$N:$N,Y$4)
A23: Résultat net | B23: =B19+B20+B21+B22 | C23: =C19+C20+C21+C22 | D23: =D19+D20+D21+D22 | E23: =E19+E20+E21+E22 | F23: =F19+F20+F21+F22 | G23: =G19+G20+G21+G22 | H23: =H19+H20+H21+H22 | I23: =I19+I20+I21+I22 | ... Y23: =Y19+Y20+Y21+Y22
A25: Écritures de clôture incluses dans le résultat
A26: dont écritures d'inventaire (type INVENTAIRE) | B26: =-SUMIFS(FEC_2024!$M:$M,FEC_2024!$O:$O,"INVENTAIRE",FEC_2024!$N:$N,B$4,FEC_2024!$Q:$Q,"6")-SUMIFS(FEC_2024!$M:$M,FEC_2024!$O:$O,"INVENTAIRE",FEC_2024!$N:$N,B$4,FEC_2024!$Q:$Q,"7") | C26: =-SUMIFS(FEC_2024!$M:$M,FEC_2024!$O:$O,"INVENTAIRE",FEC_2024!$N:$N,C$4,FEC_2024!$Q:$Q,"6")-SUMIFS(FEC_2024!$M:$M,FEC_2024!$O:$O,"INVENTAIRE",FEC_2024!$N:$N,C$4,FEC_2024!$Q:$Q,"7") | D26: =-SUMIFS(FEC_2024!$M:$M,FEC_2024!$O:$O,"INVENTAIRE",FEC_2024!$N:$N,D$4,FEC_2024!$Q:$Q,"6")-SUMIFS(FEC_2024!$M:$M,FEC_2024!$O:$O,"INVENTAIRE",FEC_2024!$N:$N,D$4,FEC_2024!$Q:$Q,"7") | E26: =-SUMIFS(FEC_2024!$M:$M,FEC_2024!$O:$O,"INVENTAIRE",FEC_2024!$N:$N,E$4,FEC_2024!$Q:$Q,"6")-SUMIFS(FEC_2024!$M:$M,FEC_2024!$O:$O,"INVENTAIRE",FEC_2024!$N:$N,E$4,FEC_2024!$Q:$Q,"7") | F26: =-SUMIFS(FEC_2024!$M:$M,FEC_2024!$O:$O,"INVENTAIRE",FEC_2024!$N:$N,F$4,FEC_2024!$Q:$Q,"6")-SUMIFS(FEC_2024!$M:$M,FEC_2024!$O:$O,"INVENTAIRE",FEC_2024!$N:$N,F$4,FEC_2024!$Q:$Q,"7") | G26: =-SUMIFS(FEC_2024!$M:$M,FEC_2024!$O:$O,"INVENTAIRE",FEC_2024!$N:$N,G$4,FEC_2024!$Q:$Q,"6")-SUMIFS(FEC_2024!$M:$M,FEC_2024!$O:$O,"INVENTAIRE",FEC_2024!$N:$N,G$4,FEC_2024!$Q:$Q,"7") | H26: =-SUMIFS(FEC_2024!$M:$M,FEC_2024!$O:$O,"INVENTAIRE",FEC_2024!$N:$N,H$4,FEC_2024!$Q:$Q,"6")-SUMIFS(FEC_2024!$M:$M,FEC_2024!$O:$O,"INVENTAIRE",FEC_2024!$N:$N,H$4,FEC_2024!$Q:$Q,"7") | I26: =-SUMIFS(FEC_2024!$M:$M,FEC_2024!$O:$O,"INVENTAIRE",FEC_2024!$N:$N,I$4,FEC_2024!$Q:$Q,"6")-SUMIFS(FEC_2024!$M:$M,FEC_2024!$O:$O,"INVENTAIRE",FEC_2024!$N:$N,I$4,FEC_2024!$Q:$Q,"7") | ... M26: =-SUMIFS(FEC_2024!$M:$M,FEC_2024!$O:$O,"INVENTAIRE",FEC_2024!$N:$N,M$4,FEC_2024!$Q:$Q,"6")-SUMIFS(FEC_2024!$M:$M,FEC_2024!$O:$O,"INVENTAIRE",FEC_2024!$N:$N,M$4,FEC_2024!$Q:$Q,"7") | N26: =-SUMIFS(FEC_2025!$M:$M,FEC_2025!$O:$O,"INVENTAIRE",FEC_2025!$N:$N,N$4,FEC_2025!$Q:$Q,"6")-SUMIFS(FEC_2025!$M:$M,FEC_2025!$O:$O,"INVENTAIRE",FEC_2025!$N:$N,N$4,FEC_2025!$Q:$Q,"7") | O26: =-SUMIFS(FEC_2025!$M:$M,FEC_2025!$O:$O,"INVENTAIRE",FEC_2025!$N:$N,O$4,FEC_2025!$Q:$Q,"6")-SUMIFS(FEC_2025!$M:$M,FEC_2025!$O:$O,"INVENTAIRE",FEC_2025!$N:$N,O$4,FEC_2025!$Q:$Q,"7") | P26: =-SUMIFS(FEC_2025!$M:$M,FEC_2025!$O:$O,"INVENTAIRE",FEC_2025!$N:$N,P$4,FEC_2025!$Q:$Q,"6")-SUMIFS(FEC_2025!$M:$M,FEC_2025!$O:$O,"INVENTAIRE",FEC_2025!$N:$N,P$4,FEC_2025!$Q:$Q,"7") | Q26: =-SUMIFS(FEC_2025!$M:$M,FEC_2025!$O:$O,"INVENTAIRE",FEC_2025!$N:$N,Q$4,FEC_2025!$Q:$Q,"6")-SUMIFS(FEC_2025!$M:$M,FEC_2025!$O:$O,"INVENTAIRE",FEC_2025!$N:$N,Q$4,FEC_2025!$Q:$Q,"7") | R26: =-SUMIFS(FEC_2025!$M:$M,FEC_2025!$O:$O,"INVENTAIRE",FEC_2025!$N:$N,R$4,FEC_2025!$Q:$Q,"6")-SUMIFS(FEC_2025!$M:$M,FEC_2025!$O:$O,"INVENTAIRE",FEC_2025!$N:$N,R$4,FEC_2025!$Q:$Q,"7") | S26: =-SUMIFS(FEC_2025!$M:$M,FEC_2025!$O:$O,"INVENTAIRE",FEC_2025!$N:$N,S$4,FEC_2025!$Q:$Q,"6")-SUMIFS(FEC_2025!$M:$M,FEC_2025!$O:$O,"INVENTAIRE",FEC_2025!$N:$N,S$4,FEC_2025!$Q:$Q,"7") | T26: =-SUMIFS(FEC_2025!$M:$M,FEC_2025!$O:$O,"INVENTAIRE",FEC_2025!$N:$N,T$4,FEC_2025!$Q:$Q,"6")-SUMIFS(FEC_2025!$M:$M,FEC_2025!$O:$O,"INVENTAIRE",FEC_2025!$N:$N,T$4,FEC_2025!$Q:$Q,"7") | U26: =-SUMIFS(FEC_2025!$M:$M,FEC_2025!$O:$O,"INVENTAIRE",FEC_2025!$N:$N,U$4,FEC_2025!$Q:$Q,"6")-SUMIFS(FEC_2025!$M:$M,FEC_2025!$O:$O,"INVENTAIRE",FEC_2025!$N:$N,U$4,FEC_2025!$Q:$Q,"7") | ... Y26: =-SUMIFS(FEC_2025!$M:$M,FEC_2025!$O:$O,"INVENTAIRE",FEC_2025!$N:$N,Y$4,FEC_2025!$Q:$Q,"6")-SUMIFS(FEC_2025!$M:$M,FEC_2025!$O:$O,"INVENTAIRE",FEC_2025!$N:$N,Y$4,FEC_2025!$Q:$Q,"7")
A27: dont extournes d'ouverture (type EXTOURNE) | B27: =-SUMIFS(FEC_2024!$M:$M,FEC_2024!$O:$O,"EXTOURNE",FEC_2024!$N:$N,B$4,FEC_2024!$Q:$Q,"6")-SUMIFS(FEC_2024!$M:$M,FEC_2024!$O:$O,"EXTOURNE",FEC_2024!$N:$N,B$4,FEC_2024!$Q:$Q,"7") | C27: =-SUMIFS(FEC_2024!$M:$M,FEC_2024!$O:$O,"EXTOURNE",FEC_2024!$N:$N,C$4,FEC_2024!$Q:$Q,"6")-SUMIFS(FEC_2024!$M:$M,FEC_2024!$O:$O,"EXTOURNE",FEC_2024!$N:$N,C$4,FEC_2024!$Q:$Q,"7") | D27: =-SUMIFS(FEC_2024!$M:$M,FEC_2024!$O:$O,"EXTOURNE",FEC_2024!$N:$N,D$4,FEC_2024!$Q:$Q,"6")-SUMIFS(FEC_2024!$M:$M,FEC_2024!$O:$O,"EXTOURNE",FEC_2024!$N:$N,D$4,FEC_2024!$Q:$Q,"7") | E27: =-SUMIFS(FEC_2024!$M:$M,FEC_2024!$O:$O,"EXTOURNE",FEC_2024!$N:$N,E$4,FEC_2024!$Q:$Q,"6")-SUMIFS(FEC_2024!$M:$M,FEC_2024!$O:$O,"EXTOURNE",FEC_2024!$N:$N,E$4,FEC_2024!$Q:$Q,"7") | F27: =-SUMIFS(FEC_2024!$M:$M,FEC_2024!$O:$O,"EXTOURNE",FEC_2024!$N:$N,F$4,FEC_2024!$Q:$Q,"6")-SUMIFS(FEC_2024!$M:$M,FEC_2024!$O:$O,"EXTOURNE",FEC_2024!$N:$N,F$4,FEC_2024!$Q:$Q,"7") | G27: =-SUMIFS(FEC_2024!$M:$M,FEC_2024!$O:$O,"EXTOURNE",FEC_2024!$N:$N,G$4,FEC_2024!$Q:$Q,"6")-SUMIFS(FEC_2024!$M:$M,FEC_2024!$O:$O,"EXTOURNE",FEC_2024!$N:$N,G$4,FEC_2024!$Q:$Q,"7") | H27: =-SUMIFS(FEC_2024!$M:$M,FEC_2024!$O:$O,"EXTOURNE",FEC_2024!$N:$N,H$4,FEC_2024!$Q:$Q,"6")-SUMIFS(FEC_2024!$M:$M,FEC_2024!$O:$O,"EXTOURNE",FEC_2024!$N:$N,H$4,FEC_2024!$Q:$Q,"7") | I27: =-SUMIFS(FEC_2024!$M:$M,FEC_2024!$O:$O,"EXTOURNE",FEC_2024!$N:$N,I$4,FEC_2024!$Q:$Q,"6")-SUMIFS(FEC_2024!$M:$M,FEC_2024!$O:$O,"EXTOURNE",FEC_2024!$N:$N,I$4,FEC_2024!$Q:$Q,"7") | ... M27: =-SUMIFS(FEC_2024!$M:$M,FEC_2024!$O:$O,"EXTOURNE",FEC_2024!$N:$N,M$4,FEC_2024!$Q:$Q,"6")-SUMIFS(FEC_2024!$M:$M,FEC_2024!$O:$O,"EXTOURNE",FEC_2024!$N:$N,M$4,FEC_2024!$Q:$Q,"7") | N27: =-SUMIFS(FEC_2025!$M:$M,FEC_2025!$O:$O,"EXTOURNE",FEC_2025!$N:$N,N$4,FEC_2025!$Q:$Q,"6")-SUMIFS(FEC_2025!$M:$M,FEC_2025!$O:$O,"EXTOURNE",FEC_2025!$N:$N,N$4,FEC_2025!$Q:$Q,"7") | O27: =-SUMIFS(FEC_2025!$M:$M,FEC_2025!$O:$O,"EXTOURNE",FEC_2025!$N:$N,O$4,FEC_2025!$Q:$Q,"6")-SUMIFS(FEC_2025!$M:$M,FEC_2025!$O:$O,"EXTOURNE",FEC_2025!$N:$N,O$4,FEC_2025!$Q:$Q,"7") | P27: =-SUMIFS(FEC_2025!$M:$M,FEC_2025!$O:$O,"EXTOURNE",FEC_2025!$N:$N,P$4,FEC_2025!$Q:$Q,"6")-SUMIFS(FEC_2025!$M:$M,FEC_2025!$O:$O,"EXTOURNE",FEC_2025!$N:$N,P$4,FEC_2025!$Q:$Q,"7") | Q27: =-SUMIFS(FEC_2025!$M:$M,FEC_2025!$O:$O,"EXTOURNE",FEC_2025!$N:$N,Q$4,FEC_2025!$Q:$Q,"6")-SUMIFS(FEC_2025!$M:$M,FEC_2025!$O:$O,"EXTOURNE",FEC_2025!$N:$N,Q$4,FEC_2025!$Q:$Q,"7") | R27: =-SUMIFS(FEC_2025!$M:$M,FEC_2025!$O:$O,"EXTOURNE",FEC_2025!$N:$N,R$4,FEC_2025!$Q:$Q,"6")-SUMIFS(FEC_2025!$M:$M,FEC_2025!$O:$O,"EXTOURNE",FEC_2025!$N:$N,R$4,FEC_2025!$Q:$Q,"7") | S27: =-SUMIFS(FEC_2025!$M:$M,FEC_2025!$O:$O,"EXTOURNE",FEC_2025!$N:$N,S$4,FEC_2025!$Q:$Q,"6")-SUMIFS(FEC_2025!$M:$M,FEC_2025!$O:$O,"EXTOURNE",FEC_2025!$N:$N,S$4,FEC_2025!$Q:$Q,"7") | T27: =-SUMIFS(FEC_2025!$M:$M,FEC_2025!$O:$O,"EXTOURNE",FEC_2025!$N:$N,T$4,FEC_2025!$Q:$Q,"6")-SUMIFS(FEC_2025!$M:$M,FEC_2025!$O:$O,"EXTOURNE",FEC_2025!$N:$N,T$4,FEC_2025!$Q:$Q,"7") | U27: =-SUMIFS(FEC_2025!$M:$M,FEC_2025!$O:$O,"EXTOURNE",FEC_2025!$N:$N,U$4,FEC_2025!$Q:$Q,"6")-SUMIFS(FEC_2025!$M:$M,FEC_2025!$O:$O,"EXTOURNE",FEC_2025!$N:$N,U$4,FEC_2025!$Q:$Q,"7") | ... Y27: =-SUMIFS(FEC_2025!$M:$M,FEC_2025!$O:$O,"EXTOURNE",FEC_2025!$N:$N,Y$4,FEC_2025!$Q:$Q,"6")-SUMIFS(FEC_2025!$M:$M,FEC_2025!$O:$O,"EXTOURNE",FEC_2025!$N:$N,Y$4,FEC_2025!$Q:$Q,"7")
A28: Résultat mensuel hors écritures de clôture | B28: =B23-B26-B27 | C28: =C23-C26-C27 | D28: =D23-D26-D27 | E28: =E23-E26-E27 | F28: =F23-F26-F27 | G28: =G23-G26-G27 | H28: =H23-H26-H27 | I28: =I23-I26-I27 | ... Y28: =Y23-Y26-Y27
A29: EBITDA mensuel hors écritures de clôture (approximation : clôture imputée en totalité à l'EBITDA) | B29: =B15-B26-B27 | C29: =C15-C26-C27 | D29: =D15-D26-D27 | E29: =E15-E26-E27 | F29: =F15-F26-F27 | G29: =G15-G26-G27 | H29: =H15-H26-H27 | I29: =I15-I26-I27 | ... Y29: =Y15-Y26-Y27

Sheet Bilan_synth
A1: Bilan économique
A2: En euros. Fournisseurs et trésorerie présentés en négatif ; dette nette positive = endettement net.
A4: Poste | B4: 2024 (31/12/2024) | C4: 2025 (31/12/2025)
A5: Immobilisations incorporelles brutes | B5: =SUMIFS(Comptes!$F$5:$F$42,Comptes!$H$5:$H$42,"IMMO_INCORP") | C5: =SUMIFS(Comptes!$I$5:$I$42,Comptes!$K$5:$K$42,"IMMO_INCORP")
A6: Immobilisations corporelles brutes | B6: =SUMIFS(Comptes!$F$5:$F$42,Comptes!$H$5:$H$42,"IMMO_CORP") | C6: =SUMIFS(Comptes!$I$5:$I$42,Comptes!$K$5:$K$42,"IMMO_CORP")
A7: Immobilisations financières | B7: =SUMIFS(Comptes!$F$5:$F$42,Comptes!$H$5:$H$42,"IMMO_FIN") | C7: =SUMIFS(Comptes!$I$5:$I$42,Comptes!$K$5:$K$42,"IMMO_FIN")
A8: Amortissements et dépréciations | B8: =SUMIFS(Comptes!$F$5:$F$42,Comptes!$H$5:$H$42,"AMORT_DEPREC") | C8: =SUMIFS(Comptes!$I$5:$I$42,Comptes!$K$5:$K$42,"AMORT_DEPREC")
A9: ACTIF IMMOBILISÉ NET | B9: =B5+B6+B7+B8 | C9: =C5+C6+C7+C8
A10: Stocks et en-cours | B10: =SUMIFS(Comptes!$F$5:$F$42,Comptes!$H$5:$H$42,"STOCKS") | C10: =SUMIFS(Comptes!$I$5:$I$42,Comptes!$K$5:$K$42,"STOCKS")
A11: Clients nets | B11: =SUMIFS(Comptes!$F$5:$F$42,Comptes!$H$5:$H$42,"CLIENTS") | C11: =SUMIFS(Comptes!$I$5:$I$42,Comptes!$K$5:$K$42,"CLIENTS")
A12: Fournisseurs | B12: =SUMIFS(Comptes!$F$5:$F$42,Comptes!$H$5:$H$42,"FOURNISSEURS") | C12: =SUMIFS(Comptes!$I$5:$I$42,Comptes!$K$5:$K$42,"FOURNISSEURS")
A13: BFR d'exploitation | B13: =B10+B11+B12 | C13: =C10+C11+C12
A14: Dettes fiscales nettes (TVA, IS, CFE) | B14: =SUMIFS(Comptes!$F$5:$F$42,Comptes!$H$5:$H$42,"DETTES_FISCALES") | C14: =SUMIFS(Comptes!$I$5:$I$42,Comptes!$K$5:$K$42,"DETTES_FISCALES")
A15: Dettes sociales | B15: =SUMIFS(Comptes!$F$5:$F$42,Comptes!$H$5:$H$42,"DETTES_SOCIALES") | C15: =SUMIFS(Comptes!$I$5:$I$42,Comptes!$K$5:$K$42,"DETTES_SOCIALES")
A16: Autres créances | B16: =SUMIFS(Comptes!$F$5:$F$42,Comptes!$H$5:$H$42,"AUTRES_CREANCES") | C16: =SUMIFS(Comptes!$I$5:$I$42,Comptes!$K$5:$K$42,"AUTRES_CREANCES")
A17: Autres dettes | B17: =SUMIFS(Comptes!$F$5:$F$42,Comptes!$H$5:$H$42,"AUTRES_DETTES") | C17: =SUMIFS(Comptes!$I$5:$I$42,Comptes!$K$5:$K$42,"AUTRES_DETTES")
A18: Charges et produits constatés d'avance | B18: =SUMIFS(Comptes!$F$5:$F$42,Comptes!$H$5:$H$42,"CCA_PCA") | C18: =SUMIFS(Comptes!$I$5:$I$42,Comptes!$K$5:$K$42,"CCA_PCA")
A19: BFR hors exploitation | B19: =B14+B15+B16+B17+B18 | C19: =C14+C15+C16+C17+C18
A20: BFR TOTAL | B20: =B13+B19 | C20: =C13+C19
A21: ACTIF ÉCONOMIQUE | B21: =B9+B20 | C21: =C9+C20
A22: Trésorerie active | B22: =-SUMIFS(Comptes!$F$5:$F$42,Comptes!$H$5:$H$42,"TRESORERIE") | C22: =-SUMIFS(Comptes!$I$5:$I$42,Comptes!$K$5:$K$42,"TRESORERIE")
A23: Compte courant factor (solde débiteur = disponible) | B23: =-SUMIFS(Comptes!$F$5:$F$42,Comptes!$H$5:$H$42,"FACTOR_CC") | C23: =-SUMIFS(Comptes!$I$5:$I$42,Comptes!$K$5:$K$42,"FACTOR_CC")
A24: Concours bancaires courants | B24: =-SUMIFS(Comptes!$F$5:$F$42,Comptes!$H$5:$H$42,"CONCOURS_BANCAIRES") | C24: =-SUMIFS(Comptes!$I$5:$I$42,Comptes!$K$5:$K$42,"CONCOURS_BANCAIRES")
A25: Emprunts (y c. intérêts courus) | B25: =-SUMIFS(Comptes!$F$5:$F$42,Comptes!$H$5:$H$42,"EMPRUNTS") | C25: =-SUMIFS(Comptes!$I$5:$I$42,Comptes!$K$5:$K$42,"EMPRUNTS")
A26: Comptes courants d'associés | B26: =-SUMIFS(Comptes!$F$5:$F$42,Comptes!$H$5:$H$42,"COMPTES_COURANTS") | C26: =-SUMIFS(Comptes!$I$5:$I$42,Comptes!$K$5:$K$42,"COMPTES_COURANTS")
A27: DETTE NETTE (y c. comptes courants) | B27: =B22+B23+B24+B25+B26 | C27: =C22+C23+C24+C25+C26
A28: Capitaux propres hors résultat | B28: =-SUMIFS(Comptes!$F$5:$F$42,Comptes!$H$5:$H$42,"CAPITAUX_PROPRES") | C28: =-SUMIFS(Comptes!$I$5:$I$42,Comptes!$K$5:$K$42,"CAPITAUX_PROPRES")
A29: Résultat de l'exercice | B29: =-SUMIFS(Comptes!$F$5:$F$42,Comptes!$A$5:$A$42,"6*")-SUMIFS(Comptes!$F$5:$F$42,Comptes!$A$5:$A$42,"7*") | C29: =-SUMIFS(Comptes!$I$5:$I$42,Comptes!$A$5:$A$42,"6*")-SUMIFS(Comptes!$I$5:$I$42,Comptes!$A$5:$A$42,"7*")
A30: Provisions pour risques et charges | B30: =-SUMIFS(Comptes!$F$5:$F$42,Comptes!$H$5:$H$42,"PROVISIONS") | C30: =-SUMIFS(Comptes!$I$5:$I$42,Comptes!$K$5:$K$42,"PROVISIONS")
A31: CAPITAUX PROPRES ET PROVISIONS | B31: =B28+B29+B30 | C31: =C28+C29+C30
A32: Contrôle : actif économique - dette nette - capitaux propres | B32: =B21-B27-B31 | C32: =C21-C27-C31
A34: Ratios de rotation
A35: Taux de TVA moyen appliqué au CA et aux achats (hypothèse, modifiable) | B35: 0.2
A36: Nombre de jours de la période | B36: 366 | C36: 365
A37: DSO (clients nets TTC / CA TTC) | B37: =IF(PnL_annuel!B5=0,0,B11/(PnL_annuel!B5*(1+$B$35))*B$36) | C37: =IF(PnL_annuel!D5=0,0,C11/(PnL_annuel!D5*(1+$B$35))*C$36)
A38: DPO (fournisseurs TTC / coûts directs et charges externes TTC) | B38: =IF((PnL_annuel!B9+PnL_annuel!B11)=0,0,B12/((PnL_annuel!B9+PnL_annuel!B11)*(1+$B$35))*B$36) | C38: =IF((PnL_annuel!D9+PnL_annuel!D11)=0,0,C12/((PnL_annuel!D9+PnL_annuel!D11)*(1+$B$35))*C$36)
A39: BFR d'exploitation en jours de CA HT | B39: =IF(PnL_annuel!B5=0,0,B13/PnL_annuel!B5*B$36) | C39: =IF(PnL_annuel!D5=0,0,C13/PnL_annuel!D5*C$36)
A40: Dette nette / EBITDA (annualisé si période partielle) | B40: =IF(PnL_annuel!B15<=0,"n.s.",B27/(PnL_annuel!B15*365/B$36)) | C40: =IF(PnL_annuel!D15<=0,"n.s.",C27/(PnL_annuel!D15*365/C$36))

Sheet Tresorerie
A1: Trésorerie comptable fin de mois
A2: Soldes des comptes 51 et 53 (hors intérêts courus 518) à chaque fin de mois, à-nouveaux inclus. Positif = disponible.
C3: 45322 | D3: 45351 | E3: 45382 | F3: 45412 | G3: 45443 | H3: 45473 | I3: 45504 | J3: 45535 | K3: 45565 | L3: 45596 | M3: 45626 | N3: 45657 | O3: 45688 | P3: 45716 | Q3: 45747 | R3: 45777 | S3: 45808 | T3: 45838 | U3: 45869 | V3: 45900 | W3: 45930 | X3: 45961 | Y3: 45991 | Z3: 46022
A4: Compte | B4: Libellé | C4: 2024-01 | D4: 2024-02 | E4: 2024-03 | F4: 2024-04 | G4: 2024-05 | H4: 2024-06 | I4: 2024-07 | J4: 2024-08 | K4: 2024-09 | L4: 2024-10 | M4: 2024-11 | N4: 2024-12 | O4: 2025-01 | P4: 2025-02 | Q4: 2025-03 | R4: 2025-04 | S4: 2025-05 | T4: 2025-06 | U4: 2025-07 | V4: 2025-08 | W4: 2025-09 | X4: 2025-10 | Y4: 2025-11 | Z4: 2025-12
A5: 512000 | B5: Banque Fictive | C5: =SUMIFS(FEC_2024!$M:$M,FEC_2024!$E:$E,$A5,FEC_2024!$D:$D,"<="&C$3) | D5: =SUMIFS(FEC_2024!$M:$M,FEC_2024!$E:$E,$A5,FEC_2024!$D:$D,"<="&D$3) | E5: =SUMIFS(FEC_2024!$M:$M,FEC_2024!$E:$E,$A5,FEC_2024!$D:$D,"<="&E$3) | F5: =SUMIFS(FEC_2024!$M:$M,FEC_2024!$E:$E,$A5,FEC_2024!$D:$D,"<="&F$3) | G5: =SUMIFS(FEC_2024!$M:$M,FEC_2024!$E:$E,$A5,FEC_2024!$D:$D,"<="&G$3) | H5: =SUMIFS(FEC_2024!$M:$M,FEC_2024!$E:$E,$A5,FEC_2024!$D:$D,"<="&H$3) | I5: =SUMIFS(FEC_2024!$M:$M,FEC_2024!$E:$E,$A5,FEC_2024!$D:$D,"<="&I$3) | J5: =SUMIFS(FEC_2024!$M:$M,FEC_2024!$E:$E,$A5,FEC_2024!$D:$D,"<="&J$3) | ... N5: =SUMIFS(FEC_2024!$M:$M,FEC_2024!$E:$E,$A5,FEC_2024!$D:$D,"<="&N$3) | O5: =SUMIFS(FEC_2025!$M:$M,FEC_2025!$E:$E,$A5,FEC_2025!$D:$D,"<="&O$3) | P5: =SUMIFS(FEC_2025!$M:$M,FEC_2025!$E:$E,$A5,FEC_2025!$D:$D,"<="&P$3) | Q5: =SUMIFS(FEC_2025!$M:$M,FEC_2025!$E:$E,$A5,FEC_2025!$D:$D,"<="&Q$3) | R5: =SUMIFS(FEC_2025!$M:$M,FEC_2025!$E:$E,$A5,FEC_2025!$D:$D,"<="&R$3) | S5: =SUMIFS(FEC_2025!$M:$M,FEC_2025!$E:$E,$A5,FEC_2025!$D:$D,"<="&S$3) | T5: =SUMIFS(FEC_2025!$M:$M,FEC_2025!$E:$E,$A5,FEC_2025!$D:$D,"<="&T$3) | U5: =SUMIFS(FEC_2025!$M:$M,FEC_2025!$E:$E,$A5,FEC_2025!$D:$D,"<="&U$3) | V5: =SUMIFS(FEC_2025!$M:$M,FEC_2025!$E:$E,$A5,FEC_2025!$D:$D,"<="&V$3) | ... Z5: =SUMIFS(FEC_2025!$M:$M,FEC_2025!$E:$E,$A5,FEC_2025!$D:$D,"<="&Z$3)
A6: TOTAL TRÉSORERIE | C6: =SUM(C5:C5) | D6: =SUM(D5:D5) | E6: =SUM(E5:E5) | F6: =SUM(F5:F5) | G6: =SUM(G5:G5) | H6: =SUM(H5:H5) | I6: =SUM(I5:I5) | J6: =SUM(J5:J5) | ... Z6: =SUM(Z5:Z5)
A8: Point bas par exercice
A9: 2024 | C9: =MIN(C6:N6)
A10: 2025 | C10: =MIN(O6:Z6)

Sheet Creances
A1: Créances clients : concentration, intragroupe, ancienneté, coupure
A2: Valeurs calculées par l'application (non recalculées dans Excel). Ancienneté : solde exact de chaque client imputé sur ses factures les plus récentes (FIFO), indépendamment du lettrage.
A4: Indicateur | B4: 2024 | C4: 2025 | D4: Lecture
A5: Chiffre d'affaires facturé HT (journaux de ventes) | B5: 1983333.3 | C5: 1520000
A6: dont sociétés du groupe | B6: 0 | C6: 0 | D6: Sociétés du groupe : aucune identifiée
A7: Part intragroupe du chiffre d'affaires | B7: 0 | C7: 0
A8: Nombre de clients facturés | B8: 8 | C8: 8
A9: Poids du 1er client hors groupe | B9: 0.1675185 | C9: 0.201038 | D9: Au-delà de 20 % : dépendance à documenter (contrat, solvabilité du client).
A10: Poids des 5 premiers clients hors groupe | B10: 0.75008603 | C10: 0.75015334
A11: Poids des 10 premiers clients hors groupe | B11: 1 | C11: 1
A12: Solde des comptes clients (411 à 417) | B12: 258238.9 | C12: 515457.32
A13: Encours clients hors groupe | B13: 258238.9 | C13: 515457.32
A14: dont plus de 90 jours | B14: 0 | C14: 48000
A15: dont plus de 180 jours | B15: 0 | C15: 25113.06 | D15: Créances anciennes non provisionnées : risque de surévaluation de l'actif.
A16: Encours sur les sociétés du groupe | B16: 0 | C16: 0 | D16: Recouvrabilité à apprécier au niveau du groupe (situation de la société débitrice).
A17: Clients créditeurs (trop-perçus, acomptes non imputés) | B17: 0 | C17: 0
A18: Créances douteuses (416) | B18: 0 | C18: 0
A19: Provisions pour dépréciation (491) | B19: 0 | C19: 0
A20: Factures à établir (418) | B20: 0 | C20: 0 | D20: Un montant identique d'un exercice à l'autre est anormal (produit ancien non facturé).
A21: DSO clients hors groupe (jours) | B21: 40 | C21: 103 | D21: Encours TTC hors groupe / CA TTC hors groupe × jours de la période.
A22: Lettrage : part du facturé lettrée | B22: 0.89149626 | C22: 0.71740278 | D22: Sous 70 % : les délais issus du lettrage sont peu fiables ; l'ancienneté FIFO ci-dessus n'en dépend pas.
A23: Facturation des 5 derniers jours (HT) | B23: 31815.11 | C23: 109914.24
A24: Moyenne de 5 jours sur l'exercice (HT) | B24: 27094.72 | C24: 20821.92
A25: Ratio fin d'exercice / moyenne | B25: 1.1742182 | C25: 5.2787761 | D25: Au-delà de 2 : vérifier la coupure (livraisons réellement faites avant la clôture).
A26: CA du dernier mois / moyenne des autres mois | B26: 0.95433782 | C26: 1.747141
A27: Avoirs émis dans les 31 jours suivant la clôture (HT) | B27: 0 | C27: n.d. | D27: Avoirs en début d'exercice suivant sur des ventes de fin d'exercice : chiffre d'affaires possiblement anticipé.
A28: Part des règlements clients passant par le factor | B28: 0 | C28: 0
A31: Top 20 clients — 2025 (chiffre d'affaires HT)
A32: Client | B32: CA HT | C32: % du total | D32: Groupe | E32: Factures
A33: Agence Mobilis | B33: 305577.75 | C33: 0.201038 | E33: 10
A34: Coworking Atelier 9 | B34: 274397.31 | C34: 0.18052455 | E34: 11
A35: Hotel Les Tilleuls | B35: 226628.29 | C35: 0.14909756 | E35: 10
A36: Boutique Hetre et Chene | B36: 181389.39 | C36: 0.11933513 | E36: 8
A37: Clinique du Parc | B37: 152240.31 | C37: 0.1001581 | E37: 6
A38: Cabinet Varenne Associes | B38: 145517.52 | C38: 0.095735212 | E38: 7
A39: Restaurant Le Comptoir | B39: 126872.8 | C39: 0.083468949 | E39: 4
A40: Residence Bel Air | B40: 107376.6 | C40: 0.070642501 | E40: 5
A43: Ancienneté des soldes clients — 2025 (au 31/12/2025), méthode FIFO
A44: Client | B44: Solde | C44: Groupe | D44: 0-30 j | E44: 31-60 j | F44: 61-90 j | G44: 91-180 j | H44: > 180 j
A45: Agence Mobilis | B45: 178027.53 | D45: 96000 | E45: 52195.22 | F45: 29832.31 | G45: 0 | H45: 0
A46: Clinique du Parc | B46: 125096.26 | D46: 24656.02 | E46: 18815.21 | F46: 33625.03 | G46: 22886.94 | H46: 25113.06
A47: Hotel Les Tilleuls | B47: 67575.82 | D47: 42716.25 | E47: 24859.57 | F47: 0 | G47: 0 | H47: 0
A48: Coworking Atelier 9 | B48: 65068.93 | D48: 35897.09 | E48: 29171.84 | F48: 0 | G48: 0 | H48: 0
A49: Cabinet Varenne Associes | B49: 50730.63 | D49: 50730.63 | E49: 0 | F49: 0 | G49: 0 | H49: 0
A50: Boutique Hetre et Chene | B50: 28958.15 | D50: 0 | E50: 28958.15 | F50: 0 | G50: 0 | H50: 0
A51: TOTAL | B51: =SUM(B45:B50) | D51: =SUM(D45:D50) | E51: =SUM(E45:E50) | F51: =SUM(F45:F50) | G51: =SUM(G45:G50) | H51: =SUM(H45:H50)

Sheet Dettes_fournisseurs
A1: Dettes fournisseurs : concentration, intragroupe, ancienneté, factures non parvenues
A2: Valeurs calculées par l'application. Ancienneté : solde exact de chaque fournisseur imputé sur ses factures les plus récentes (FIFO), depuis la date de pièce.
A4: Indicateur | B4: 2024 | C4: 2025 | D4: Lecture
A5: Achats facturés HT (journaux d'achats) | B5: 1013184 | C5: 860910.51
A6: dont sociétés du groupe | B6: 0 | C6: 0 | D6: Sociétés du groupe : aucune identifiée
A7: Part intragroupe des achats | B7: 0 | C7: 0
A8: Nombre de fournisseurs | B8: 8 | C8: 8
A9: Poids du 1er fournisseur hors groupe | B9: 0.36517028 | C9: 0.38577445 | D9: Au-delà de 30 % : dépendance ; ce fournisseur est souvent le créancier qui décide du sort de l'entreprise.
A10: Poids des 5 premiers fournisseurs hors groupe | B10: 0.9587834 | C10: 0.95149322
A11: Poids des 10 premiers fournisseurs hors groupe | B11: 1 | C11: 1
A12: Dettes fournisseurs hors groupe (401 à 404) | B12: 153814.87 | C12: 202786.83
A13: dont factures de plus de 60 jours | B13: 0 | C13: 36776.26 | D13: Délai légal : 60 jours date de facture (45 jours fin de mois sur option), sauf accord particulier.
A14: dont plus de 90 jours | B14: 0 | C14: 15500
A15: dont plus d'un an | B15: 0 | C15: 0 | D15: Dettes anciennes : passif gelé (procédure, plan) ou litige ; à qualifier.
A16: Dettes envers les sociétés du groupe | B16: 0 | C16: 0
A17: dont effets à payer (403) | B17: 0 | C17: 0
A18: dont fournisseurs d'immobilisations (404) | B18: 0 | C18: 0
A19: Fournisseurs débiteurs (soldes débiteurs) | B19: 0 | C19: 0 | D19: Avoirs à recevoir, acomptes, doubles paiements : à justifier.
A20: Avances et acomptes versés (409) | B20: 0 | C20: 0
A21: Factures non parvenues (408) | B21: 0 | C21: 0
A22: Mouvements du compte 408 dans l'exercice (lignes) | B22: 0 | C22: 0 | D22: Aucun mouvement et solde identique : provision figée, sans rapport avec des factures attendues.
A23: 408 identique à l'exercice précédent | B23: n.d. | C23: non
A24: DPO hors groupe (jours) | B24: 46 | C24: 72 | D24: Dettes TTC hors groupe / achats TTC hors groupe × jours de la période.
A27: Top 20 fournisseurs — 2025 (achats HT)
A28: Fournisseur | B28: Achats HT | C28: % du total | D28: Groupe | E28: Factures
A29: Scierie du Nord | B29: 332117.28 | C29: 0.38577445 | E29: 16
A30: Quincaillerie Pro Est | B30: 192383.68 | C30: 0.22346536 | E30: 9
A31: Vernis et Finitions | B31: 157499.05 | C31: 0.18294474 | E31: 9
A32: SCI Les Halles | B32: 102000 | C32: 0.11847921 | E32: 12
A33: Energie Plus | B33: 35150.5 | C33: 0.040829447 | E33: 12
A34: Cabinet Comptable Exemple | B34: 24000 | C34: 0.027877462 | E34: 4
A35: Assurances Mutuelles Exemple | B35: 12000 | C35: 0.013938731 | E35: 4
A36: Telecom Pro | B36: 5760 | C36: 0.0066905909 | E36: 12
A39: Ancienneté des dettes fournisseurs — 2025 (au 31/12/2025), méthode FIFO
A40: Fournisseur | B40: Solde | C40: Groupe | D40: 0-30 j | E40: 31-60 j | F40: 61-90 j | G40: 91-180 j | H40: 181-365 j | I40: > 1 an
A41: Scierie du Nord | B41: 144759.99 | D41: 72380 | E41: 72379.99 | F41: 0 | G41: 0 | H41: 0 | I41: 0
A42: Quincaillerie Pro Est | B42: 21276.26 | D42: 0 | E42: 0 | F42: 21276.26 | G42: 0 | H42: 0 | I42: 0
A43: Vernis et Finitions | B43: 14400 | D43: 0 | E43: 0 | F43: 0 | G43: 14400 | H43: 0 | I43: 0
A44: SCI Les Halles | B44: 10200 | D44: 10200 | E44: 0 | F44: 0 | G44: 0 | H44: 0 | I44: 0
A45: Cabinet Comptable Exemple | B45: 8300 | D45: 7200 | E45: 0 | F45: 0 | G45: 1100 | H45: 0 | I45: 0
A46: Energie Plus | B46: 3274.58 | D46: 3274.58 | E46: 0 | F46: 0 | G46: 0 | H46: 0 | I46: 0
A47: Telecom Pro | B47: 576 | D47: 576 | E47: 0 | F47: 0 | G47: 0 | H47: 0 | I47: 0
A48: TOTAL | B48: =SUM(B41:B47) | D48: =SUM(D41:D47) | E48: =SUM(E41:E47) | F48: =SUM(F41:F47) | G48: =SUM(G41:G47) | H48: =SUM(H41:H47) | I48: =SUM(I41:I47)

Sheet Social_fiscal
A1: Dettes sociales et fiscales : dû comptabilisé / payé en banque
A2: Valeurs calculées par l'application. Doublons d'import écartés ; cotisations des mois de paie non comptabilisée estimées. À confirmer par les relevés des organismes (URSSAF, retraite, prévoyance, mutuelle, compte fiscal).
A4: 2024 (du 01/01/2024 au 31/12/2024)
A5: Organisme | B5: Comptes | C5: Ouverture (corrigée) | D5: Dû comptabilisé | E5: Doublons écartés | F5: Payé en banque | G5: Remboursements reçus | H5: Autres apurements (OD) | I5: Clôture (corrigée) | J5: Estimation mois non comptabilisés | K5: Solde estimé | L5: Dû mensuel moyen | M5: Retard (mois)
A6: URSSAF | B6: 431000 | C6: 18000 | D6: 398883.36 | E6: 0 | F6: 383590.84 | G6: 0 | H6: 0 | I6: 33292.52 | J6: 0 | K6: =I6+J6 | L6: 33277.73 | M6: =IF(L6>1,MAX(0,K6)/L6,"n.d.")
A7: TVA | B7: 445510 | C7: 12000 | D7: 196429.9 | E7: 0 | F7: 193634.04 | G7: 0 | H7: 0 | I7: 14795.86 | J7: 0 | K7: =I7+J7 | L7: 16046.41 | M7: =IF(L7>1,MAX(0,K7)/L7,"n.d.")
A8: Impôt sur les sociétés | B8: 444000 | C8: 0 | D8: 9067.03 | E8: 0 | F8: 0 | G8: 0 | H8: 0 | I8: 9067.03 | J8: 0 | K8: =I8+J8 | L8: 9067.03 | M8: =IF(L8>1,MAX(0,K8)/L8,"n.d.")
A9: Crédits d'impôt comptabilisés en produit (CIR, CII…) | C9: 0
A10: Paie par mois : charges comptabilisées (64) / salaires nets versés en banque
C11: 2024-01 | D11: 2024-02 | E11: 2024-03 | F11: 2024-04 | G11: 2024-05 | H11: 2024-06 | I11: 2024-07 | J11: 2024-08 | K11: 2024-09 | L11: 2024-10 | M11: 2024-11 | N11: 2024-12
A12: Charges de personnel comptabilisées | C12: 74866.36 | D12: 73160.52 | E12: 73610.09 | F12: 74662.95 | G12: 73026.87 | H12: 72685.94 | I12: 74679.04 | J12: 72480.58 | K12: 74960.21 | L12: 73614.28 | M12: 73407.82 | N12: 73867.78
A13: Salaires nets versés (banque) | C13: 41123.78 | D13: 40186.76 | E13: 40433.71 | F13: 41012.04 | G13: 40113.35 | H13: 39926.08 | I13: 41020.88 | J13: 39813.27 | K13: 41175.33 | L13: 40436.01 | M13: 40322.61 | N13: 40575.26
A14: URSSAF : dû / payé | C14: 33743 / 18000 | D14: 32974 / 33743 | E14: 33176 / 32974 | F14: 33651 / 33176 | G14: 32914 / 33651 | H14: 32760 / 32914 | I14: 33658 / 32760 | J14: 32667 / 33658 | K14: 33785 / 32667 | L14: 33178 / 33785 | M14: 33085 / 33178 | N14: 33293 / 33085
A15: TVA : dû / payé | C15: 14131 / 12000 | D15: 14999 / 14131 | E15: 16610 / 14999 | F15: 17878 / 16610 | G15: 18958 / 17878 | H15: 17575 / 18958 | I15: 16019 / 17575 | J15: 11101 / 16019 | K15: 16586 / 11101 | L15: 18966 / 16586 | M15: 18811 / 18966 | N15: 14796 / 18811
A18: 2025 (du 01/01/2025 au 31/12/2025)
A19: Organisme | B19: Comptes | C19: Ouverture (corrigée) | D19: Dû comptabilisé | E19: Doublons écartés | F19: Payé en banque | G19: Remboursements reçus | H19: Autres apurements (OD) | I19: Clôture (corrigée) | J19: Estimation mois non comptabilisés | K19: Solde estimé | L19: Dû mensuel moyen | M19: Retard (mois)
A20: URSSAF | B20: 431000 | C20: 33292.52 | D20: 384973.21 | E20: 0 | F20: 289968.84 | G20: 0 | H20: 0 | I20: 128296.89 | J20: 0 | K20: =I20+J20 | L20: 32062.58 | M20: =IF(L20>1,MAX(0,K20)/L20,"n.d.")
A21: TVA | B21: 445510 | C21: 14795.86 | D21: 139017.92 | E21: 0 | F21: 127752.21 | G21: 0 | H21: 4800 | I21: 21261.57 | J21: 0 | K21: =I21+J21 | L21: 12148.71 | M21: =IF(L21>1,MAX(0,K21)/L21,"n.d.")
A22: Impôt sur les sociétés | B22: 444000 | C22: 9067.03 | D22: 0 | E22: 0 | F22: 9067.03 | G22: 0 | H22: 0 | I22: 0 | J22: 0 | K22: =I22+J22 | L22: 0 | M22: =IF(L22>1,MAX(0,K22)/L22,"n.d.")
A23: Crédits d'impôt comptabilisés en produit (CIR, CII…) | C23: 0
A24: Paie par mois : charges comptabilisées (64) / salaires nets versés en banque
C25: 2025-01 | D25: 2025-02 | E25: 2025-03 | F25: 2025-04 | G25: 2025-05 | H25: 2025-06 | I25: 2025-07 | J25: 2025-08 | K25: 2025-09 | L25: 2025-10 | M25: 2025-11 | N25: 2025-12
A26: Charges de personnel comptabilisées | C26: 69810.57 | D26: 71567.25 | E26: 71550.04 | F26: 70259.6 | G26: 71817.11 | H26: 72321.61 | I26: 72145.73 | J26: 70028.65 | K26: 70119.97 | L26: 72324.86 | M26: 72276.24 | N26: 69937.63
A27: Salaires nets versés (banque) | C27: 38346.65 | D27: 39311.59 | E27: 39302.13 | F27: 38593.3 | G27: 39448.84 | H27: 39725.95 | I27: 39629.34 | J27: 38466.44 | K27: 38516.6 | L27: 39727.74 | M27: 39701.03 | N27: 38416.44
A28: URSSAF : dû / payé | C28: 31464 / 33293 | D28: 32256 / 31464 | E28: 32248 / 32256 | F28: 31666 / 32248 | G28: 32368 / 31666 | H28: 32596 / 32368 | I28: 32516 / 32596 | J28: 31562 / 32516 | K28: 31603 / 31562 | L28: 32597 / 0 | M28: 32575 / 0 | N28: 31521 / 0
A29: TVA : dû / payé | C29: 9401 / 14796 | D29: 17286 / 9401 | E29: 9420 / 17286 | F29: 9926 / 9420 | G29: 10617 / 9926 | H29: 9475 / 10617 | I29: 9285 / 9475 | J29: 6198 / 9285 | K29: 8832 / 6198 | L29: 11289 / 8832 | M29: 11227 / 11289 | N29: 26062 / 11227
A32: Lecture : un retard d'environ 1 mois est normal (cotisations payées le mois suivant). Au-delà de 2 mois, dette échue probable : demander la situation du compte à l'organisme et les éventuels plans d'apurement.

Sheet Stock
A1: Stocks : cohérence de la variation, rotation, dépréciation (module d'amorce)
A2: Valeurs calculées par l'application. Le FEC ne donne ni quantités ni prix unitaires : points d'attention à documenter avec l'état d'inventaire valorisé.
A4: Indicateur | B4: 2024 | C4: 2025 | D4: Lecture
A5: Stock brut à l'ouverture (à-nouveaux) | B5: 45000 | C5: 52000
A6: Stock brut à la clôture | B6: 52000 | C6: 61000
A7: Variation au bilan (clôture - ouverture) | B7: 7000 | C7: 9000
A8: Variation au compte de résultat (603x, 713) | B8: 7000 | C8: 9000
A9: Écart (doit être nul) | B9: 0 | C9: 0 | D9: Un écart signifie qu'une écriture de stock a été passée sans sa contrepartie de variation (ou inversement) : à expliquer.
A10: Poids de la variation de stock dans le résultat (valeur absolue) | B10: 0.13624015 | C10: 0.041276868 | D10: Au-delà de 50 % : le résultat dépend surtout de la valorisation du stock.
A11: Dépréciations des stocks (39x) | B11: 0 | C11: 0
A12: Taux de dépréciation | B12: 0 | C12: 0 | D12: À rapprocher de la rotation : rotation lente et dépréciation stable ou en baisse = risque de surévaluation.
A13: Stock total en jours de CA HT | B13: 10 | C13: 15
A15: Matières et approvisionnements
A16: Ouverture | B16: 45000 | C16: 52000
A17: Clôture | B17: 52000 | C17: 61000
A18: Variation au compte de résultat | B18: 7000 | C18: 9000
A19: Écart bilan / résultat | B19: 0 | C19: 0
A20: Dépréciation | B20: 0 | C20: 0
A21: Taux de dépréciation | B21: 0 | C21: 0
A22: Rotation (jours) | B22: 23 | C22: 33 | D22: jours d'achats consommés
A23: Écritures de stock dans l'exercice / dont validées > 120 j après la clôture | B23: 2 / 0 | C23: 2 / 0
A25: À construire (nécessite l'état d'inventaire valorisé)
A26: • Rotation et ancienneté par article ; stock sans mouvement depuis plus de 12 mois.
A27: • Comparaison des prix unitaires d'inventaire aux derniers prix d'achat (surévaluation).
A28: • Écart entre inventaire physique et stock comptable ; provisions par famille.
A29: • Marge du mois de clôture comparée aux autres mois (coupure des achats et des ventes).

Sheet Cloture
A1: Clôture et qualité du résultat
A2: Ce que les écritures d'arrêté des comptes apportent au résultat. Le FEC montre l'écriture, pas sa justification : chaque montant est une question à poser, pas une erreur.
A4: Indicateur | B4: 2024 | C4: 2025 | D4: Lecture
A5: Résultat et écritures de clôture
A6: Résultat net comptable | B6: 51379.86 | C6: -218039.8
A7: Impact des écritures de clôture (onglet Ecritures_cloture) | B7: =SUMIFS(Ecritures_cloture!$I$5:$I$11,Ecritures_cloture!$A$5:$A$11,"2024",Ecritures_cloture!$M$5:$M$11,"Clôture") | C7: =SUMIFS(Ecritures_cloture!$I$5:$I$11,Ecritures_cloture!$A$5:$A$11,"2025",Ecritures_cloture!$M$5:$M$11,"Clôture") | D7: Somme des écritures listées : retirer une ligne de la liste la sort du calcul.
A8: Part du résultat net (valeur absolue) | B8: =IF(ABS(B6)<9660,"résultat proche de zéro",ABS(B7/B6)) | C8: =IF(ABS(C6)<8690,"résultat proche de zéro",ABS(C7/C6)) | D8: Au-delà de 30 % : le résultat dépend surtout des écritures d'inventaire.
A9: Résultat avant écritures de clôture | B9: =B6-B7 | C9: =C6-C7 | D9: Base de départ des retraitements (EBITDA normatif).
A10: dont Variation de stocks | B10: 7000 | C10: 9000
A11: dont Amortissements | B11: -23000 | C11: -23000
A12: dont Impôt sur les bénéfices, crédits d'impôt | B12: -9067.03 | C12: 0
A13: Extournes en début d'exercice (impact résultat) | B13: =SUMIFS(Ecritures_cloture!$I$5:$I$11,Ecritures_cloture!$A$5:$A$11,"2024",Ecritures_cloture!$M$5:$M$11,"Extourne N-1") | C13: =SUMIFS(Ecritures_cloture!$I$5:$I$11,Ecritures_cloture!$A$5:$A$11,"2025",Ecritures_cloture!$M$5:$M$11,"Extourne N-1") | D13: Reprise des écritures de clôture de l'exercice précédent.
A15: Provisions et amortissements
A16: Dotations aux provisions et dépréciations (hors amortissements) | B16: 0 | C16: 0
A17: Reprises de provisions et dépréciations | B17: 0 | C17: 0
A18: Pertes constatées sur créances et comptes courants (654, 664, 6714) | B18: 0 | C18: 0 | D18: Une reprise qui couvre une perte constatée ne soutient pas le résultat.
A19: Reprises nettes des dotations et des pertes (positif = améliore le résultat) | B19: =B17-B16-B18 | C19: =C17-C16-C18 | D19: Positif : le résultat est soutenu par des reprises. Vérifier que le risque a disparu.
A20: Dotations aux amortissements | B20: 23000 | C20: 23000
A21: Immobilisations brutes (20 à 23) | B21: 205000 | C21: 205000
A22: Taux d'amortissement apparent | B22: =IFERROR(B20/B21,"n.d.") | C22: =IFERROR(C20/C21,"n.d.") | D22: Une baisse nette sans cession ni fin d'amortissement peut signaler un allongement des durées.
A24: Comptes de régularisation (solde présenté en positif)
A26: Produits sans encaissement et exceptionnel
A27: Production immobilisée (72) | B27: 0 | C27: 0
A28: Transferts de charges (791) | B28: 0 | C28: 0
A29: Crédits d'impôt en produit (CIR, CII…) | B29: 0 | C29: 0
A30: Variation de stock (hausse = produit) | B30: 7000 | C30: 9000
A31: Total produits sans encaissement | B31: =SUM(B27:B30) | C31: =SUM(C27:C30)
A32: Résultat exceptionnel (77 − 67) | B32: 0 | C32: 0
A33: dont apurement du passif, abandons de créances (libellés) | B33: 0 | C33: 0 | D33: Détection par libellé : à confirmer.
A34: Résultat hors exceptionnel | B34: =B6-B32 | C34: =C6-C32
A36: Coupure
A37: CA comptabilisé hors journal de ventes | B37: 0 | C37: 0
A38: Ventes des 5 derniers jours / moyenne (×) | B38: 1.2 | C38: 5.3 | D38: Au-delà de 2× : facturation anticipée possible ; voir aussi les avoirs émis après la clôture (onglet Creances).
A39: Achats des 5 derniers jours / moyenne (×) | B39: 2.1 | C39: 2.6 | D39: Très bas sans factures non parvenues : charges manquantes possibles.
A41: Points d'attention
A42: 2024 · À documenter | B42: Écritures de clôture : -25 067 € sur le résultat (49 % du résultat net). Résultat avant ces écritures : 76 447 €. Demander le détail et les justificatifs des principales écritures (liste dans l'Excel, onglet Cloture).
A43: 2024 · Info | B43: 3 écriture(s) de clôture en montant rond (multiple de 1 000 €), 120 000 € au total : estimations à documenter.
A44: 2025 · À documenter | B44: Créances clients hors groupe de plus de 180 jours : 25 113 €, dépréciées à 0 € (0 %). Faible couverture : demander l'analyse du recouvrement.
A45: 2025 · Info | B45: 3 écriture(s) de clôture en montant rond (multiple de 1 000 €), 136 000 € au total : estimations à documenter.
A47: Principales écritures exceptionnelles (toutes écritures de l'exercice)
A48: Exercice · libellé | B48: Date | C48: Impact résultat | D48: Journal / N°

Sheet Ecritures_cloture
A1: Écritures de clôture ayant un impact sur le résultat
A2: Journaux d'inventaire et d'extourne, opérations diverses des 15 derniers jours ou validées plus de 30 jours après la clôture. Colonnes K et L (jaunes) : statut et commentaire à renseigner avec le dirigeant.
A4: Exercice | B4: Journal | C4: N° écriture | D4: Date | E4: Validée le | F4: Libellé | G4: Comptes | H4: Nature principale | I4: Impact résultat | J4: Montant rond | K4: Statut | L4: Commentaire | M4: Type
A5: 2024 | B5: INV | C5: INV00002 | D5: 45657 | E5: 45659 | F5: Stock final au 31/12/2024 | G5: 310000 603100 | H5: Variation de stocks | I5: 52000 | J5: oui | K5: À documenter | M5: Clôture
A6: 2024 | B6: INV | C6: INV00001 | D6: 45657 | E6: 45662 | F6: Annulation stock initial 2024 | G6: 603100 310000 | H6: Variation de stocks | I6: -45000 | J6: oui | K6: À documenter | M6: Clôture
A7: 2024 | B7: OD | C7: OD00013 | D7: 45657 | E7: 45668 | F7: Dotations aux amortissements 2024 | G7: 681120 281540 281830 | H7: Amortissements | I7: -23000 | J7: oui | K7: À documenter | M7: Clôture
A8: 2024 | B8: OD | C8: OD00014 | D8: 45657 | E8: 45674 | F8: Impot sur les societes 2024 | G8: 695000 444000 | H8: Impôt sur les bénéfices, crédits d'impôt | I8: -9067.03 | K8: À documenter | M8: Clôture
A9: 2025 | B9: INV | C9: INV00002 | D9: 46022 | E9: 46033 | F9: Stock final au 31/12/2025 | G9: 310000 603100 | H9: Variation de stocks | I9: 61000 | J9: oui | K9: À documenter | M9: Clôture
A10: 2025 | B10: INV | C10: INV00001 | D10: 46022 | E10: 46035 | F10: Annulation stock initial 2025 | G10: 603100 310000 | H10: Variation de stocks | I10: -52000 | J10: oui | K10: À documenter | M10: Clôture
A11: 2025 | B11: OD | C11: OD00015 | D11: 46022 | E11: 46030 | F11: Dotations aux amortissements 2025 | G11: 681120 281540 281830 | H11: Amortissements | I11: -23000 | J11: oui | K11: À documenter | M11: Clôture

Sheet Tiers
A1: Clients et fournisseurs — 2025 (au 31/12/2025)
A2: Valeurs calculées par l'application (non recalculées dans Excel). Ancienneté depuis la date de pièce (échéances absentes du FEC) ; règlements imputés sur les pièces les plus anciennes.
A4: Top 15 clients (débits des comptes clients dans les journaux de ventes)
A5: Tiers | B5: Facturé TTC | C5: % du total | D5: % cumulé
A6: Agence Mobilis | B6: 366693.29 | C6: 0.20103799 | D6: 0.20103799
A7: Coworking Atelier 9 | B7: 329276.77 | C7: 0.18052455 | D7: 0.38156254
A8: Hotel Les Tilleuls | B8: 271953.95 | C8: 0.14909756 | D8: 0.5306601
A9: Boutique Hetre et Chene | B9: 217667.28 | C9: 0.11933513 | D9: 0.64999523
A10: Clinique du Parc | B10: 182688.38 | C10: 0.1001581 | D10: 0.75015334
A11: Cabinet Varenne Associes | B11: 174621.02 | C11: 0.095735209 | D11: 0.84588855
A12: Restaurant Le Comptoir | B12: 152247.37 | C12: 0.083468954 | D12: 0.9293575
A13: Residence Bel Air | B13: 128851.92 | C13: 0.070642501 | D13: 1
A14: Total (8 tiers) | B14: 1824000
A16: Top 15 fournisseurs (crédits des comptes fournisseurs dans les journaux d'achats)
A17: Tiers | B17: Facturé TTC | C17: % du total | D17: % cumulé
A18: Scierie du Nord | B18: 398540.74 | C18: 0.38667275 | D18: 0.38667275
A19: Quincaillerie Pro Est | B19: 230860.41 | C19: 0.22398571 | D19: 0.61065845
A20: Vernis et Finitions | B20: 188998.86 | C20: 0.18337074 | D20: 0.79402919
A21: SCI Les Halles | B21: 122400 | C21: 0.1187551 | D21: 0.91278429
A22: Energie Plus | B22: 42180.59 | C22: 0.04092451 | D22: 0.9537088
A23: Cabinet Comptable Exemple | B23: 28800 | C23: 0.027942376 | D23: 0.98165117
A24: Assurances Mutuelles Exemple | B24: 12000 | C24: 0.011642657 | D24: 0.99329383
A25: Telecom Pro | B25: 6912 | C25: 0.0067061702 | D25: 1
A26: Total (8 tiers) | B26: 1030692.6
A28: Balance âgée clients (postes non lettrés au 31/12/2025)
A29: Tiers | B29: Solde ouvert | C29: 0-30 j | D29: 31-60 j | E29: 61-90 j | F29: 91-180 j | G29: > 180 j | H29: Trop-perçu / non imputé | I29: Dont > 90 j
A30: Agence Mobilis | B30: 178027.53 | C30: 96000 | D30: 52195.22 | E30: 29832.31 | F30: 0 | G30: 0 | H30: 0 | I30: =IF(B30<=0,0,(F30+G30)/B30)
A31: Clinique du Parc | B31: 125096.26 | C31: 24656.02 | D31: 18815.21 | E31: 33625.03 | F31: 0 | G31: 48000 | H31: 0 | I31: =IF(B31<=0,0,(F31+G31)/B31)
A32: Hotel Les Tilleuls | B32: 67575.82 | C32: 42716.25 | D32: 24859.57 | E32: 0 | F32: 0 | G32: 0 | H32: 0 | I32: =IF(B32<=0,0,(F32+G32)/B32)
A33: Coworking Atelier 9 | B33: 65068.93 | C33: 35897.09 | D33: 29171.84 | E33: 0 | F33: 0 | G33: 0 | H33: 0 | I33: =IF(B33<=0,0,(F33+G33)/B33)
A34: Cabinet Varenne Associes | B34: 50730.63 | C34: 50730.63 | D34: 0 | E34: 0 | F34: 0 | G34: 0 | H34: 0 | I34: =IF(B34<=0,0,(F34+G34)/B34)
A35: Boutique Hetre et Chene | B35: 28958.15 | C35: 0 | D35: 28958.15 | E35: 0 | F35: 0 | G35: 0 | H35: 0 | I35: =IF(B35<=0,0,(F35+G35)/B35)
A36: TOTAL | B36: =SUM(B30:B35) | C36: =SUM(C30:C35) | D36: =SUM(D30:D35) | E36: =SUM(E30:E35) | F36: =SUM(F30:F35) | G36: =SUM(G30:G35) | H36: =SUM(H30:H35) | I36: =IF(B36<=0,0,(F36+G36)/B36)
A39: Balance âgée fournisseurs (postes non lettrés au 31/12/2025)
A40: Tiers | B40: Solde ouvert | C40: 0-30 j | D40: 31-60 j | E40: 61-90 j | F40: 91-180 j | G40: > 180 j | H40: Trop-perçu / non imputé | I40: Dont > 90 j
A41: Scierie du Nord | B41: 144759.99 | C41: 72380 | D41: 72379.99 | E41: 0 | F41: 0 | G41: 0 | H41: 0 | I41: =IF(B41<=0,0,(F41+G41)/B41)
A42: Quincaillerie Pro Est | B42: 21276.26 | C42: 0 | D42: 0 | E42: 21276.26 | F42: 0 | G42: 0 | H42: 0 | I42: =IF(B42<=0,0,(F42+G42)/B42)
A43: Vernis et Finitions | B43: 14400 | C43: 0 | D43: 0 | E43: 0 | F43: 0 | G43: 14400 | H43: 0 | I43: =IF(B43<=0,0,(F43+G43)/B43)
A44: SCI Les Halles | B44: 10200 | C44: 10200 | D44: 0 | E44: 0 | F44: 0 | G44: 0 | H44: 0 | I44: =IF(B44<=0,0,(F44+G44)/B44)
A45: Cabinet Comptable Exemple | B45: 8300 | C45: 7200 | D45: 0 | E45: 0 | F45: 1100 | G45: 0 | H45: 0 | I45: =IF(B45<=0,0,(F45+G45)/B45)
A46: Energie Plus | B46: 3274.58 | C46: 3274.58 | D46: 0 | E46: 0 | F46: 0 | G46: 0 | H46: 0 | I46: =IF(B46<=0,0,(F46+G46)/B46)
A47: Telecom Pro | B47: 576 | C47: 576 | D47: 0 | E47: 0 | F47: 0 | G47: 0 | H47: 0 | I47: =IF(B47<=0,0,(F47+G47)/B47)
A48: TOTAL | B48: =SUM(B41:B47) | C48: =SUM(C41:C47) | D48: =SUM(D41:D47) | E48: =SUM(E41:E47) | F48: =SUM(F41:F47) | G48: =SUM(G41:G47) | H48: =SUM(H41:H47) | I48: =IF(B48<=0,0,(F48+G48)/B48)

Sheet Liasse
A1: Rapprochement FEC / liasse fiscale
A2: Colonnes « Liasse » : montants lus automatiquement dans le PDF (bleu, modifiables). Tolérance d'arrondi : 1 € par ligne, 3 € sur les totaux.
A4: Code | B4: Poste | C4: Formulaire | D4: Groupe | E4: Sens | F4: Liasse 2024 | G4: FEC 2024 | H4: Écart 2024 | I4: Statut 2024 | J4: Liasse 2025 | K4: FEC 2025 | L4: Écart 2025 | M4: Statut 2025
A5: AR | B5: Installations techniques, matériel et outillage | C5: 2050 | D5: ACTIF_BRUT | E5: 1 | G5: =1*SUMIFS(Comptes!$F$5:$F$42,Comptes!$G$5:$G$42,$A5) | H5: =G5-F5 | I5: n.d. | K5: =1*SUMIFS(Comptes!$I$5:$I$42,Comptes!$J$5:$J$42,$A5) | L5: =K5-J5 | M5: n.d.
A6: AS | B6: Amort. installations techniques | C6: 2050 | D6: AMORT | E6: -1 | G6: =-1*SUMIFS(Comptes!$F$5:$F$42,Comptes!$G$5:$G$42,$A6) | H6: =G6-F6 | I6: n.d. | K6: =-1*SUMIFS(Comptes!$I$5:$I$42,Comptes!$J$5:$J$42,$A6) | L6: =K6-J6 | M6: n.d.
A7: AT | B7: Autres immobilisations corporelles | C7: 2050 | D7: ACTIF_BRUT | E7: 1 | G7: =1*SUMIFS(Comptes!$F$5:$F$42,Comptes!$G$5:$G$42,$A7) | H7: =G7-F7 | I7: n.d. | K7: =1*SUMIFS(Comptes!$I$5:$I$42,Comptes!$J$5:$J$42,$A7) | L7: =K7-J7 | M7: n.d.
A8: AU | B8: Amort. autres immo. corporelles | C8: 2050 | D8: AMORT | E8: -1 | G8: =-1*SUMIFS(Comptes!$F$5:$F$42,Comptes!$G$5:$G$42,$A8) | H8: =G8-F8 | I8: n.d. | K8: =-1*SUMIFS(Comptes!$I$5:$I$42,Comptes!$J$5:$J$42,$A8) | L8: =K8-J8 | M8: n.d.
A9: BL | B9: Matières premières, approvisionnements | C9: 2050 | D9: ACTIF_BRUT | E9: 1 | G9: =1*SUMIFS(Comptes!$F$5:$F$42,Comptes!$G$5:$G$42,$A9) | H9: =G9-F9 | I9: n.d. | K9: =1*SUMIFS(Comptes!$I$5:$I$42,Comptes!$J$5:$J$42,$A9) | L9: =K9-J9 | M9: n.d.
A10: BX | B10: Clients et comptes rattachés | C10: 2050 | D10: ACTIF_BRUT | E10: 1 | G10: =1*SUMIFS(Comptes!$F$5:$F$42,Comptes!$G$5:$G$42,$A10) | H10: =G10-F10 | I10: n.d. | K10: =1*SUMIFS(Comptes!$I$5:$I$42,Comptes!$J$5:$J$42,$A10) | L10: =K10-J10 | M10: n.d.
A11: BZ | B11: Autres créances | C11: 2050 | D11: ACTIF_BRUT | E11: 1 | G11: =1*SUMIFS(Comptes!$F$5:$F$42,Comptes!$G$5:$G$42,$A11) | H11: =G11-F11 | I11: n.d. | K11: =1*SUMIFS(Comptes!$I$5:$I$42,Comptes!$J$5:$J$42,$A11) | L11: =K11-J11 | M11: n.d.
A12: CF | B12: Disponibilités | C12: 2050 | D12: ACTIF_BRUT | E12: 1 | G12: =1*SUMIFS(Comptes!$F$5:$F$42,Comptes!$G$5:$G$42,$A12) | H12: =G12-F12 | I12: n.d. | K12: =1*SUMIFS(Comptes!$I$5:$I$42,Comptes!$J$5:$J$42,$A12) | L12: =K12-J12 | M12: n.d.
A13: DA | B13: Capital social | C13: 2051 | D13: PASSIF | E13: -1 | G13: =-1*SUMIFS(Comptes!$F$5:$F$42,Comptes!$G$5:$G$42,$A13) | H13: =G13-F13 | I13: n.d. | K13: =-1*SUMIFS(Comptes!$I$5:$I$42,Comptes!$J$5:$J$42,$A13) | L13: =K13-J13 | M13: n.d.
A14: DD | B14: Réserve légale | C14: 2051 | D14: PASSIF | E14: -1 | G14: =-1*SUMIFS(Comptes!$F$5:$F$42,Comptes!$G$5:$G$42,$A14) | H14: =G14-F14 | I14: n.d. | K14: =-1*SUMIFS(Comptes!$I$5:$I$42,Comptes!$J$5:$J$42,$A14) | L14: =K14-J14 | M14: n.d.
A15: DH | B15: Report à nouveau | C15: 2051 | D15: PASSIF | E15: -1 | G15: =-1*SUMIFS(Comptes!$F$5:$F$42,Comptes!$G$5:$G$42,$A15) | H15: =G15-F15 | I15: n.d. | K15: =-1*SUMIFS(Comptes!$I$5:$I$42,Comptes!$J$5:$J$42,$A15) | L15: =K15-J15 | M15: n.d.
A16: DI | B16: Résultat de l'exercice | C16: 2051 | D16: PASSIF | E16: -1 | G16: =-SUMIFS(Comptes!$F$5:$F$42,Comptes!$A$5:$A$42,"6*")-SUMIFS(Comptes!$F$5:$F$42,Comptes!$A$5:$A$42,"7*") | H16: =G16-F16 | I16: n.d. | K16: =-SUMIFS(Comptes!$I$5:$I$42,Comptes!$A$5:$A$42,"6*")-SUMIFS(Comptes!$I$5:$I$42,Comptes!$A$5:$A$42,"7*") | L16: =K16-J16 | M16: n.d.
A17: DU | B17: Emprunts et dettes auprès des établissements de crédit | C17: 2051 | D17: PASSIF | E17: -1 | G17: =-1*SUMIFS(Comptes!$F$5:$F$42,Comptes!$G$5:$G$42,$A17) | H17: =G17-F17 | I17: n.d. | K17: =-1*SUMIFS(Comptes!$I$5:$I$42,Comptes!$J$5:$J$42,$A17) | L17: =K17-J17 | M17: n.d.
A18: DV | B18: Emprunts et dettes financières divers | C18: 2051 | D18: PASSIF | E18: -1 | G18: =-1*SUMIFS(Comptes!$F$5:$F$42,Comptes!$G$5:$G$42,$A18) | H18: =G18-F18 | I18: n.d. | K18: =-1*SUMIFS(Comptes!$I$5:$I$42,Comptes!$J$5:$J$42,$A18) | L18: =K18-J18 | M18: n.d.
A19: DX | B19: Dettes fournisseurs | C19: 2051 | D19: PASSIF | E19: -1 | G19: =-1*SUMIFS(Comptes!$F$5:$F$42,Comptes!$G$5:$G$42,$A19) | H19: =G19-F19 | I19: n.d. | K19: =-1*SUMIFS(Comptes!$I$5:$I$42,Comptes!$J$5:$J$42,$A19) | L19: =K19-J19 | M19: n.d.
A20: DY | B20: Dettes fiscales et sociales | C20: 2051 | D20: PASSIF | E20: -1 | G20: =-1*SUMIFS(Comptes!$F$5:$F$42,Comptes!$G$5:$G$42,$A20) | H20: =G20-F20 | I20: n.d. | K20: =-1*SUMIFS(Comptes!$I$5:$I$42,Comptes!$J$5:$J$42,$A20) | L20: =K20-J20 | M20: n.d.
A21: EA | B21: Autres dettes | C21: 2051 | D21: PASSIF | E21: -1 | G21: =-1*SUMIFS(Comptes!$F$5:$F$42,Comptes!$G$5:$G$42,$A21) | H21: =G21-F21 | I21: n.d. | K21: =-1*SUMIFS(Comptes!$I$5:$I$42,Comptes!$J$5:$J$42,$A21) | L21: =K21-J21 | M21: n.d.
A22: FF | B22: Production vendue - biens | C22: 2052 | D22: PROD_EXPL | E22: -1 | G22: =-1*SUMIFS(Comptes!$F$5:$F$42,Comptes!$G$5:$G$42,$A22) | H22: =G22-F22 | I22: n.d. | K22: =-1*SUMIFS(Comptes!$I$5:$I$42,Comptes!$J$5:$J$42,$A22) | L22: =K22-J22 | M22: n.d.
A23: FU | B23: Achats de matières premières et approvisionnements | C23: 2052 | D23: CHG_EXPL | E23: 1 | G23: =1*SUMIFS(Comptes!$F$5:$F$42,Comptes!$G$5:$G$42,$A23) | H23: =G23-F23 | I23: n.d. | K23: =1*SUMIFS(Comptes!$I$5:$I$42,Comptes!$J$5:$J$42,$A23) | L23: =K23-J23 | M23: n.d.
A24: FV | B24: Variation de stocks (matières) | C24: 2052 | D24: CHG_EXPL | E24: 1 | G24: =1*SUMIFS(Comptes!$F$5:$F$42,Comptes!$G$5:$G$42,$A24) | H24: =G24-F24 | I24: n.d. | K24: =1*SUMIFS(Comptes!$I$5:$I$42,Comptes!$J$5:$J$42,$A24) | L24: =K24-J24 | M24: n.d.
A25: FW | B25: Autres achats et charges externes | C25: 2052 | D25: CHG_EXPL | E25: 1 | G25: =1*SUMIFS(Comptes!$F$5:$F$42,Comptes!$G$5:$G$42,$A25) | H25: =G25-F25 | I25: n.d. | K25: =1*SUMIFS(Comptes!$I$5:$I$42,Comptes!$J$5:$J$42,$A25) | L25: =K25-J25 | M25: n.d.
A26: FX | B26: Impôts, taxes et versements assimilés | C26: 2052 | D26: CHG_EXPL | E26: 1 | G26: =1*SUMIFS(Comptes!$F$5:$F$42,Comptes!$G$5:$G$42,$A26) | H26: =G26-F26 | I26: n.d. | K26: =1*SUMIFS(Comptes!$I$5:$I$42,Comptes!$J$5:$J$42,$A26) | L26: =K26-J26 | M26: n.d.
A27: FY | B27: Salaires et traitements | C27: 2052 | D27: CHG_EXPL | E27: 1 | G27: =1*SUMIFS(Comptes!$F$5:$F$42,Comptes!$G$5:$G$42,$A27) | H27: =G27-F27 | I27: n.d. | K27: =1*SUMIFS(Comptes!$I$5:$I$42,Comptes!$J$5:$J$42,$A27) | L27: =K27-J27 | M27: n.d.
A28: FZ | B28: Charges sociales | C28: 2052 | D28: CHG_EXPL | E28: 1 | G28: =1*SUMIFS(Comptes!$F$5:$F$42,Comptes!$G$5:$G$42,$A28) | H28: =G28-F28 | I28: n.d. | K28: =1*SUMIFS(Comptes!$I$5:$I$42,Comptes!$J$5:$J$42,$A28) | L28: =K28-J28 | M28: n.d.
A29: GA | B29: Dotations aux amortissements | C29: 2052 | D29: CHG_EXPL | E29: 1 | G29: =1*SUMIFS(Comptes!$F$5:$F$42,Comptes!$G$5:$G$42,$A29) | H29: =G29-F29 | I29: n.d. | K29: =1*SUMIFS(Comptes!$I$5:$I$42,Comptes!$J$5:$J$42,$A29) | L29: =K29-J29 | M29: n.d.
A30: GR | B30: Intérêts et charges assimilées | C30: 2052 | D30: CHG_FIN | E30: 1 | G30: =1*SUMIFS(Comptes!$F$5:$F$42,Comptes!$G$5:$G$42,$A30) | H30: =G30-F30 | I30: n.d. | K30: =1*SUMIFS(Comptes!$I$5:$I$42,Comptes!$J$5:$J$42,$A30) | L30: =K30-J30 | M30: n.d.
A31: HK | B31: Impôts sur les bénéfices | C31: 2053 | D31: IS_PART | E31: 1 | G31: =1*SUMIFS(Comptes!$F$5:$F$42,Comptes!$G$5:$G$42,$A31) | H31: =G31-F31 | I31: n.d. | K31: =1*SUMIFS(Comptes!$I$5:$I$42,Comptes!$J$5:$J$42,$A31) | L31: =K31-J31 | M31: n.d.
A33: Totaux
A34: CO | B34: TOTAL ACTIF BRUT | C34: total 2050 | G34: =SUMIFS($G$5:$G$31,$D$5:$D$31,"ACTIF_BRUT") | H34: =G34-F34 | I34: n.d. | K34: =SUMIFS($K$5:$K$31,$D$5:$D$31,"ACTIF_BRUT") | L34: =K34-J34 | M34: n.d.
A35: EE | B35: TOTAL PASSIF (= actif net) | C35: total 2050 | G35: =SUMIFS($G$5:$G$31,$D$5:$D$31,"PASSIF") | H35: =G35-F35 | I35: n.d. | K35: =SUMIFS($K$5:$K$31,$D$5:$D$31,"PASSIF") | L35: =K35-J35 | M35: n.d.
A36: FR | B36: Total produits d'exploitation | C36: total 2050 | G36: =SUMIFS($G$5:$G$31,$D$5:$D$31,"PROD_EXPL") | H36: =G36-F36 | I36: n.d. | K36: =SUMIFS($K$5:$K$31,$D$5:$D$31,"PROD_EXPL") | L36: =K36-J36 | M36: n.d.
A37: GF | B37: Total charges d'exploitation | C37: total 2050 | G37: =SUMIFS($G$5:$G$31,$D$5:$D$31,"CHG_EXPL") | H37: =G37-F37 | I37: n.d. | K37: =SUMIFS($K$5:$K$31,$D$5:$D$31,"CHG_EXPL") | L37: =K37-J37 | M37: n.d.
A38: GG | B38: Résultat d'exploitation | C38: total 2050 | G38: =SUMIFS($G$5:$G$31,$D$5:$D$31,"PROD_EXPL")-SUMIFS($G$5:$G$31,$D$5:$D$31,"CHG_EXPL") | H38: =G38-F38 | I38: n.d. | K38: =SUMIFS($K$5:$K$31,$D$5:$D$31,"PROD_EXPL")-SUMIFS($K$5:$K$31,$D$5:$D$31,"CHG_EXPL") | L38: =K38-J38 | M38: n.d.
A39: GV | B39: Résultat financier | C39: total 2050 | G39: =SUMIFS($G$5:$G$31,$D$5:$D$31,"PROD_FIN")-SUMIFS($G$5:$G$31,$D$5:$D$31,"CHG_FIN") | H39: =G39-F39 | I39: n.d. | K39: =SUMIFS($K$5:$K$31,$D$5:$D$31,"PROD_FIN")-SUMIFS($K$5:$K$31,$D$5:$D$31,"CHG_FIN") | L39: =K39-J39 | M39: n.d.
A40: HD | B40: Total produits exceptionnels | C40: total 2050 | G40: =SUMIFS($G$5:$G$31,$D$5:$D$31,"PROD_EXC") | H40: =G40-F40 | I40: n.d. | K40: =SUMIFS($K$5:$K$31,$D$5:$D$31,"PROD_EXC") | L40: =K40-J40 | M40: n.d.
A41: HH | B41: Total charges exceptionnelles | C41: total 2050 | G41: =SUMIFS($G$5:$G$31,$D$5:$D$31,"CHG_EXC") | H41: =G41-F41 | I41: n.d. | K41: =SUMIFS($K$5:$K$31,$D$5:$D$31,"CHG_EXC") | L41: =K41-J41 | M41: n.d.
A42: HI | B42: Résultat exceptionnel | C42: total 2050 | G42: =SUMIFS($G$5:$G$31,$D$5:$D$31,"PROD_EXC")-SUMIFS($G$5:$G$31,$D$5:$D$31,"CHG_EXC") | H42: =G42-F42 | I42: n.d. | K42: =SUMIFS($K$5:$K$31,$D$5:$D$31,"PROD_EXC")-SUMIFS($K$5:$K$31,$D$5:$D$31,"CHG_EXC") | L42: =K42-J42 | M42: n.d.
A43: HN | B43: Bénéfice ou perte | C43: total 2050 | G43: =SUMIFS($G$5:$G$31,$D$5:$D$31,"PROD_EXPL")-SUMIFS($G$5:$G$31,$D$5:$D$31,"CHG_EXPL")+SUMIFS($G$5:$G$31,$D$5:$D$31,"PROD_FIN")-SUMIFS($G$5:$G$31,$D$5:$D$31,"CHG_FIN")+SUMIFS($G$5:$G$31,$D$5:$D$31,"PROD_EXC")-SUMIFS($G$5:$G$31,$D$5:$D$31,"CHG_EXC")-SUMIFS($G$5:$G$31,$D$5:$D$31,"IS_PART") | H43: =G43-F43 | I43: n.d. | K43: =SUMIFS($K$5:$K$31,$D$5:$D$31,"PROD_EXPL")-SUMIFS($K$5:$K$31,$D$5:$D$31,"CHG_EXPL")+SUMIFS($K$5:$K$31,$D$5:$D$31,"PROD_FIN")-SUMIFS($K$5:$K$31,$D$5:$D$31,"CHG_FIN")+SUMIFS($K$5:$K$31,$D$5:$D$31,"PROD_EXC")-SUMIFS($K$5:$K$31,$D$5:$D$31,"CHG_EXC")-SUMIFS($K$5:$K$31,$D$5:$D$31,"IS_PART") | L43: =K43-J43 | M43: n.d.
A44: ACTIF NET | B44: Actif brut - amortissements et dépréciations (= total passif) | G44: =G34-SUMIFS($G$5:$G$31,$D$5:$D$31,"AMORT") | H44: =G44-F44 | I44: n.d. | K44: =K34-SUMIFS($K$5:$K$31,$D$5:$D$31,"AMORT") | L44: =K44-J44 | M44: n.d.

Sheet Comptes
A1: Balance des comptes et affectation
A2: Soldes recalculés depuis chaque FEC. Surcharges (D, E, jaunes) : uniquement pour corriger une affectation propre au dossier.
A4: Compte | B4: Libellé | C4: Racine retenue | D4: Surcharge poste liasse | E4: Surcharge agrégat | F4: Solde 2024 | G4: Poste 2024 | H4: Agrégat 2024 | I4: Solde 2025 | J4: Poste 2025 | K4: Agrégat 2025
A5: 101300 | B5: Capital souscrit appele verse | C5: =IF(ISNUMBER(MATCH(LEFT($A5,4),Referentiel!$A$5:$A$193,0)),LEFT($A5,4),IF(ISNUMBER(MATCH(LEFT($A5,3),Referentiel!$A$5:$A$193,0)),LEFT($A5,3),IF(ISNUMBER(MATCH(LEFT($A5,2),Referentiel!$A$5:$A$193,0)),LEFT($A5,2),"NON MAPPÉ"))) | F5: =ROUND(SUMIFS(FEC_2024!$I:$I,FEC_2024!$E:$E,$A5)-SUMIFS(FEC_2024!$J:$J,FEC_2024!$E:$E,$A5),2) | G5: =IF($D5<>"",$D5,IF($C5="NON MAPPÉ","?",IF(F5>=0,INDEX(Referentiel!$C$5:$C$193,MATCH($C5,Referentiel!$A$5:$A$193,0)),INDEX(Referentiel!$D$5:$D$193,MATCH($C5,Referentiel!$A$5:$A$193,0))))) | H5: =IF($E5<>"",$E5,IF($C5="NON MAPPÉ","?",IF(F5>=0,INDEX(Referentiel!$E$5:$E$193,MATCH($C5,Referentiel!$A$5:$A$193,0)),INDEX(Referentiel!$F$5:$F$193,MATCH($C5,Referentiel!$A$5:$A$193,0))))) | I5: =ROUND(SUMIFS(FEC_2025!$I:$I,FEC_2025!$E:$E,$A5)-SUMIFS(FEC_2025!$J:$J,FEC_2025!$E:$E,$A5),2) | J5: =IF($D5<>"",$D5,IF($C5="NON MAPPÉ","?",IF(I5>=0,INDEX(Referentiel!$C$5:$C$193,MATCH($C5,Referentiel!$A$5:$A$193,0)),INDEX(Referentiel!$D$5:$D$193,MATCH($C5,Referentiel!$A$5:$A$193,0))))) | K5: =IF($E5<>"",$E5,IF($C5="NON MAPPÉ","?",IF(I5>=0,INDEX(Referentiel!$E$5:$E$193,MATCH($C5,Referentiel!$A$5:$A$193,0)),INDEX(Referentiel!$F$5:$F$193,MATCH($C5,Referentiel!$A$5:$A$193,0)))))
A6: 106100 | B6: Reserve legale | C6: =IF(ISNUMBER(MATCH(LEFT($A6,4),Referentiel!$A$5:$A$193,0)),LEFT($A6,4),IF(ISNUMBER(MATCH(LEFT($A6,3),Referentiel!$A$5:$A$193,0)),LEFT($A6,3),IF(ISNUMBER(MATCH(LEFT($A6,2),Referentiel!$A$5:$A$193,0)),LEFT($A6,2),"NON MAPPÉ"))) | F6: =ROUND(SUMIFS(FEC_2024!$I:$I,FEC_2024!$E:$E,$A6)-SUMIFS(FEC_2024!$J:$J,FEC_2024!$E:$E,$A6),2) | G6: =IF($D6<>"",$D6,IF($C6="NON MAPPÉ","?",IF(F6>=0,INDEX(Referentiel!$C$5:$C$193,MATCH($C6,Referentiel!$A$5:$A$193,0)),INDEX(Referentiel!$D$5:$D$193,MATCH($C6,Referentiel!$A$5:$A$193,0))))) | H6: =IF($E6<>"",$E6,IF($C6="NON MAPPÉ","?",IF(F6>=0,INDEX(Referentiel!$E$5:$E$193,MATCH($C6,Referentiel!$A$5:$A$193,0)),INDEX(Referentiel!$F$5:$F$193,MATCH($C6,Referentiel!$A$5:$A$193,0))))) | I6: =ROUND(SUMIFS(FEC_2025!$I:$I,FEC_2025!$E:$E,$A6)-SUMIFS(FEC_2025!$J:$J,FEC_2025!$E:$E,$A6),2) | J6: =IF($D6<>"",$D6,IF($C6="NON MAPPÉ","?",IF(I6>=0,INDEX(Referentiel!$C$5:$C$193,MATCH($C6,Referentiel!$A$5:$A$193,0)),INDEX(Referentiel!$D$5:$D$193,MATCH($C6,Referentiel!$A$5:$A$193,0))))) | K6: =IF($E6<>"",$E6,IF($C6="NON MAPPÉ","?",IF(I6>=0,INDEX(Referentiel!$E$5:$E$193,MATCH($C6,Referentiel!$A$5:$A$193,0)),INDEX(Referentiel!$F$5:$F$193,MATCH($C6,Referentiel!$A$5:$A$193,0)))))
A7: 110000 | B7: Report a nouveau | C7: =IF(ISNUMBER(MATCH(LEFT($A7,4),Referentiel!$A$5:$A$193,0)),LEFT($A7,4),IF(ISNUMBER(MATCH(LEFT($A7,3),Referentiel!$A$5:$A$193,0)),LEFT($A7,3),IF(ISNUMBER(MATCH(LEFT($A7,2),Referentiel!$A$5:$A$193,0)),LEFT($A7,2),"NON MAPPÉ"))) | F7: =ROUND(SUMIFS(FEC_2024!$I:$I,FEC_2024!$E:$E,$A7)-SUMIFS(FEC_2024!$J:$J,FEC_2024!$E:$E,$A7),2) | G7: =IF($D7<>"",$D7,IF($C7="NON MAPPÉ","?",IF(F7>=0,INDEX(Referentiel!$C$5:$C$193,MATCH($C7,Referentiel!$A$5:$A$193,0)),INDEX(Referentiel!$D$5:$D$193,MATCH($C7,Referentiel!$A$5:$A$193,0))))) | H7: =IF($E7<>"",$E7,IF($C7="NON MAPPÉ","?",IF(F7>=0,INDEX(Referentiel!$E$5:$E$193,MATCH($C7,Referentiel!$A$5:$A$193,0)),INDEX(Referentiel!$F$5:$F$193,MATCH($C7,Referentiel!$A$5:$A$193,0))))) | I7: =ROUND(SUMIFS(FEC_2025!$I:$I,FEC_2025!$E:$E,$A7)-SUMIFS(FEC_2025!$J:$J,FEC_2025!$E:$E,$A7),2) | J7: =IF($D7<>"",$D7,IF($C7="NON MAPPÉ","?",IF(I7>=0,INDEX(Referentiel!$C$5:$C$193,MATCH($C7,Referentiel!$A$5:$A$193,0)),INDEX(Referentiel!$D$5:$D$193,MATCH($C7,Referentiel!$A$5:$A$193,0))))) | K7: =IF($E7<>"",$E7,IF($C7="NON MAPPÉ","?",IF(I7>=0,INDEX(Referentiel!$E$5:$E$193,MATCH($C7,Referentiel!$A$5:$A$193,0)),INDEX(Referentiel!$F$5:$F$193,MATCH($C7,Referentiel!$A$5:$A$193,0)))))
A8: 120000 | B8: Resultat de l'exercice | C8: =IF(ISNUMBER(MATCH(LEFT($A8,4),Referentiel!$A$5:$A$193,0)),LEFT($A8,4),IF(ISNUMBER(MATCH(LEFT($A8,3),Referentiel!$A$5:$A$193,0)),LEFT($A8,3),IF(ISNUMBER(MATCH(LEFT($A8,2),Referentiel!$A$5:$A$193,0)),LEFT($A8,2),"NON MAPPÉ"))) | F8: =ROUND(SUMIFS(FEC_2024!$I:$I,FEC_2024!$E:$E,$A8)-SUMIFS(FEC_2024!$J:$J,FEC_2024!$E:$E,$A8),2) | G8: =IF($D8<>"",$D8,IF($C8="NON MAPPÉ","?",IF(F8>=0,INDEX(Referentiel!$C$5:$C$193,MATCH($C8,Referentiel!$A$5:$A$193,0)),INDEX(Referentiel!$D$5:$D$193,MATCH($C8,Referentiel!$A$5:$A$193,0))))) | H8: =IF($E8<>"",$E8,IF($C8="NON MAPPÉ","?",IF(F8>=0,INDEX(Referentiel!$E$5:$E$193,MATCH($C8,Referentiel!$A$5:$A$193,0)),INDEX(Referentiel!$F$5:$F$193,MATCH($C8,Referentiel!$A$5:$A$193,0))))) | I8: =ROUND(SUMIFS(FEC_2025!$I:$I,FEC_2025!$E:$E,$A8)-SUMIFS(FEC_2025!$J:$J,FEC_2025!$E:$E,$A8),2) | J8: =IF($D8<>"",$D8,IF($C8="NON MAPPÉ","?",IF(I8>=0,INDEX(Referentiel!$C$5:$C$193,MATCH($C8,Referentiel!$A$5:$A$193,0)),INDEX(Referentiel!$D$5:$D$193,MATCH($C8,Referentiel!$A$5:$A$193,0))))) | K8: =IF($E8<>"",$E8,IF($C8="NON MAPPÉ","?",IF(I8>=0,INDEX(Referentiel!$E$5:$E$193,MATCH($C8,Referentiel!$A$5:$A$193,0)),INDEX(Referentiel!$F$5:$F$193,MATCH($C8,Referentiel!$A$5:$A$193,0)))))
A9: 164000 | B9: Emprunts aupres des etablissements de credit | C9: =IF(ISNUMBER(MATCH(LEFT($A9,4),Referentiel!$A$5:$A$193,0)),LEFT($A9,4),IF(ISNUMBER(MATCH(LEFT($A9,3),Referentiel!$A$5:$A$193,0)),LEFT($A9,3),IF(ISNUMBER(MATCH(LEFT($A9,2),Referentiel!$A$5:$A$193,0)),LEFT($A9,2),"NON MAPPÉ"))) | F9: =ROUND(SUMIFS(FEC_2024!$I:$I,FEC_2024!$E:$E,$A9)-SUMIFS(FEC_2024!$J:$J,FEC_2024!$E:$E,$A9),2) | G9: =IF($D9<>"",$D9,IF($C9="NON MAPPÉ","?",IF(F9>=0,INDEX(Referentiel!$C$5:$C$193,MATCH($C9,Referentiel!$A$5:$A$193,0)),INDEX(Referentiel!$D$5:$D$193,MATCH($C9,Referentiel!$A$5:$A$193,0))))) | H9: =IF($E9<>"",$E9,IF($C9="NON MAPPÉ","?",IF(F9>=0,INDEX(Referentiel!$E$5:$E$193,MATCH($C9,Referentiel!$A$5:$A$193,0)),INDEX(Referentiel!$F$5:$F$193,MATCH($C9,Referentiel!$A$5:$A$193,0))))) | I9: =ROUND(SUMIFS(FEC_2025!$I:$I,FEC_2025!$E:$E,$A9)-SUMIFS(FEC_2025!$J:$J,FEC_2025!$E:$E,$A9),2) | J9: =IF($D9<>"",$D9,IF($C9="NON MAPPÉ","?",IF(I9>=0,INDEX(Referentiel!$C$5:$C$193,MATCH($C9,Referentiel!$A$5:$A$193,0)),INDEX(Referentiel!$D$5:$D$193,MATCH($C9,Referentiel!$A$5:$A$193,0))))) | K9: =IF($E9<>"",$E9,IF($C9="NON MAPPÉ","?",IF(I9>=0,INDEX(Referentiel!$E$5:$E$193,MATCH($C9,Referentiel!$A$5:$A$193,0)),INDEX(Referentiel!$F$5:$F$193,MATCH($C9,Referentiel!$A$5:$A$193,0)))))
A10: 215400 | B10: Materiel industriel | C10: =IF(ISNUMBER(MATCH(LEFT($A10,4),Referentiel!$A$5:$A$193,0)),LEFT($A10,4),IF(ISNUMBER(MATCH(LEFT($A10,3),Referentiel!$A$5:$A$193,0)),LEFT($A10,3),IF(ISNUMBER(MATCH(LEFT($A10,2),Referentiel!$A$5:$A$193,0)),LEFT($A10,2),"NON MAPPÉ"))) | F10: =ROUND(SUMIFS(FEC_2024!$I:$I,FEC_2024!$E:$E,$A10)-SUMIFS(FEC_2024!$J:$J,FEC_2024!$E:$E,$A10),2) | G10: =IF($D10<>"",$D10,IF($C10="NON MAPPÉ","?",IF(F10>=0,INDEX(Referentiel!$C$5:$C$193,MATCH($C10,Referentiel!$A$5:$A$193,0)),INDEX(Referentiel!$D$5:$D$193,MATCH($C10,Referentiel!$A$5:$A$193,0))))) | H10: =IF($E10<>"",$E10,IF($C10="NON MAPPÉ","?",IF(F10>=0,INDEX(Referentiel!$E$5:$E$193,MATCH($C10,Referentiel!$A$5:$A$193,0)),INDEX(Referentiel!$F$5:$F$193,MATCH($C10,Referentiel!$A$5:$A$193,0))))) | I10: =ROUND(SUMIFS(FEC_2025!$I:$I,FEC_2025!$E:$E,$A10)-SUMIFS(FEC_2025!$J:$J,FEC_2025!$E:$E,$A10),2) | J10: =IF($D10<>"",$D10,IF($C10="NON MAPPÉ","?",IF(I10>=0,INDEX(Referentiel!$C$5:$C$193,MATCH($C10,Referentiel!$A$5:$A$193,0)),INDEX(Referentiel!$D$5:$D$193,MATCH($C10,Referentiel!$A$5:$A$193,0))))) | K10: =IF($E10<>"",$E10,IF($C10="NON MAPPÉ","?",IF(I10>=0,INDEX(Referentiel!$E$5:$E$193,MATCH($C10,Referentiel!$A$5:$A$193,0)),INDEX(Referentiel!$F$5:$F$193,MATCH($C10,Referentiel!$A$5:$A$193,0)))))
A11: 218300 | B11: Materiel de bureau et informatique | C11: =IF(ISNUMBER(MATCH(LEFT($A11,4),Referentiel!$A$5:$A$193,0)),LEFT($A11,4),IF(ISNUMBER(MATCH(LEFT($A11,3),Referentiel!$A$5:$A$193,0)),LEFT($A11,3),IF(ISNUMBER(MATCH(LEFT($A11,2),Referentiel!$A$5:$A$193,0)),LEFT($A11,2),"NON MAPPÉ"))) | F11: =ROUND(SUMIFS(FEC_2024!$I:$I,FEC_2024!$E:$E,$A11)-SUMIFS(FEC_2024!$J:$J,FEC_2024!$E:$E,$A11),2) | G11: =IF($D11<>"",$D11,IF($C11="NON MAPPÉ","?",IF(F11>=0,INDEX(Referentiel!$C$5:$C$193,MATCH($C11,Referentiel!$A$5:$A$193,0)),INDEX(Referentiel!$D$5:$D$193,MATCH($C11,Referentiel!$A$5:$A$193,0))))) | H11: =IF($E11<>"",$E11,IF($C11="NON MAPPÉ","?",IF(F11>=0,INDEX(Referentiel!$E$5:$E$193,MATCH($C11,Referentiel!$A$5:$A$193,0)),INDEX(Referentiel!$F$5:$F$193,MATCH($C11,Referentiel!$A$5:$A$193,0))))) | I11: =ROUND(SUMIFS(FEC_2025!$I:$I,FEC_2025!$E:$E,$A11)-SUMIFS(FEC_2025!$J:$J,FEC_2025!$E:$E,$A11),2) | J11: =IF($D11<>"",$D11,IF($C11="NON MAPPÉ","?",IF(I11>=0,INDEX(Referentiel!$C$5:$C$193,MATCH($C11,Referentiel!$A$5:$A$193,0)),INDEX(Referentiel!$D$5:$D$193,MATCH($C11,Referentiel!$A$5:$A$193,0))))) | K11: =IF($E11<>"",$E11,IF($C11="NON MAPPÉ","?",IF(I11>=0,INDEX(Referentiel!$E$5:$E$193,MATCH($C11,Referentiel!$A$5:$A$193,0)),INDEX(Referentiel!$F$5:$F$193,MATCH($C11,Referentiel!$A$5:$A$193,0)))))
A12: 281540 | B12: Amortissements materiel industriel | C12: =IF(ISNUMBER(MATCH(LEFT($A12,4),Referentiel!$A$5:$A$193,0)),LEFT($A12,4),IF(ISNUMBER(MATCH(LEFT($A12,3),Referentiel!$A$5:$A$193,0)),LEFT($A12,3),IF(ISNUMBER(MATCH(LEFT($A12,2),Referentiel!$A$5:$A$193,0)),LEFT($A12,2),"NON MAPPÉ"))) | F12: =ROUND(SUMIFS(FEC_2024!$I:$I,FEC_2024!$E:$E,$A12)-SUMIFS(FEC_2024!$J:$J,FEC_2024!$E:$E,$A12),2) | G12: =IF($D12<>"",$D12,IF($C12="NON MAPPÉ","?",IF(F12>=0,INDEX(Referentiel!$C$5:$C$193,MATCH($C12,Referentiel!$A$5:$A$193,0)),INDEX(Referentiel!$D$5:$D$193,MATCH($C12,Referentiel!$A$5:$A$193,0))))) | H12: =IF($E12<>"",$E12,IF($C12="NON MAPPÉ","?",IF(F12>=0,INDEX(Referentiel!$E$5:$E$193,MATCH($C12,Referentiel!$A$5:$A$193,0)),INDEX(Referentiel!$F$5:$F$193,MATCH($C12,Referentiel!$A$5:$A$193,0))))) | I12: =ROUND(SUMIFS(FEC_2025!$I:$I,FEC_2025!$E:$E,$A12)-SUMIFS(FEC_2025!$J:$J,FEC_2025!$E:$E,$A12),2) | J12: =IF($D12<>"",$D12,IF($C12="NON MAPPÉ","?",IF(I12>=0,INDEX(Referentiel!$C$5:$C$193,MATCH($C12,Referentiel!$A$5:$A$193,0)),INDEX(Referentiel!$D$5:$D$193,MATCH($C12,Referentiel!$A$5:$A$193,0))))) | K12: =IF($E12<>"",$E12,IF($C12="NON MAPPÉ","?",IF(I12>=0,INDEX(Referentiel!$E$5:$E$193,MATCH($C12,Referentiel!$A$5:$A$193,0)),INDEX(Referentiel!$F$5:$F$193,MATCH($C12,Referentiel!$A$5:$A$193,0)))))
A13: 281830 | B13: Amortissements materiel de bureau | C13: =IF(ISNUMBER(MATCH(LEFT($A13,4),Referentiel!$A$5:$A$193,0)),LEFT($A13,4),IF(ISNUMBER(MATCH(LEFT($A13,3),Referentiel!$A$5:$A$193,0)),LEFT($A13,3),IF(ISNUMBER(MATCH(LEFT($A13,2),Referentiel!$A$5:$A$193,0)),LEFT($A13,2),"NON MAPPÉ"))) | F13: =ROUND(SUMIFS(FEC_2024!$I:$I,FEC_2024!$E:$E,$A13)-SUMIFS(FEC_2024!$J:$J,FEC_2024!$E:$E,$A13),2) | G13: =IF($D13<>"",$D13,IF($C13="NON MAPPÉ","?",IF(F13>=0,INDEX(Referentiel!$C$5:$C$193,MATCH($C13,Referentiel!$A$5:$A$193,0)),INDEX(Referentiel!$D$5:$D$193,MATCH($C13,Referentiel!$A$5:$A$193,0))))) | H13: =IF($E13<>"",$E13,IF($C13="NON MAPPÉ","?",IF(F13>=0,INDEX(Referentiel!$E$5:$E$193,MATCH($C13,Referentiel!$A$5:$A$193,0)),INDEX(Referentiel!$F$5:$F$193,MATCH($C13,Referentiel!$A$5:$A$193,0))))) | I13: =ROUND(SUMIFS(FEC_2025!$I:$I,FEC_2025!$E:$E,$A13)-SUMIFS(FEC_2025!$J:$J,FEC_2025!$E:$E,$A13),2) | J13: =IF($D13<>"",$D13,IF($C13="NON MAPPÉ","?",IF(I13>=0,INDEX(Referentiel!$C$5:$C$193,MATCH($C13,Referentiel!$A$5:$A$193,0)),INDEX(Referentiel!$D$5:$D$193,MATCH($C13,Referentiel!$A$5:$A$193,0))))) | K13: =IF($E13<>"",$E13,IF($C13="NON MAPPÉ","?",IF(I13>=0,INDEX(Referentiel!$E$5:$E$193,MATCH($C13,Referentiel!$A$5:$A$193,0)),INDEX(Referentiel!$F$5:$F$193,MATCH($C13,Referentiel!$A$5:$A$193,0)))))
A14: 310000 | B14: Stocks de matieres premieres | C14: =IF(ISNUMBER(MATCH(LEFT($A14,4),Referentiel!$A$5:$A$193,0)),LEFT($A14,4),IF(ISNUMBER(MATCH(LEFT($A14,3),Referentiel!$A$5:$A$193,0)),LEFT($A14,3),IF(ISNUMBER(MATCH(LEFT($A14,2),Referentiel!$A$5:$A$193,0)),LEFT($A14,2),"NON MAPPÉ"))) | F14: =ROUND(SUMIFS(FEC_2024!$I:$I,FEC_2024!$E:$E,$A14)-SUMIFS(FEC_2024!$J:$J,FEC_2024!$E:$E,$A14),2) | G14: =IF($D14<>"",$D14,IF($C14="NON MAPPÉ","?",IF(F14>=0,INDEX(Referentiel!$C$5:$C$193,MATCH($C14,Referentiel!$A$5:$A$193,0)),INDEX(Referentiel!$D$5:$D$193,MATCH($C14,Referentiel!$A$5:$A$193,0))))) | H14: =IF($E14<>"",$E14,IF($C14="NON MAPPÉ","?",IF(F14>=0,INDEX(Referentiel!$E$5:$E$193,MATCH($C14,Referentiel!$A$5:$A$193,0)),INDEX(Referentiel!$F$5:$F$193,MATCH($C14,Referentiel!$A$5:$A$193,0))))) | I14: =ROUND(SUMIFS(FEC_2025!$I:$I,FEC_2025!$E:$E,$A14)-SUMIFS(FEC_2025!$J:$J,FEC_2025!$E:$E,$A14),2) | J14: =IF($D14<>"",$D14,IF($C14="NON MAPPÉ","?",IF(I14>=0,INDEX(Referentiel!$C$5:$C$193,MATCH($C14,Referentiel!$A$5:$A$193,0)),INDEX(Referentiel!$D$5:$D$193,MATCH($C14,Referentiel!$A$5:$A$193,0))))) | K14: =IF($E14<>"",$E14,IF($C14="NON MAPPÉ","?",IF(I14>=0,INDEX(Referentiel!$E$5:$E$193,MATCH($C14,Referentiel!$A$5:$A$193,0)),INDEX(Referentiel!$F$5:$F$193,MATCH($C14,Referentiel!$A$5:$A$193,0)))))
A15: 401000 | B15: Fournisseurs — tiers débiteurs | C15: =IF(ISNUMBER(MATCH(LEFT($A15,4),Referentiel!$A$5:$A$193,0)),LEFT($A15,4),IF(ISNUMBER(MATCH(LEFT($A15,3),Referentiel!$A$5:$A$193,0)),LEFT($A15,3),IF(ISNUMBER(MATCH(LEFT($A15,2),Referentiel!$A$5:$A$193,0)),LEFT($A15,2),"NON MAPPÉ"))) | F15: =ROUND(SUMIFS(Soldes_tiers!$E$5:$E$20,Soldes_tiers!$B$5:$B$20,$A15,Soldes_tiers!$E$5:$E$20,">0"),2) | G15: =IF($D15<>"",$D15,IF($C15="NON MAPPÉ","?",IF(F15>=0,INDEX(Referentiel!$C$5:$C$193,MATCH($C15,Referentiel!$A$5:$A$193,0)),INDEX(Referentiel!$D$5:$D$193,MATCH($C15,Referentiel!$A$5:$A$193,0))))) | H15: =IF($E15<>"",$E15,IF($C15="NON MAPPÉ","?",IF(F15>=0,INDEX(Referentiel!$E$5:$E$193,MATCH($C15,Referentiel!$A$5:$A$193,0)),INDEX(Referentiel!$F$5:$F$193,MATCH($C15,Referentiel!$A$5:$A$193,0))))) | I15: =ROUND(SUMIFS(Soldes_tiers!$F$5:$F$20,Soldes_tiers!$B$5:$B$20,$A15,Soldes_tiers!$F$5:$F$20,">0"),2) | J15: =IF($D15<>"",$D15,IF($C15="NON MAPPÉ","?",IF(I15>=0,INDEX(Referentiel!$C$5:$C$193,MATCH($C15,Referentiel!$A$5:$A$193,0)),INDEX(Referentiel!$D$5:$D$193,MATCH($C15,Referentiel!$A$5:$A$193,0))))) | K15: =IF($E15<>"",$E15,IF($C15="NON MAPPÉ","?",IF(I15>=0,INDEX(Referentiel!$E$5:$E$193,MATCH($C15,Referentiel!$A$5:$A$193,0)),INDEX(Referentiel!$F$5:$F$193,MATCH($C15,Referentiel!$A$5:$A$193,0)))))
A16: 401000 | B16: Fournisseurs — tiers créditeurs et non ventilé | C16: =IF(ISNUMBER(MATCH(LEFT($A16,4),Referentiel!$A$5:$A$193,0)),LEFT($A16,4),IF(ISNUMBER(MATCH(LEFT($A16,3),Referentiel!$A$5:$A$193,0)),LEFT($A16,3),IF(ISNUMBER(MATCH(LEFT($A16,2),Referentiel!$A$5:$A$193,0)),LEFT($A16,2),"NON MAPPÉ"))) | F16: =ROUND(SUMIFS(FEC_2024!$I:$I,FEC_2024!$E:$E,$A16)-SUMIFS(FEC_2024!$J:$J,FEC_2024!$E:$E,$A16),2)-F15 | G16: =IF($D16<>"",$D16,IF($C16="NON MAPPÉ","?",IF(F16>=0,INDEX(Referentiel!$C$5:$C$193,MATCH($C16,Referentiel!$A$5:$A$193,0)),INDEX(Referentiel!$D$5:$D$193,MATCH($C16,Referentiel!$A$5:$A$193,0))))) | H16: =IF($E16<>"",$E16,IF($C16="NON MAPPÉ","?",IF(F16>=0,INDEX(Referentiel!$E$5:$E$193,MATCH($C16,Referentiel!$A$5:$A$193,0)),INDEX(Referentiel!$F$5:$F$193,MATCH($C16,Referentiel!$A$5:$A$193,0))))) | I16: =ROUND(SUMIFS(FEC_2025!$I:$I,FEC_2025!$E:$E,$A16)-SUMIFS(FEC_2025!$J:$J,FEC_2025!$E:$E,$A16),2)-I15 | J16: =IF($D16<>"",$D16,IF($C16="NON MAPPÉ","?",IF(I16>=0,INDEX(Referentiel!$C$5:$C$193,MATCH($C16,Referentiel!$A$5:$A$193,0)),INDEX(Referentiel!$D$5:$D$193,MATCH($C16,Referentiel!$A$5:$A$193,0))))) | K16: =IF($E16<>"",$E16,IF($C16="NON MAPPÉ","?",IF(I16>=0,INDEX(Referentiel!$E$5:$E$193,MATCH($C16,Referentiel!$A$5:$A$193,0)),INDEX(Referentiel!$F$5:$F$193,MATCH($C16,Referentiel!$A$5:$A$193,0)))))
A17: 411000 | B17: Clients — tiers débiteurs | C17: =IF(ISNUMBER(MATCH(LEFT($A17,4),Referentiel!$A$5:$A$193,0)),LEFT($A17,4),IF(ISNUMBER(MATCH(LEFT($A17,3),Referentiel!$A$5:$A$193,0)),LEFT($A17,3),IF(ISNUMBER(MATCH(LEFT($A17,2),Referentiel!$A$5:$A$193,0)),LEFT($A17,2),"NON MAPPÉ"))) | F17: =ROUND(SUMIFS(Soldes_tiers!$E$5:$E$20,Soldes_tiers!$B$5:$B$20,$A17,Soldes_tiers!$E$5:$E$20,">0"),2) | G17: =IF($D17<>"",$D17,IF($C17="NON MAPPÉ","?",IF(F17>=0,INDEX(Referentiel!$C$5:$C$193,MATCH($C17,Referentiel!$A$5:$A$193,0)),INDEX(Referentiel!$D$5:$D$193,MATCH($C17,Referentiel!$A$5:$A$193,0))))) | H17: =IF($E17<>"",$E17,IF($C17="NON MAPPÉ","?",IF(F17>=0,INDEX(Referentiel!$E$5:$E$193,MATCH($C17,Referentiel!$A$5:$A$193,0)),INDEX(Referentiel!$F$5:$F$193,MATCH($C17,Referentiel!$A$5:$A$193,0))))) | I17: =ROUND(SUMIFS(Soldes_tiers!$F$5:$F$20,Soldes_tiers!$B$5:$B$20,$A17,Soldes_tiers!$F$5:$F$20,">0"),2) | J17: =IF($D17<>"",$D17,IF($C17="NON MAPPÉ","?",IF(I17>=0,INDEX(Referentiel!$C$5:$C$193,MATCH($C17,Referentiel!$A$5:$A$193,0)),INDEX(Referentiel!$D$5:$D$193,MATCH($C17,Referentiel!$A$5:$A$193,0))))) | K17: =IF($E17<>"",$E17,IF($C17="NON MAPPÉ","?",IF(I17>=0,INDEX(Referentiel!$E$5:$E$193,MATCH($C17,Referentiel!$A$5:$A$193,0)),INDEX(Referentiel!$F$5:$F$193,MATCH($C17,Referentiel!$A$5:$A$193,0)))))
A18: 411000 | B18: Clients — tiers créditeurs et non ventilé | C18: =IF(ISNUMBER(MATCH(LEFT($A18,4),Referentiel!$A$5:$A$193,0)),LEFT($A18,4),IF(ISNUMBER(MATCH(LEFT($A18,3),Referentiel!$A$5:$A$193,0)),LEFT($A18,3),IF(ISNUMBER(MATCH(LEFT($A18,2),Referentiel!$A$5:$A$193,0)),LEFT($A18,2),"NON MAPPÉ"))) | F18: =ROUND(SUMIFS(FEC_2024!$I:$I,FEC_2024!$E:$E,$A18)-SUMIFS(FEC_2024!$J:$J,FEC_2024!$E:$E,$A18),2)-F17 | G18: =IF($D18<>"",$D18,IF($C18="NON MAPPÉ","?",IF(F18>=0,INDEX(Referentiel!$C$5:$C$193,MATCH($C18,Referentiel!$A$5:$A$193,0)),INDEX(Referentiel!$D$5:$D$193,MATCH($C18,Referentiel!$A$5:$A$193,0))))) | H18: =IF($E18<>"",$E18,IF($C18="NON MAPPÉ","?",IF(F18>=0,INDEX(Referentiel!$E$5:$E$193,MATCH($C18,Referentiel!$A$5:$A$193,0)),INDEX(Referentiel!$F$5:$F$193,MATCH($C18,Referentiel!$A$5:$A$193,0))))) | I18: =ROUND(SUMIFS(FEC_2025!$I:$I,FEC_2025!$E:$E,$A18)-SUMIFS(FEC_2025!$J:$J,FEC_2025!$E:$E,$A18),2)-I17 | J18: =IF($D18<>"",$D18,IF($C18="NON MAPPÉ","?",IF(I18>=0,INDEX(Referentiel!$C$5:$C$193,MATCH($C18,Referentiel!$A$5:$A$193,0)),INDEX(Referentiel!$D$5:$D$193,MATCH($C18,Referentiel!$A$5:$A$193,0))))) | K18: =IF($E18<>"",$E18,IF($C18="NON MAPPÉ","?",IF(I18>=0,INDEX(Referentiel!$E$5:$E$193,MATCH($C18,Referentiel!$A$5:$A$193,0)),INDEX(Referentiel!$F$5:$F$193,MATCH($C18,Referentiel!$A$5:$A$193,0)))))
A19: 421000 | B19: Personnel remunerations dues | C19: =IF(ISNUMBER(MATCH(LEFT($A19,4),Referentiel!$A$5:$A$193,0)),LEFT($A19,4),IF(ISNUMBER(MATCH(LEFT($A19,3),Referentiel!$A$5:$A$193,0)),LEFT($A19,3),IF(ISNUMBER(MATCH(LEFT($A19,2),Referentiel!$A$5:$A$193,0)),LEFT($A19,2),"NON MAPPÉ"))) | F19: =ROUND(SUMIFS(FEC_2024!$I:$I,FEC_2024!$E:$E,$A19)-SUMIFS(FEC_2024!$J:$J,FEC_2024!$E:$E,$A19),2) | G19: =IF($D19<>"",$D19,IF($C19="NON MAPPÉ","?",IF(F19>=0,INDEX(Referentiel!$C$5:$C$193,MATCH($C19,Referentiel!$A$5:$A$193,0)),INDEX(Referentiel!$D$5:$D$193,MATCH($C19,Referentiel!$A$5:$A$193,0))))) | H19: =IF($E19<>"",$E19,IF($C19="NON MAPPÉ","?",IF(F19>=0,INDEX(Referentiel!$E$5:$E$193,MATCH($C19,Referentiel!$A$5:$A$193,0)),INDEX(Referentiel!$F$5:$F$193,MATCH($C19,Referentiel!$A$5:$A$193,0))))) | I19: =ROUND(SUMIFS(FEC_2025!$I:$I,FEC_2025!$E:$E,$A19)-SUMIFS(FEC_2025!$J:$J,FEC_2025!$E:$E,$A19),2) | J19: =IF($D19<>"",$D19,IF($C19="NON MAPPÉ","?",IF(I19>=0,INDEX(Referentiel!$C$5:$C$193,MATCH($C19,Referentiel!$A$5:$A$193,0)),INDEX(Referentiel!$D$5:$D$193,MATCH($C19,Referentiel!$A$5:$A$193,0))))) | K19: =IF($E19<>"",$E19,IF($C19="NON MAPPÉ","?",IF(I19>=0,INDEX(Referentiel!$E$5:$E$193,MATCH($C19,Referentiel!$A$5:$A$193,0)),INDEX(Referentiel!$F$5:$F$193,MATCH($C19,Referentiel!$A$5:$A$193,0)))))
A20: 431000 | B20: Securite sociale | C20: =IF(ISNUMBER(MATCH(LEFT($A20,4),Referentiel!$A$5:$A$193,0)),LEFT($A20,4),IF(ISNUMBER(MATCH(LEFT($A20,3),Referentiel!$A$5:$A$193,0)),LEFT($A20,3),IF(ISNUMBER(MATCH(LEFT($A20,2),Referentiel!$A$5:$A$193,0)),LEFT($A20,2),"NON MAPPÉ"))) | F20: =ROUND(SUMIFS(FEC_2024!$I:$I,FEC_2024!$E:$E,$A20)-SUMIFS(FEC_2024!$J:$J,FEC_2024!$E:$E,$A20),2) | G20: =IF($D20<>"",$D20,IF($C20="NON MAPPÉ","?",IF(F20>=0,INDEX(Referentiel!$C$5:$C$193,MATCH($C20,Referentiel!$A$5:$A$193,0)),INDEX(Referentiel!$D$5:$D$193,MATCH($C20,Referentiel!$A$5:$A$193,0))))) | H20: =IF($E20<>"",$E20,IF($C20="NON MAPPÉ","?",IF(F20>=0,INDEX(Referentiel!$E$5:$E$193,MATCH($C20,Referentiel!$A$5:$A$193,0)),INDEX(Referentiel!$F$5:$F$193,MATCH($C20,Referentiel!$A$5:$A$193,0))))) | I20: =ROUND(SUMIFS(FEC_2025!$I:$I,FEC_2025!$E:$E,$A20)-SUMIFS(FEC_2025!$J:$J,FEC_2025!$E:$E,$A20),2) | J20: =IF($D20<>"",$D20,IF($C20="NON MAPPÉ","?",IF(I20>=0,INDEX(Referentiel!$C$5:$C$193,MATCH($C20,Referentiel!$A$5:$A$193,0)),INDEX(Referentiel!$D$5:$D$193,MATCH($C20,Referentiel!$A$5:$A$193,0))))) | K20: =IF($E20<>"",$E20,IF($C20="NON MAPPÉ","?",IF(I20>=0,INDEX(Referentiel!$E$5:$E$193,MATCH($C20,Referentiel!$A$5:$A$193,0)),INDEX(Referentiel!$F$5:$F$193,MATCH($C20,Referentiel!$A$5:$A$193,0)))))
A21: 444000 | B21: Etat impot sur les benefices | C21: =IF(ISNUMBER(MATCH(LEFT($A21,4),Referentiel!$A$5:$A$193,0)),LEFT($A21,4),IF(ISNUMBER(MATCH(LEFT($A21,3),Referentiel!$A$5:$A$193,0)),LEFT($A21,3),IF(ISNUMBER(MATCH(LEFT($A21,2),Referentiel!$A$5:$A$193,0)),LEFT($A21,2),"NON MAPPÉ"))) | F21: =ROUND(SUMIFS(FEC_2024!$I:$I,FEC_2024!$E:$E,$A21)-SUMIFS(FEC_2024!$J:$J,FEC_2024!$E:$E,$A21),2) | G21: =IF($D21<>"",$D21,IF($C21="NON MAPPÉ","?",IF(F21>=0,INDEX(Referentiel!$C$5:$C$193,MATCH($C21,Referentiel!$A$5:$A$193,0)),INDEX(Referentiel!$D$5:$D$193,MATCH($C21,Referentiel!$A$5:$A$193,0))))) | H21: =IF($E21<>"",$E21,IF($C21="NON MAPPÉ","?",IF(F21>=0,INDEX(Referentiel!$E$5:$E$193,MATCH($C21,Referentiel!$A$5:$A$193,0)),INDEX(Referentiel!$F$5:$F$193,MATCH($C21,Referentiel!$A$5:$A$193,0))))) | I21: =ROUND(SUMIFS(FEC_2025!$I:$I,FEC_2025!$E:$E,$A21)-SUMIFS(FEC_2025!$J:$J,FEC_2025!$E:$E,$A21),2) | J21: =IF($D21<>"",$D21,IF($C21="NON MAPPÉ","?",IF(I21>=0,INDEX(Referentiel!$C$5:$C$193,MATCH($C21,Referentiel!$A$5:$A$193,0)),INDEX(Referentiel!$D$5:$D$193,MATCH($C21,Referentiel!$A$5:$A$193,0))))) | K21: =IF($E21<>"",$E21,IF($C21="NON MAPPÉ","?",IF(I21>=0,INDEX(Referentiel!$E$5:$E$193,MATCH($C21,Referentiel!$A$5:$A$193,0)),INDEX(Referentiel!$F$5:$F$193,MATCH($C21,Referentiel!$A$5:$A$193,0)))))
A22: 445510 | B22: TVA a decaisser | C22: =IF(ISNUMBER(MATCH(LEFT($A22,4),Referentiel!$A$5:$A$193,0)),LEFT($A22,4),IF(ISNUMBER(MATCH(LEFT($A22,3),Referentiel!$A$5:$A$193,0)),LEFT($A22,3),IF(ISNUMBER(MATCH(LEFT($A22,2),Referentiel!$A$5:$A$193,0)),LEFT($A22,2),"NON MAPPÉ"))) | F22: =ROUND(SUMIFS(FEC_2024!$I:$I,FEC_2024!$E:$E,$A22)-SUMIFS(FEC_2024!$J:$J,FEC_2024!$E:$E,$A22),2) | G22: =IF($D22<>"",$D22,IF($C22="NON MAPPÉ","?",IF(F22>=0,INDEX(Referentiel!$C$5:$C$193,MATCH($C22,Referentiel!$A$5:$A$193,0)),INDEX(Referentiel!$D$5:$D$193,MATCH($C22,Referentiel!$A$5:$A$193,0))))) | H22: =IF($E22<>"",$E22,IF($C22="NON MAPPÉ","?",IF(F22>=0,INDEX(Referentiel!$E$5:$E$193,MATCH($C22,Referentiel!$A$5:$A$193,0)),INDEX(Referentiel!$F$5:$F$193,MATCH($C22,Referentiel!$A$5:$A$193,0))))) | I22: =ROUND(SUMIFS(FEC_2025!$I:$I,FEC_2025!$E:$E,$A22)-SUMIFS(FEC_2025!$J:$J,FEC_2025!$E:$E,$A22),2) | J22: =IF($D22<>"",$D22,IF($C22="NON MAPPÉ","?",IF(I22>=0,INDEX(Referentiel!$C$5:$C$193,MATCH($C22,Referentiel!$A$5:$A$193,0)),INDEX(Referentiel!$D$5:$D$193,MATCH($C22,Referentiel!$A$5:$A$193,0))))) | K22: =IF($E22<>"",$E22,IF($C22="NON MAPPÉ","?",IF(I22>=0,INDEX(Referentiel!$E$5:$E$193,MATCH($C22,Referentiel!$A$5:$A$193,0)),INDEX(Referentiel!$F$5:$F$193,MATCH($C22,Referentiel!$A$5:$A$193,0)))))
A23: 445660 | B23: TVA deductible sur ABS | C23: =IF(ISNUMBER(MATCH(LEFT($A23,4),Referentiel!$A$5:$A$193,0)),LEFT($A23,4),IF(ISNUMBER(MATCH(LEFT($A23,3),Referentiel!$A$5:$A$193,0)),LEFT($A23,3),IF(ISNUMBER(MATCH(LEFT($A23,2),Referentiel!$A$5:$A$193,0)),LEFT($A23,2),"NON MAPPÉ"))) | F23: =ROUND(SUMIFS(FEC_2024!$I:$I,FEC_2024!$E:$E,$A23)-SUMIFS(FEC_2024!$J:$J,FEC_2024!$E:$E,$A23),2) | G23: =IF($D23<>"",$D23,IF($C23="NON MAPPÉ","?",IF(F23>=0,INDEX(Referentiel!$C$5:$C$193,MATCH($C23,Referentiel!$A$5:$A$193,0)),INDEX(Referentiel!$D$5:$D$193,MATCH($C23,Referentiel!$A$5:$A$193,0))))) | H23: =IF($E23<>"",$E23,IF($C23="NON MAPPÉ","?",IF(F23>=0,INDEX(Referentiel!$E$5:$E$193,MATCH($C23,Referentiel!$A$5:$A$193,0)),INDEX(Referentiel!$F$5:$F$193,MATCH($C23,Referentiel!$A$5:$A$193,0))))) | I23: =ROUND(SUMIFS(FEC_2025!$I:$I,FEC_2025!$E:$E,$A23)-SUMIFS(FEC_2025!$J:$J,FEC_2025!$E:$E,$A23),2) | J23: =IF($D23<>"",$D23,IF($C23="NON MAPPÉ","?",IF(I23>=0,INDEX(Referentiel!$C$5:$C$193,MATCH($C23,Referentiel!$A$5:$A$193,0)),INDEX(Referentiel!$D$5:$D$193,MATCH($C23,Referentiel!$A$5:$A$193,0))))) | K23: =IF($E23<>"",$E23,IF($C23="NON MAPPÉ","?",IF(I23>=0,INDEX(Referentiel!$E$5:$E$193,MATCH($C23,Referentiel!$A$5:$A$193,0)),INDEX(Referentiel!$F$5:$F$193,MATCH($C23,Referentiel!$A$5:$A$193,0)))))
A24: 445710 | B24: TVA collectee | C24: =IF(ISNUMBER(MATCH(LEFT($A24,4),Referentiel!$A$5:$A$193,0)),LEFT($A24,4),IF(ISNUMBER(MATCH(LEFT($A24,3),Referentiel!$A$5:$A$193,0)),LEFT($A24,3),IF(ISNUMBER(MATCH(LEFT($A24,2),Referentiel!$A$5:$A$193,0)),LEFT($A24,2),"NON MAPPÉ"))) | F24: =ROUND(SUMIFS(FEC_2024!$I:$I,FEC_2024!$E:$E,$A24)-SUMIFS(FEC_2024!$J:$J,FEC_2024!$E:$E,$A24),2) | G24: =IF($D24<>"",$D24,IF($C24="NON MAPPÉ","?",IF(F24>=0,INDEX(Referentiel!$C$5:$C$193,MATCH($C24,Referentiel!$A$5:$A$193,0)),INDEX(Referentiel!$D$5:$D$193,MATCH($C24,Referentiel!$A$5:$A$193,0))))) | H24: =IF($E24<>"",$E24,IF($C24="NON MAPPÉ","?",IF(F24>=0,INDEX(Referentiel!$E$5:$E$193,MATCH($C24,Referentiel!$A$5:$A$193,0)),INDEX(Referentiel!$F$5:$F$193,MATCH($C24,Referentiel!$A$5:$A$193,0))))) | I24: =ROUND(SUMIFS(FEC_2025!$I:$I,FEC_2025!$E:$E,$A24)-SUMIFS(FEC_2025!$J:$J,FEC_2025!$E:$E,$A24),2) | J24: =IF($D24<>"",$D24,IF($C24="NON MAPPÉ","?",IF(I24>=0,INDEX(Referentiel!$C$5:$C$193,MATCH($C24,Referentiel!$A$5:$A$193,0)),INDEX(Referentiel!$D$5:$D$193,MATCH($C24,Referentiel!$A$5:$A$193,0))))) | K24: =IF($E24<>"",$E24,IF($C24="NON MAPPÉ","?",IF(I24>=0,INDEX(Referentiel!$E$5:$E$193,MATCH($C24,Referentiel!$A$5:$A$193,0)),INDEX(Referentiel!$F$5:$F$193,MATCH($C24,Referentiel!$A$5:$A$193,0)))))
A25: 455100 | B25: Compte courant d'associe | C25: =IF(ISNUMBER(MATCH(LEFT($A25,4),Referentiel!$A$5:$A$193,0)),LEFT($A25,4),IF(ISNUMBER(MATCH(LEFT($A25,3),Referentiel!$A$5:$A$193,0)),LEFT($A25,3),IF(ISNUMBER(MATCH(LEFT($A25,2),Referentiel!$A$5:$A$193,0)),LEFT($A25,2),"NON MAPPÉ"))) | F25: =ROUND(SUMIFS(FEC_2024!$I:$I,FEC_2024!$E:$E,$A25)-SUMIFS(FEC_2024!$J:$J,FEC_2024!$E:$E,$A25),2) | G25: =IF($D25<>"",$D25,IF($C25="NON MAPPÉ","?",IF(F25>=0,INDEX(Referentiel!$C$5:$C$193,MATCH($C25,Referentiel!$A$5:$A$193,0)),INDEX(Referentiel!$D$5:$D$193,MATCH($C25,Referentiel!$A$5:$A$193,0))))) | H25: =IF($E25<>"",$E25,IF($C25="NON MAPPÉ","?",IF(F25>=0,INDEX(Referentiel!$E$5:$E$193,MATCH($C25,Referentiel!$A$5:$A$193,0)),INDEX(Referentiel!$F$5:$F$193,MATCH($C25,Referentiel!$A$5:$A$193,0))))) | I25: =ROUND(SUMIFS(FEC_2025!$I:$I,FEC_2025!$E:$E,$A25)-SUMIFS(FEC_2025!$J:$J,FEC_2025!$E:$E,$A25),2) | J25: =IF($D25<>"",$D25,IF($C25="NON MAPPÉ","?",IF(I25>=0,INDEX(Referentiel!$C$5:$C$193,MATCH($C25,Referentiel!$A$5:$A$193,0)),INDEX(Referentiel!$D$5:$D$193,MATCH($C25,Referentiel!$A$5:$A$193,0))))) | K25: =IF($E25<>"",$E25,IF($C25="NON MAPPÉ","?",IF(I25>=0,INDEX(Referentiel!$E$5:$E$193,MATCH($C25,Referentiel!$A$5:$A$193,0)),INDEX(Referentiel!$F$5:$F$193,MATCH($C25,Referentiel!$A$5:$A$193,0)))))
A26: 512000 | B26: Banque Fictive | C26: =IF(ISNUMBER(MATCH(LEFT($A26,4),Referentiel!$A$5:$A$193,0)),LEFT($A26,4),IF(ISNUMBER(MATCH(LEFT($A26,3),Referentiel!$A$5:$A$193,0)),LEFT($A26,3),IF(ISNUMBER(MATCH(LEFT($A26,2),Referentiel!$A$5:$A$193,0)),LEFT($A26,2),"NON MAPPÉ"))) | F26: =ROUND(SUMIFS(FEC_2024!$I:$I,FEC_2024!$E:$E,$A26)-SUMIFS(FEC_2024!$J:$J,FEC_2024!$E:$E,$A26),2) | G26: =IF($D26<>"",$D26,IF($C26="NON MAPPÉ","?",IF(F26>=0,INDEX(Referentiel!$C$5:$C$193,MATCH($C26,Referentiel!$A$5:$A$193,0)),INDEX(Referentiel!$D$5:$D$193,MATCH($C26,Referentiel!$A$5:$A$193,0))))) | H26: =IF($E26<>"",$E26,IF($C26="NON MAPPÉ","?",IF(F26>=0,INDEX(Referentiel!$E$5:$E$193,MATCH($C26,Referentiel!$A$5:$A$193,0)),INDEX(Referentiel!$F$5:$F$193,MATCH($C26,Referentiel!$A$5:$A$193,0))))) | I26: =ROUND(SUMIFS(FEC_2025!$I:$I,FEC_2025!$E:$E,$A26)-SUMIFS(FEC_2025!$J:$J,FEC_2025!$E:$E,$A26),2) | J26: =IF($D26<>"",$D26,IF($C26="NON MAPPÉ","?",IF(I26>=0,INDEX(Referentiel!$C$5:$C$193,MATCH($C26,Referentiel!$A$5:$A$193,0)),INDEX(Referentiel!$D$5:$D$193,MATCH($C26,Referentiel!$A$5:$A$193,0))))) | K26: =IF($E26<>"",$E26,IF($C26="NON MAPPÉ","?",IF(I26>=0,INDEX(Referentiel!$E$5:$E$193,MATCH($C26,Referentiel!$A$5:$A$193,0)),INDEX(Referentiel!$F$5:$F$193,MATCH($C26,Referentiel!$A$5:$A$193,0)))))
A27: 601000 | B27: Achats de matieres premieres | C27: =IF(ISNUMBER(MATCH(LEFT($A27,4),Referentiel!$A$5:$A$193,0)),LEFT($A27,4),IF(ISNUMBER(MATCH(LEFT($A27,3),Referentiel!$A$5:$A$193,0)),LEFT($A27,3),IF(ISNUMBER(MATCH(LEFT($A27,2),Referentiel!$A$5:$A$193,0)),LEFT($A27,2),"NON MAPPÉ"))) | F27: =ROUND(SUMIFS(FEC_2024!$I:$I,FEC_2024!$E:$E,$A27)-SUMIFS(FEC_2024!$J:$J,FEC_2024!$E:$E,$A27),2) | G27: =IF($D27<>"",$D27,IF($C27="NON MAPPÉ","?",IF(F27>=0,INDEX(Referentiel!$C$5:$C$193,MATCH($C27,Referentiel!$A$5:$A$193,0)),INDEX(Referentiel!$D$5:$D$193,MATCH($C27,Referentiel!$A$5:$A$193,0))))) | H27: =IF($E27<>"",$E27,IF($C27="NON MAPPÉ","?",IF(F27>=0,INDEX(Referentiel!$E$5:$E$193,MATCH($C27,Referentiel!$A$5:$A$193,0)),INDEX(Referentiel!$F$5:$F$193,MATCH($C27,Referentiel!$A$5:$A$193,0))))) | I27: =ROUND(SUMIFS(FEC_2025!$I:$I,FEC_2025!$E:$E,$A27)-SUMIFS(FEC_2025!$J:$J,FEC_2025!$E:$E,$A27),2) | J27: =IF($D27<>"",$D27,IF($C27="NON MAPPÉ","?",IF(I27>=0,INDEX(Referentiel!$C$5:$C$193,MATCH($C27,Referentiel!$A$5:$A$193,0)),INDEX(Referentiel!$D$5:$D$193,MATCH($C27,Referentiel!$A$5:$A$193,0))))) | K27: =IF($E27<>"",$E27,IF($C27="NON MAPPÉ","?",IF(I27>=0,INDEX(Referentiel!$E$5:$E$193,MATCH($C27,Referentiel!$A$5:$A$193,0)),INDEX(Referentiel!$F$5:$F$193,MATCH($C27,Referentiel!$A$5:$A$193,0)))))
A28: 603100 | B28: Variation des stocks de matieres premieres | C28: =IF(ISNUMBER(MATCH(LEFT($A28,4),Referentiel!$A$5:$A$193,0)),LEFT($A28,4),IF(ISNUMBER(MATCH(LEFT($A28,3),Referentiel!$A$5:$A$193,0)),LEFT($A28,3),IF(ISNUMBER(MATCH(LEFT($A28,2),Referentiel!$A$5:$A$193,0)),LEFT($A28,2),"NON MAPPÉ"))) | F28: =ROUND(SUMIFS(FEC_2024!$I:$I,FEC_2024!$E:$E,$A28)-SUMIFS(FEC_2024!$J:$J,FEC_2024!$E:$E,$A28),2) | G28: =IF($D28<>"",$D28,IF($C28="NON MAPPÉ","?",IF(F28>=0,INDEX(Referentiel!$C$5:$C$193,MATCH($C28,Referentiel!$A$5:$A$193,0)),INDEX(Referentiel!$D$5:$D$193,MATCH($C28,Referentiel!$A$5:$A$193,0))))) | H28: =IF($E28<>"",$E28,IF($C28="NON MAPPÉ","?",IF(F28>=0,INDEX(Referentiel!$E$5:$E$193,MATCH($C28,Referentiel!$A$5:$A$193,0)),INDEX(Referentiel!$F$5:$F$193,MATCH($C28,Referentiel!$A$5:$A$193,0))))) | I28: =ROUND(SUMIFS(FEC_2025!$I:$I,FEC_2025!$E:$E,$A28)-SUMIFS(FEC_2025!$J:$J,FEC_2025!$E:$E,$A28),2) | J28: =IF($D28<>"",$D28,IF($C28="NON MAPPÉ","?",IF(I28>=0,INDEX(Referentiel!$C$5:$C$193,MATCH($C28,Referentiel!$A$5:$A$193,0)),INDEX(Referentiel!$D$5:$D$193,MATCH($C28,Referentiel!$A$5:$A$193,0))))) | K28: =IF($E28<>"",$E28,IF($C28="NON MAPPÉ","?",IF(I28>=0,INDEX(Referentiel!$E$5:$E$193,MATCH($C28,Referentiel!$A$5:$A$193,0)),INDEX(Referentiel!$F$5:$F$193,MATCH($C28,Referentiel!$A$5:$A$193,0)))))
A29: 606100 | B29: Fournitures non stockables energie | C29: =IF(ISNUMBER(MATCH(LEFT($A29,4),Referentiel!$A$5:$A$193,0)),LEFT($A29,4),IF(ISNUMBER(MATCH(LEFT($A29,3),Referentiel!$A$5:$A$193,0)),LEFT($A29,3),IF(ISNUMBER(MATCH(LEFT($A29,2),Referentiel!$A$5:$A$193,0)),LEFT($A29,2),"NON MAPPÉ"))) | F29: =ROUND(SUMIFS(FEC_2024!$I:$I,FEC_2024!$E:$E,$A29)-SUMIFS(FEC_2024!$J:$J,FEC_2024!$E:$E,$A29),2) | G29: =IF($D29<>"",$D29,IF($C29="NON MAPPÉ","?",IF(F29>=0,INDEX(Referentiel!$C$5:$C$193,MATCH($C29,Referentiel!$A$5:$A$193,0)),INDEX(Referentiel!$D$5:$D$193,MATCH($C29,Referentiel!$A$5:$A$193,0))))) | H29: =IF($E29<>"",$E29,IF($C29="NON MAPPÉ","?",IF(F29>=0,INDEX(Referentiel!$E$5:$E$193,MATCH($C29,Referentiel!$A$5:$A$193,0)),INDEX(Referentiel!$F$5:$F$193,MATCH($C29,Referentiel!$A$5:$A$193,0))))) | I29: =ROUND(SUMIFS(FEC_2025!$I:$I,FEC_2025!$E:$E,$A29)-SUMIFS(FEC_2025!$J:$J,FEC_2025!$E:$E,$A29),2) | J29: =IF($D29<>"",$D29,IF($C29="NON MAPPÉ","?",IF(I29>=0,INDEX(Referentiel!$C$5:$C$193,MATCH($C29,Referentiel!$A$5:$A$193,0)),INDEX(Referentiel!$D$5:$D$193,MATCH($C29,Referentiel!$A$5:$A$193,0))))) | K29: =IF($E29<>"",$E29,IF($C29="NON MAPPÉ","?",IF(I29>=0,INDEX(Referentiel!$E$5:$E$193,MATCH($C29,Referentiel!$A$5:$A$193,0)),INDEX(Referentiel!$F$5:$F$193,MATCH($C29,Referentiel!$A$5:$A$193,0)))))
A30: 613200 | B30: Locations immobilieres | C30: =IF(ISNUMBER(MATCH(LEFT($A30,4),Referentiel!$A$5:$A$193,0)),LEFT($A30,4),IF(ISNUMBER(MATCH(LEFT($A30,3),Referentiel!$A$5:$A$193,0)),LEFT($A30,3),IF(ISNUMBER(MATCH(LEFT($A30,2),Referentiel!$A$5:$A$193,0)),LEFT($A30,2),"NON MAPPÉ"))) | F30: =ROUND(SUMIFS(FEC_2024!$I:$I,FEC_2024!$E:$E,$A30)-SUMIFS(FEC_2024!$J:$J,FEC_2024!$E:$E,$A30),2) | G30: =IF($D30<>"",$D30,IF($C30="NON MAPPÉ","?",IF(F30>=0,INDEX(Referentiel!$C$5:$C$193,MATCH($C30,Referentiel!$A$5:$A$193,0)),INDEX(Referentiel!$D$5:$D$193,MATCH($C30,Referentiel!$A$5:$A$193,0))))) | H30: =IF($E30<>"",$E30,IF($C30="NON MAPPÉ","?",IF(F30>=0,INDEX(Referentiel!$E$5:$E$193,MATCH($C30,Referentiel!$A$5:$A$193,0)),INDEX(Referentiel!$F$5:$F$193,MATCH($C30,Referentiel!$A$5:$A$193,0))))) | I30: =ROUND(SUMIFS(FEC_2025!$I:$I,FEC_2025!$E:$E,$A30)-SUMIFS(FEC_2025!$J:$J,FEC_2025!$E:$E,$A30),2) | J30: =IF($D30<>"",$D30,IF($C30="NON MAPPÉ","?",IF(I30>=0,INDEX(Referentiel!$C$5:$C$193,MATCH($C30,Referentiel!$A$5:$A$193,0)),INDEX(Referentiel!$D$5:$D$193,MATCH($C30,Referentiel!$A$5:$A$193,0))))) | K30: =IF($E30<>"",$E30,IF($C30="NON MAPPÉ","?",IF(I30>=0,INDEX(Referentiel!$E$5:$E$193,MATCH($C30,Referentiel!$A$5:$A$193,0)),INDEX(Referentiel!$F$5:$F$193,MATCH($C30,Referentiel!$A$5:$A$193,0)))))
... A42: 701000 | B42: Ventes de produits finis | C42: =IF(ISNUMBER(MATCH(LEFT($A42,4),Referentiel!$A$5:$A$193,0)),LEFT($A42,4),IF(ISNUMBER(MATCH(LEFT($A42,3),Referentiel!$A$5:$A$193,0)),LEFT($A42,3),IF(ISNUMBER(MATCH(LEFT($A42,2),Referentiel!$A$5:$A$193,0)),LEFT($A42,2),"NON MAPPÉ"))) | F42: =ROUND(SUMIFS(FEC_2024!$I:$I,FEC_2024!$E:$E,$A42)-SUMIFS(FEC_2024!$J:$J,FEC_2024!$E:$E,$A42),2) | G42: =IF($D42<>"",$D42,IF($C42="NON MAPPÉ","?",IF(F42>=0,INDEX(Referentiel!$C$5:$C$193,MATCH($C42,Referentiel!$A$5:$A$193,0)),INDEX(Referentiel!$D$5:$D$193,MATCH($C42,Referentiel!$A$5:$A$193,0))))) | H42: =IF($E42<>"",$E42,IF($C42="NON MAPPÉ","?",IF(F42>=0,INDEX(Referentiel!$E$5:$E$193,MATCH($C42,Referentiel!$A$5:$A$193,0)),INDEX(Referentiel!$F$5:$F$193,MATCH($C42,Referentiel!$A$5:$A$193,0))))) | I42: =ROUND(SUMIFS(FEC_2025!$I:$I,FEC_2025!$E:$E,$A42)-SUMIFS(FEC_2025!$J:$J,FEC_2025!$E:$E,$A42),2) | J42: =IF($D42<>"",$D42,IF($C42="NON MAPPÉ","?",IF(I42>=0,INDEX(Referentiel!$C$5:$C$193,MATCH($C42,Referentiel!$A$5:$A$193,0)),INDEX(Referentiel!$D$5:$D$193,MATCH($C42,Referentiel!$A$5:$A$193,0))))) | K42: =IF($E42<>"",$E42,IF($C42="NON MAPPÉ","?",IF(I42>=0,INDEX(Referentiel!$E$5:$E$193,MATCH($C42,Referentiel!$A$5:$A$193,0)),INDEX(Referentiel!$F$5:$F$193,MATCH($C42,Referentiel!$A$5:$A$193,0)))))

Sheet Soldes_tiers
A1: Soldes par tiers des comptes collectifs
A2: Sert à séparer, comme la liasse, les soldes débiteurs et créditeurs des tiers (ex. clients créditeurs classés en autres dettes).
A4: Clé | B4: Compte | C4: Auxiliaire | D4: Tiers | E4: Solde 2024 | F4: Solde 2025
A5: 401000|F001 | B5: 401000 | C5: F001 | D5: Scierie du Nord | E5: =SUMIFS(FEC_2024!$M:$M,FEC_2024!$R:$R,$A5) | F5: =SUMIFS(FEC_2025!$M:$M,FEC_2025!$R:$R,$A5)
A6: 401000|F002 | B6: 401000 | C6: F002 | D6: Quincaillerie Pro Est | E6: =SUMIFS(FEC_2024!$M:$M,FEC_2024!$R:$R,$A6) | F6: =SUMIFS(FEC_2025!$M:$M,FEC_2025!$R:$R,$A6)
A7: 401000|F003 | B7: 401000 | C7: F003 | D7: Vernis et Finitions | E7: =SUMIFS(FEC_2024!$M:$M,FEC_2024!$R:$R,$A7) | F7: =SUMIFS(FEC_2025!$M:$M,FEC_2025!$R:$R,$A7)
A8: 401000|F004 | B8: 401000 | C8: F004 | D8: SCI Les Halles | E8: =SUMIFS(FEC_2024!$M:$M,FEC_2024!$R:$R,$A8) | F8: =SUMIFS(FEC_2025!$M:$M,FEC_2025!$R:$R,$A8)
A9: 401000|F005 | B9: 401000 | C9: F005 | D9: Energie Plus | E9: =SUMIFS(FEC_2024!$M:$M,FEC_2024!$R:$R,$A9) | F9: =SUMIFS(FEC_2025!$M:$M,FEC_2025!$R:$R,$A9)
A10: 401000|F006 | B10: 401000 | C10: F006 | D10: Assurances Mutuelles Exemple | E10: =SUMIFS(FEC_2024!$M:$M,FEC_2024!$R:$R,$A10) | F10: =SUMIFS(FEC_2025!$M:$M,FEC_2025!$R:$R,$A10)
A11: 401000|F007 | B11: 401000 | C11: F007 | D11: Cabinet Comptable Exemple | E11: =SUMIFS(FEC_2024!$M:$M,FEC_2024!$R:$R,$A11) | F11: =SUMIFS(FEC_2025!$M:$M,FEC_2025!$R:$R,$A11)
A12: 401000|F008 | B12: 401000 | C12: F008 | D12: Telecom Pro | E12: =SUMIFS(FEC_2024!$M:$M,FEC_2024!$R:$R,$A12) | F12: =SUMIFS(FEC_2025!$M:$M,FEC_2025!$R:$R,$A12)
A13: 411000|C001 | B13: 411000 | C13: C001 | D13: Hotel Les Tilleuls | E13: =SUMIFS(FEC_2024!$M:$M,FEC_2024!$R:$R,$A13) | F13: =SUMIFS(FEC_2025!$M:$M,FEC_2025!$R:$R,$A13)
A14: 411000|C002 | B14: 411000 | C14: C002 | D14: Agence Mobilis | E14: =SUMIFS(FEC_2024!$M:$M,FEC_2024!$R:$R,$A14) | F14: =SUMIFS(FEC_2025!$M:$M,FEC_2025!$R:$R,$A14)
A15: 411000|C003 | B15: 411000 | C15: C003 | D15: Residence Bel Air | E15: =SUMIFS(FEC_2024!$M:$M,FEC_2024!$R:$R,$A15) | F15: =SUMIFS(FEC_2025!$M:$M,FEC_2025!$R:$R,$A15)
A16: 411000|C004 | B16: 411000 | C16: C004 | D16: Cabinet Varenne Associes | E16: =SUMIFS(FEC_2024!$M:$M,FEC_2024!$R:$R,$A16) | F16: =SUMIFS(FEC_2025!$M:$M,FEC_2025!$R:$R,$A16)
... A20: 411000|C008 | B20: 411000 | C20: C008 | D20: Coworking Atelier 9 | E20: =SUMIFS(FEC_2024!$M:$M,FEC_2024!$R:$R,$A20) | F20: =SUMIFS(FEC_2025!$M:$M,FEC_2025!$R:$R,$A20)

Sheet Referentiel
A1: Référentiel de mapping Vestis
A2: Racine la plus longue retenue (4, 3 puis 2 caractères). Colonnes C à F modifiables : toute modification se répercute dans le classeur. | H2: Régime simplifié : correspondance des postes 2050-2053 vers les cases 2033-A et 2033-B.
A4: Racine | B4: Libellé | C4: Poste liasse si débiteur | D4: Poste liasse si créditeur | E4: Agrégat Vestis si débiteur | F4: Agrégat Vestis si créditeur | H4: Poste 2050 | I4: Case 2033
A5: 101 | B5: Capital | C5: DA | D5: DA | E5: CAPITAUX_PROPRES | F5: CAPITAUX_PROPRES | H5: AH | I5: 010
A6: 104 | B6: Primes d'émission | C6: DB | D6: DB | E6: CAPITAUX_PROPRES | F6: CAPITAUX_PROPRES | H6: AB | I6: 014
A7: 105 | B7: Écarts de réévaluation | C7: DC | D7: DC | E7: CAPITAUX_PROPRES | F7: CAPITAUX_PROPRES | H7: CX | I7: 014
A8: 1061 | B8: Réserve légale | C8: DD | D8: DD | E8: CAPITAUX_PROPRES | F8: CAPITAUX_PROPRES | H8: AF | I8: 014
A9: 1062 | B9: Réserves indisponibles | C9: DG | D9: DG | E9: CAPITAUX_PROPRES | F9: CAPITAUX_PROPRES | H9: AJ | I9: 014
A10: 1063 | B10: Réserves statutaires | C10: DE | D10: DE | E10: CAPITAUX_PROPRES | F10: CAPITAUX_PROPRES | H10: AL | I10: 014
A11: 1064 | B11: Réserves réglementées | C11: DF | D11: DF | E11: CAPITAUX_PROPRES | F11: CAPITAUX_PROPRES | H11: AI | I11: 012
A12: 1068 | B12: Autres réserves | C12: DG | D12: DG | E12: CAPITAUX_PROPRES | F12: CAPITAUX_PROPRES | H12: AC | I12: 016
A13: 11 | B13: Report à nouveau | C13: DH | D13: DH | E13: CAPITAUX_PROPRES | F13: CAPITAUX_PROPRES | H13: CQ | I13: 016
A14: 12 | B14: Résultat de l'exercice (si présent) | C14: DI | D14: DI | E14: CAPITAUX_PROPRES | F14: CAPITAUX_PROPRES | H14: AG | I14: 016
A15: 13 | B15: Subventions d'investissement | C15: DJ | D15: DJ | E15: CAPITAUX_PROPRES | F15: CAPITAUX_PROPRES | H15: AK | I15: 016
... A119: 53 | B119: Caisse | C119: CF | D119: CF | E119: TRESORERIE | F119: TRESORERIE | H119: HK | I119: 306
A120: 58 | B120: Virements internes | C120: CF | D120: EA | E120: TRESORERIE | F120: TRESORERIE
A121: 59 | B121: Dépréc. VMP | C121: CE | D121: CE | E121: TRESORERIE | F121: TRESORERIE | H121: Exception : comptes 45 (comptes courants) → case 173 au lieu de 156.
A122: 601 | B122: Achats de matières premières | C122: FU | D122: FU | E122: COUTS_DIRECTS | F122: COUTS_DIRECTS
A123: 602 | B123: Achats d'autres approvisionnements | C123: FU | D123: FU | E123: COUTS_DIRECTS | F123: COUTS_DIRECTS
A124: 6031 | B124: Variation de stock de matières | C124: FV | D124: FV | E124: COUTS_DIRECTS | F124: COUTS_DIRECTS
A125: 6032 | B125: Variation de stock d'approvisionnements | C125: FV | D125: FV | E125: COUTS_DIRECTS | F125: COUTS_DIRECTS
A126: 6037 | B126: Variation de stock de marchandises | C126: FT | D126: FT | E126: COUTS_DIRECTS | F126: COUTS_DIRECTS
A127: 604 | B127: Achats d'études et prestations (sous-traitance) | C127: FW | D127: FW | E127: COUTS_DIRECTS | F127: COUTS_DIRECTS
A128: 605 | B128: Achats de matériel et travaux | C128: FW | D128: FW | E128: COUTS_DIRECTS | F128: COUTS_DIRECTS
A129: 606 | B129: Achats non stockés | C129: FW | D129: FW | E129: CHARGES_EXTERNES | F129: CHARGES_EXTERNES
A130: 607 | B130: Achats de marchandises | C130: FS | D130: FS | E130: COUTS_DIRECTS | F130: COUTS_DIRECTS
A131: 608 | B131: Frais accessoires sur achats | C131: FU | D131: FU | E131: COUTS_DIRECTS | F131: COUTS_DIRECTS
A132: 609 | B132: Rabais, remises obtenus | C132: FU | D132: FU | E132: COUTS_DIRECTS | F132: COUTS_DIRECTS
A133: 61 | B133: Services extérieurs | C133: FW | D133: FW | E133: CHARGES_EXTERNES | F133: CHARGES_EXTERNES
... A193: 772 | B193: Produits sur exercices antérieurs | C193: HA | D193: HA | E193: EXCEPTIONNEL | F193: EXCEPTIONNEL

Sheet Journaux
A1: Typologie des journaux
A2: Type déduit automatiquement ; colonne E modifiable (A-NOUVEAUX, ACHATS, VENTES, BANQUE, OD, INVENTAIRE, EXTOURNE).
A4: Clé | B4: Exercice | C4: Code | D4: Libellé | E4: Type | F4: Nb lignes
A5: 2024|AC | B5: 2024 | C5: AC | D5: Journal des achats | E5: ACHATS | F5: =COUNTIF(FEC_2024!$A:$A,C5)
A6: 2024|AN | B6: 2024 | C6: AN | D6: A-nouveaux | E6: A-NOUVEAUX | F6: =COUNTIF(FEC_2024!$A:$A,C6)
A7: 2024|BQ | B7: 2024 | C7: BQ | D7: Banque Fictive | E7: BANQUE | F7: =COUNTIF(FEC_2024!$A:$A,C7)
A8: 2024|INV | B8: 2024 | C8: INV | D8: Inventaire | E8: INVENTAIRE | F8: =COUNTIF(FEC_2024!$A:$A,C8)
A9: 2024|OD | B9: 2024 | C9: OD | D9: Operations diverses | E9: OD | F9: =COUNTIF(FEC_2024!$A:$A,C9)
A10: 2024|SA | B10: 2024 | C10: SA | D10: Salaires | E10: OD | F10: =COUNTIF(FEC_2024!$A:$A,C10)
A11: 2024|VT | B11: 2024 | C11: VT | D11: Journal des ventes | E11: VENTES | F11: =COUNTIF(FEC_2024!$A:$A,C11)
A12: 2025|AC | B12: 2025 | C12: AC | D12: Journal des achats | E12: ACHATS | F12: =COUNTIF(FEC_2025!$A:$A,C12)
A13: 2025|AN | B13: 2025 | C13: AN | D13: A-nouveaux | E13: A-NOUVEAUX | F13: =COUNTIF(FEC_2025!$A:$A,C13)
A14: 2025|BQ | B14: 2025 | C14: BQ | D14: Banque Fictive | E14: BANQUE | F14: =COUNTIF(FEC_2025!$A:$A,C14)
A15: 2025|INV | B15: 2025 | C15: INV | D15: Inventaire | E15: INVENTAIRE | F15: =COUNTIF(FEC_2025!$A:$A,C15)
A16: 2025|OD | B16: 2025 | C16: OD | D16: Operations diverses | E16: OD | F16: =COUNTIF(FEC_2025!$A:$A,C16)
A17: 2025|SA | B17: 2025 | C17: SA | D17: Salaires | E17: OD | F17: =COUNTIF(FEC_2025!$A:$A,C17)
A18: 2025|VT | B18: 2025 | C18: VT | D18: Journal des ventes | E18: VENTES | F18: =COUNTIF(FEC_2025!$A:$A,C18)

Sheet FEC_2024
A1: JournalCode | B1: JournalLib | C1: EcritureNum | D1: EcritureDate | E1: CompteNum | F1: CompteLib | G1: PieceRef | H1: EcritureLib | I1: Debit | J1: Credit | K1: EcritureLet | L1: Tiers | M1: Montant (D-C) | N1: Mois | O1: Type journal | P1: Agrégat Vestis | Q1: Classe | R1: Clé tiers
A2: AN | B2: A-nouveaux | C2: AN00001 | D2: 45292 | E2: 101300 | F2: Capital souscrit appele verse | G2: AN2024 | H2: A-nouveaux 2024 | I2: 0 | J2: 100000 | M2: =I2-J2 | N2: 2024-01 | O2: =INDEX(Journaux!$E$5:$E$18,MATCH("2024|"&A2,Journaux!$A$5:$A$18,0)) | P2: =INDEX(Comptes!$H$5:$H$42,MATCH(E2,Comptes!$A$5:$A$42,0)) | Q2: 1
A3: AN | B3: A-nouveaux | C3: AN00001 | D3: 45292 | E3: 106100 | F3: Reserve legale | G3: AN2024 | H3: A-nouveaux 2024 | I3: 0 | J3: 10000 | M3: =I3-J3 | N3: 2024-01 | O3: =INDEX(Journaux!$E$5:$E$18,MATCH("2024|"&A3,Journaux!$A$5:$A$18,0)) | P3: =INDEX(Comptes!$H$5:$H$42,MATCH(E3,Comptes!$A$5:$A$42,0)) | Q3: 1
A4: AN | B4: A-nouveaux | C4: AN00001 | D4: 45292 | E4: 110000 | F4: Report a nouveau | G4: AN2024 | H4: A-nouveaux 2024 | I4: 0 | J4: 68000 | M4: =I4-J4 | N4: 2024-01 | O4: =INDEX(Journaux!$E$5:$E$18,MATCH("2024|"&A4,Journaux!$A$5:$A$18,0)) | P4: =INDEX(Comptes!$H$5:$H$42,MATCH(E4,Comptes!$A$5:$A$42,0)) | Q4: 1
A5: AN | B5: A-nouveaux | C5: AN00001 | D5: 45292 | E5: 164000 | F5: Emprunts aupres des etablissements de credit | G5: AN2024 | H5: A-nouveaux 2024 | I5: 0 | J5: 90000 | M5: =I5-J5 | N5: 2024-01 | O5: =INDEX(Journaux!$E$5:$E$18,MATCH("2024|"&A5,Journaux!$A$5:$A$18,0)) | P5: =INDEX(Comptes!$H$5:$H$42,MATCH(E5,Comptes!$A$5:$A$42,0)) | Q5: 1
A6: AN | B6: A-nouveaux | C6: AN00001 | D6: 45292 | E6: 215400 | F6: Materiel industriel | G6: AN2024 | H6: A-nouveaux 2024 | I6: 180000 | J6: 0 | M6: =I6-J6 | N6: 2024-01 | O6: =INDEX(Journaux!$E$5:$E$18,MATCH("2024|"&A6,Journaux!$A$5:$A$18,0)) | P6: =INDEX(Comptes!$H$5:$H$42,MATCH(E6,Comptes!$A$5:$A$42,0)) | Q6: 2
A7: AN | B7: A-nouveaux | C7: AN00001 | D7: 45292 | E7: 218300 | F7: Materiel de bureau et informatique | G7: AN2024 | H7: A-nouveaux 2024 | I7: 25000 | J7: 0 | M7: =I7-J7 | N7: 2024-01 | O7: =INDEX(Journaux!$E$5:$E$18,MATCH("2024|"&A7,Journaux!$A$5:$A$18,0)) | P7: =INDEX(Comptes!$H$5:$H$42,MATCH(E7,Comptes!$A$5:$A$42,0)) | Q7: 2
A8: AN | B8: A-nouveaux | C8: AN00001 | D8: 45292 | E8: 281540 | F8: Amortissements materiel industriel | G8: AN2024 | H8: A-nouveaux 2024 | I8: 0 | J8: 70000 | M8: =I8-J8 | N8: 2024-01 | O8: =INDEX(Journaux!$E$5:$E$18,MATCH("2024|"&A8,Journaux!$A$5:$A$18,0)) | P8: =INDEX(Comptes!$H$5:$H$42,MATCH(E8,Comptes!$A$5:$A$42,0)) | Q8: 2
A9: AN | B9: A-nouveaux | C9: AN00001 | D9: 45292 | E9: 281830 | F9: Amortissements materiel de bureau | G9: AN2024 | H9: A-nouveaux 2024 | I9: 0 | J9: 12000 | M9: =I9-J9 | N9: 2024-01 | O9: =INDEX(Journaux!$E$5:$E$18,MATCH("2024|"&A9,Journaux!$A$5:$A$18,0)) | P9: =INDEX(Comptes!$H$5:$H$42,MATCH(E9,Comptes!$A$5:$A$42,0)) | Q9: 2
A10: AN | B10: A-nouveaux | C10: AN00001 | D10: 45292 | E10: 310000 | F10: Stocks de matieres premieres | G10: AN2024 | H10: A-nouveaux 2024 | I10: 45000 | J10: 0 | M10: =I10-J10 | N10: 2024-01 | O10: =INDEX(Journaux!$E$5:$E$18,MATCH("2024|"&A10,Journaux!$A$5:$A$18,0)) | P10: =INDEX(Comptes!$H$5:$H$42,MATCH(E10,Comptes!$A$5:$A$42,0)) | Q10: 3
A11: AN | B11: A-nouveaux | C11: AN00001 | D11: 45292 | E11: 512000 | F11: Banque Fictive | G11: AN2024 | H11: A-nouveaux 2024 | I11: 85000 | J11: 0 | M11: =I11-J11 | N11: 2024-01 | O11: =INDEX(Journaux!$E$5:$E$18,MATCH("2024|"&A11,Journaux!$A$5:$A$18,0)) | P11: =INDEX(Comptes!$H$5:$H$42,MATCH(E11,Comptes!$A$5:$A$42,0)) | Q11: 5
A12: AN | B12: A-nouveaux | C12: AN00001 | D12: 45292 | E12: 455100 | F12: Compte courant d'associe | G12: AN2024 | H12: A-nouveaux 2024 | I12: 0 | J12: 15000 | M12: =I12-J12 | N12: 2024-01 | O12: =INDEX(Journaux!$E$5:$E$18,MATCH("2024|"&A12,Journaux!$A$5:$A$18,0)) | P12: =INDEX(Comptes!$H$5:$H$42,MATCH(E12,Comptes!$A$5:$A$42,0)) | Q12: 4
A13: AN | B13: A-nouveaux | C13: AN00001 | D13: 45292 | E13: 431000 | F13: Securite sociale | G13: AN2024 | H13: A-nouveaux 2024 | I13: 0 | J13: 18000 | M13: =I13-J13 | N13: 2024-01 | O13: =INDEX(Journaux!$E$5:$E$18,MATCH("2024|"&A13,Journaux!$A$5:$A$18,0)) | P13: =INDEX(Comptes!$H$5:$H$42,MATCH(E13,Comptes!$A$5:$A$42,0)) | Q13: 4
A14: AN | B14: A-nouveaux | C14: AN00001 | D14: 45292 | E14: 445510 | F14: TVA a decaisser | G14: AN2024 | H14: A-nouveaux 2024 | I14: 0 | J14: 12000 | M14: =I14-J14 | N14: 2024-01 | O14: =INDEX(Journaux!$E$5:$E$18,MATCH("2024|"&A14,Journaux!$A$5:$A$18,0)) | P14: =INDEX(Comptes!$H$5:$H$42,MATCH(E14,Comptes!$A$5:$A$42,0)) | Q14: 4
A15: AN | B15: A-nouveaux | C15: AN00001 | D15: 45292 | E15: 411000 | F15: Clients | G15: AN2024 | H15: A-nouveaux 2024 | I15: 30000 | J15: 0 | K15: AAA | L15: Hotel Les Tilleuls | M15: =I15-J15 | N15: 2024-01 | O15: =INDEX(Journaux!$E$5:$E$18,MATCH("2024|"&A15,Journaux!$A$5:$A$18,0)) | P15: =INDEX(Comptes!$H$5:$H$42,MATCH(E15,Comptes!$A$5:$A$42,0)) | Q15: 4 | R15: 411000|C001
A16: AN | B16: A-nouveaux | C16: AN00001 | D16: 45292 | E16: 411000 | F16: Clients | G16: AN2024 | H16: A-nouveaux 2024 | I16: 26000 | J16: 0 | K16: AAB | L16: Residence Bel Air | M16: =I16-J16 | N16: 2024-01 | O16: =INDEX(Journaux!$E$5:$E$18,MATCH("2024|"&A16,Journaux!$A$5:$A$18,0)) | P16: =INDEX(Comptes!$H$5:$H$42,MATCH(E16,Comptes!$A$5:$A$42,0)) | Q16: 4 | R16: 411000|C003
A17: AN | B17: A-nouveaux | C17: AN00001 | D17: 45292 | E17: 411000 | F17: Clients | G17: AN2024 | H17: A-nouveaux 2024 | I17: 22000 | J17: 0 | K17: AAC | L17: Cabinet Varenne Associes | M17: =I17-J17 | N17: 2024-01 | O17: =INDEX(Journaux!$E$5:$E$18,MATCH("2024|"&A17,Journaux!$A$5:$A$18,0)) | P17: =INDEX(Comptes!$H$5:$H$42,MATCH(E17,Comptes!$A$5:$A$42,0)) | Q17: 4 | R17: 411000|C004
A18: AN | B18: A-nouveaux | C18: AN00001 | D18: 45292 | E18: 411000 | F18: Clients | G18: AN2024 | H18: A-nouveaux 2024 | I18: 24000 | J18: 0 | K18: AAD | L18: Clinique du Parc | M18: =I18-J18 | N18: 2024-01 | O18: =INDEX(Journaux!$E$5:$E$18,MATCH("2024|"&A18,Journaux!$A$5:$A$18,0)) | P18: =INDEX(Comptes!$H$5:$H$42,MATCH(E18,Comptes!$A$5:$A$42,0)) | Q18: 4 | R18: 411000|C006
A19: AN | B19: A-nouveaux | C19: AN00001 | D19: 45292 | E19: 411000 | F19: Clients | G19: AN2024 | H19: A-nouveaux 2024 | I19: 18000 | J19: 0 | K19: AAE | L19: Coworking Atelier 9 | M19: =I19-J19 | N19: 2024-01 | O19: =INDEX(Journaux!$E$5:$E$18,MATCH("2024|"&A19,Journaux!$A$5:$A$18,0)) | P19: =INDEX(Comptes!$H$5:$H$42,MATCH(E19,Comptes!$A$5:$A$42,0)) | Q19: 4 | R19: 411000|C008
A20: AN | B20: A-nouveaux | C20: AN00001 | D20: 45292 | E20: 401000 | F20: Fournisseurs | G20: AN2024 | H20: A-nouveaux 2024 | I20: 0 | J20: 28000 | K20: ABH | L20: Scierie du Nord | M20: =I20-J20 | N20: 2024-01 | O20: =INDEX(Journaux!$E$5:$E$18,MATCH("2024|"&A20,Journaux!$A$5:$A$18,0)) | P20: =INDEX(Comptes!$H$5:$H$42,MATCH(E20,Comptes!$A$5:$A$42,0)) | Q20: 4 | R20: 401000|F001
A21: AN | B21: A-nouveaux | C21: AN00001 | D21: 45292 | E21: 401000 | F21: Fournisseurs | G21: AN2024 | H21: A-nouveaux 2024 | I21: 0 | J21: 12000 | K21: ABI | L21: Quincaillerie Pro Est | M21: =I21-J21 | N21: 2024-01 | O21: =INDEX(Journaux!$E$5:$E$18,MATCH("2024|"&A21,Journaux!$A$5:$A$18,0)) | P21: =INDEX(Comptes!$H$5:$H$42,MATCH(E21,Comptes!$A$5:$A$42,0)) | Q21: 4 | R21: 401000|F002
A22: AN | B22: A-nouveaux | C22: AN00001 | D22: 45292 | E22: 401000 | F22: Fournisseurs | G22: AN2024 | H22: A-nouveaux 2024 | I22: 0 | J22: 9000 | K22: ABJ | L22: Vernis et Finitions | M22: =I22-J22 | N22: 2024-01 | O22: =INDEX(Journaux!$E$5:$E$18,MATCH("2024|"&A22,Journaux!$A$5:$A$18,0)) | P22: =INDEX(Comptes!$H$5:$H$42,MATCH(E22,Comptes!$A$5:$A$42,0)) | Q22: 4 | R22: 401000|F003
A23: AN | B23: A-nouveaux | C23: AN00001 | D23: 45292 | E23: 401000 | F23: Fournisseurs | G23: AN2024 | H23: A-nouveaux 2024 | I23: 0 | J23: 4000 | K23: ABK | L23: Energie Plus | M23: =I23-J23 | N23: 2024-01 | O23: =INDEX(Journaux!$E$5:$E$18,MATCH("2024|"&A23,Journaux!$A$5:$A$18,0)) | P23: =INDEX(Comptes!$H$5:$H$42,MATCH(E23,Comptes!$A$5:$A$42,0)) | Q23: 4 | R23: 401000|F005
A24: AN | B24: A-nouveaux | C24: AN00001 | D24: 45292 | E24: 401000 | F24: Fournisseurs | G24: AN2024 | H24: A-nouveaux 2024 | I24: 0 | J24: 7000 | K24: ABL | L24: SCI Les Halles | M24: =I24-J24 | N24: 2024-01 | O24: =INDEX(Journaux!$E$5:$E$18,MATCH("2024|"&A24,Journaux!$A$5:$A$18,0)) | P24: =INDEX(Comptes!$H$5:$H$42,MATCH(E24,Comptes!$A$5:$A$42,0)) | Q24: 4 | R24: 401000|F004
A25: VT | B25: Journal des ventes | C25: VT00002 | D25: 45292 | E25: 411000 | F25: Clients | G25: FA2024-0002 | H25: Facture FA2024-0002 Hotel Les Tilleuls | I25: 38532.72 | J25: 0 | K25: AAG | L25: Hotel Les Tilleuls | M25: =I25-J25 | N25: 2024-01 | O25: =INDEX(Journaux!$E$5:$E$18,MATCH("2024|"&A25,Journaux!$A$5:$A$18,0)) | P25: =INDEX(Comptes!$H$5:$H$42,MATCH(E25,Comptes!$A$5:$A$42,0)) | Q25: 4 | R25: 411000|C001
A26: VT | B26: Journal des ventes | C26: VT00002 | D26: 45292 | E26: 701000 | F26: Ventes de produits finis | G26: FA2024-0002 | H26: Facture FA2024-0002 Hotel Les Tilleuls | I26: 0 | J26: 32110.6 | M26: =I26-J26 | N26: 2024-01 | O26: =INDEX(Journaux!$E$5:$E$18,MATCH("2024|"&A26,Journaux!$A$5:$A$18,0)) | P26: =INDEX(Comptes!$H$5:$H$42,MATCH(E26,Comptes!$A$5:$A$42,0)) | Q26: 7
A27: VT | B27: Journal des ventes | C27: VT00002 | D27: 45292 | E27: 445710 | F27: TVA collectee | G27: FA2024-0002 | H27: Facture FA2024-0002 Hotel Les Tilleuls | I27: 0 | J27: 6422.12 | M27: =I27-J27 | N27: 2024-01 | O27: =INDEX(Journaux!$E$5:$E$18,MATCH("2024|"&A27,Journaux!$A$5:$A$18,0)) | P27: =INDEX(Comptes!$H$5:$H$42,MATCH(E27,Comptes!$A$5:$A$42,0)) | Q27: 4
A28: AC | B28: Journal des achats | C28: AC00002 | D28: 45294 | E28: 601000 | F28: Achats de matieres premieres | G28: F001-2024012 | H28: Facture Scierie du Nord F001-2024012 | I28: 26592.21 | J28: 0 | M28: =I28-J28 | N28: 2024-01 | O28: =INDEX(Journaux!$E$5:$E$18,MATCH("2024|"&A28,Journaux!$A$5:$A$18,0)) | P28: =INDEX(Comptes!$H$5:$H$42,MATCH(E28,Comptes!$A$5:$A$42,0)) | Q28: 6
A29: AC | B29: Journal des achats | C29: AC00002 | D29: 45294 | E29: 445660 | F29: TVA deductible sur ABS | G29: F001-2024012 | H29: Facture Scierie du Nord F001-2024012 | I29: 5318.44 | J29: 0 | M29: =I29-J29 | N29: 2024-01 | O29: =INDEX(Journaux!$E$5:$E$18,MATCH("2024|"&A29,Journaux!$A$5:$A$18,0)) | P29: =INDEX(Comptes!$H$5:$H$42,MATCH(E29,Comptes!$A$5:$A$42,0)) | Q29: 4
A30: AC | B30: Journal des achats | C30: AC00002 | D30: 45294 | E30: 401000 | F30: Fournisseurs | G30: F001-2024012 | H30: Facture Scierie du Nord F001-2024012 | I30: 0 | J30: 31910.65 | K30: ABN | L30: Scierie du Nord | M30: =I30-J30 | N30: 2024-01 | O30: =INDEX(Journaux!$E$5:$E$18,MATCH("2024|"&A30,Journaux!$A$5:$A$18,0)) | P30: =INDEX(Comptes!$H$5:$H$42,MATCH(E30,Comptes!$A$5:$A$42,0)) | Q30: 4 | R30: 401000|F001
A31: AC | B31: Journal des achats | C31: AC00003 | D31: 45296 | E31: 613200 | F31: Locations immobilieres | G31: F004-202401 | H31: Facture SCI Les Halles 2024-01 | I31: 8500 | J31: 0 | M31: =I31-J31 | N31: 2024-01 | O31: =INDEX(Journaux!$E$5:$E$18,MATCH("2024|"&A31,Journaux!$A$5:$A$18,0)) | P31: =INDEX(Comptes!$H$5:$H$42,MATCH(E31,Comptes!$A$5:$A$42,0)) | Q31: 6
A32: AC | B32: Journal des achats | C32: AC00003 | D32: 45296 | E32: 445660 | F32: TVA deductible sur ABS | G32: F004-202401 | H32: Facture SCI Les Halles 2024-01 | I32: 1700 | J32: 0 | M32: =I32-J32 | N32: 2024-01 | O32: =INDEX(Journaux!$E$5:$E$18,MATCH("2024|"&A32,Journaux!$A$5:$A$18,0)) | P32: =INDEX(Comptes!$H$5:$H$42,MATCH(E32,Comptes!$A$5:$A$42,0)) | Q32: 4
A33: AC | B33: Journal des achats | C33: AC00003 | D33: 45296 | E33: 401000 | F33: Fournisseurs | G33: F004-202401 | H33: Facture SCI Les Halles 2024-01 | I33: 0 | J33: 10200 | K33: ABO | L33: SCI Les Halles | M33: =I33-J33 | N33: 2024-01 | O33: =INDEX(Journaux!$E$5:$E$18,MATCH("2024|"&A33,Journaux!$A$5:$A$18,0)) | P33: =INDEX(Comptes!$H$5:$H$42,MATCH(E33,Comptes!$A$5:$A$42,0)) | Q33: 4 | R33: 401000|F004
A34: AC | B34: Journal des achats | C34: AC00004 | D34: 45296 | E34: 606100 | F34: Fournitures non stockables energie | G34: F005-202401 | H34: Facture Energie Plus 2024-01 | I34: 2530.57 | J34: 0 | M34: =I34-J34 | N34: 2024-01 | O34: =INDEX(Journaux!$E$5:$E$18,MATCH("2024|"&A34,Journaux!$A$5:$A$18,0)) | P34: =INDEX(Comptes!$H$5:$H$42,MATCH(E34,Comptes!$A$5:$A$42,0)) | Q34: 6
A35: AC | B35: Journal des achats | C35: AC00004 | D35: 45296 | E35: 445660 | F35: TVA deductible sur ABS | G35: F005-202401 | H35: Facture Energie Plus 2024-01 | I35: 506.11 | J35: 0 | M35: =I35-J35 | N35: 2024-01 | O35: =INDEX(Journaux!$E$5:$E$18,MATCH("2024|"&A35,Journaux!$A$5:$A$18,0)) | P35: =INDEX(Comptes!$H$5:$H$42,MATCH(E35,Comptes!$A$5:$A$42,0)) | Q35: 4
A36: AC | B36: Journal des achats | C36: AC00004 | D36: 45296 | E36: 401000 | F36: Fournisseurs | G36: F005-202401 | H36: Facture Energie Plus 2024-01 | I36: 0 | J36: 3036.68 | K36: ABP | L36: Energie Plus | M36: =I36-J36 | N36: 2024-01 | O36: =INDEX(Journaux!$E$5:$E$18,MATCH("2024|"&A36,Journaux!$A$5:$A$18,0)) | P36: =INDEX(Comptes!$H$5:$H$42,MATCH(E36,Comptes!$A$5:$A$42,0)) | Q36: 4 | R36: 401000|F005
A37: AC | B37: Journal des achats | C37: AC00005 | D37: 45296 | E37: 626000 | F37: Frais postaux et telecommunications | G37: F008-202401 | H37: Facture Telecom Pro 2024-01 | I37: 480 | J37: 0 | M37: =I37-J37 | N37: 2024-01 | O37: =INDEX(Journaux!$E$5:$E$18,MATCH("2024|"&A37,Journaux!$A$5:$A$18,0)) | P37: =INDEX(Comptes!$H$5:$H$42,MATCH(E37,Comptes!$A$5:$A$42,0)) | Q37: 6
A38: AC | B38: Journal des achats | C38: AC00005 | D38: 45296 | E38: 445660 | F38: TVA deductible sur ABS | G38: F008-202401 | H38: Facture Telecom Pro 2024-01 | I38: 96 | J38: 0 | M38: =I38-J38 | N38: 2024-01 | O38: =INDEX(Journaux!$E$5:$E$18,MATCH("2024|"&A38,Journaux!$A$5:$A$18,0)) | P38: =INDEX(Comptes!$H$5:$H$42,MATCH(E38,Comptes!$A$5:$A$42,0)) | Q38: 4
A39: AC | B39: Journal des achats | C39: AC00005 | D39: 45296 | E39: 401000 | F39: Fournisseurs | G39: F008-202401 | H39: Facture Telecom Pro 2024-01 | I39: 0 | J39: 576 | K39: ABQ | L39: Telecom Pro | M39: =I39-J39 | N39: 2024-01 | O39: =INDEX(Journaux!$E$5:$E$18,MATCH("2024|"&A39,Journaux!$A$5:$A$18,0)) | P39: =INDEX(Comptes!$H$5:$H$42,MATCH(E39,Comptes!$A$5:$A$42,0)) | Q39: 4 | R39: 401000|F008
A40: AC | B40: Journal des achats | C40: AC00006 | D40: 45296 | E40: 616000 | F40: Primes d'assurance | G40: F006-202401 | H40: Facture Assurances Mutuelles Exemple 2024-01 | I40: 3000 | J40: 0 | M40: =I40-J40 | N40: 2024-01 | O40: =INDEX(Journaux!$E$5:$E$18,MATCH("2024|"&A40,Journaux!$A$5:$A$18,0)) | P40: =INDEX(Comptes!$H$5:$H$42,MATCH(E40,Comptes!$A$5:$A$42,0)) | Q40: 6
A41: AC | B41: Journal des achats | C41: AC00006 | D41: 45296 | E41: 401000 | F41: Fournisseurs | G41: F006-202401 | H41: Facture Assurances Mutuelles Exemple 2024-01 | I41: 0 | J41: 3000 | K41: ABR | L41: Assurances Mutuelles Exemple | M41: =I41-J41 | N41: 2024-01 | O41: =INDEX(Journaux!$E$5:$E$18,MATCH("2024|"&A41,Journaux!$A$5:$A$18,0)) | P41: =INDEX(Comptes!$H$5:$H$42,MATCH(E41,Comptes!$A$5:$A$42,0)) | Q41: 4 | R41: 401000|F006
A42: VT | B42: Journal des ventes | C42: VT00003 | D42: 45299 | E42: 411000 | F42: Clients | G42: FA2024-0003 | H42: Facture FA2024-0003 Cabinet Varenne Associes | I42: 25702.04 | J42: 0 | K42: AAH | L42: Cabinet Varenne Associes | M42: =I42-J42 | N42: 2024-01 | O42: =INDEX(Journaux!$E$5:$E$18,MATCH("2024|"&A42,Journaux!$A$5:$A$18,0)) | P42: =INDEX(Comptes!$H$5:$H$42,MATCH(E42,Comptes!$A$5:$A$42,0)) | Q42: 4 | R42: 411000|C004
A43: VT | B43: Journal des ventes | C43: VT00003 | D43: 45299 | E43: 701000 | F43: Ventes de produits finis | G43: FA2024-0003 | H43: Facture FA2024-0003 Cabinet Varenne Associes | I43: 0 | J43: 21418.37 | M43: =I43-J43 | N43: 2024-01 | O43: =INDEX(Journaux!$E$5:$E$18,MATCH("2024|"&A43,Journaux!$A$5:$A$18,0)) | P43: =INDEX(Comptes!$H$5:$H$42,MATCH(E43,Comptes!$A$5:$A$42,0)) | Q43: 7
A44: VT | B44: Journal des ventes | C44: VT00003 | D44: 45299 | E44: 445710 | F44: TVA collectee | G44: FA2024-0003 | H44: Facture FA2024-0003 Cabinet Varenne Associes | I44: 0 | J44: 4283.67 | M44: =I44-J44 | N44: 2024-01 | O44: =INDEX(Journaux!$E$5:$E$18,MATCH("2024|"&A44,Journaux!$A$5:$A$18,0)) | P44: =INDEX(Comptes!$H$5:$H$42,MATCH(E44,Comptes!$A$5:$A$42,0)) | Q44: 4
A45: VT | B45: Journal des ventes | C45: VT00005 | D45: 45299 | E45: 411000 | F45: Clients | G45: FA2024-0005 | H45: Facture FA2024-0005 Boutique Hetre et Chene | I45: 22023.36 | J45: 0 | K45: AAJ | L45: Boutique Hetre et Chene | M45: =I45-J45 | N45: 2024-01 | O45: =INDEX(Journaux!$E$5:$E$18,MATCH("2024|"&A45,Journaux!$A$5:$A$18,0)) | P45: =INDEX(Comptes!$H$5:$H$42,MATCH(E45,Comptes!$A$5:$A$42,0)) | Q45: 4 | R45: 411000|C007
A46: VT | B46: Journal des ventes | C46: VT00005 | D46: 45299 | E46: 701000 | F46: Ventes de produits finis | G46: FA2024-0005 | H46: Facture FA2024-0005 Boutique Hetre et Chene | I46: 0 | J46: 18352.8 | M46: =I46-J46 | N46: 2024-01 | O46: =INDEX(Journaux!$E$5:$E$18,MATCH("2024|"&A46,Journaux!$A$5:$A$18,0)) | P46: =INDEX(Comptes!$H$5:$H$42,MATCH(E46,Comptes!$A$5:$A$42,0)) | Q46: 7
A47: VT | B47: Journal des ventes | C47: VT00005 | D47: 45299 | E47: 445710 | F47: TVA collectee | G47: FA2024-0005 | H47: Facture FA2024-0005 Boutique Hetre et Chene | I47: 0 | J47: 3670.56 | M47: =I47-J47 | N47: 2024-01 | O47: =INDEX(Journaux!$E$5:$E$18,MATCH("2024|"&A47,Journaux!$A$5:$A$18,0)) | P47: =INDEX(Comptes!$H$5:$H$42,MATCH(E47,Comptes!$A$5:$A$42,0)) | Q47: 4
A48: BQ | B48: Banque Fictive | C48: BQ00002 | D48: 45301 | E48: 164000 | F48: Emprunts aupres des etablissements de credit | G48: ECH202401 | H48: Echeance emprunt 01/2024 | I48: 2000 | J48: 0 | M48: =I48-J48 | N48: 2024-01 | O48: =INDEX(Journaux!$E$5:$E$18,MATCH("2024|"&A48,Journaux!$A$5:$A$18,0)) | P48: =INDEX(Comptes!$H$5:$H$42,MATCH(E48,Comptes!$A$5:$A$42,0)) | Q48: 1
A49: BQ | B49: Banque Fictive | C49: BQ00002 | D49: 45301 | E49: 661100 | F49: Interets des emprunts | G49: ECH202401 | H49: Echeance emprunt 01/2024 | I49: 300 | J49: 0 | M49: =I49-J49 | N49: 2024-01 | O49: =INDEX(Journaux!$E$5:$E$18,MATCH("2024|"&A49,Journaux!$A$5:$A$18,0)) | P49: =INDEX(Comptes!$H$5:$H$42,MATCH(E49,Comptes!$A$5:$A$42,0)) | Q49: 6
A50: BQ | B50: Banque Fictive | C50: BQ00002 | D50: 45301 | E50: 512000 | F50: Banque Fictive | G50: ECH202401 | H50: Echeance emprunt 01/2024 | I50: 0 | J50: 2300 | M50: =I50-J50 | N50: 2024-01 | O50: =INDEX(Journaux!$E$5:$E$18,MATCH("2024|"&A50,Journaux!$A$5:$A$18,0)) | P50: =INDEX(Comptes!$H$5:$H$42,MATCH(E50,Comptes!$A$5:$A$42,0)) | Q50: 5
A51: BQ | B51: Banque Fictive | C51: BQ00120 | D51: 45301 | E51: 401000 | F51: Fournisseurs | G51: DEC-AN2024 | H51: Reglement fournisseur Scierie du Nord AN2024 | I51: 28000 | J51: 0 | K51: ABH | L51: Scierie du Nord | M51: =I51-J51 | N51: 2024-01 | O51: =INDEX(Journaux!$E$5:$E$18,MATCH("2024|"&A51,Journaux!$A$5:$A$18,0)) | P51: =INDEX(Comptes!$H$5:$H$42,MATCH(E51,Comptes!$A$5:$A$42,0)) | Q51: 4 | R51: 401000|F001
A52: BQ | B52: Banque Fictive | C52: BQ00120 | D52: 45301 | E52: 512000 | F52: Banque Fictive | G52: DEC-AN2024 | H52: Reglement fournisseur Scierie du Nord AN2024 | I52: 0 | J52: 28000 | M52: =I52-J52 | N52: 2024-01 | O52: =INDEX(Journaux!$E$5:$E$18,MATCH("2024|"&A52,Journaux!$A$5:$A$18,0)) | P52: =INDEX(Comptes!$H$5:$H$42,MATCH(E52,Comptes!$A$5:$A$42,0)) | Q52: 5
A53: BQ | B53: Banque Fictive | C53: BQ00037 | D53: 45306 | E53: 431000 | F53: Securite sociale | G53: URSSAF202312 | H53: Reglement URSSAF 12/2023 | I53: 18000 | J53: 0 | M53: =I53-J53 | N53: 2024-01 | O53: =INDEX(Journaux!$E$5:$E$18,MATCH("2024|"&A53,Journaux!$A$5:$A$18,0)) | P53: =INDEX(Comptes!$H$5:$H$42,MATCH(E53,Comptes!$A$5:$A$42,0)) | Q53: 4
A54: BQ | B54: Banque Fictive | C54: BQ00037 | D54: 45306 | E54: 512000 | F54: Banque Fictive | G54: URSSAF202312 | H54: Reglement URSSAF 12/2023 | I54: 0 | J54: 18000 | M54: =I54-J54 | N54: 2024-01 | O54: =INDEX(Journaux!$E$5:$E$18,MATCH("2024|"&A54,Journaux!$A$5:$A$18,0)) | P54: =INDEX(Comptes!$H$5:$H$42,MATCH(E54,Comptes!$A$5:$A$42,0)) | Q54: 5
A55: BQ | B55: Banque Fictive | C55: BQ00061 | D55: 45306 | E55: 512000 | F55: Banque Fictive | G55: ENC-AN2024 | H55: Reglement client Hotel Les Tilleuls AN2024 | I55: 30000 | J55: 0 | M55: =I55-J55 | N55: 2024-01 | O55: =INDEX(Journaux!$E$5:$E$18,MATCH("2024|"&A55,Journaux!$A$5:$A$18,0)) | P55: =INDEX(Comptes!$H$5:$H$42,MATCH(E55,Comptes!$A$5:$A$42,0)) | Q55: 5
A56: BQ | B56: Banque Fictive | C56: BQ00061 | D56: 45306 | E56: 411000 | F56: Clients | G56: ENC-AN2024 | H56: Reglement client Hotel Les Tilleuls AN2024 | I56: 0 | J56: 30000 | K56: AAA | L56: Hotel Les Tilleuls | M56: =I56-J56 | N56: 2024-01 | O56: =INDEX(Journaux!$E$5:$E$18,MATCH("2024|"&A56,Journaux!$A$5:$A$18,0)) | P56: =INDEX(Comptes!$H$5:$H$42,MATCH(E56,Comptes!$A$5:$A$42,0)) | Q56: 4 | R56: 411000|C001
A57: BQ | B57: Banque Fictive | C57: BQ00121 | D57: 45306 | E57: 401000 | F57: Fournisseurs | G57: DEC-AN2024 | H57: Reglement fournisseur Quincaillerie Pro Est AN2024 | I57: 12000 | J57: 0 | K57: ABI | L57: Quincaillerie Pro Est | M57: =I57-J57 | N57: 2024-01 | O57: =INDEX(Journaux!$E$5:$E$18,MATCH("2024|"&A57,Journaux!$A$5:$A$18,0)) | P57: =INDEX(Comptes!$H$5:$H$42,MATCH(E57,Comptes!$A$5:$A$42,0)) | Q57: 4 | R57: 401000|F002
A58: BQ | B58: Banque Fictive | C58: BQ00121 | D58: 45306 | E58: 512000 | F58: Banque Fictive | G58: DEC-AN2024 | H58: Reglement fournisseur Quincaillerie Pro Est AN2024 | I58: 0 | J58: 12000 | M58: =I58-J58 | N58: 2024-01 | O58: =INDEX(Journaux!$E$5:$E$18,MATCH("2024|"&A58,Journaux!$A$5:$A$18,0)) | P58: =INDEX(Comptes!$H$5:$H$42,MATCH(E58,Comptes!$A$5:$A$42,0)) | Q58: 5
A59: BQ | B59: Banque Fictive | C59: BQ00062 | D59: 45309 | E59: 512000 | F59: Banque Fictive | G59: ENC-AN2024 | H59: Reglement client Residence Bel Air AN2024 | I59: 26000 | J59: 0 | M59: =I59-J59 | N59: 2024-01 | O59: =INDEX(Journaux!$E$5:$E$18,MATCH("2024|"&A59,Journaux!$A$5:$A$18,0)) | P59: =INDEX(Comptes!$H$5:$H$42,MATCH(E59,Comptes!$A$5:$A$42,0)) | Q59: 5
A60: BQ | B60: Banque Fictive | C60: BQ00062 | D60: 45309 | E60: 411000 | F60: Clients | G60: ENC-AN2024 | H60: Reglement client Residence Bel Air AN2024 | I60: 0 | J60: 26000 | K60: AAB | L60: Residence Bel Air | M60: =I60-J60 | N60: 2024-01 | O60: =INDEX(Journaux!$E$5:$E$18,MATCH("2024|"&A60,Journaux!$A$5:$A$18,0)) | P60: =INDEX(Comptes!$H$5:$H$42,MATCH(E60,Comptes!$A$5:$A$42,0)) | Q60: 4 | R60: 411000|C003
A61: BQ | B61: Banque Fictive | C61: BQ00122 | D61: 45309 | E61: 401000 | F61: Fournisseurs | G61: DEC-AN2024 | H61: Reglement fournisseur Vernis et Finitions AN2024 | I61: 9000 | J61: 0 | K61: ABJ | L61: Vernis et Finitions | M61: =I61-J61 | N61: 2024-01 | O61: =INDEX(Journaux!$E$5:$E$18,MATCH("2024|"&A61,Journaux!$A$5:$A$18,0)) | P61: =INDEX(Comptes!$H$5:$H$42,MATCH(E61,Comptes!$A$5:$A$42,0)) | Q61: 4 | R61: 401000|F003
A62: BQ | B62: Banque Fictive | C62: BQ00122 | D62: 45309 | E62: 512000 | F62: Banque Fictive | G62: DEC-AN2024 | H62: Reglement fournisseur Vernis et Finitions AN2024 | I62: 0 | J62: 9000 | M62: =I62-J62 | N62: 2024-01 | O62: =INDEX(Journaux!$E$5:$E$18,MATCH("2024|"&A62,Journaux!$A$5:$A$18,0)) | P62: =INDEX(Comptes!$H$5:$H$42,MATCH(E62,Comptes!$A$5:$A$42,0)) | Q62: 5
A63: VT | B63: Journal des ventes | C63: VT00004 | D63: 45309 | E63: 411000 | F63: Clients | G63: FA2024-0004 | H63: Facture FA2024-0004 Hotel Les Tilleuls | I63: 22980.32 | J63: 0 | K63: AAI | L63: Hotel Les Tilleuls | M63: =I63-J63 | N63: 2024-01 | O63: =INDEX(Journaux!$E$5:$E$18,MATCH("2024|"&A63,Journaux!$A$5:$A$18,0)) | P63: =INDEX(Comptes!$H$5:$H$42,MATCH(E63,Comptes!$A$5:$A$42,0)) | Q63: 4 | R63: 411000|C001
A64: VT | B64: Journal des ventes | C64: VT00004 | D64: 45309 | E64: 701000 | F64: Ventes de produits finis | G64: FA2024-0004 | H64: Facture FA2024-0004 Hotel Les Tilleuls | I64: 0 | J64: 19150.27 | M64: =I64-J64 | N64: 2024-01 | O64: =INDEX(Journaux!$E$5:$E$18,MATCH("2024|"&A64,Journaux!$A$5:$A$18,0)) | P64: =INDEX(Comptes!$H$5:$H$42,MATCH(E64,Comptes!$A$5:$A$42,0)) | Q64: 7
A65: VT | B65: Journal des ventes | C65: VT00004 | D65: 45309 | E65: 445710 | F65: TVA collectee | G65: FA2024-0004 | H65: Facture FA2024-0004 Hotel Les Tilleuls | I65: 0 | J65: 3830.05 | M65: =I65-J65 | N65: 2024-01 | O65: =INDEX(Journaux!$E$5:$E$18,MATCH("2024|"&A65,Journaux!$A$5:$A$18,0)) | P65: =INDEX(Comptes!$H$5:$H$42,MATCH(E65,Comptes!$A$5:$A$42,0)) | Q65: 4
A66: VT | B66: Journal des ventes | C66: VT00001 | D66: 45310 | E66: 411000 | F66: Clients | G66: FA2024-0001 | H66: Facture FA2024-0001 Agence Mobilis | I66: 22251.64 | J66: 0 | K66: AAF | L66: Agence Mobilis | M66: =I66-J66 | N66: 2024-01 | O66: =INDEX(Journaux!$E$5:$E$18,MATCH("2024|"&A66,Journaux!$A$5:$A$18,0)) | P66: =INDEX(Comptes!$H$5:$H$42,MATCH(E66,Comptes!$A$5:$A$42,0)) | Q66: 4 | R66: 411000|C002
A67: VT | B67: Journal des ventes | C67: VT00001 | D67: 45310 | E67: 701000 | F67: Ventes de produits finis | G67: FA2024-0001 | H67: Facture FA2024-0001 Agence Mobilis | I67: 0 | J67: 18543.03 | M67: =I67-J67 | N67: 2024-01 | O67: =INDEX(Journaux!$E$5:$E$18,MATCH("2024|"&A67,Journaux!$A$5:$A$18,0)) | P67: =INDEX(Comptes!$H$5:$H$42,MATCH(E67,Comptes!$A$5:$A$42,0)) | Q67: 7
A68: VT | B68: Journal des ventes | C68: VT00001 | D68: 45310 | E68: 445710 | F68: TVA collectee | G68: FA2024-0001 | H68: Facture FA2024-0001 Agence Mobilis | I68: 0 | J68: 3708.61 | M68: =I68-J68 | N68: 2024-01 | O68: =INDEX(Journaux!$E$5:$E$18,MATCH("2024|"&A68,Journaux!$A$5:$A$18,0)) | P68: =INDEX(Comptes!$H$5:$H$42,MATCH(E68,Comptes!$A$5:$A$42,0)) | Q68: 4
A69: BQ | B69: Banque Fictive | C69: BQ00038 | D69: 45311 | E69: 445510 | F69: TVA a decaisser | G69: TVA202312 | H69: Reglement TVA 12/2023 | I69: 12000 | J69: 0 | M69: =I69-J69 | N69: 2024-01 | O69: =INDEX(Journaux!$E$5:$E$18,MATCH("2024|"&A69,Journaux!$A$5:$A$18,0)) | P69: =INDEX(Comptes!$H$5:$H$42,MATCH(E69,Comptes!$A$5:$A$42,0)) | Q69: 4
A70: BQ | B70: Banque Fictive | C70: BQ00038 | D70: 45311 | E70: 512000 | F70: Banque Fictive | G70: TVA202312 | H70: Reglement TVA 12/2023 | I70: 0 | J70: 12000 | M70: =I70-J70 | N70: 2024-01 | O70: =INDEX(Journaux!$E$5:$E$18,MATCH("2024|"&A70,Journaux!$A$5:$A$18,0)) | P70: =INDEX(Comptes!$H$5:$H$42,MATCH(E70,Comptes!$A$5:$A$42,0)) | Q70: 5
A71: BQ | B71: Banque Fictive | C71: BQ00063 | D71: 45313 | E71: 512000 | F71: Banque Fictive | G71: ENC-AN2024 | H71: Reglement client Cabinet Varenne Associes AN2024 | I71: 22000 | J71: 0 | M71: =I71-J71 | N71: 2024-01 | O71: =INDEX(Journaux!$E$5:$E$18,MATCH("2024|"&A71,Journaux!$A$5:$A$18,0)) | P71: =INDEX(Comptes!$H$5:$H$42,MATCH(E71,Comptes!$A$5:$A$42,0)) | Q71: 5
A72: BQ | B72: Banque Fictive | C72: BQ00063 | D72: 45313 | E72: 411000 | F72: Clients | G72: ENC-AN2024 | H72: Reglement client Cabinet Varenne Associes AN2024 | I72: 0 | J72: 22000 | K72: AAC | L72: Cabinet Varenne Associes | M72: =I72-J72 | N72: 2024-01 | O72: =INDEX(Journaux!$E$5:$E$18,MATCH("2024|"&A72,Journaux!$A$5:$A$18,0)) | P72: =INDEX(Comptes!$H$5:$H$42,MATCH(E72,Comptes!$A$5:$A$42,0)) | Q72: 4 | R72: 411000|C004
A73: BQ | B73: Banque Fictive | C73: BQ00123 | D73: 45313 | E73: 401000 | F73: Fournisseurs | G73: DEC-AN2024 | H73: Reglement fournisseur Energie Plus AN2024 | I73: 4000 | J73: 0 | K73: ABK | L73: Energie Plus | M73: =I73-J73 | N73: 2024-01 | O73: =INDEX(Journaux!$E$5:$E$18,MATCH("2024|"&A73,Journaux!$A$5:$A$18,0)) | P73: =INDEX(Comptes!$H$5:$H$42,MATCH(E73,Comptes!$A$5:$A$42,0)) | Q73: 4 | R73: 401000|F005
A74: BQ | B74: Banque Fictive | C74: BQ00123 | D74: 45313 | E74: 512000 | F74: Banque Fictive | G74: DEC-AN2024 | H74: Reglement fournisseur Energie Plus AN2024 | I74: 0 | J74: 4000 | M74: =I74-J74 | N74: 2024-01 | O74: =INDEX(Journaux!$E$5:$E$18,MATCH("2024|"&A74,Journaux!$A$5:$A$18,0)) | P74: =INDEX(Comptes!$H$5:$H$42,MATCH(E74,Comptes!$A$5:$A$42,0)) | Q74: 5
A75: BQ | B75: Banque Fictive | C75: BQ00064 | D75: 45315 | E75: 512000 | F75: Banque Fictive | G75: ENC-AN2024 | H75: Reglement client Clinique du Parc AN2024 | I75: 24000 | J75: 0 | M75: =I75-J75 | N75: 2024-01 | O75: =INDEX(Journaux!$E$5:$E$18,MATCH("2024|"&A75,Journaux!$A$5:$A$18,0)) | P75: =INDEX(Comptes!$H$5:$H$42,MATCH(E75,Comptes!$A$5:$A$42,0)) | Q75: 5
A76: BQ | B76: Banque Fictive | C76: BQ00064 | D76: 45315 | E76: 411000 | F76: Clients | G76: ENC-AN2024 | H76: Reglement client Clinique du Parc AN2024 | I76: 0 | J76: 24000 | K76: AAD | L76: Clinique du Parc | M76: =I76-J76 | N76: 2024-01 | O76: =INDEX(Journaux!$E$5:$E$18,MATCH("2024|"&A76,Journaux!$A$5:$A$18,0)) | P76: =INDEX(Comptes!$H$5:$H$42,MATCH(E76,Comptes!$A$5:$A$42,0)) | Q76: 4 | R76: 411000|C006
A77: BQ | B77: Banque Fictive | C77: BQ00124 | D77: 45317 | E77: 401000 | F77: Fournisseurs | G77: DEC-AN2024 | H77: Reglement fournisseur SCI Les Halles AN2024 | I77: 7000 | J77: 0 | K77: ABL | L77: SCI Les Halles | M77: =I77-J77 | N77: 2024-01 | O77: =INDEX(Journaux!$E$5:$E$18,MATCH("2024|"&A77,Journaux!$A$5:$A$18,0)) | P77: =INDEX(Comptes!$H$5:$H$42,MATCH(E77,Comptes!$A$5:$A$42,0)) | Q77: 4 | R77: 401000|F004
A78: BQ | B78: Banque Fictive | C78: BQ00124 | D78: 45317 | E78: 512000 | F78: Banque Fictive | G78: DEC-AN2024 | H78: Reglement fournisseur SCI Les Halles AN2024 | I78: 0 | J78: 7000 | M78: =I78-J78 | N78: 2024-01 | O78: =INDEX(Journaux!$E$5:$E$18,MATCH("2024|"&A78,Journaux!$A$5:$A$18,0)) | P78: =INDEX(Comptes!$H$5:$H$42,MATCH(E78,Comptes!$A$5:$A$42,0)) | Q78: 5
A79: VT | B79: Journal des ventes | C79: VT00006 | D79: 45317 | E79: 411000 | F79: Clients | G79: FA2024-0006 | H79: Facture FA2024-0006 Restaurant Le Comptoir | I79: 38509.92 | J79: 0 | K79: AAK | L79: Restaurant Le Comptoir | M79: =I79-J79 | N79: 2024-01 | O79: =INDEX(Journaux!$E$5:$E$18,MATCH("2024|"&A79,Journaux!$A$5:$A$18,0)) | P79: =INDEX(Comptes!$H$5:$H$42,MATCH(E79,Comptes!$A$5:$A$42,0)) | Q79: 4 | R79: 411000|C005
A80: VT | B80: Journal des ventes | C80: VT00006 | D80: 45317 | E80: 701000 | F80: Ventes de produits finis | G80: FA2024-0006 | H80: Facture FA2024-0006 Restaurant Le Comptoir | I80: 0 | J80: 32091.6 | M80: =I80-J80 | N80: 2024-01 | O80: =INDEX(Journaux!$E$5:$E$18,MATCH("2024|"&A80,Journaux!$A$5:$A$18,0)) | P80: =INDEX(Comptes!$H$5:$H$42,MATCH(E80,Comptes!$A$5:$A$42,0)) | Q80: 7
A81: VT | B81: Journal des ventes | C81: VT00006 | D81: 45317 | E81: 445710 | F81: TVA collectee | G81: FA2024-0006 | H81: Facture FA2024-0006 Restaurant Le Comptoir | I81: 0 | J81: 6418.32 | M81: =I81-J81 | N81: 2024-01 | O81: =INDEX(Journaux!$E$5:$E$18,MATCH("2024|"&A81,Journaux!$A$5:$A$18,0)) | P81: =INDEX(Comptes!$H$5:$H$42,MATCH(E81,Comptes!$A$5:$A$42,0)) | Q81: 4
A82: BQ | B82: Banque Fictive | C82: BQ00065 | D82: 45320 | E82: 512000 | F82: Banque Fictive | G82: ENC-AN2024 | H82: Reglement client Coworking Atelier 9 AN2024 | I82: 18000 | J82: 0 | M82: =I82-J82 | N82: 2024-01 | O82: =INDEX(Journaux!$E$5:$E$18,MATCH("2024|"&A82,Journaux!$A$5:$A$18,0)) | P82: =INDEX(Comptes!$H$5:$H$42,MATCH(E82,Comptes!$A$5:$A$42,0)) | Q82: 5
A83: BQ | B83: Banque Fictive | C83: BQ00065 | D83: 45320 | E83: 411000 | F83: Clients | G83: ENC-AN2024 | H83: Reglement client Coworking Atelier 9 AN2024 | I83: 0 | J83: 18000 | K83: AAE | L83: Coworking Atelier 9 | M83: =I83-J83 | N83: 2024-01 | O83: =INDEX(Journaux!$E$5:$E$18,MATCH("2024|"&A83,Journaux!$A$5:$A$18,0)) | P83: =INDEX(Comptes!$H$5:$H$42,MATCH(E83,Comptes!$A$5:$A$42,0)) | Q83: 4 | R83: 411000|C008
A84: BQ | B84: Banque Fictive | C84: BQ00067 | D84: 45320 | E84: 512000 | F84: Banque Fictive | G84: ENC-FA2024-0002 | H84: Reglement client Hotel Les Tilleuls FA2024-0002 | I84: 38532.72 | J84: 0 | M84: =I84-J84 | N84: 2024-01 | O84: =INDEX(Journaux!$E$5:$E$18,MATCH("2024|"&A84,Journaux!$A$5:$A$18,0)) | P84: =INDEX(Comptes!$H$5:$H$42,MATCH(E84,Comptes!$A$5:$A$42,0)) | Q84: 5
A85: BQ | B85: Banque Fictive | C85: BQ00067 | D85: 45320 | E85: 411000 | F85: Clients | G85: ENC-FA2024-0002 | H85: Reglement client Hotel Les Tilleuls FA2024-0002 | I85: 0 | J85: 38532.72 | K85: AAG | L85: Hotel Les Tilleuls | M85: =I85-J85 | N85: 2024-01 | O85: =INDEX(Journaux!$E$5:$E$18,MATCH("2024|"&A85,Journaux!$A$5:$A$18,0)) | P85: =INDEX(Comptes!$H$5:$H$42,MATCH(E85,Comptes!$A$5:$A$42,0)) | Q85: 4 | R85: 411000|C001
A86: AC | B86: Journal des achats | C86: AC00001 | D86: 45322 | E86: 601000 | F86: Achats de matieres premieres | G86: F001-2024011 | H86: Facture Scierie du Nord F001-2024011 | I86: 32907.79 | J86: 0 | M86: =I86-J86 | N86: 2024-01 | O86: =INDEX(Journaux!$E$5:$E$18,MATCH("2024|"&A86,Journaux!$A$5:$A$18,0)) | P86: =INDEX(Comptes!$H$5:$H$42,MATCH(E86,Comptes!$A$5:$A$42,0)) | Q86: 6
A87: AC | B87: Journal des achats | C87: AC00001 | D87: 45322 | E87: 445660 | F87: TVA deductible sur ABS | G87: F001-2024011 | H87: Facture Scierie du Nord F001-2024011 | I87: 6581.56 | J87: 0 | M87: =I87-J87 | N87: 2024-01 | O87: =INDEX(Journaux!$E$5:$E$18,MATCH("2024|"&A87,Journaux!$A$5:$A$18,0)) | P87: =INDEX(Comptes!$H$5:$H$42,MATCH(E87,Comptes!$A$5:$A$42,0)) | Q87: 4
A88: AC | B88: Journal des achats | C88: AC00001 | D88: 45322 | E88: 401000 | F88: Fournisseurs | G88: F001-2024011 | H88: Facture Scierie du Nord F001-2024011 | I88: 0 | J88: 39489.35 | K88: ABM | L88: Scierie du Nord | M88: =I88-J88 | N88: 2024-01 | O88: =INDEX(Journaux!$E$5:$E$18,MATCH("2024|"&A88,Journaux!$A$5:$A$18,0)) | P88: =INDEX(Comptes!$H$5:$H$42,MATCH(E88,Comptes!$A$5:$A$42,0)) | Q88: 4 | R88: 401000|F001
A89: BQ | B89: Banque Fictive | C89: BQ00001 | D89: 45322 | E89: 421000 | F89: Personnel remunerations dues | G89: VIRSAL202401 | H89: Virement salaires 01/2024 | I89: 41123.78 | J89: 0 | M89: =I89-J89 | N89: 2024-01 | O89: =INDEX(Journaux!$E$5:$E$18,MATCH("2024|"&A89,Journaux!$A$5:$A$18,0)) | P89: =INDEX(Comptes!$H$5:$H$42,MATCH(E89,Comptes!$A$5:$A$42,0)) | Q89: 4
A90: BQ | B90: Banque Fictive | C90: BQ00001 | D90: 45322 | E90: 512000 | F90: Banque Fictive | G90: VIRSAL202401 | H90: Virement salaires 01/2024 | I90: 0 | J90: 41123.78 | M90: =I90-J90 | N90: 2024-01 | O90: =INDEX(Journaux!$E$5:$E$18,MATCH("2024|"&A90,Journaux!$A$5:$A$18,0)) | P90: =INDEX(Comptes!$H$5:$H$42,MATCH(E90,Comptes!$A$5:$A$42,0)) | Q90: 5
A91: BQ | B91: Banque Fictive | C91: BQ00003 | D91: 45322 | E91: 627000 | F91: Services bancaires | G91: FRB202401 | H91: Frais bancaires 01/2024 | I91: 85 | J91: 0 | M91: =I91-J91 | N91: 2024-01 | O91: =INDEX(Journaux!$E$5:$E$18,MATCH("2024|"&A91,Journaux!$A$5:$A$18,0)) | P91: =INDEX(Comptes!$H$5:$H$42,MATCH(E91,Comptes!$A$5:$A$42,0)) | Q91: 6
A92: BQ | B92: Banque Fictive | C92: BQ00003 | D92: 45322 | E92: 512000 | F92: Banque Fictive | G92: FRB202401 | H92: Frais bancaires 01/2024 | I92: 0 | J92: 85 | M92: =I92-J92 | N92: 2024-01 | O92: =INDEX(Journaux!$E$5:$E$18,MATCH("2024|"&A92,Journaux!$A$5:$A$18,0)) | P92: =INDEX(Comptes!$H$5:$H$42,MATCH(E92,Comptes!$A$5:$A$42,0)) | Q92: 5
A93: OD | B93: Operations diverses | C93: OD00001 | D93: 45322 | E93: 445710 | F93: TVA collectee | G93: CA3-202401 | H93: Declaration TVA 01/2024 | I93: 28333.33 | J93: 0 | M93: =I93-J93 | N93: 2024-01 | O93: =INDEX(Journaux!$E$5:$E$18,MATCH("2024|"&A93,Journaux!$A$5:$A$18,0)) | P93: =INDEX(Comptes!$H$5:$H$42,MATCH(E93,Comptes!$A$5:$A$42,0)) | Q93: 4
A94: OD | B94: Operations diverses | C94: OD00001 | D94: 45322 | E94: 445660 | F94: TVA deductible sur ABS | G94: CA3-202401 | H94: Declaration TVA 01/2024 | I94: 0 | J94: 14202.11 | M94: =I94-J94 | N94: 2024-01 | O94: =INDEX(Journaux!$E$5:$E$18,MATCH("2024|"&A94,Journaux!$A$5:$A$18,0)) | P94: =INDEX(Comptes!$H$5:$H$42,MATCH(E94,Comptes!$A$5:$A$42,0)) | Q94: 4
A95: OD | B95: Operations diverses | C95: OD00001 | D95: 45322 | E95: 445510 | F95: TVA a decaisser | G95: CA3-202401 | H95: Declaration TVA 01/2024 | I95: 0 | J95: 14131.22 | M95: =I95-J95 | N95: 2024-01 | O95: =INDEX(Journaux!$E$5:$E$18,MATCH("2024|"&A95,Journaux!$A$5:$A$18,0)) | P95: =INDEX(Comptes!$H$5:$H$42,MATCH(E95,Comptes!$A$5:$A$42,0)) | Q95: 4
A96: SA | B96: Salaires | C96: SA00001 | D96: 45322 | E96: 641000 | F96: Remunerations du personnel | G96: PAIE202401 | H96: Paie 01/2024 | I96: 52722.79 | J96: 0 | M96: =I96-J96 | N96: 2024-01 | O96: =INDEX(Journaux!$E$5:$E$18,MATCH("2024|"&A96,Journaux!$A$5:$A$18,0)) | P96: =INDEX(Comptes!$H$5:$H$42,MATCH(E96,Comptes!$A$5:$A$42,0)) | Q96: 6
A97: SA | B97: Salaires | C97: SA00001 | D97: 45322 | E97: 645100 | F97: Cotisations URSSAF | G97: PAIE202401 | H97: Paie 01/2024 | I97: 22143.57 | J97: 0 | M97: =I97-J97 | N97: 2024-01 | O97: =INDEX(Journaux!$E$5:$E$18,MATCH("2024|"&A97,Journaux!$A$5:$A$18,0)) | P97: =INDEX(Comptes!$H$5:$H$42,MATCH(E97,Comptes!$A$5:$A$42,0)) | Q97: 6
A98: SA | B98: Salaires | C98: SA00001 | D98: 45322 | E98: 421000 | F98: Personnel remunerations dues | G98: PAIE202401 | H98: Paie 01/2024 | I98: 0 | J98: 41123.78 | M98: =I98-J98 | N98: 2024-01 | O98: =INDEX(Journaux!$E$5:$E$18,MATCH("2024|"&A98,Journaux!$A$5:$A$18,0)) | P98: =INDEX(Comptes!$H$5:$H$42,MATCH(E98,Comptes!$A$5:$A$42,0)) | Q98: 4
A99: SA | B99: Salaires | C99: SA00001 | D99: 45322 | E99: 431000 | F99: Securite sociale | G99: PAIE202401 | H99: Paie 01/2024 | I99: 0 | J99: 33742.58 | M99: =I99-J99 | N99: 2024-01 | O99: =INDEX(Journaux!$E$5:$E$18,MATCH("2024|"&A99,Journaux!$A$5:$A$18,0)) | P99: =INDEX(Comptes!$H$5:$H$42,MATCH(E99,Comptes!$A$5:$A$42,0)) | Q99: 4
A100: VT | B100: Journal des ventes | C100: VT00009 | D100: 45324 | E100: 411000 | F100: Clients | G100: FA2024-0009 | H100: Facture FA2024-0009 Agence Mobilis | I100: 34050.62 | J100: 0 | K100: AAN | L100: Agence Mobilis | M100: =I100-J100 | N100: 2024-02 | O100: =INDEX(Journaux!$E$5:$E$18,MATCH("2024|"&A100,Journaux!$A$5:$A$18,0)) | P100: =INDEX(Comptes!$H$5:$H$42,MATCH(E100,Comptes!$A$5:$A$42,0)) | Q100: 4 | R100: 411000|C002
...

Sheet FEC_2025
A1: JournalCode | B1: JournalLib | C1: EcritureNum | D1: EcritureDate | E1: CompteNum | F1: CompteLib | G1: PieceRef | H1: EcritureLib | I1: Debit | J1: Credit | K1: EcritureLet | L1: Tiers | M1: Montant (D-C) | N1: Mois | O1: Type journal | P1: Agrégat Vestis | Q1: Classe | R1: Clé tiers
A2: AN | B2: A-nouveaux | C2: AN00001 | D2: 45658 | E2: 101300 | F2: Capital souscrit appele verse | G2: AN2025 | H2: A-nouveaux 2025 | I2: 0 | J2: 100000 | M2: =I2-J2 | N2: 2025-01 | O2: =INDEX(Journaux!$E$5:$E$18,MATCH("2025|"&A2,Journaux!$A$5:$A$18,0)) | P2: =INDEX(Comptes!$K$5:$K$42,MATCH(E2,Comptes!$A$5:$A$42,0)) | Q2: 1
A3: AN | B3: A-nouveaux | C3: AN00001 | D3: 45658 | E3: 106100 | F3: Reserve legale | G3: AN2025 | H3: A-nouveaux 2025 | I3: 0 | J3: 10000 | M3: =I3-J3 | N3: 2025-01 | O3: =INDEX(Journaux!$E$5:$E$18,MATCH("2025|"&A3,Journaux!$A$5:$A$18,0)) | P3: =INDEX(Comptes!$K$5:$K$42,MATCH(E3,Comptes!$A$5:$A$42,0)) | Q3: 1
A4: AN | B4: A-nouveaux | C4: AN00001 | D4: 45658 | E4: 110000 | F4: Report a nouveau | G4: AN2025 | H4: A-nouveaux 2025 | I4: 0 | J4: 68000 | M4: =I4-J4 | N4: 2025-01 | O4: =INDEX(Journaux!$E$5:$E$18,MATCH("2025|"&A4,Journaux!$A$5:$A$18,0)) | P4: =INDEX(Comptes!$K$5:$K$42,MATCH(E4,Comptes!$A$5:$A$42,0)) | Q4: 1
A5: AN | B5: A-nouveaux | C5: AN00001 | D5: 45658 | E5: 164000 | F5: Emprunts aupres des etablissements de credit | G5: AN2025 | H5: A-nouveaux 2025 | I5: 0 | J5: 66000 | M5: =I5-J5 | N5: 2025-01 | O5: =INDEX(Journaux!$E$5:$E$18,MATCH("2025|"&A5,Journaux!$A$5:$A$18,0)) | P5: =INDEX(Comptes!$K$5:$K$42,MATCH(E5,Comptes!$A$5:$A$42,0)) | Q5: 1
A6: AN | B6: A-nouveaux | C6: AN00001 | D6: 45658 | E6: 215400 | F6: Materiel industriel | G6: AN2025 | H6: A-nouveaux 2025 | I6: 180000 | J6: 0 | M6: =I6-J6 | N6: 2025-01 | O6: =INDEX(Journaux!$E$5:$E$18,MATCH("2025|"&A6,Journaux!$A$5:$A$18,0)) | P6: =INDEX(Comptes!$K$5:$K$42,MATCH(E6,Comptes!$A$5:$A$42,0)) | Q6: 2
A7: AN | B7: A-nouveaux | C7: AN00001 | D7: 45658 | E7: 218300 | F7: Materiel de bureau et informatique | G7: AN2025 | H7: A-nouveaux 2025 | I7: 25000 | J7: 0 | M7: =I7-J7 | N7: 2025-01 | O7: =INDEX(Journaux!$E$5:$E$18,MATCH("2025|"&A7,Journaux!$A$5:$A$18,0)) | P7: =INDEX(Comptes!$K$5:$K$42,MATCH(E7,Comptes!$A$5:$A$42,0)) | Q7: 2
A8: AN | B8: A-nouveaux | C8: AN00001 | D8: 45658 | E8: 281540 | F8: Amortissements materiel industriel | G8: AN2025 | H8: A-nouveaux 2025 | I8: 0 | J8: 88000 | M8: =I8-J8 | N8: 2025-01 | O8: =INDEX(Journaux!$E$5:$E$18,MATCH("2025|"&A8,Journaux!$A$5:$A$18,0)) | P8: =INDEX(Comptes!$K$5:$K$42,MATCH(E8,Comptes!$A$5:$A$42,0)) | Q8: 2
A9: AN | B9: A-nouveaux | C9: AN00001 | D9: 45658 | E9: 281830 | F9: Amortissements materiel de bureau | G9: AN2025 | H9: A-nouveaux 2025 | I9: 0 | J9: 17000 | M9: =I9-J9 | N9: 2025-01 | O9: =INDEX(Journaux!$E$5:$E$18,MATCH("2025|"&A9,Journaux!$A$5:$A$18,0)) | P9: =INDEX(Comptes!$K$5:$K$42,MATCH(E9,Comptes!$A$5:$A$42,0)) | Q9: 2
A10: AN | B10: A-nouveaux | C10: AN00001 | D10: 45658 | E10: 310000 | F10: Stocks de matieres premieres | G10: AN2025 | H10: A-nouveaux 2025 | I10: 52000 | J10: 0 | M10: =I10-J10 | N10: 2025-01 | O10: =INDEX(Journaux!$E$5:$E$18,MATCH("2025|"&A10,Journaux!$A$5:$A$18,0)) | P10: =INDEX(Comptes!$K$5:$K$42,MATCH(E10,Comptes!$A$5:$A$42,0)) | Q10: 3
A11: AN | B11: A-nouveaux | C11: AN00001 | D11: 45658 | E11: 431000 | F11: Securite sociale | G11: AN2025 | H11: A-nouveaux 2025 | I11: 0 | J11: 33292.52 | M11: =I11-J11 | N11: 2025-01 | O11: =INDEX(Journaux!$E$5:$E$18,MATCH("2025|"&A11,Journaux!$A$5:$A$18,0)) | P11: =INDEX(Comptes!$K$5:$K$42,MATCH(E11,Comptes!$A$5:$A$42,0)) | Q11: 4
A12: AN | B12: A-nouveaux | C12: AN00001 | D12: 45658 | E12: 444000 | F12: Etat impot sur les benefices | G12: AN2025 | H12: A-nouveaux 2025 | I12: 0 | J12: 9067.03 | M12: =I12-J12 | N12: 2025-01 | O12: =INDEX(Journaux!$E$5:$E$18,MATCH("2025|"&A12,Journaux!$A$5:$A$18,0)) | P12: =INDEX(Comptes!$K$5:$K$42,MATCH(E12,Comptes!$A$5:$A$42,0)) | Q12: 4
A13: AN | B13: A-nouveaux | C13: AN00001 | D13: 45658 | E13: 445510 | F13: TVA a decaisser | G13: AN2025 | H13: A-nouveaux 2025 | I13: 0 | J13: 14795.86 | M13: =I13-J13 | N13: 2025-01 | O13: =INDEX(Journaux!$E$5:$E$18,MATCH("2025|"&A13,Journaux!$A$5:$A$18,0)) | P13: =INDEX(Comptes!$K$5:$K$42,MATCH(E13,Comptes!$A$5:$A$42,0)) | Q13: 4
... A16: AN | B16: A-nouveaux | C16: AN00001 | D16: 45658 | E16: 120000 | F16: Resultat de l'exercice | G16: AN2025 | H16: A-nouveaux 2025 | I16: 0 | J16: 51379.86 | M16: =I16-J16 | N16: 2025-01 | O16: =INDEX(Journaux!$E$5:$E$18,MATCH("2025|"&A16,Journaux!$A$5:$A$18,0)) | P16: =INDEX(Comptes!$K$5:$K$42,MATCH(E16,Comptes!$A$5:$A$42,0)) | Q16: 1
A17: AN | B17: A-nouveaux | C17: AN00001 | D17: 45658 | E17: 411000 | F17: Clients | G17: AN2025 | H17: A-nouveaux 2025 | I17: 32352.62 | J17: 0 | K17: AAA | L17: Coworking Atelier 9 | M17: =I17-J17 | N17: 2025-01 | O17: =INDEX(Journaux!$E$5:$E$18,MATCH("2025|"&A17,Journaux!$A$5:$A$18,0)) | P17: =INDEX(Comptes!$K$5:$K$42,MATCH(E17,Comptes!$A$5:$A$42,0)) | Q17: 4 | R17: 411000|C008
A18: AN | B18: A-nouveaux | C18: AN00001 | D18: 45658 | E18: 411000 | F18: Clients | G18: AN2025 | H18: A-nouveaux 2025 | I18: 35886.29 | J18: 0 | K18: AAB | L18: Agence Mobilis | M18: =I18-J18 | N18: 2025-01 | O18: =INDEX(Journaux!$E$5:$E$18,MATCH("2025|"&A18,Journaux!$A$5:$A$18,0)) | P18: =INDEX(Comptes!$K$5:$K$42,MATCH(E18,Comptes!$A$5:$A$42,0)) | Q18: 4 | R18: 411000|C002
A19: AN | B19: A-nouveaux | C19: AN00001 | D19: 45658 | E19: 411000 | F19: Clients | G19: AN2025 | H19: A-nouveaux 2025 | I19: 37138.48 | J19: 0 | K19: AAC | L19: Residence Bel Air | M19: =I19-J19 | N19: 2025-01 | O19: =INDEX(Journaux!$E$5:$E$18,MATCH("2025|"&A19,Journaux!$A$5:$A$18,0)) | P19: =INDEX(Comptes!$K$5:$K$42,MATCH(E19,Comptes!$A$5:$A$42,0)) | Q19: 4 | R19: 411000|C003
A20: AN | B20: A-nouveaux | C20: AN00001 | D20: 45658 | E20: 411000 | F20: Clients | G20: AN2025 | H20: A-nouveaux 2025 | I20: 26280.64 | J20: 0 | K20: AAD | L20: Clinique du Parc | M20: =I20-J20 | N20: 2025-01 | O20: =INDEX(Journaux!$E$5:$E$18,MATCH("2025|"&A20,Journaux!$A$5:$A$18,0)) | P20: =INDEX(Comptes!$K$5:$K$42,MATCH(E20,Comptes!$A$5:$A$42,0)) | Q20: 4 | R20: 411000|C006
A21: AN | B21: A-nouveaux | C21: AN00001 | D21: 45658 | E21: 411000 | F21: Clients | G21: AN2025 | H21: A-nouveaux 2025 | I21: 31150.6 | J21: 0 | K21: AAE | L21: Cabinet Varenne Associes | M21: =I21-J21 | N21: 2025-01 | O21: =INDEX(Journaux!$E$5:$E$18,MATCH("2025|"&A21,Journaux!$A$5:$A$18,0)) | P21: =INDEX(Comptes!$K$5:$K$42,MATCH(E21,Comptes!$A$5:$A$42,0)) | Q21: 4 | R21: 411000|C004
A22: AN | B22: A-nouveaux | C22: AN00001 | D22: 45658 | E22: 411000 | F22: Clients | G22: AN2025 | H22: A-nouveaux 2025 | I22: 20557.5 | J22: 0 | K22: AAF | L22: Agence Mobilis | M22: =I22-J22 | N22: 2025-01 | O22: =INDEX(Journaux!$E$5:$E$18,MATCH("2025|"&A22,Journaux!$A$5:$A$18,0)) | P22: =INDEX(Comptes!$K$5:$K$42,MATCH(E22,Comptes!$A$5:$A$42,0)) | Q22: 4 | R22: 411000|C002
A23: AN | B23: A-nouveaux | C23: AN00001 | D23: 45658 | E23: 411000 | F23: Clients | G23: AN2025 | H23: A-nouveaux 2025 | I23: 38178.13 | J23: 0 | K23: AAG | L23: Coworking Atelier 9 | M23: =I23-J23 | N23: 2025-01 | O23: =INDEX(Journaux!$E$5:$E$18,MATCH("2025|"&A23,Journaux!$A$5:$A$18,0)) | P23: =INDEX(Comptes!$K$5:$K$42,MATCH(E23,Comptes!$A$5:$A$42,0)) | Q23: 4 | R23: 411000|C008
A24: AN | B24: A-nouveaux | C24: AN00001 | D24: 45658 | E24: 411000 | F24: Clients | G24: AN2025 | H24: A-nouveaux 2025 | I24: 36694.64 | J24: 0 | K24: AAH | L24: Clinique du Parc | M24: =I24-J24 | N24: 2025-01 | O24: =INDEX(Journaux!$E$5:$E$18,MATCH("2025|"&A24,Journaux!$A$5:$A$18,0)) | P24: =INDEX(Comptes!$K$5:$K$42,MATCH(E24,Comptes!$A$5:$A$42,0)) | Q24: 4 | R24: 411000|C006
A25: AN | B25: A-nouveaux | C25: AN00001 | D25: 45658 | E25: 401000 | F25: Fournisseurs | G25: AN2025 | H25: A-nouveaux 2025 | I25: 0 | J25: 52590.01 | K25: ABB | L25: Quincaillerie Pro Est | M25: =I25-J25 | N25: 2025-01 | O25: =INDEX(Journaux!$E$5:$E$18,MATCH("2025|"&A25,Journaux!$A$5:$A$18,0)) | P25: =INDEX(Comptes!$K$5:$K$42,MATCH(E25,Comptes!$A$5:$A$42,0)) | Q25: 4 | R25: 401000|F002
A26: AN | B26: A-nouveaux | C26: AN00001 | D26: 45658 | E26: 401000 | F26: Fournisseurs | G26: AN2025 | H26: A-nouveaux 2025 | I26: 0 | J26: 34477.39 | K26: ABC | L26: Vernis et Finitions | M26: =I26-J26 | N26: 2025-01 | O26: =INDEX(Journaux!$E$5:$E$18,MATCH("2025|"&A26,Journaux!$A$5:$A$18,0)) | P26: =INDEX(Comptes!$K$5:$K$42,MATCH(E26,Comptes!$A$5:$A$42,0)) | Q26: 4 | R26: 401000|F003
A27: AN | B27: A-nouveaux | C27: AN00001 | D27: 45658 | E27: 401000 | F27: Fournisseurs | G27: AN2025 | H27: A-nouveaux 2025 | I27: 0 | J27: 45322.61 | K27: ABD | L27: Quincaillerie Pro Est | M27: =I27-J27 | N27: 2025-01 | O27: =INDEX(Journaux!$E$5:$E$18,MATCH("2025|"&A27,Journaux!$A$5:$A$18,0)) | P27: =INDEX(Comptes!$K$5:$K$42,MATCH(E27,Comptes!$A$5:$A$42,0)) | Q27: 4 | R27: 401000|F002
A28: AN | B28: A-nouveaux | C28: AN00001 | D28: 45658 | E28: 401000 | F28: Fournisseurs | G28: AN2025 | H28: A-nouveaux 2025 | I28: 0 | J28: 10200 | K28: ABE | L28: SCI Les Halles | M28: =I28-J28 | N28: 2025-01 | O28: =INDEX(Journaux!$E$5:$E$18,MATCH("2025|"&A28,Journaux!$A$5:$A$18,0)) | P28: =INDEX(Comptes!$K$5:$K$42,MATCH(E28,Comptes!$A$5:$A$42,0)) | Q28: 4 | R28: 401000|F004
... A31: AN | B31: A-nouveaux | C31: AN00001 | D31: 45658 | E31: 401000 | F31: Fournisseurs | G31: AN2025 | H31: A-nouveaux 2025 | I31: 0 | J31: 7200 | K31: ABH | L31: Cabinet Comptable Exemple | M31: =I31-J31 | N31: 2025-01 | O31: =INDEX(Journaux!$E$5:$E$18,MATCH("2025|"&A31,Journaux!$A$5:$A$18,0)) | P31: =INDEX(Comptes!$K$5:$K$42,MATCH(E31,Comptes!$A$5:$A$42,0)) | Q31: 4 | R31: 401000|F007
A32: AC | B32: Journal des achats | C32: AC00004 | D32: 45662 | E32: 613200 | F32: Locations immobilieres | G32: F004-202501 | H32: Facture SCI Les Halles 2025-01 | I32: 8500 | J32: 0 | M32: =I32-J32 | N32: 2025-01 | O32: =INDEX(Journaux!$E$5:$E$18,MATCH("2025|"&A32,Journaux!$A$5:$A$18,0)) | P32: =INDEX(Comptes!$K$5:$K$42,MATCH(E32,Comptes!$A$5:$A$42,0)) | Q32: 6
A33: AC | B33: Journal des achats | C33: AC00004 | D33: 45662 | E33: 445660 | F33: TVA deductible sur ABS | G33: F004-202501 | H33: Facture SCI Les Halles 2025-01 | I33: 1700 | J33: 0 | M33: =I33-J33 | N33: 2025-01 | O33: =INDEX(Journaux!$E$5:$E$18,MATCH("2025|"&A33,Journaux!$A$5:$A$18,0)) | P33: =INDEX(Comptes!$K$5:$K$42,MATCH(E33,Comptes!$A$5:$A$42,0)) | Q33: 4
A34: AC | B34: Journal des achats | C34: AC00004 | D34: 45662 | E34: 401000 | F34: Fournisseurs | G34: F004-202501 | H34: Facture SCI Les Halles 2025-01 | I34: 0 | J34: 10200 | K34: ABL | L34: SCI Les Halles | M34: =I34-J34 | N34: 2025-01 | O34: =INDEX(Journaux!$E$5:$E$18,MATCH("2025|"&A34,Journaux!$A$5:$A$18,0)) | P34: =INDEX(Comptes!$K$5:$K$42,MATCH(E34,Comptes!$A$5:$A$42,0)) | Q34: 4 | R34: 401000|F004
A35: AC | B35: Journal des achats | C35: AC00005 | D35: 45662 | E35: 606100 | F35: Fournitures non stockables energie | G35: F005-202501 | H35: Facture Energie Plus 2025-01 | I35: 2757.27 | J35: 0 | M35: =I35-J35 | N35: 2025-01 | O35: =INDEX(Journaux!$E$5:$E$18,MATCH("2025|"&A35,Journaux!$A$5:$A$18,0)) | P35: =INDEX(Comptes!$K$5:$K$42,MATCH(E35,Comptes!$A$5:$A$42,0)) | Q35: 6
A36: AC | B36: Journal des achats | C36: AC00005 | D36: 45662 | E36: 445660 | F36: TVA deductible sur ABS | G36: F005-202501 | H36: Facture Energie Plus 2025-01 | I36: 551.45 | J36: 0 | M36: =I36-J36 | N36: 2025-01 | O36: =INDEX(Journaux!$E$5:$E$18,MATCH("2025|"&A36,Journaux!$A$5:$A$18,0)) | P36: =INDEX(Comptes!$K$5:$K$42,MATCH(E36,Comptes!$A$5:$A$42,0)) | Q36: 4
A37: AC | B37: Journal des achats | C37: AC00005 | D37: 45662 | E37: 401000 | F37: Fournisseurs | G37: F005-202501 | H37: Facture Energie Plus 2025-01 | I37: 0 | J37: 3308.72 | K37: ABM | L37: Energie Plus | M37: =I37-J37 | N37: 2025-01 | O37: =INDEX(Journaux!$E$5:$E$18,MATCH("2025|"&A37,Journaux!$A$5:$A$18,0)) | P37: =INDEX(Comptes!$K$5:$K$42,MATCH(E37,Comptes!$A$5:$A$42,0)) | Q37: 4 | R37: 401000|F005
A38: AC | B38: Journal des achats | C38: AC00006 | D38: 45662 | E38: 626000 | F38: Frais postaux et telecommunications | G38: F008-202501 | H38: Facture Telecom Pro 2025-01 | I38: 480 | J38: 0 | M38: =I38-J38 | N38: 2025-01 | O38: =INDEX(Journaux!$E$5:$E$18,MATCH("2025|"&A38,Journaux!$A$5:$A$18,0)) | P38: =INDEX(Comptes!$K$5:$K$42,MATCH(E38,Comptes!$A$5:$A$42,0)) | Q38: 6
A39: AC | B39: Journal des achats | C39: AC00006 | D39: 45662 | E39: 445660 | F39: TVA deductible sur ABS | G39: F008-202501 | H39: Facture Telecom Pro 2025-01 | I39: 96 | J39: 0 | M39: =I39-J39 | N39: 2025-01 | O39: =INDEX(Journaux!$E$5:$E$18,MATCH("2025|"&A39,Journaux!$A$5:$A$18,0)) | P39: =INDEX(Comptes!$K$5:$K$42,MATCH(E39,Comptes!$A$5:$A$42,0)) | Q39: 4
A40: AC | B40: Journal des achats | C40: AC00006 | D40: 45662 | E40: 401000 | F40: Fournisseurs | G40: F008-202501 | H40: Facture Telecom Pro 2025-01 | I40: 0 | J40: 576 | K40: ABN | L40: Telecom Pro | M40: =I40-J40 | N40: 2025-01 | O40: =INDEX(Journaux!$E$5:$E$18,MATCH("2025|"&A40,Journaux!$A$5:$A$18,0)) | P40: =INDEX(Comptes!$K$5:$K$42,MATCH(E40,Comptes!$A$5:$A$42,0)) | Q40: 4 | R40: 401000|F008
A41: AC | B41: Journal des achats | C41: AC00007 | D41: 45662 | E41: 616000 | F41: Primes d'assurance | G41: F006-202501 | H41: Facture Assurances Mutuelles Exemple 2025-01 | I41: 3000 | J41: 0 | M41: =I41-J41 | N41: 2025-01 | O41: =INDEX(Journaux!$E$5:$E$18,MATCH("2025|"&A41,Journaux!$A$5:$A$18,0)) | P41: =INDEX(Comptes!$K$5:$K$42,MATCH(E41,Comptes!$A$5:$A$42,0)) | Q41: 6
A42: AC | B42: Journal des achats | C42: AC00007 | D42: 45662 | E42: 401000 | F42: Fournisseurs | G42: F006-202501 | H42: Facture Assurances Mutuelles Exemple 2025-01 | I42: 0 | J42: 3000 | K42: ABO | L42: Assurances Mutuelles Exemple | M42: =I42-J42 | N42: 2025-01 | O42: =INDEX(Journaux!$E$5:$E$18,MATCH("2025|"&A42,Journaux!$A$5:$A$18,0)) | P42: =INDEX(Comptes!$K$5:$K$42,MATCH(E42,Comptes!$A$5:$A$42,0)) | Q42: 4 | R42: 401000|F006
A43: BQ | B43: Banque Fictive | C43: BQ00060 | D43: 45663 | E43: 512000 | F43: Banque Fictive | G43: ENC-AN2025 | H43: Reglement client Coworking Atelier 9 AN2025 | I43: 32352.62 | J43: 0 | M43: =I43-J43 | N43: 2025-01 | O43: =INDEX(Journaux!$E$5:$E$18,MATCH("2025|"&A43,Journaux!$A$5:$A$18,0)) | P43: =INDEX(Comptes!$K$5:$K$42,MATCH(E43,Comptes!$A$5:$A$42,0)) | Q43: 5
A44: BQ | B44: Banque Fictive | C44: BQ00060 | D44: 45663 | E44: 411000 | F44: Clients | G44: ENC-AN2025 | H44: Reglement client Coworking Atelier 9 AN2025 | I44: 0 | J44: 32352.62 | K44: AAA | L44: Coworking Atelier 9 | M44: =I44-J44 | N44: 2025-01 | O44: =INDEX(Journaux!$E$5:$E$18,MATCH("2025|"&A44,Journaux!$A$5:$A$18,0)) | P44: =INDEX(Comptes!$K$5:$K$42,MATCH(E44,Comptes!$A$5:$A$42,0)) | Q44: 4 | R44: 411000|C008
A45: BQ | B45: Banque Fictive | C45: BQ00116 | D45: 45663 | E45: 401000 | F45: Fournisseurs | G45: DEC-AN2025 | H45: Reglement fournisseur SCI Les Halles AN2025 | I45: 10200 | J45: 0 | K45: ABE | L45: SCI Les Halles | M45: =I45-J45 | N45: 2025-01 | O45: =INDEX(Journaux!$E$5:$E$18,MATCH("2025|"&A45,Journaux!$A$5:$A$18,0)) | P45: =INDEX(Comptes!$K$5:$K$42,MATCH(E45,Comptes!$A$5:$A$42,0)) | Q45: 4 | R45: 401000|F004
A46: BQ | B46: Banque Fictive | C46: BQ00116 | D46: 45663 | E46: 512000 | F46: Banque Fictive | G46: DEC-AN2025 | H46: Reglement fournisseur SCI Les Halles AN2025 | I46: 0 | J46: 10200 | M46: =I46-J46 | N46: 2025-01 | O46: =INDEX(Journaux!$E$5:$E$18,MATCH("2025|"&A46,Journaux!$A$5:$A$18,0)) | P46: =INDEX(Comptes!$K$5:$K$42,MATCH(E46,Comptes!$A$5:$A$42,0)) | Q46: 5
A47: BQ | B47: Banque Fictive | C47: BQ00117 | D47: 45663 | E47: 401000 | F47: Fournisseurs | G47: DEC-AN2025 | H47: Reglement fournisseur Energie Plus AN2025 | I47: 3448.86 | J47: 0 | K47: ABF | L47: Energie Plus | M47: =I47-J47 | N47: 2025-01 | O47: =INDEX(Journaux!$E$5:$E$18,MATCH("2025|"&A47,Journaux!$A$5:$A$18,0)) | P47: =INDEX(Comptes!$K$5:$K$42,MATCH(E47,Comptes!$A$5:$A$42,0)) | Q47: 4 | R47: 401000|F005
A48: BQ | B48: Banque Fictive | C48: BQ00117 | D48: 45663 | E48: 512000 | F48: Banque Fictive | G48: DEC-AN2025 | H48: Reglement fournisseur Energie Plus AN2025 | I48: 0 | J48: 3448.86 | M48: =I48-J48 | N48: 2025-01 | O48: =INDEX(Journaux!$E$5:$E$18,MATCH("2025|"&A48,Journaux!$A$5:$A$18,0)) | P48: =INDEX(Comptes!$K$5:$K$42,MATCH(E48,Comptes!$A$5:$A$42,0)) | Q48: 5
A49: BQ | B49: Banque Fictive | C49: BQ00118 | D49: 45663 | E49: 401000 | F49: Fournisseurs | G49: DEC-AN2025 | H49: Reglement fournisseur Telecom Pro AN2025 | I49: 576 | J49: 0 | K49: ABG | L49: Telecom Pro | M49: =I49-J49 | N49: 2025-01 | O49: =INDEX(Journaux!$E$5:$E$18,MATCH("2025|"&A49,Journaux!$A$5:$A$18,0)) | P49: =INDEX(Comptes!$K$5:$K$42,MATCH(E49,Comptes!$A$5:$A$42,0)) | Q49: 4 | R49: 401000|F008
A50: BQ | B50: Banque Fictive | C50: BQ00118 | D50: 45663 | E50: 512000 | F50: Banque Fictive | G50: DEC-AN2025 | H50: Reglement fournisseur Telecom Pro AN2025 | I50: 0 | J50: 576 | M50: =I50-J50 | N50: 2025-01 | O50: =INDEX(Journaux!$E$5:$E$18,MATCH("2025|"&A50,Journaux!$A$5:$A$18,0)) | P50: =INDEX(Comptes!$K$5:$K$42,MATCH(E50,Comptes!$A$5:$A$42,0)) | Q50: 5
A51: BQ | B51: Banque Fictive | C51: BQ00119 | D51: 45663 | E51: 401000 | F51: Fournisseurs | G51: DEC-AN2025 | H51: Reglement fournisseur Cabinet Comptable Exemple AN2025 | I51: 7200 | J51: 0 | K51: ABH | L51: Cabinet Comptable Exemple | M51: =I51-J51 | N51: 2025-01 | O51: =INDEX(Journaux!$E$5:$E$18,MATCH("2025|"&A51,Journaux!$A$5:$A$18,0)) | P51: =INDEX(Comptes!$K$5:$K$42,MATCH(E51,Comptes!$A$5:$A$42,0)) | Q51: 4 | R51: 401000|F007
A52: BQ | B52: Banque Fictive | C52: BQ00119 | D52: 45663 | E52: 512000 | F52: Banque Fictive | G52: DEC-AN2025 | H52: Reglement fournisseur Cabinet Comptable Exemple AN2025 | I52: 0 | J52: 7200 | M52: =I52-J52 | N52: 2025-01 | O52: =INDEX(Journaux!$E$5:$E$18,MATCH("2025|"&A52,Journaux!$A$5:$A$18,0)) | P52: =INDEX(Comptes!$K$5:$K$42,MATCH(E52,Comptes!$A$5:$A$42,0)) | Q52: 5
A53: BQ | B53: Banque Fictive | C53: BQ00064 | D53: 45665 | E53: 512000 | F53: Banque Fictive | G53: ENC-AN2025 | H53: Reglement client Cabinet Varenne Associes AN2025 | I53: 31150.6 | J53: 0 | M53: =I53-J53 | N53: 2025-01 | O53: =INDEX(Journaux!$E$5:$E$18,MATCH("2025|"&A53,Journaux!$A$5:$A$18,0)) | P53: =INDEX(Comptes!$K$5:$K$42,MATCH(E53,Comptes!$A$5:$A$42,0)) | Q53: 5
A54: BQ | B54: Banque Fictive | C54: BQ00064 | D54: 45665 | E54: 411000 | F54: Clients | G54: ENC-AN2025 | H54: Reglement client Cabinet Varenne Associes AN2025 | I54: 0 | J54: 31150.6 | K54: AAE | L54: Cabinet Varenne Associes | M54: =I54-J54 | N54: 2025-01 | O54: =INDEX(Journaux!$E$5:$E$18,MATCH("2025|"&A54,Journaux!$A$5:$A$18,0)) | P54: =INDEX(Comptes!$K$5:$K$42,MATCH(E54,Comptes!$A$5:$A$42,0)) | Q54: 4 | R54: 411000|C004
A55: BQ | B55: Banque Fictive | C55: BQ00065 | D55: 45665 | E55: 512000 | F55: Banque Fictive | G55: ENC-AN2025 | H55: Reglement client Agence Mobilis AN2025 | I55: 20557.5 | J55: 0 | M55: =I55-J55 | N55: 2025-01 | O55: =INDEX(Journaux!$E$5:$E$18,MATCH("2025|"&A55,Journaux!$A$5:$A$18,0)) | P55: =INDEX(Comptes!$K$5:$K$42,MATCH(E55,Comptes!$A$5:$A$42,0)) | Q55: 5
A56: BQ | B56: Banque Fictive | C56: BQ00065 | D56: 45665 | E56: 411000 | F56: Clients | G56: ENC-AN2025 | H56: Reglement client Agence Mobilis AN2025 | I56: 0 | J56: 20557.5 | K56: AAF | L56: Agence Mobilis | M56: =I56-J56 | N56: 2025-01 | O56: =INDEX(Journaux!$E$5:$E$18,MATCH("2025|"&A56,Journaux!$A$5:$A$18,0)) | P56: =INDEX(Comptes!$K$5:$K$42,MATCH(E56,Comptes!$A$5:$A$42,0)) | Q56: 4 | R56: 411000|C002
A57: VT | B57: Journal des ventes | C57: VT00004 | D57: 45665 | E57: 411000 | F57: Clients | G57: FA2025-0004 | H57: Facture FA2025-0004 Agence Mobilis | I57: 34109.22 | J57: 0 | K57: AAL | L57: Agence Mobilis | M57: =I57-J57 | N57: 2025-01 | O57: =INDEX(Journaux!$E$5:$E$18,MATCH("2025|"&A57,Journaux!$A$5:$A$18,0)) | P57: =INDEX(Comptes!$K$5:$K$42,MATCH(E57,Comptes!$A$5:$A$42,0)) | Q57: 4 | R57: 411000|C002
A58: VT | B58: Journal des ventes | C58: VT00004 | D58: 45665 | E58: 701000 | F58: Ventes de produits finis | G58: FA2025-0004 | H58: Facture FA2025-0004 Agence Mobilis | I58: 0 | J58: 28424.35 | M58: =I58-J58 | N58: 2025-01 | O58: =INDEX(Journaux!$E$5:$E$18,MATCH("2025|"&A58,Journaux!$A$5:$A$18,0)) | P58: =INDEX(Comptes!$K$5:$K$42,MATCH(E58,Comptes!$A$5:$A$42,0)) | Q58: 7
A59: VT | B59: Journal des ventes | C59: VT00004 | D59: 45665 | E59: 445710 | F59: TVA collectee | G59: FA2025-0004 | H59: Facture FA2025-0004 Agence Mobilis | I59: 0 | J59: 5684.87 | M59: =I59-J59 | N59: 2025-01 | O59: =INDEX(Journaux!$E$5:$E$18,MATCH("2025|"&A59,Journaux!$A$5:$A$18,0)) | P59: =INDEX(Comptes!$K$5:$K$42,MATCH(E59,Comptes!$A$5:$A$42,0)) | Q59: 4
A60: AC | B60: Journal des achats | C60: AC00001 | D60: 45667 | E60: 601000 | F60: Achats de matieres premieres | G60: F003-2025011 | H60: Facture Vernis et Finitions F003-2025011 | I60: 16035.64 | J60: 0 | M60: =I60-J60 | N60: 2025-01 | O60: =INDEX(Journaux!$E$5:$E$18,MATCH("2025|"&A60,Journaux!$A$5:$A$18,0)) | P60: =INDEX(Comptes!$K$5:$K$42,MATCH(E60,Comptes!$A$5:$A$42,0)) | Q60: 6
A61: AC | B61: Journal des achats | C61: AC00001 | D61: 45667 | E61: 445660 | F61: TVA deductible sur ABS | G61: F003-2025011 | H61: Facture Vernis et Finitions F003-2025011 | I61: 3207.13 | J61: 0 | M61: =I61-J61 | N61: 2025-01 | O61: =INDEX(Journaux!$E$5:$E$18,MATCH("2025|"&A61,Journaux!$A$5:$A$18,0)) | P61: =INDEX(Comptes!$K$5:$K$42,MATCH(E61,Comptes!$A$5:$A$42,0)) | Q61: 4
A62: AC | B62: Journal des achats | C62: AC00001 | D62: 45667 | E62: 401000 | F62: Fournisseurs | G62: F003-2025011 | H62: Facture Vernis et Finitions F003-2025011 | I62: 0 | J62: 19242.77 | K62: ABI | L62: Vernis et Finitions | M62: =I62-J62 | N62: 2025-01 | O62: =INDEX(Journaux!$E$5:$E$18,MATCH("2025|"&A62,Journaux!$A$5:$A$18,0)) | P62: =INDEX(Comptes!$K$5:$K$42,MATCH(E62,Comptes!$A$5:$A$42,0)) | Q62: 4 | R62: 401000|F003
A63: BQ | B63: Banque Fictive | C63: BQ00002 | D63: 45667 | E63: 164000 | F63: Emprunts aupres des etablissements de credit | G63: ECH202501 | H63: Echeance emprunt 01/2025 | I63: 2000 | J63: 0 | M63: =I63-J63 | N63: 2025-01 | O63: =INDEX(Journaux!$E$5:$E$18,MATCH("2025|"&A63,Journaux!$A$5:$A$18,0)) | P63: =INDEX(Comptes!$K$5:$K$42,MATCH(E63,Comptes!$A$5:$A$42,0)) | Q63: 1
A64: BQ | B64: Banque Fictive | C64: BQ00002 | D64: 45667 | E64: 661100 | F64: Interets des emprunts | G64: ECH202501 | H64: Echeance emprunt 01/2025 | I64: 220 | J64: 0 | M64: =I64-J64 | N64: 2025-01 | O64: =INDEX(Journaux!$E$5:$E$18,MATCH("2025|"&A64,Journaux!$A$5:$A$18,0)) | P64: =INDEX(Comptes!$K$5:$K$42,MATCH(E64,Comptes!$A$5:$A$42,0)) | Q64: 6
A65: BQ | B65: Banque Fictive | C65: BQ00002 | D65: 45667 | E65: 512000 | F65: Banque Fictive | G65: ECH202501 | H65: Echeance emprunt 01/2025 | I65: 0 | J65: 2220 | M65: =I65-J65 | N65: 2025-01 | O65: =INDEX(Journaux!$E$5:$E$18,MATCH("2025|"&A65,Journaux!$A$5:$A$18,0)) | P65: =INDEX(Comptes!$K$5:$K$42,MATCH(E65,Comptes!$A$5:$A$42,0)) | Q65: 5
A66: VT | B66: Journal des ventes | C66: VT00001 | D66: 45670 | E66: 411000 | F66: Clients | G66: FA2025-0001 | H66: Facture FA2025-0001 Agence Mobilis | I66: 23082.83 | J66: 0 | K66: AAI | L66: Agence Mobilis | M66: =I66-J66 | N66: 2025-01 | O66: =INDEX(Journaux!$E$5:$E$18,MATCH("2025|"&A66,Journaux!$A$5:$A$18,0)) | P66: =INDEX(Comptes!$K$5:$K$42,MATCH(E66,Comptes!$A$5:$A$42,0)) | Q66: 4 | R66: 411000|C002
A67: VT | B67: Journal des ventes | C67: VT00001 | D67: 45670 | E67: 701000 | F67: Ventes de produits finis | G67: FA2025-0001 | H67: Facture FA2025-0001 Agence Mobilis | I67: 0 | J67: 19235.69 | M67: =I67-J67 | N67: 2025-01 | O67: =INDEX(Journaux!$E$5:$E$18,MATCH("2025|"&A67,Journaux!$A$5:$A$18,0)) | P67: =INDEX(Comptes!$K$5:$K$42,MATCH(E67,Comptes!$A$5:$A$42,0)) | Q67: 7
A68: VT | B68: Journal des ventes | C68: VT00001 | D68: 45670 | E68: 445710 | F68: TVA collectee | G68: FA2025-0001 | H68: Facture FA2025-0001 Agence Mobilis | I68: 0 | J68: 3847.14 | M68: =I68-J68 | N68: 2025-01 | O68: =INDEX(Journaux!$E$5:$E$18,MATCH("2025|"&A68,Journaux!$A$5:$A$18,0)) | P68: =INDEX(Comptes!$K$5:$K$42,MATCH(E68,Comptes!$A$5:$A$42,0)) | Q68: 4
A69: BQ | B69: Banque Fictive | C69: BQ00113 | D69: 45671 | E69: 401000 | F69: Fournisseurs | G69: DEC-AN2025 | H69: Reglement fournisseur Quincaillerie Pro Est AN2025 | I69: 52590.01 | J69: 0 | K69: ABB | L69: Quincaillerie Pro Est | M69: =I69-J69 | N69: 2025-01 | O69: =INDEX(Journaux!$E$5:$E$18,MATCH("2025|"&A69,Journaux!$A$5:$A$18,0)) | P69: =INDEX(Comptes!$K$5:$K$42,MATCH(E69,Comptes!$A$5:$A$42,0)) | Q69: 4 | R69: 401000|F002
A70: BQ | B70: Banque Fictive | C70: BQ00113 | D70: 45671 | E70: 512000 | F70: Banque Fictive | G70: DEC-AN2025 | H70: Reglement fournisseur Quincaillerie Pro Est AN2025 | I70: 0 | J70: 52590.01 | M70: =I70-J70 | N70: 2025-01 | O70: =INDEX(Journaux!$E$5:$E$18,MATCH("2025|"&A70,Journaux!$A$5:$A$18,0)) | P70: =INDEX(Comptes!$K$5:$K$42,MATCH(E70,Comptes!$A$5:$A$42,0)) | Q70: 5
A71: BQ | B71: Banque Fictive | C71: BQ00037 | D71: 45672 | E71: 431000 | F71: Securite sociale | G71: URSSAF202412 | H71: Reglement URSSAF 12/2024 | I71: 33292.52 | J71: 0 | M71: =I71-J71 | N71: 2025-01 | O71: =INDEX(Journaux!$E$5:$E$18,MATCH("2025|"&A71,Journaux!$A$5:$A$18,0)) | P71: =INDEX(Comptes!$K$5:$K$42,MATCH(E71,Comptes!$A$5:$A$42,0)) | Q71: 4
A72: BQ | B72: Banque Fictive | C72: BQ00037 | D72: 45672 | E72: 512000 | F72: Banque Fictive | G72: URSSAF202412 | H72: Reglement URSSAF 12/2024 | I72: 0 | J72: 33292.52 | M72: =I72-J72 | N72: 2025-01 | O72: =INDEX(Journaux!$E$5:$E$18,MATCH("2025|"&A72,Journaux!$A$5:$A$18,0)) | P72: =INDEX(Comptes!$K$5:$K$42,MATCH(E72,Comptes!$A$5:$A$42,0)) | Q72: 5
A73: BQ | B73: Banque Fictive | C73: BQ00061 | D73: 45672 | E73: 512000 | F73: Banque Fictive | G73: ENC-AN2025 | H73: Reglement client Agence Mobilis AN2025 | I73: 35886.29 | J73: 0 | M73: =I73-J73 | N73: 2025-01 | O73: =INDEX(Journaux!$E$5:$E$18,MATCH("2025|"&A73,Journaux!$A$5:$A$18,0)) | P73: =INDEX(Comptes!$K$5:$K$42,MATCH(E73,Comptes!$A$5:$A$42,0)) | Q73: 5
A74: BQ | B74: Banque Fictive | C74: BQ00061 | D74: 45672 | E74: 411000 | F74: Clients | G74: ENC-AN2025 | H74: Reglement client Agence Mobilis AN2025 | I74: 0 | J74: 35886.29 | K74: AAB | L74: Agence Mobilis | M74: =I74-J74 | N74: 2025-01 | O74: =INDEX(Journaux!$E$5:$E$18,MATCH("2025|"&A74,Journaux!$A$5:$A$18,0)) | P74: =INDEX(Comptes!$K$5:$K$42,MATCH(E74,Comptes!$A$5:$A$42,0)) | Q74: 4 | R74: 411000|C002
A75: AC | B75: Journal des achats | C75: AC00002 | D75: 45677 | E75: 601000 | F75: Achats de matieres premieres | G75: F001-2025012 | H75: Facture Scierie du Nord F001-2025012 | I75: 15958.36 | J75: 0 | M75: =I75-J75 | N75: 2025-01 | O75: =INDEX(Journaux!$E$5:$E$18,MATCH("2025|"&A75,Journaux!$A$5:$A$18,0)) | P75: =INDEX(Comptes!$K$5:$K$42,MATCH(E75,Comptes!$A$5:$A$42,0)) | Q75: 6
A76: AC | B76: Journal des achats | C76: AC00002 | D76: 45677 | E76: 445660 | F76: TVA deductible sur ABS | G76: F001-2025012 | H76: Facture Scierie du Nord F001-2025012 | I76: 3191.67 | J76: 0 | M76: =I76-J76 | N76: 2025-01 | O76: =INDEX(Journaux!$E$5:$E$18,MATCH("2025|"&A76,Journaux!$A$5:$A$18,0)) | P76: =INDEX(Comptes!$K$5:$K$42,MATCH(E76,Comptes!$A$5:$A$42,0)) | Q76: 4
A77: AC | B77: Journal des achats | C77: AC00002 | D77: 45677 | E77: 401000 | F77: Fournisseurs | G77: F001-2025012 | H77: Facture Scierie du Nord F001-2025012 | I77: 0 | J77: 19150.03 | K77: ABJ | L77: Scierie du Nord | M77: =I77-J77 | N77: 2025-01 | O77: =INDEX(Journaux!$E$5:$E$18,MATCH("2025|"&A77,Journaux!$A$5:$A$18,0)) | P77: =INDEX(Comptes!$K$5:$K$42,MATCH(E77,Comptes!$A$5:$A$42,0)) | Q77: 4 | R77: 401000|F001
A78: BQ | B78: Banque Fictive | C78: BQ00038 | D78: 45677 | E78: 445510 | F78: TVA a decaisser | G78: TVA202412 | H78: Reglement TVA 12/2024 | I78: 14795.86 | J78: 0 | M78: =I78-J78 | N78: 2025-01 | O78: =INDEX(Journaux!$E$5:$E$18,MATCH("2025|"&A78,Journaux!$A$5:$A$18,0)) | P78: =INDEX(Comptes!$K$5:$K$42,MATCH(E78,Comptes!$A$5:$A$42,0)) | Q78: 4
A79: BQ | B79: Banque Fictive | C79: BQ00038 | D79: 45677 | E79: 512000 | F79: Banque Fictive | G79: TVA202412 | H79: Reglement TVA 12/2024 | I79: 0 | J79: 14795.86 | M79: =I79-J79 | N79: 2025-01 | O79: =INDEX(Journaux!$E$5:$E$18,MATCH("2025|"&A79,Journaux!$A$5:$A$18,0)) | P79: =INDEX(Comptes!$K$5:$K$42,MATCH(E79,Comptes!$A$5:$A$42,0)) | Q79: 5
A80: VT | B80: Journal des ventes | C80: VT00005 | D80: 45677 | E80: 411000 | F80: Clients | G80: FA2025-0005 | H80: Facture FA2025-0005 Boutique Hetre et Chene | I80: 18286.85 | J80: 0 | K80: AAM | L80: Boutique Hetre et Chene | M80: =I80-J80 | N80: 2025-01 | O80: =INDEX(Journaux!$E$5:$E$18,MATCH("2025|"&A80,Journaux!$A$5:$A$18,0)) | P80: =INDEX(Comptes!$K$5:$K$42,MATCH(E80,Comptes!$A$5:$A$42,0)) | Q80: 4 | R80: 411000|C007
A81: VT | B81: Journal des ventes | C81: VT00005 | D81: 45677 | E81: 701000 | F81: Ventes de produits finis | G81: FA2025-0005 | H81: Facture FA2025-0005 Boutique Hetre et Chene | I81: 0 | J81: 15239.04 | M81: =I81-J81 | N81: 2025-01 | O81: =INDEX(Journaux!$E$5:$E$18,MATCH("2025|"&A81,Journaux!$A$5:$A$18,0)) | P81: =INDEX(Comptes!$K$5:$K$42,MATCH(E81,Comptes!$A$5:$A$42,0)) | Q81: 7
A82: VT | B82: Journal des ventes | C82: VT00005 | D82: 45677 | E82: 445710 | F82: TVA collectee | G82: FA2025-0005 | H82: Facture FA2025-0005 Boutique Hetre et Chene | I82: 0 | J82: 3047.81 | M82: =I82-J82 | N82: 2025-01 | O82: =INDEX(Journaux!$E$5:$E$18,MATCH("2025|"&A82,Journaux!$A$5:$A$18,0)) | P82: =INDEX(Comptes!$K$5:$K$42,MATCH(E82,Comptes!$A$5:$A$42,0)) | Q82: 4
A83: AC | B83: Journal des achats | C83: AC00003 | D83: 45678 | E83: 601000 | F83: Achats de matieres premieres | G83: F001-2025013 | H83: Facture Scierie du Nord F001-2025013 | I83: 20097.67 | J83: 0 | M83: =I83-J83 | N83: 2025-01 | O83: =INDEX(Journaux!$E$5:$E$18,MATCH("2025|"&A83,Journaux!$A$5:$A$18,0)) | P83: =INDEX(Comptes!$K$5:$K$42,MATCH(E83,Comptes!$A$5:$A$42,0)) | Q83: 6
A84: AC | B84: Journal des achats | C84: AC00003 | D84: 45678 | E84: 445660 | F84: TVA deductible sur ABS | G84: F001-2025013 | H84: Facture Scierie du Nord F001-2025013 | I84: 4019.53 | J84: 0 | M84: =I84-J84 | N84: 2025-01 | O84: =INDEX(Journaux!$E$5:$E$18,MATCH("2025|"&A84,Journaux!$A$5:$A$18,0)) | P84: =INDEX(Comptes!$K$5:$K$42,MATCH(E84,Comptes!$A$5:$A$42,0)) | Q84: 4
A85: AC | B85: Journal des achats | C85: AC00003 | D85: 45678 | E85: 401000 | F85: Fournisseurs | G85: F001-2025013 | H85: Facture Scierie du Nord F001-2025013 | I85: 0 | J85: 24117.2 | K85: ABK | L85: Scierie du Nord | M85: =I85-J85 | N85: 2025-01 | O85: =INDEX(Journaux!$E$5:$E$18,MATCH("2025|"&A85,Journaux!$A$5:$A$18,0)) | P85: =INDEX(Comptes!$K$5:$K$42,MATCH(E85,Comptes!$A$5:$A$42,0)) | Q85: 4 | R85: 401000|F001
A86: VT | B86: Journal des ventes | C86: VT00002 | D86: 45678 | E86: 411000 | F86: Clients | G86: FA2025-0002 | H86: Facture FA2025-0002 Agence Mobilis | I86: 36305.42 | J86: 0 | K86: AAJ | L86: Agence Mobilis | M86: =I86-J86 | N86: 2025-01 | O86: =INDEX(Journaux!$E$5:$E$18,MATCH("2025|"&A86,Journaux!$A$5:$A$18,0)) | P86: =INDEX(Comptes!$K$5:$K$42,MATCH(E86,Comptes!$A$5:$A$42,0)) | Q86: 4 | R86: 411000|C002
A87: VT | B87: Journal des ventes | C87: VT00002 | D87: 45678 | E87: 701000 | F87: Ventes de produits finis | G87: FA2025-0002 | H87: Facture FA2025-0002 Agence Mobilis | I87: 0 | J87: 30254.52 | M87: =I87-J87 | N87: 2025-01 | O87: =INDEX(Journaux!$E$5:$E$18,MATCH("2025|"&A87,Journaux!$A$5:$A$18,0)) | P87: =INDEX(Comptes!$K$5:$K$42,MATCH(E87,Comptes!$A$5:$A$42,0)) | Q87: 7
A88: VT | B88: Journal des ventes | C88: VT00002 | D88: 45678 | E88: 445710 | F88: TVA collectee | G88: FA2025-0002 | H88: Facture FA2025-0002 Agence Mobilis | I88: 0 | J88: 6050.9 | M88: =I88-J88 | N88: 2025-01 | O88: =INDEX(Journaux!$E$5:$E$18,MATCH("2025|"&A88,Journaux!$A$5:$A$18,0)) | P88: =INDEX(Comptes!$K$5:$K$42,MATCH(E88,Comptes!$A$5:$A$42,0)) | Q88: 4
A89: BQ | B89: Banque Fictive | C89: BQ00062 | D89: 45680 | E89: 512000 | F89: Banque Fictive | G89: ENC-AN2025 | H89: Reglement client Residence Bel Air AN2025 | I89: 37138.48 | J89: 0 | M89: =I89-J89 | N89: 2025-01 | O89: =INDEX(Journaux!$E$5:$E$18,MATCH("2025|"&A89,Journaux!$A$5:$A$18,0)) | P89: =INDEX(Comptes!$K$5:$K$42,MATCH(E89,Comptes!$A$5:$A$42,0)) | Q89: 5
A90: BQ | B90: Banque Fictive | C90: BQ00062 | D90: 45680 | E90: 411000 | F90: Clients | G90: ENC-AN2025 | H90: Reglement client Residence Bel Air AN2025 | I90: 0 | J90: 37138.48 | K90: AAC | L90: Residence Bel Air | M90: =I90-J90 | N90: 2025-01 | O90: =INDEX(Journaux!$E$5:$E$18,MATCH("2025|"&A90,Journaux!$A$5:$A$18,0)) | P90: =INDEX(Comptes!$K$5:$K$42,MATCH(E90,Comptes!$A$5:$A$42,0)) | Q90: 4 | R90: 411000|C003
A91: BQ | B91: Banque Fictive | C91: BQ00115 | D91: 45684 | E91: 401000 | F91: Fournisseurs | G91: DEC-AN2025 | H91: Reglement fournisseur Quincaillerie Pro Est AN2025 | I91: 45322.61 | J91: 0 | K91: ABD | L91: Quincaillerie Pro Est | M91: =I91-J91 | N91: 2025-01 | O91: =INDEX(Journaux!$E$5:$E$18,MATCH("2025|"&A91,Journaux!$A$5:$A$18,0)) | P91: =INDEX(Comptes!$K$5:$K$42,MATCH(E91,Comptes!$A$5:$A$42,0)) | Q91: 4 | R91: 401000|F002
A92: BQ | B92: Banque Fictive | C92: BQ00115 | D92: 45684 | E92: 512000 | F92: Banque Fictive | G92: DEC-AN2025 | H92: Reglement fournisseur Quincaillerie Pro Est AN2025 | I92: 0 | J92: 45322.61 | M92: =I92-J92 | N92: 2025-01 | O92: =INDEX(Journaux!$E$5:$E$18,MATCH("2025|"&A92,Journaux!$A$5:$A$18,0)) | P92: =INDEX(Comptes!$K$5:$K$42,MATCH(E92,Comptes!$A$5:$A$42,0)) | Q92: 5
