Workbook

Sheet LISEZMOI
A1: Vestis — Trésorerie historique reconstituée depuis le FEC
A2: Exercices : 2024, 2025. Généré le 19/10/2026.
A4: Méthode | B4: Chaque écriture qui mouvemente un compte de banque (512, 514, 517, 53) est lue par sa contrepartie : 411 = encaissement client, 421 = salaires, 431 = URSSAF, 445 = TVA, 164 = emprunt, etc. Les à-nouveaux ne sont pas des flux : ils donnent la trésorerie d'ouverture.
A5: Reclasser un flux | B5: Flux_detail, colonne M « Surcharge » (jaune) : saisir une catégorie de l'onglet Categories. Tous les tableaux se recalculent.
A6: Limites | B6: Le FEC s'arrête à la dernière saisie du cabinet : les semaines récentes viendront des relevés bancaires. Le solde est comptable, pas le solde de relevé (rapprochement bancaire à vérifier). Les virements via 58 et les comptes d'attente sont signalés dans les contrôles.
A7: Ordre de lecture | B7: 1. Controles 2. Flux_mensuels 3. Solde_quotidien (point bas) 4. Flux_hebdo 5. Delais 6. Recurrences.
A8: Confidentialité | B8: Classeur produit localement : les fichiers n'ont été transmis à aucun serveur.

Sheet Controles
A1: Contrôles de la reconstitution des flux
A2: La trésorerie de fin d'exercice recalculée à partir des flux doit égaler le solde comptable des banques.
A4: Contrôle | B4: 2024 | C4: Statut | D4: 2025 | E4: Statut
A5: Trésorerie d'ouverture (à-nouveaux bancaires) | B5: 85000 | D5: 111111.24
A6: Flux nets de l'exercice (somme des flux détaillés) | B6: =SUMIFS(Flux_detail!$K$2:$K$403,Flux_detail!$D$2:$D$403,"2024") | D6: =SUMIFS(Flux_detail!$K$2:$K$403,Flux_detail!$D$2:$D$403,"2025")
A7: Trésorerie de clôture recalculée | B7: =B5+B6 | D7: =D5+D6
A8: Solde comptable des banques à la clôture | B8: 111111.24 | D8: -152621.97
A9: Écart (doit être nul) | B9: =B7-B8 | C9: =IF(ABS(B9)<=1,"OK","À VOIR") | D9: =D7-D8 | E9: =IF(ABS(D9)<=1,"OK","À VOIR")
A10: Écritures de banque déséquilibrées (montant) | B10: 0 | C10: =IF(ABS(B10)<=1,"OK","À VOIR") | D10: 0 | E10: =IF(ABS(D10)<=1,"OK","À VOIR")
A11: Part des flux non affectés (attente, divers, transit) | B11: 0 | C11: =IF(B11<=0.05,"OK","À VOIR") | D11: 0 | E11: =IF(D11<=0.05,"OK","À VOIR")
A12: Fonds en transit (comptes 58) à la clôture | B12: 0 | C12: =IF(ABS(B12)<=1,"OK","À VOIR") | D12: 0 | E12: =IF(ABS(D12)<=1,"OK","À VOIR")
A13: Nombre de flux reconstitués | B13: 202 | D13: 200
A14: Comptes de banque | B14: 512000 | D14: 512000

Sheet Flux_mensuels
A1: Flux de trésorerie mensuels
A2: Encaissements positifs, décaissements négatifs. Reconstitués depuis les écritures de banque du FEC (contrepartie de chaque écriture).
B3: 2024 | C3: 2024 | D3: 2024 | E3: 2024 | F3: 2024 | G3: 2024 | H3: 2024 | I3: 2024 | J3: 2024 | K3: 2024 | L3: 2024 | M3: 2024 | N3: 2025 | O3: 2025 | P3: 2025 | Q3: 2025 | R3: 2025 | S3: 2025 | T3: 2025 | U3: 2025 | V3: 2025 | W3: 2025 | X3: 2025 | Y3: 2025
A4: En euros | B4: 2024-01 | C4: 2024-02 | D4: 2024-03 | E4: 2024-04 | F4: 2024-05 | G4: 2024-06 | H4: 2024-07 | I4: 2024-08 | J4: 2024-09 | K4: 2024-10 | L4: 2024-11 | M4: 2024-12 | N4: 2025-01 | O4: 2025-02 | P4: 2025-03 | Q4: 2025-04 | R4: 2025-05 | S4: 2025-06 | T4: 2025-07 | U4: 2025-08 | V4: 2025-09 | W4: 2025-10 | X4: 2025-11 | Y4: 2025-12
A5: Flux d'exploitation
A6: Clients | B6: =SUMIFS(Flux_detail!$K$2:$K$403,Flux_detail!$N$2:$N$403,$A6,Flux_detail!$C$2:$C$403,B$4) | C6: =SUMIFS(Flux_detail!$K$2:$K$403,Flux_detail!$N$2:$N$403,$A6,Flux_detail!$C$2:$C$403,C$4) | D6: =SUMIFS(Flux_detail!$K$2:$K$403,Flux_detail!$N$2:$N$403,$A6,Flux_detail!$C$2:$C$403,D$4) | E6: =SUMIFS(Flux_detail!$K$2:$K$403,Flux_detail!$N$2:$N$403,$A6,Flux_detail!$C$2:$C$403,E$4) | F6: =SUMIFS(Flux_detail!$K$2:$K$403,Flux_detail!$N$2:$N$403,$A6,Flux_detail!$C$2:$C$403,F$4) | G6: =SUMIFS(Flux_detail!$K$2:$K$403,Flux_detail!$N$2:$N$403,$A6,Flux_detail!$C$2:$C$403,G$4) | H6: =SUMIFS(Flux_detail!$K$2:$K$403,Flux_detail!$N$2:$N$403,$A6,Flux_detail!$C$2:$C$403,H$4) | I6: =SUMIFS(Flux_detail!$K$2:$K$403,Flux_detail!$N$2:$N$403,$A6,Flux_detail!$C$2:$C$403,I$4) | ... Y6: =SUMIFS(Flux_detail!$K$2:$K$403,Flux_detail!$N$2:$N$403,$A6,Flux_detail!$C$2:$C$403,Y$4)
A7: Fournisseurs et charges externes | B7: =SUMIFS(Flux_detail!$K$2:$K$403,Flux_detail!$N$2:$N$403,$A7,Flux_detail!$C$2:$C$403,B$4) | C7: =SUMIFS(Flux_detail!$K$2:$K$403,Flux_detail!$N$2:$N$403,$A7,Flux_detail!$C$2:$C$403,C$4) | D7: =SUMIFS(Flux_detail!$K$2:$K$403,Flux_detail!$N$2:$N$403,$A7,Flux_detail!$C$2:$C$403,D$4) | E7: =SUMIFS(Flux_detail!$K$2:$K$403,Flux_detail!$N$2:$N$403,$A7,Flux_detail!$C$2:$C$403,E$4) | F7: =SUMIFS(Flux_detail!$K$2:$K$403,Flux_detail!$N$2:$N$403,$A7,Flux_detail!$C$2:$C$403,F$4) | G7: =SUMIFS(Flux_detail!$K$2:$K$403,Flux_detail!$N$2:$N$403,$A7,Flux_detail!$C$2:$C$403,G$4) | H7: =SUMIFS(Flux_detail!$K$2:$K$403,Flux_detail!$N$2:$N$403,$A7,Flux_detail!$C$2:$C$403,H$4) | I7: =SUMIFS(Flux_detail!$K$2:$K$403,Flux_detail!$N$2:$N$403,$A7,Flux_detail!$C$2:$C$403,I$4) | ... Y7: =SUMIFS(Flux_detail!$K$2:$K$403,Flux_detail!$N$2:$N$403,$A7,Flux_detail!$C$2:$C$403,Y$4)
A8: Frais bancaires | B8: =SUMIFS(Flux_detail!$K$2:$K$403,Flux_detail!$N$2:$N$403,$A8,Flux_detail!$C$2:$C$403,B$4) | C8: =SUMIFS(Flux_detail!$K$2:$K$403,Flux_detail!$N$2:$N$403,$A8,Flux_detail!$C$2:$C$403,C$4) | D8: =SUMIFS(Flux_detail!$K$2:$K$403,Flux_detail!$N$2:$N$403,$A8,Flux_detail!$C$2:$C$403,D$4) | E8: =SUMIFS(Flux_detail!$K$2:$K$403,Flux_detail!$N$2:$N$403,$A8,Flux_detail!$C$2:$C$403,E$4) | F8: =SUMIFS(Flux_detail!$K$2:$K$403,Flux_detail!$N$2:$N$403,$A8,Flux_detail!$C$2:$C$403,F$4) | G8: =SUMIFS(Flux_detail!$K$2:$K$403,Flux_detail!$N$2:$N$403,$A8,Flux_detail!$C$2:$C$403,G$4) | H8: =SUMIFS(Flux_detail!$K$2:$K$403,Flux_detail!$N$2:$N$403,$A8,Flux_detail!$C$2:$C$403,H$4) | I8: =SUMIFS(Flux_detail!$K$2:$K$403,Flux_detail!$N$2:$N$403,$A8,Flux_detail!$C$2:$C$403,I$4) | ... Y8: =SUMIFS(Flux_detail!$K$2:$K$403,Flux_detail!$N$2:$N$403,$A8,Flux_detail!$C$2:$C$403,Y$4)
A9: Salaires et personnel | B9: =SUMIFS(Flux_detail!$K$2:$K$403,Flux_detail!$N$2:$N$403,$A9,Flux_detail!$C$2:$C$403,B$4) | C9: =SUMIFS(Flux_detail!$K$2:$K$403,Flux_detail!$N$2:$N$403,$A9,Flux_detail!$C$2:$C$403,C$4) | D9: =SUMIFS(Flux_detail!$K$2:$K$403,Flux_detail!$N$2:$N$403,$A9,Flux_detail!$C$2:$C$403,D$4) | E9: =SUMIFS(Flux_detail!$K$2:$K$403,Flux_detail!$N$2:$N$403,$A9,Flux_detail!$C$2:$C$403,E$4) | F9: =SUMIFS(Flux_detail!$K$2:$K$403,Flux_detail!$N$2:$N$403,$A9,Flux_detail!$C$2:$C$403,F$4) | G9: =SUMIFS(Flux_detail!$K$2:$K$403,Flux_detail!$N$2:$N$403,$A9,Flux_detail!$C$2:$C$403,G$4) | H9: =SUMIFS(Flux_detail!$K$2:$K$403,Flux_detail!$N$2:$N$403,$A9,Flux_detail!$C$2:$C$403,H$4) | I9: =SUMIFS(Flux_detail!$K$2:$K$403,Flux_detail!$N$2:$N$403,$A9,Flux_detail!$C$2:$C$403,I$4) | ... Y9: =SUMIFS(Flux_detail!$K$2:$K$403,Flux_detail!$N$2:$N$403,$A9,Flux_detail!$C$2:$C$403,Y$4)
A10: Charges sociales | B10: =SUMIFS(Flux_detail!$K$2:$K$403,Flux_detail!$N$2:$N$403,$A10,Flux_detail!$C$2:$C$403,B$4) | C10: =SUMIFS(Flux_detail!$K$2:$K$403,Flux_detail!$N$2:$N$403,$A10,Flux_detail!$C$2:$C$403,C$4) | D10: =SUMIFS(Flux_detail!$K$2:$K$403,Flux_detail!$N$2:$N$403,$A10,Flux_detail!$C$2:$C$403,D$4) | E10: =SUMIFS(Flux_detail!$K$2:$K$403,Flux_detail!$N$2:$N$403,$A10,Flux_detail!$C$2:$C$403,E$4) | F10: =SUMIFS(Flux_detail!$K$2:$K$403,Flux_detail!$N$2:$N$403,$A10,Flux_detail!$C$2:$C$403,F$4) | G10: =SUMIFS(Flux_detail!$K$2:$K$403,Flux_detail!$N$2:$N$403,$A10,Flux_detail!$C$2:$C$403,G$4) | H10: =SUMIFS(Flux_detail!$K$2:$K$403,Flux_detail!$N$2:$N$403,$A10,Flux_detail!$C$2:$C$403,H$4) | I10: =SUMIFS(Flux_detail!$K$2:$K$403,Flux_detail!$N$2:$N$403,$A10,Flux_detail!$C$2:$C$403,I$4) | ... Y10: =SUMIFS(Flux_detail!$K$2:$K$403,Flux_detail!$N$2:$N$403,$A10,Flux_detail!$C$2:$C$403,Y$4)
A11: TVA | B11: =SUMIFS(Flux_detail!$K$2:$K$403,Flux_detail!$N$2:$N$403,$A11,Flux_detail!$C$2:$C$403,B$4) | C11: =SUMIFS(Flux_detail!$K$2:$K$403,Flux_detail!$N$2:$N$403,$A11,Flux_detail!$C$2:$C$403,C$4) | D11: =SUMIFS(Flux_detail!$K$2:$K$403,Flux_detail!$N$2:$N$403,$A11,Flux_detail!$C$2:$C$403,D$4) | E11: =SUMIFS(Flux_detail!$K$2:$K$403,Flux_detail!$N$2:$N$403,$A11,Flux_detail!$C$2:$C$403,E$4) | F11: =SUMIFS(Flux_detail!$K$2:$K$403,Flux_detail!$N$2:$N$403,$A11,Flux_detail!$C$2:$C$403,F$4) | G11: =SUMIFS(Flux_detail!$K$2:$K$403,Flux_detail!$N$2:$N$403,$A11,Flux_detail!$C$2:$C$403,G$4) | H11: =SUMIFS(Flux_detail!$K$2:$K$403,Flux_detail!$N$2:$N$403,$A11,Flux_detail!$C$2:$C$403,H$4) | I11: =SUMIFS(Flux_detail!$K$2:$K$403,Flux_detail!$N$2:$N$403,$A11,Flux_detail!$C$2:$C$403,I$4) | ... Y11: =SUMIFS(Flux_detail!$K$2:$K$403,Flux_detail!$N$2:$N$403,$A11,Flux_detail!$C$2:$C$403,Y$4)
A12: Impôt sur les sociétés | B12: =SUMIFS(Flux_detail!$K$2:$K$403,Flux_detail!$N$2:$N$403,$A12,Flux_detail!$C$2:$C$403,B$4) | C12: =SUMIFS(Flux_detail!$K$2:$K$403,Flux_detail!$N$2:$N$403,$A12,Flux_detail!$C$2:$C$403,C$4) | D12: =SUMIFS(Flux_detail!$K$2:$K$403,Flux_detail!$N$2:$N$403,$A12,Flux_detail!$C$2:$C$403,D$4) | E12: =SUMIFS(Flux_detail!$K$2:$K$403,Flux_detail!$N$2:$N$403,$A12,Flux_detail!$C$2:$C$403,E$4) | F12: =SUMIFS(Flux_detail!$K$2:$K$403,Flux_detail!$N$2:$N$403,$A12,Flux_detail!$C$2:$C$403,F$4) | G12: =SUMIFS(Flux_detail!$K$2:$K$403,Flux_detail!$N$2:$N$403,$A12,Flux_detail!$C$2:$C$403,G$4) | H12: =SUMIFS(Flux_detail!$K$2:$K$403,Flux_detail!$N$2:$N$403,$A12,Flux_detail!$C$2:$C$403,H$4) | I12: =SUMIFS(Flux_detail!$K$2:$K$403,Flux_detail!$N$2:$N$403,$A12,Flux_detail!$C$2:$C$403,I$4) | ... Y12: =SUMIFS(Flux_detail!$K$2:$K$403,Flux_detail!$N$2:$N$403,$A12,Flux_detail!$C$2:$C$403,Y$4)
A13: Autres impôts et taxes | B13: =SUMIFS(Flux_detail!$K$2:$K$403,Flux_detail!$N$2:$N$403,$A13,Flux_detail!$C$2:$C$403,B$4) | C13: =SUMIFS(Flux_detail!$K$2:$K$403,Flux_detail!$N$2:$N$403,$A13,Flux_detail!$C$2:$C$403,C$4) | D13: =SUMIFS(Flux_detail!$K$2:$K$403,Flux_detail!$N$2:$N$403,$A13,Flux_detail!$C$2:$C$403,D$4) | E13: =SUMIFS(Flux_detail!$K$2:$K$403,Flux_detail!$N$2:$N$403,$A13,Flux_detail!$C$2:$C$403,E$4) | F13: =SUMIFS(Flux_detail!$K$2:$K$403,Flux_detail!$N$2:$N$403,$A13,Flux_detail!$C$2:$C$403,F$4) | G13: =SUMIFS(Flux_detail!$K$2:$K$403,Flux_detail!$N$2:$N$403,$A13,Flux_detail!$C$2:$C$403,G$4) | H13: =SUMIFS(Flux_detail!$K$2:$K$403,Flux_detail!$N$2:$N$403,$A13,Flux_detail!$C$2:$C$403,H$4) | I13: =SUMIFS(Flux_detail!$K$2:$K$403,Flux_detail!$N$2:$N$403,$A13,Flux_detail!$C$2:$C$403,I$4) | ... Y13: =SUMIFS(Flux_detail!$K$2:$K$403,Flux_detail!$N$2:$N$403,$A13,Flux_detail!$C$2:$C$403,Y$4)
A14: Total flux d'exploitation | B14: =SUMIFS(Flux_detail!$K$2:$K$403,Flux_detail!$O$2:$O$403,"EXPL",Flux_detail!$C$2:$C$403,B$4) | C14: =SUMIFS(Flux_detail!$K$2:$K$403,Flux_detail!$O$2:$O$403,"EXPL",Flux_detail!$C$2:$C$403,C$4) | D14: =SUMIFS(Flux_detail!$K$2:$K$403,Flux_detail!$O$2:$O$403,"EXPL",Flux_detail!$C$2:$C$403,D$4) | E14: =SUMIFS(Flux_detail!$K$2:$K$403,Flux_detail!$O$2:$O$403,"EXPL",Flux_detail!$C$2:$C$403,E$4) | F14: =SUMIFS(Flux_detail!$K$2:$K$403,Flux_detail!$O$2:$O$403,"EXPL",Flux_detail!$C$2:$C$403,F$4) | G14: =SUMIFS(Flux_detail!$K$2:$K$403,Flux_detail!$O$2:$O$403,"EXPL",Flux_detail!$C$2:$C$403,G$4) | H14: =SUMIFS(Flux_detail!$K$2:$K$403,Flux_detail!$O$2:$O$403,"EXPL",Flux_detail!$C$2:$C$403,H$4) | I14: =SUMIFS(Flux_detail!$K$2:$K$403,Flux_detail!$O$2:$O$403,"EXPL",Flux_detail!$C$2:$C$403,I$4) | ... Y14: =SUMIFS(Flux_detail!$K$2:$K$403,Flux_detail!$O$2:$O$403,"EXPL",Flux_detail!$C$2:$C$403,Y$4)
A16: Flux de financement
A17: Emprunts - capital | B17: =SUMIFS(Flux_detail!$K$2:$K$403,Flux_detail!$N$2:$N$403,$A17,Flux_detail!$C$2:$C$403,B$4) | C17: =SUMIFS(Flux_detail!$K$2:$K$403,Flux_detail!$N$2:$N$403,$A17,Flux_detail!$C$2:$C$403,C$4) | D17: =SUMIFS(Flux_detail!$K$2:$K$403,Flux_detail!$N$2:$N$403,$A17,Flux_detail!$C$2:$C$403,D$4) | E17: =SUMIFS(Flux_detail!$K$2:$K$403,Flux_detail!$N$2:$N$403,$A17,Flux_detail!$C$2:$C$403,E$4) | F17: =SUMIFS(Flux_detail!$K$2:$K$403,Flux_detail!$N$2:$N$403,$A17,Flux_detail!$C$2:$C$403,F$4) | G17: =SUMIFS(Flux_detail!$K$2:$K$403,Flux_detail!$N$2:$N$403,$A17,Flux_detail!$C$2:$C$403,G$4) | H17: =SUMIFS(Flux_detail!$K$2:$K$403,Flux_detail!$N$2:$N$403,$A17,Flux_detail!$C$2:$C$403,H$4) | I17: =SUMIFS(Flux_detail!$K$2:$K$403,Flux_detail!$N$2:$N$403,$A17,Flux_detail!$C$2:$C$403,I$4) | ... Y17: =SUMIFS(Flux_detail!$K$2:$K$403,Flux_detail!$N$2:$N$403,$A17,Flux_detail!$C$2:$C$403,Y$4)
A18: Intérêts et charges financières | B18: =SUMIFS(Flux_detail!$K$2:$K$403,Flux_detail!$N$2:$N$403,$A18,Flux_detail!$C$2:$C$403,B$4) | C18: =SUMIFS(Flux_detail!$K$2:$K$403,Flux_detail!$N$2:$N$403,$A18,Flux_detail!$C$2:$C$403,C$4) | D18: =SUMIFS(Flux_detail!$K$2:$K$403,Flux_detail!$N$2:$N$403,$A18,Flux_detail!$C$2:$C$403,D$4) | E18: =SUMIFS(Flux_detail!$K$2:$K$403,Flux_detail!$N$2:$N$403,$A18,Flux_detail!$C$2:$C$403,E$4) | F18: =SUMIFS(Flux_detail!$K$2:$K$403,Flux_detail!$N$2:$N$403,$A18,Flux_detail!$C$2:$C$403,F$4) | G18: =SUMIFS(Flux_detail!$K$2:$K$403,Flux_detail!$N$2:$N$403,$A18,Flux_detail!$C$2:$C$403,G$4) | H18: =SUMIFS(Flux_detail!$K$2:$K$403,Flux_detail!$N$2:$N$403,$A18,Flux_detail!$C$2:$C$403,H$4) | I18: =SUMIFS(Flux_detail!$K$2:$K$403,Flux_detail!$N$2:$N$403,$A18,Flux_detail!$C$2:$C$403,I$4) | ... Y18: =SUMIFS(Flux_detail!$K$2:$K$403,Flux_detail!$N$2:$N$403,$A18,Flux_detail!$C$2:$C$403,Y$4)
A19: Associés et groupe | B19: =SUMIFS(Flux_detail!$K$2:$K$403,Flux_detail!$N$2:$N$403,$A19,Flux_detail!$C$2:$C$403,B$4) | C19: =SUMIFS(Flux_detail!$K$2:$K$403,Flux_detail!$N$2:$N$403,$A19,Flux_detail!$C$2:$C$403,C$4) | D19: =SUMIFS(Flux_detail!$K$2:$K$403,Flux_detail!$N$2:$N$403,$A19,Flux_detail!$C$2:$C$403,D$4) | E19: =SUMIFS(Flux_detail!$K$2:$K$403,Flux_detail!$N$2:$N$403,$A19,Flux_detail!$C$2:$C$403,E$4) | F19: =SUMIFS(Flux_detail!$K$2:$K$403,Flux_detail!$N$2:$N$403,$A19,Flux_detail!$C$2:$C$403,F$4) | G19: =SUMIFS(Flux_detail!$K$2:$K$403,Flux_detail!$N$2:$N$403,$A19,Flux_detail!$C$2:$C$403,G$4) | H19: =SUMIFS(Flux_detail!$K$2:$K$403,Flux_detail!$N$2:$N$403,$A19,Flux_detail!$C$2:$C$403,H$4) | I19: =SUMIFS(Flux_detail!$K$2:$K$403,Flux_detail!$N$2:$N$403,$A19,Flux_detail!$C$2:$C$403,I$4) | ... Y19: =SUMIFS(Flux_detail!$K$2:$K$403,Flux_detail!$N$2:$N$403,$A19,Flux_detail!$C$2:$C$403,Y$4)
A20: Total flux de financement | B20: =SUMIFS(Flux_detail!$K$2:$K$403,Flux_detail!$O$2:$O$403,"FIN",Flux_detail!$C$2:$C$403,B$4) | C20: =SUMIFS(Flux_detail!$K$2:$K$403,Flux_detail!$O$2:$O$403,"FIN",Flux_detail!$C$2:$C$403,C$4) | D20: =SUMIFS(Flux_detail!$K$2:$K$403,Flux_detail!$O$2:$O$403,"FIN",Flux_detail!$C$2:$C$403,D$4) | E20: =SUMIFS(Flux_detail!$K$2:$K$403,Flux_detail!$O$2:$O$403,"FIN",Flux_detail!$C$2:$C$403,E$4) | F20: =SUMIFS(Flux_detail!$K$2:$K$403,Flux_detail!$O$2:$O$403,"FIN",Flux_detail!$C$2:$C$403,F$4) | G20: =SUMIFS(Flux_detail!$K$2:$K$403,Flux_detail!$O$2:$O$403,"FIN",Flux_detail!$C$2:$C$403,G$4) | H20: =SUMIFS(Flux_detail!$K$2:$K$403,Flux_detail!$O$2:$O$403,"FIN",Flux_detail!$C$2:$C$403,H$4) | I20: =SUMIFS(Flux_detail!$K$2:$K$403,Flux_detail!$O$2:$O$403,"FIN",Flux_detail!$C$2:$C$403,I$4) | ... Y20: =SUMIFS(Flux_detail!$K$2:$K$403,Flux_detail!$O$2:$O$403,"FIN",Flux_detail!$C$2:$C$403,Y$4)
A22: VARIATION DE TRÉSORERIE | B22: =SUMIFS(Flux_detail!$K$2:$K$403,Flux_detail!$C$2:$C$403,B$4) | C22: =SUMIFS(Flux_detail!$K$2:$K$403,Flux_detail!$C$2:$C$403,C$4) | D22: =SUMIFS(Flux_detail!$K$2:$K$403,Flux_detail!$C$2:$C$403,D$4) | E22: =SUMIFS(Flux_detail!$K$2:$K$403,Flux_detail!$C$2:$C$403,E$4) | F22: =SUMIFS(Flux_detail!$K$2:$K$403,Flux_detail!$C$2:$C$403,F$4) | G22: =SUMIFS(Flux_detail!$K$2:$K$403,Flux_detail!$C$2:$C$403,G$4) | H22: =SUMIFS(Flux_detail!$K$2:$K$403,Flux_detail!$C$2:$C$403,H$4) | I22: =SUMIFS(Flux_detail!$K$2:$K$403,Flux_detail!$C$2:$C$403,I$4) | ... Y22: =SUMIFS(Flux_detail!$K$2:$K$403,Flux_detail!$C$2:$C$403,Y$4)
A24: Trésorerie début de mois | B24: 85000 | C24: =B25 | D24: =C25 | E24: =D25 | F24: =E25 | G24: =F25 | H24: =G25 | I24: =H25 | J24: =I25 | ... M24: =L25 | N24: 111111.24 | O24: =N25 | P24: =O25 | Q24: =P25 | R24: =Q25 | S24: =R25 | T24: =S25 | U24: =T25 | V24: =U25 | ... Y24: =X25
A25: Trésorerie fin de mois (calculée) | B25: =B24+B22 | C25: =C24+C22 | D25: =D24+D22 | E25: =E24+E22 | F25: =F24+F22 | G25: =G24+G22 | H25: =H24+H22 | I25: =I24+I22 | ... Y25: =Y24+Y22
A26: Trésorerie fin de mois (comptable, contrôle) | B26: 110023.94 | C26: 102329 | D26: 48747.98 | E26: 95305.65 | F26: -21773.84 | G26: 122831.59 | H26: 115988.87 | I26: 124609.33 | J26: 118507.3 | K26: 32377.97 | L26: 127978.73 | M26: 111111.24 | N26: 96813.86 | O26: 27235.8 | P26: 3791.5 | Q26: -50695.23 | R26: -73747.36 | S26: -36030.33 | T26: -20597.29 | U26: -143681.77 | V26: -157121.59 | W26: -104050.96 | X26: -82041.16 | Y26: -152621.97
A27: Écart | B27: =B25-B26 | C27: =C25-C26 | D27: =D25-D26 | E27: =E25-E26 | F27: =F25-F26 | G27: =G25-G26 | H27: =H25-H26 | I27: =I25-I26 | ... Y27: =Y25-Y26
A28: Point bas du mois (solde quotidien) | B28: =_xlfn.MINIFS(Solde_quotidien!$G:$G,Solde_quotidien!$D:$D,B$4) | C28: =_xlfn.MINIFS(Solde_quotidien!$G:$G,Solde_quotidien!$D:$D,C$4) | D28: =_xlfn.MINIFS(Solde_quotidien!$G:$G,Solde_quotidien!$D:$D,D$4) | E28: =_xlfn.MINIFS(Solde_quotidien!$G:$G,Solde_quotidien!$D:$D,E$4) | F28: =_xlfn.MINIFS(Solde_quotidien!$G:$G,Solde_quotidien!$D:$D,F$4) | G28: =_xlfn.MINIFS(Solde_quotidien!$G:$G,Solde_quotidien!$D:$D,G$4) | H28: =_xlfn.MINIFS(Solde_quotidien!$G:$G,Solde_quotidien!$D:$D,H$4) | I28: =_xlfn.MINIFS(Solde_quotidien!$G:$G,Solde_quotidien!$D:$D,I$4) | ... Y28: =_xlfn.MINIFS(Solde_quotidien!$G:$G,Solde_quotidien!$D:$D,Y$4)
A29: La première colonne de chaque exercice repart des à-nouveaux bancaires (bleu). Le solde de fin de mois masque souvent un point bas plus profond en cours de mois (salaires, URSSAF).

Sheet Flux_hebdo
A1: Flux de trésorerie hebdomadaires — 52 dernières semaines des données
A2: Base historique du prévisionnel à 13 semaines : rythme des encaissements et des décaissements par nature.
B3: 45663 | C3: 45670 | D3: 45677 | E3: 45684 | F3: 45691 | G3: 45698 | H3: 45705 | I3: 45712 | J3: 45719 | K3: 45726 | L3: 45733 | M3: 45740 | N3: 45747 | O3: 45754 | P3: 45761 | Q3: 45768 | R3: 45775 | S3: 45782 | T3: 45789 | U3: 45796 | V3: 45803 | W3: 45810 | X3: 45817 | Y3: 45824 | Z3: 45831 | AA3: 45838 | AB3: 45845 | AC3: 45852 | AD3: 45859 | AE3: 45866 | AF3: 45873 | AG3: 45880 | AH3: 45887 | AI3: 45894 | AJ3: 45901 | AK3: 45908 | AL3: 45915 | AM3: 45922 | AN3: 45929 | AO3: 45936 | AP3: 45943 | AQ3: 45950 | AR3: 45957 | AS3: 45964 | AT3: 45971 | AU3: 45978 | AV3: 45985 | AW3: 45992 | AX3: 45999 | AY3: 46006 | AZ3: 46013 | BA3: 46020
A4: En euros | B4: 2025-S02 | C4: 2025-S03 | D4: 2025-S04 | E4: 2025-S05 | F4: 2025-S06 | G4: 2025-S07 | H4: 2025-S08 | I4: 2025-S09 | J4: 2025-S10 | K4: 2025-S11 | L4: 2025-S12 | M4: 2025-S13 | N4: 2025-S14 | O4: 2025-S15 | P4: 2025-S16 | Q4: 2025-S17 | R4: 2025-S18 | S4: 2025-S19 | T4: 2025-S20 | U4: 2025-S21 | V4: 2025-S22 | W4: 2025-S23 | X4: 2025-S24 | Y4: 2025-S25 | Z4: 2025-S26 | AA4: 2025-S27 | AB4: 2025-S28 | AC4: 2025-S29 | AD4: 2025-S30 | AE4: 2025-S31 | AF4: 2025-S32 | AG4: 2025-S33 | AH4: 2025-S34 | AI4: 2025-S35 | AJ4: 2025-S36 | AK4: 2025-S37 | AL4: 2025-S38 | AM4: 2025-S39 | AN4: 2025-S40 | AO4: 2025-S41 | AP4: 2025-S42 | AQ4: 2025-S43 | AR4: 2025-S44 | AS4: 2025-S45 | AT4: 2025-S46 | AU4: 2025-S47 | AV4: 2025-S48 | AW4: 2025-S49 | AX4: 2025-S50 | AY4: 2025-S51 | AZ4: 2025-S52 | BA4: 2026-S01
A5: Flux d'exploitation
A6: Clients | B6: =SUMIFS(Flux_detail!$K$2:$K$403,Flux_detail!$N$2:$N$403,$A6,Flux_detail!$B$2:$B$403,B$4) | C6: =SUMIFS(Flux_detail!$K$2:$K$403,Flux_detail!$N$2:$N$403,$A6,Flux_detail!$B$2:$B$403,C$4) | D6: =SUMIFS(Flux_detail!$K$2:$K$403,Flux_detail!$N$2:$N$403,$A6,Flux_detail!$B$2:$B$403,D$4) | E6: =SUMIFS(Flux_detail!$K$2:$K$403,Flux_detail!$N$2:$N$403,$A6,Flux_detail!$B$2:$B$403,E$4) | F6: =SUMIFS(Flux_detail!$K$2:$K$403,Flux_detail!$N$2:$N$403,$A6,Flux_detail!$B$2:$B$403,F$4) | G6: =SUMIFS(Flux_detail!$K$2:$K$403,Flux_detail!$N$2:$N$403,$A6,Flux_detail!$B$2:$B$403,G$4) | H6: =SUMIFS(Flux_detail!$K$2:$K$403,Flux_detail!$N$2:$N$403,$A6,Flux_detail!$B$2:$B$403,H$4) | I6: =SUMIFS(Flux_detail!$K$2:$K$403,Flux_detail!$N$2:$N$403,$A6,Flux_detail!$B$2:$B$403,I$4) | ... BA6: =SUMIFS(Flux_detail!$K$2:$K$403,Flux_detail!$N$2:$N$403,$A6,Flux_detail!$B$2:$B$403,BA$4)
A7: Fournisseurs et charges externes | B7: =SUMIFS(Flux_detail!$K$2:$K$403,Flux_detail!$N$2:$N$403,$A7,Flux_detail!$B$2:$B$403,B$4) | C7: =SUMIFS(Flux_detail!$K$2:$K$403,Flux_detail!$N$2:$N$403,$A7,Flux_detail!$B$2:$B$403,C$4) | D7: =SUMIFS(Flux_detail!$K$2:$K$403,Flux_detail!$N$2:$N$403,$A7,Flux_detail!$B$2:$B$403,D$4) | E7: =SUMIFS(Flux_detail!$K$2:$K$403,Flux_detail!$N$2:$N$403,$A7,Flux_detail!$B$2:$B$403,E$4) | F7: =SUMIFS(Flux_detail!$K$2:$K$403,Flux_detail!$N$2:$N$403,$A7,Flux_detail!$B$2:$B$403,F$4) | G7: =SUMIFS(Flux_detail!$K$2:$K$403,Flux_detail!$N$2:$N$403,$A7,Flux_detail!$B$2:$B$403,G$4) | H7: =SUMIFS(Flux_detail!$K$2:$K$403,Flux_detail!$N$2:$N$403,$A7,Flux_detail!$B$2:$B$403,H$4) | I7: =SUMIFS(Flux_detail!$K$2:$K$403,Flux_detail!$N$2:$N$403,$A7,Flux_detail!$B$2:$B$403,I$4) | ... BA7: =SUMIFS(Flux_detail!$K$2:$K$403,Flux_detail!$N$2:$N$403,$A7,Flux_detail!$B$2:$B$403,BA$4)
A8: Frais bancaires | B8: =SUMIFS(Flux_detail!$K$2:$K$403,Flux_detail!$N$2:$N$403,$A8,Flux_detail!$B$2:$B$403,B$4) | C8: =SUMIFS(Flux_detail!$K$2:$K$403,Flux_detail!$N$2:$N$403,$A8,Flux_detail!$B$2:$B$403,C$4) | D8: =SUMIFS(Flux_detail!$K$2:$K$403,Flux_detail!$N$2:$N$403,$A8,Flux_detail!$B$2:$B$403,D$4) | E8: =SUMIFS(Flux_detail!$K$2:$K$403,Flux_detail!$N$2:$N$403,$A8,Flux_detail!$B$2:$B$403,E$4) | F8: =SUMIFS(Flux_detail!$K$2:$K$403,Flux_detail!$N$2:$N$403,$A8,Flux_detail!$B$2:$B$403,F$4) | G8: =SUMIFS(Flux_detail!$K$2:$K$403,Flux_detail!$N$2:$N$403,$A8,Flux_detail!$B$2:$B$403,G$4) | H8: =SUMIFS(Flux_detail!$K$2:$K$403,Flux_detail!$N$2:$N$403,$A8,Flux_detail!$B$2:$B$403,H$4) | I8: =SUMIFS(Flux_detail!$K$2:$K$403,Flux_detail!$N$2:$N$403,$A8,Flux_detail!$B$2:$B$403,I$4) | ... BA8: =SUMIFS(Flux_detail!$K$2:$K$403,Flux_detail!$N$2:$N$403,$A8,Flux_detail!$B$2:$B$403,BA$4)
A9: Salaires et personnel | B9: =SUMIFS(Flux_detail!$K$2:$K$403,Flux_detail!$N$2:$N$403,$A9,Flux_detail!$B$2:$B$403,B$4) | C9: =SUMIFS(Flux_detail!$K$2:$K$403,Flux_detail!$N$2:$N$403,$A9,Flux_detail!$B$2:$B$403,C$4) | D9: =SUMIFS(Flux_detail!$K$2:$K$403,Flux_detail!$N$2:$N$403,$A9,Flux_detail!$B$2:$B$403,D$4) | E9: =SUMIFS(Flux_detail!$K$2:$K$403,Flux_detail!$N$2:$N$403,$A9,Flux_detail!$B$2:$B$403,E$4) | F9: =SUMIFS(Flux_detail!$K$2:$K$403,Flux_detail!$N$2:$N$403,$A9,Flux_detail!$B$2:$B$403,F$4) | G9: =SUMIFS(Flux_detail!$K$2:$K$403,Flux_detail!$N$2:$N$403,$A9,Flux_detail!$B$2:$B$403,G$4) | H9: =SUMIFS(Flux_detail!$K$2:$K$403,Flux_detail!$N$2:$N$403,$A9,Flux_detail!$B$2:$B$403,H$4) | I9: =SUMIFS(Flux_detail!$K$2:$K$403,Flux_detail!$N$2:$N$403,$A9,Flux_detail!$B$2:$B$403,I$4) | ... BA9: =SUMIFS(Flux_detail!$K$2:$K$403,Flux_detail!$N$2:$N$403,$A9,Flux_detail!$B$2:$B$403,BA$4)
A10: Charges sociales | B10: =SUMIFS(Flux_detail!$K$2:$K$403,Flux_detail!$N$2:$N$403,$A10,Flux_detail!$B$2:$B$403,B$4) | C10: =SUMIFS(Flux_detail!$K$2:$K$403,Flux_detail!$N$2:$N$403,$A10,Flux_detail!$B$2:$B$403,C$4) | D10: =SUMIFS(Flux_detail!$K$2:$K$403,Flux_detail!$N$2:$N$403,$A10,Flux_detail!$B$2:$B$403,D$4) | E10: =SUMIFS(Flux_detail!$K$2:$K$403,Flux_detail!$N$2:$N$403,$A10,Flux_detail!$B$2:$B$403,E$4) | F10: =SUMIFS(Flux_detail!$K$2:$K$403,Flux_detail!$N$2:$N$403,$A10,Flux_detail!$B$2:$B$403,F$4) | G10: =SUMIFS(Flux_detail!$K$2:$K$403,Flux_detail!$N$2:$N$403,$A10,Flux_detail!$B$2:$B$403,G$4) | H10: =SUMIFS(Flux_detail!$K$2:$K$403,Flux_detail!$N$2:$N$403,$A10,Flux_detail!$B$2:$B$403,H$4) | I10: =SUMIFS(Flux_detail!$K$2:$K$403,Flux_detail!$N$2:$N$403,$A10,Flux_detail!$B$2:$B$403,I$4) | ... BA10: =SUMIFS(Flux_detail!$K$2:$K$403,Flux_detail!$N$2:$N$403,$A10,Flux_detail!$B$2:$B$403,BA$4)
A11: TVA | B11: =SUMIFS(Flux_detail!$K$2:$K$403,Flux_detail!$N$2:$N$403,$A11,Flux_detail!$B$2:$B$403,B$4) | C11: =SUMIFS(Flux_detail!$K$2:$K$403,Flux_detail!$N$2:$N$403,$A11,Flux_detail!$B$2:$B$403,C$4) | D11: =SUMIFS(Flux_detail!$K$2:$K$403,Flux_detail!$N$2:$N$403,$A11,Flux_detail!$B$2:$B$403,D$4) | E11: =SUMIFS(Flux_detail!$K$2:$K$403,Flux_detail!$N$2:$N$403,$A11,Flux_detail!$B$2:$B$403,E$4) | F11: =SUMIFS(Flux_detail!$K$2:$K$403,Flux_detail!$N$2:$N$403,$A11,Flux_detail!$B$2:$B$403,F$4) | G11: =SUMIFS(Flux_detail!$K$2:$K$403,Flux_detail!$N$2:$N$403,$A11,Flux_detail!$B$2:$B$403,G$4) | H11: =SUMIFS(Flux_detail!$K$2:$K$403,Flux_detail!$N$2:$N$403,$A11,Flux_detail!$B$2:$B$403,H$4) | I11: =SUMIFS(Flux_detail!$K$2:$K$403,Flux_detail!$N$2:$N$403,$A11,Flux_detail!$B$2:$B$403,I$4) | ... BA11: =SUMIFS(Flux_detail!$K$2:$K$403,Flux_detail!$N$2:$N$403,$A11,Flux_detail!$B$2:$B$403,BA$4)
A12: Impôt sur les sociétés | B12: =SUMIFS(Flux_detail!$K$2:$K$403,Flux_detail!$N$2:$N$403,$A12,Flux_detail!$B$2:$B$403,B$4) | C12: =SUMIFS(Flux_detail!$K$2:$K$403,Flux_detail!$N$2:$N$403,$A12,Flux_detail!$B$2:$B$403,C$4) | D12: =SUMIFS(Flux_detail!$K$2:$K$403,Flux_detail!$N$2:$N$403,$A12,Flux_detail!$B$2:$B$403,D$4) | E12: =SUMIFS(Flux_detail!$K$2:$K$403,Flux_detail!$N$2:$N$403,$A12,Flux_detail!$B$2:$B$403,E$4) | F12: =SUMIFS(Flux_detail!$K$2:$K$403,Flux_detail!$N$2:$N$403,$A12,Flux_detail!$B$2:$B$403,F$4) | G12: =SUMIFS(Flux_detail!$K$2:$K$403,Flux_detail!$N$2:$N$403,$A12,Flux_detail!$B$2:$B$403,G$4) | H12: =SUMIFS(Flux_detail!$K$2:$K$403,Flux_detail!$N$2:$N$403,$A12,Flux_detail!$B$2:$B$403,H$4) | I12: =SUMIFS(Flux_detail!$K$2:$K$403,Flux_detail!$N$2:$N$403,$A12,Flux_detail!$B$2:$B$403,I$4) | ... BA12: =SUMIFS(Flux_detail!$K$2:$K$403,Flux_detail!$N$2:$N$403,$A12,Flux_detail!$B$2:$B$403,BA$4)
A13: Autres impôts et taxes | B13: =SUMIFS(Flux_detail!$K$2:$K$403,Flux_detail!$N$2:$N$403,$A13,Flux_detail!$B$2:$B$403,B$4) | C13: =SUMIFS(Flux_detail!$K$2:$K$403,Flux_detail!$N$2:$N$403,$A13,Flux_detail!$B$2:$B$403,C$4) | D13: =SUMIFS(Flux_detail!$K$2:$K$403,Flux_detail!$N$2:$N$403,$A13,Flux_detail!$B$2:$B$403,D$4) | E13: =SUMIFS(Flux_detail!$K$2:$K$403,Flux_detail!$N$2:$N$403,$A13,Flux_detail!$B$2:$B$403,E$4) | F13: =SUMIFS(Flux_detail!$K$2:$K$403,Flux_detail!$N$2:$N$403,$A13,Flux_detail!$B$2:$B$403,F$4) | G13: =SUMIFS(Flux_detail!$K$2:$K$403,Flux_detail!$N$2:$N$403,$A13,Flux_detail!$B$2:$B$403,G$4) | H13: =SUMIFS(Flux_detail!$K$2:$K$403,Flux_detail!$N$2:$N$403,$A13,Flux_detail!$B$2:$B$403,H$4) | I13: =SUMIFS(Flux_detail!$K$2:$K$403,Flux_detail!$N$2:$N$403,$A13,Flux_detail!$B$2:$B$403,I$4) | ... BA13: =SUMIFS(Flux_detail!$K$2:$K$403,Flux_detail!$N$2:$N$403,$A13,Flux_detail!$B$2:$B$403,BA$4)
A14: Total flux d'exploitation | B14: =SUMIFS(Flux_detail!$K$2:$K$403,Flux_detail!$O$2:$O$403,"EXPL",Flux_detail!$B$2:$B$403,B$4) | C14: =SUMIFS(Flux_detail!$K$2:$K$403,Flux_detail!$O$2:$O$403,"EXPL",Flux_detail!$B$2:$B$403,C$4) | D14: =SUMIFS(Flux_detail!$K$2:$K$403,Flux_detail!$O$2:$O$403,"EXPL",Flux_detail!$B$2:$B$403,D$4) | E14: =SUMIFS(Flux_detail!$K$2:$K$403,Flux_detail!$O$2:$O$403,"EXPL",Flux_detail!$B$2:$B$403,E$4) | F14: =SUMIFS(Flux_detail!$K$2:$K$403,Flux_detail!$O$2:$O$403,"EXPL",Flux_detail!$B$2:$B$403,F$4) | G14: =SUMIFS(Flux_detail!$K$2:$K$403,Flux_detail!$O$2:$O$403,"EXPL",Flux_detail!$B$2:$B$403,G$4) | H14: =SUMIFS(Flux_detail!$K$2:$K$403,Flux_detail!$O$2:$O$403,"EXPL",Flux_detail!$B$2:$B$403,H$4) | I14: =SUMIFS(Flux_detail!$K$2:$K$403,Flux_detail!$O$2:$O$403,"EXPL",Flux_detail!$B$2:$B$403,I$4) | ... BA14: =SUMIFS(Flux_detail!$K$2:$K$403,Flux_detail!$O$2:$O$403,"EXPL",Flux_detail!$B$2:$B$403,BA$4)
A16: Flux de financement
A17: Emprunts - capital | B17: =SUMIFS(Flux_detail!$K$2:$K$403,Flux_detail!$N$2:$N$403,$A17,Flux_detail!$B$2:$B$403,B$4) | C17: =SUMIFS(Flux_detail!$K$2:$K$403,Flux_detail!$N$2:$N$403,$A17,Flux_detail!$B$2:$B$403,C$4) | D17: =SUMIFS(Flux_detail!$K$2:$K$403,Flux_detail!$N$2:$N$403,$A17,Flux_detail!$B$2:$B$403,D$4) | E17: =SUMIFS(Flux_detail!$K$2:$K$403,Flux_detail!$N$2:$N$403,$A17,Flux_detail!$B$2:$B$403,E$4) | F17: =SUMIFS(Flux_detail!$K$2:$K$403,Flux_detail!$N$2:$N$403,$A17,Flux_detail!$B$2:$B$403,F$4) | G17: =SUMIFS(Flux_detail!$K$2:$K$403,Flux_detail!$N$2:$N$403,$A17,Flux_detail!$B$2:$B$403,G$4) | H17: =SUMIFS(Flux_detail!$K$2:$K$403,Flux_detail!$N$2:$N$403,$A17,Flux_detail!$B$2:$B$403,H$4) | I17: =SUMIFS(Flux_detail!$K$2:$K$403,Flux_detail!$N$2:$N$403,$A17,Flux_detail!$B$2:$B$403,I$4) | ... BA17: =SUMIFS(Flux_detail!$K$2:$K$403,Flux_detail!$N$2:$N$403,$A17,Flux_detail!$B$2:$B$403,BA$4)
A18: Intérêts et charges financières | B18: =SUMIFS(Flux_detail!$K$2:$K$403,Flux_detail!$N$2:$N$403,$A18,Flux_detail!$B$2:$B$403,B$4) | C18: =SUMIFS(Flux_detail!$K$2:$K$403,Flux_detail!$N$2:$N$403,$A18,Flux_detail!$B$2:$B$403,C$4) | D18: =SUMIFS(Flux_detail!$K$2:$K$403,Flux_detail!$N$2:$N$403,$A18,Flux_detail!$B$2:$B$403,D$4) | E18: =SUMIFS(Flux_detail!$K$2:$K$403,Flux_detail!$N$2:$N$403,$A18,Flux_detail!$B$2:$B$403,E$4) | F18: =SUMIFS(Flux_detail!$K$2:$K$403,Flux_detail!$N$2:$N$403,$A18,Flux_detail!$B$2:$B$403,F$4) | G18: =SUMIFS(Flux_detail!$K$2:$K$403,Flux_detail!$N$2:$N$403,$A18,Flux_detail!$B$2:$B$403,G$4) | H18: =SUMIFS(Flux_detail!$K$2:$K$403,Flux_detail!$N$2:$N$403,$A18,Flux_detail!$B$2:$B$403,H$4) | I18: =SUMIFS(Flux_detail!$K$2:$K$403,Flux_detail!$N$2:$N$403,$A18,Flux_detail!$B$2:$B$403,I$4) | ... BA18: =SUMIFS(Flux_detail!$K$2:$K$403,Flux_detail!$N$2:$N$403,$A18,Flux_detail!$B$2:$B$403,BA$4)
A19: Associés et groupe | B19: =SUMIFS(Flux_detail!$K$2:$K$403,Flux_detail!$N$2:$N$403,$A19,Flux_detail!$B$2:$B$403,B$4) | C19: =SUMIFS(Flux_detail!$K$2:$K$403,Flux_detail!$N$2:$N$403,$A19,Flux_detail!$B$2:$B$403,C$4) | D19: =SUMIFS(Flux_detail!$K$2:$K$403,Flux_detail!$N$2:$N$403,$A19,Flux_detail!$B$2:$B$403,D$4) | E19: =SUMIFS(Flux_detail!$K$2:$K$403,Flux_detail!$N$2:$N$403,$A19,Flux_detail!$B$2:$B$403,E$4) | F19: =SUMIFS(Flux_detail!$K$2:$K$403,Flux_detail!$N$2:$N$403,$A19,Flux_detail!$B$2:$B$403,F$4) | G19: =SUMIFS(Flux_detail!$K$2:$K$403,Flux_detail!$N$2:$N$403,$A19,Flux_detail!$B$2:$B$403,G$4) | H19: =SUMIFS(Flux_detail!$K$2:$K$403,Flux_detail!$N$2:$N$403,$A19,Flux_detail!$B$2:$B$403,H$4) | I19: =SUMIFS(Flux_detail!$K$2:$K$403,Flux_detail!$N$2:$N$403,$A19,Flux_detail!$B$2:$B$403,I$4) | ... BA19: =SUMIFS(Flux_detail!$K$2:$K$403,Flux_detail!$N$2:$N$403,$A19,Flux_detail!$B$2:$B$403,BA$4)
A20: Total flux de financement | B20: =SUMIFS(Flux_detail!$K$2:$K$403,Flux_detail!$O$2:$O$403,"FIN",Flux_detail!$B$2:$B$403,B$4) | C20: =SUMIFS(Flux_detail!$K$2:$K$403,Flux_detail!$O$2:$O$403,"FIN",Flux_detail!$B$2:$B$403,C$4) | D20: =SUMIFS(Flux_detail!$K$2:$K$403,Flux_detail!$O$2:$O$403,"FIN",Flux_detail!$B$2:$B$403,D$4) | E20: =SUMIFS(Flux_detail!$K$2:$K$403,Flux_detail!$O$2:$O$403,"FIN",Flux_detail!$B$2:$B$403,E$4) | F20: =SUMIFS(Flux_detail!$K$2:$K$403,Flux_detail!$O$2:$O$403,"FIN",Flux_detail!$B$2:$B$403,F$4) | G20: =SUMIFS(Flux_detail!$K$2:$K$403,Flux_detail!$O$2:$O$403,"FIN",Flux_detail!$B$2:$B$403,G$4) | H20: =SUMIFS(Flux_detail!$K$2:$K$403,Flux_detail!$O$2:$O$403,"FIN",Flux_detail!$B$2:$B$403,H$4) | I20: =SUMIFS(Flux_detail!$K$2:$K$403,Flux_detail!$O$2:$O$403,"FIN",Flux_detail!$B$2:$B$403,I$4) | ... BA20: =SUMIFS(Flux_detail!$K$2:$K$403,Flux_detail!$O$2:$O$403,"FIN",Flux_detail!$B$2:$B$403,BA$4)
A22: VARIATION DE TRÉSORERIE | B22: =SUMIFS(Flux_detail!$K$2:$K$403,Flux_detail!$B$2:$B$403,B$4) | C22: =SUMIFS(Flux_detail!$K$2:$K$403,Flux_detail!$B$2:$B$403,C$4) | D22: =SUMIFS(Flux_detail!$K$2:$K$403,Flux_detail!$B$2:$B$403,D$4) | E22: =SUMIFS(Flux_detail!$K$2:$K$403,Flux_detail!$B$2:$B$403,E$4) | F22: =SUMIFS(Flux_detail!$K$2:$K$403,Flux_detail!$B$2:$B$403,F$4) | G22: =SUMIFS(Flux_detail!$K$2:$K$403,Flux_detail!$B$2:$B$403,G$4) | H22: =SUMIFS(Flux_detail!$K$2:$K$403,Flux_detail!$B$2:$B$403,H$4) | I22: =SUMIFS(Flux_detail!$K$2:$K$403,Flux_detail!$B$2:$B$403,I$4) | ... BA22: =SUMIFS(Flux_detail!$K$2:$K$403,Flux_detail!$B$2:$B$403,BA$4)
A24: Moyenne hebdomadaire des 13 dernières semaines | B24: =AVERAGE(AO22:BA22)
A25: Moyenne hebdomadaire des 52 semaines | B25: =AVERAGE(B22:BA22)

Sheet Solde_quotidien
A1: Solde bancaire quotidien (tous comptes)
A2: Flux du jour et solde reconstitués depuis le FEC. Le point bas quotidien est la référence pour le besoin de trésorerie, pas le solde de fin de mois.
A4: Date | B4: Flux du jour | C4: Solde bancaire | D4: Mois | E4: Exercice | F4: Fonds en transit (58) | G4: Solde disponible | I4: Mois | J4: Solde bancaire fin de mois | K4: Point bas (disponible) | L4: Date du point bas | M4: Solde moyen (disponible)
A5: 45292 | B5: =SUMIFS(Flux_detail!$K$2:$K$403,Flux_detail!$A$2:$A$403,A5) | C5: =85000+B5 | D5: 2024-01 | E5: 2024 | F5: 0 | G5: =C5+F5 | I5: 2024-01 | J5: =INDEX($C$5:$C$735,MATCH(I5,$D$5:$D$735,1)) | K5: =_xlfn.MINIFS($G$5:$G$735,$D$5:$D$735,I5) | L5: 45301 | M5: =AVERAGEIFS($G$5:$G$735,$D$5:$D$735,I5)
A6: 45293 | B6: =SUMIFS(Flux_detail!$K$2:$K$403,Flux_detail!$A$2:$A$403,A6) | C6: =C5+B6 | D6: 2024-01 | E6: 2024 | F6: 0 | G6: =C6+F6 | I6: 2024-02 | J6: =INDEX($C$5:$C$735,MATCH(I6,$D$5:$D$735,1)) | K6: =_xlfn.MINIFS($G$5:$G$735,$D$5:$D$735,I6) | L6: 45337 | M6: =AVERAGEIFS($G$5:$G$735,$D$5:$D$735,I6)
A7: 45294 | B7: =SUMIFS(Flux_detail!$K$2:$K$403,Flux_detail!$A$2:$A$403,A7) | C7: =C6+B7 | D7: 2024-01 | E7: 2024 | F7: 0 | G7: =C7+F7 | I7: 2024-03 | J7: =INDEX($C$5:$C$735,MATCH(I7,$D$5:$D$735,1)) | K7: =_xlfn.MINIFS($G$5:$G$735,$D$5:$D$735,I7) | L7: 45382 | M7: =AVERAGEIFS($G$5:$G$735,$D$5:$D$735,I7)
A8: 45295 | B8: =SUMIFS(Flux_detail!$K$2:$K$403,Flux_detail!$A$2:$A$403,A8) | C8: =C7+B8 | D8: 2024-01 | E8: 2024 | F8: 0 | G8: =C8+F8 | I8: 2024-04 | J8: =INDEX($C$5:$C$735,MATCH(I8,$D$5:$D$735,1)) | K8: =_xlfn.MINIFS($G$5:$G$735,$D$5:$D$735,I8) | L8: 45392 | M8: =AVERAGEIFS($G$5:$G$735,$D$5:$D$735,I8)
A9: 45296 | B9: =SUMIFS(Flux_detail!$K$2:$K$403,Flux_detail!$A$2:$A$403,A9) | C9: =C8+B9 | D9: 2024-01 | E9: 2024 | F9: 0 | G9: =C9+F9 | I9: 2024-05 | J9: =INDEX($C$5:$C$735,MATCH(I9,$D$5:$D$735,1)) | K9: =_xlfn.MINIFS($G$5:$G$735,$D$5:$D$735,I9) | L9: 45443 | M9: =AVERAGEIFS($G$5:$G$735,$D$5:$D$735,I9)
A10: 45297 | B10: =SUMIFS(Flux_detail!$K$2:$K$403,Flux_detail!$A$2:$A$403,A10) | C10: =C9+B10 | D10: 2024-01 | E10: 2024 | F10: 0 | G10: =C10+F10 | I10: 2024-06 | J10: =INDEX($C$5:$C$735,MATCH(I10,$D$5:$D$735,1)) | K10: =_xlfn.MINIFS($G$5:$G$735,$D$5:$D$735,I10) | L10: 45444 | M10: =AVERAGEIFS($G$5:$G$735,$D$5:$D$735,I10)
A11: 45298 | B11: =SUMIFS(Flux_detail!$K$2:$K$403,Flux_detail!$A$2:$A$403,A11) | C11: =C10+B11 | D11: 2024-01 | E11: 2024 | F11: 0 | G11: =C11+F11 | I11: 2024-07 | J11: =INDEX($C$5:$C$735,MATCH(I11,$D$5:$D$735,1)) | K11: =_xlfn.MINIFS($G$5:$G$735,$D$5:$D$735,I11) | L11: 45504 | M11: =AVERAGEIFS($G$5:$G$735,$D$5:$D$735,I11)
A12: 45299 | B12: =SUMIFS(Flux_detail!$K$2:$K$403,Flux_detail!$A$2:$A$403,A12) | C12: =C11+B12 | D12: 2024-01 | E12: 2024 | F12: 0 | G12: =C12+F12 | I12: 2024-08 | J12: =INDEX($C$5:$C$735,MATCH(I12,$D$5:$D$735,1)) | K12: =_xlfn.MINIFS($G$5:$G$735,$D$5:$D$735,I12) | L12: 45519 | M12: =AVERAGEIFS($G$5:$G$735,$D$5:$D$735,I12)
A13: 45300 | B13: =SUMIFS(Flux_detail!$K$2:$K$403,Flux_detail!$A$2:$A$403,A13) | C13: =C12+B13 | D13: 2024-01 | E13: 2024 | F13: 0 | G13: =C13+F13 | I13: 2024-09 | J13: =INDEX($C$5:$C$735,MATCH(I13,$D$5:$D$735,1)) | K13: =_xlfn.MINIFS($G$5:$G$735,$D$5:$D$735,I13) | L13: 45565 | M13: =AVERAGEIFS($G$5:$G$735,$D$5:$D$735,I13)
A14: 45301 | B14: =SUMIFS(Flux_detail!$K$2:$K$403,Flux_detail!$A$2:$A$403,A14) | C14: =C13+B14 | D14: 2024-01 | E14: 2024 | F14: 0 | G14: =C14+F14 | I14: 2024-10 | J14: =INDEX($C$5:$C$735,MATCH(I14,$D$5:$D$735,1)) | K14: =_xlfn.MINIFS($G$5:$G$735,$D$5:$D$735,I14) | L14: 45596 | M14: =AVERAGEIFS($G$5:$G$735,$D$5:$D$735,I14)
A15: 45302 | B15: =SUMIFS(Flux_detail!$K$2:$K$403,Flux_detail!$A$2:$A$403,A15) | C15: =C14+B15 | D15: 2024-01 | E15: 2024 | F15: 0 | G15: =C15+F15 | I15: 2024-11 | J15: =INDEX($C$5:$C$735,MATCH(I15,$D$5:$D$735,1)) | K15: =_xlfn.MINIFS($G$5:$G$735,$D$5:$D$735,I15) | L15: 45606 | M15: =AVERAGEIFS($G$5:$G$735,$D$5:$D$735,I15)
A16: 45303 | B16: =SUMIFS(Flux_detail!$K$2:$K$403,Flux_detail!$A$2:$A$403,A16) | C16: =C15+B16 | D16: 2024-01 | E16: 2024 | F16: 0 | G16: =C16+F16 | I16: 2024-12 | J16: =INDEX($C$5:$C$735,MATCH(I16,$D$5:$D$735,1)) | K16: =_xlfn.MINIFS($G$5:$G$735,$D$5:$D$735,I16) | L16: 45657 | M16: =AVERAGEIFS($G$5:$G$735,$D$5:$D$735,I16)
A17: 45304 | B17: =SUMIFS(Flux_detail!$K$2:$K$403,Flux_detail!$A$2:$A$403,A17) | C17: =C16+B17 | D17: 2024-01 | E17: 2024 | F17: 0 | G17: =C17+F17 | I17: 2025-01 | J17: =INDEX($C$5:$C$735,MATCH(I17,$D$5:$D$735,1)) | K17: =_xlfn.MINIFS($G$5:$G$735,$D$5:$D$735,I17) | L17: 45688 | M17: =AVERAGEIFS($G$5:$G$735,$D$5:$D$735,I17)
... A28: 45315 | B28: =SUMIFS(Flux_detail!$K$2:$K$403,Flux_detail!$A$2:$A$403,A28) | C28: =C27+B28 | D28: 2024-01 | E28: 2024 | F28: 0 | G28: =C28+F28 | I28: 2025-12 | J28: =INDEX($C$5:$C$735,MATCH(I28,$D$5:$D$735,1)) | K28: =_xlfn.MINIFS($G$5:$G$735,$D$5:$D$735,I28) | L28: 46022 | M28: =AVERAGEIFS($G$5:$G$735,$D$5:$D$735,I28)
A29: 45316 | B29: =SUMIFS(Flux_detail!$K$2:$K$403,Flux_detail!$A$2:$A$403,A29) | C29: =C28+B29 | D29: 2024-01 | E29: 2024 | F29: 0 | G29: =C29+F29
A30: 45317 | B30: =SUMIFS(Flux_detail!$K$2:$K$403,Flux_detail!$A$2:$A$403,A30) | C30: =C29+B30 | D30: 2024-01 | E30: 2024 | F30: 0 | G30: =C30+F30 | I30: Solde disponible = solde bancaire + fonds en transit (virements sortis d'un compte, pas encore arrivés sur l'autre). Le point bas se lit sur le disponible.
A31: 45318 | B31: =SUMIFS(Flux_detail!$K$2:$K$403,Flux_detail!$A$2:$A$403,A31) | C31: =C30+B31 | D31: 2024-01 | E31: 2024 | F31: 0 | G31: =C31+F31
A32: 45319 | B32: =SUMIFS(Flux_detail!$K$2:$K$403,Flux_detail!$A$2:$A$403,A32) | C32: =C31+B32 | D32: 2024-01 | E32: 2024 | F32: 0 | G32: =C32+F32
A33: 45320 | B33: =SUMIFS(Flux_detail!$K$2:$K$403,Flux_detail!$A$2:$A$403,A33) | C33: =C32+B33 | D33: 2024-01 | E33: 2024 | F33: 0 | G33: =C33+F33
A34: 45321 | B34: =SUMIFS(Flux_detail!$K$2:$K$403,Flux_detail!$A$2:$A$403,A34) | C34: =C33+B34 | D34: 2024-01 | E34: 2024 | F34: 0 | G34: =C34+F34
A35: 45322 | B35: =SUMIFS(Flux_detail!$K$2:$K$403,Flux_detail!$A$2:$A$403,A35) | C35: =C34+B35 | D35: 2024-01 | E35: 2024 | F35: 0 | G35: =C35+F35
A36: 45323 | B36: =SUMIFS(Flux_detail!$K$2:$K$403,Flux_detail!$A$2:$A$403,A36) | C36: =C35+B36 | D36: 2024-02 | E36: 2024 | F36: 0 | G36: =C36+F36
A37: 45324 | B37: =SUMIFS(Flux_detail!$K$2:$K$403,Flux_detail!$A$2:$A$403,A37) | C37: =C36+B37 | D37: 2024-02 | E37: 2024 | F37: 0 | G37: =C37+F37
A38: 45325 | B38: =SUMIFS(Flux_detail!$K$2:$K$403,Flux_detail!$A$2:$A$403,A38) | C38: =C37+B38 | D38: 2024-02 | E38: 2024 | F38: 0 | G38: =C38+F38
A39: 45326 | B39: =SUMIFS(Flux_detail!$K$2:$K$403,Flux_detail!$A$2:$A$403,A39) | C39: =C38+B39 | D39: 2024-02 | E39: 2024 | F39: 0 | G39: =C39+F39
A40: 45327 | B40: =SUMIFS(Flux_detail!$K$2:$K$403,Flux_detail!$A$2:$A$403,A40) | C40: =C39+B40 | D40: 2024-02 | E40: 2024 | F40: 0 | G40: =C40+F40
A41: 45328 | B41: =SUMIFS(Flux_detail!$K$2:$K$403,Flux_detail!$A$2:$A$403,A41) | C41: =C40+B41 | D41: 2024-02 | E41: 2024 | F41: 0 | G41: =C41+F41
A42: 45329 | B42: =SUMIFS(Flux_detail!$K$2:$K$403,Flux_detail!$A$2:$A$403,A42) | C42: =C41+B42 | D42: 2024-02 | E42: 2024 | F42: 0 | G42: =C42+F42
... A370: 45657 | B370: =SUMIFS(Flux_detail!$K$2:$K$403,Flux_detail!$A$2:$A$403,A370) | C370: =C369+B370 | D370: 2024-12 | E370: 2024 | F370: 0 | G370: =C370+F370
A371: 45658 | B371: =SUMIFS(Flux_detail!$K$2:$K$403,Flux_detail!$A$2:$A$403,A371) | C371: =111111.24+B371 | D371: 2025-01 | E371: 2025 | F371: 0 | G371: =C371+F371
A372: 45659 | B372: =SUMIFS(Flux_detail!$K$2:$K$403,Flux_detail!$A$2:$A$403,A372) | C372: =C371+B372 | D372: 2025-01 | E372: 2025 | F372: 0 | G372: =C372+F372
A373: 45660 | B373: =SUMIFS(Flux_detail!$K$2:$K$403,Flux_detail!$A$2:$A$403,A373) | C373: =C372+B373 | D373: 2025-01 | E373: 2025 | F373: 0 | G373: =C373+F373
A374: 45661 | B374: =SUMIFS(Flux_detail!$K$2:$K$403,Flux_detail!$A$2:$A$403,A374) | C374: =C373+B374 | D374: 2025-01 | E374: 2025 | F374: 0 | G374: =C374+F374
A375: 45662 | B375: =SUMIFS(Flux_detail!$K$2:$K$403,Flux_detail!$A$2:$A$403,A375) | C375: =C374+B375 | D375: 2025-01 | E375: 2025 | F375: 0 | G375: =C375+F375
A376: 45663 | B376: =SUMIFS(Flux_detail!$K$2:$K$403,Flux_detail!$A$2:$A$403,A376) | C376: =C375+B376 | D376: 2025-01 | E376: 2025 | F376: 0 | G376: =C376+F376
A377: 45664 | B377: =SUMIFS(Flux_detail!$K$2:$K$403,Flux_detail!$A$2:$A$403,A377) | C377: =C376+B377 | D377: 2025-01 | E377: 2025 | F377: 0 | G377: =C377+F377
A378: 45665 | B378: =SUMIFS(Flux_detail!$K$2:$K$403,Flux_detail!$A$2:$A$403,A378) | C378: =C377+B378 | D378: 2025-01 | E378: 2025 | F378: 0 | G378: =C378+F378
A379: 45666 | B379: =SUMIFS(Flux_detail!$K$2:$K$403,Flux_detail!$A$2:$A$403,A379) | C379: =C378+B379 | D379: 2025-01 | E379: 2025 | F379: 0 | G379: =C379+F379
A380: 45667 | B380: =SUMIFS(Flux_detail!$K$2:$K$403,Flux_detail!$A$2:$A$403,A380) | C380: =C379+B380 | D380: 2025-01 | E380: 2025 | F380: 0 | G380: =C380+F380
A381: 45668 | B381: =SUMIFS(Flux_detail!$K$2:$K$403,Flux_detail!$A$2:$A$403,A381) | C381: =C380+B381 | D381: 2025-01 | E381: 2025 | F381: 0 | G381: =C381+F381
A382: 45669 | B382: =SUMIFS(Flux_detail!$K$2:$K$403,Flux_detail!$A$2:$A$403,A382) | C382: =C381+B382 | D382: 2025-01 | E382: 2025 | F382: 0 | G382: =C382+F382
A383: 45670 | B383: =SUMIFS(Flux_detail!$K$2:$K$403,Flux_detail!$A$2:$A$403,A383) | C383: =C382+B383 | D383: 2025-01 | E383: 2025 | F383: 0 | G383: =C383+F383
... A735: 46022 | B735: =SUMIFS(Flux_detail!$K$2:$K$403,Flux_detail!$A$2:$A$403,A735) | C735: =C734+B735 | D735: 2025-12 | E735: 2025 | F735: 0 | G735: =C735+F735

Sheet Delais
A1: Délais réels d'encaissement et de paiement
A2: Calculés sur les factures lettrées avec un règlement bancaire : date de pièce de la facture → date du règlement, pondéré par les montants. Valeurs calculées par l'application.
A4: 2024 — Clients : délai d'encaissement : 37 jours en moyenne pondérée (56 lettrages, 2 241 761 €)
A5: Trimestre de règlement | B5: Délai moyen (jours) | C5: Montant réglé
A6: 2024-T1 | B6: 31 | C6: 353472
A7: 2024-T2 | B7: 40 | C7: 643203
A8: 2024-T3 | B8: 38 | C8: 632247
A9: 2024-T4 | B9: 37 | C9: 612839
A11: Tiers (15 premiers en volume) | B11: Montant réglé | C11: Délai (jours) | D11: Nb
A12: Residence Bel Air | B12: 387556 | C12: 37 | D12: 9
A13: Agence Mobilis | B13: 321775 | C13: 40 | D13: 8
A14: Clinique du Parc | B14: 315491 | C14: 39 | D14: 8
A15: Cabinet Varenne Associes | B15: 299328 | C15: 36 | D15: 7
A16: Coworking Atelier 9 | B16: 292816 | C16: 38 | D16: 7
A17: Hotel Les Tilleuls | B17: 283521 | C17: 36 | D17: 8
A18: Restaurant Le Comptoir | B18: 275105 | C18: 35 | D18: 7
A19: Boutique Hetre et Chene | B19: 66170 | C19: 30 | D19: 2
A22: 2024 — Fournisseurs : délai de paiement : 47 jours en moyenne pondérée (70 lettrages, 1 119 606 €)
A23: Trimestre de règlement | B23: Délai moyen (jours) | C23: Montant réglé
A24: 2024-T1 | B24: 38 | C24: 198333
A25: 2024-T2 | B25: 46 | C25: 269806
A26: 2024-T3 | B26: 50 | C26: 318432
A27: 2024-T4 | B27: 50 | C27: 333035
A29: Tiers (15 premiers en volume) | B29: Montant réglé | C29: Délai (jours) | D29: Nb
A30: Scierie du Nord | B30: 471982 | C30: 50 | D30: 14
A31: Quincaillerie Pro Est | B31: 296051 | C31: 51 | D31: 8
A32: Vernis et Finitions | B32: 148178 | C32: 53 | D32: 6
A33: SCI Les Halles | B33: 119200 | C33: 30 | D33: 12
A34: Energie Plus | B34: 44260 | C34: 30 | D34: 12
A35: Cabinet Comptable Exemple | B35: 21600 | C35: 31 | D35: 3
A36: Assurances Mutuelles Exemple | B36: 12000 | C36: 31 | D36: 4
A37: Telecom Pro | B37: 6336 | C37: 30 | D37: 11
A40: 2025 — Clients : délai d'encaissement : 55 jours en moyenne pondérée (46 lettrages, 1 566 782 €)
A41: Trimestre de règlement | B41: Délai moyen (jours) | C41: Montant réglé
A42: 2025-T1 | B42: 34 | C42: 257900
A43: 2025-T2 | B43: 61 | C43: 286729
A44: 2025-T3 | B44: 57 | C44: 570112
A45: 2025-T4 | B45: 62 | C45: 452040
A47: Tiers (15 premiers en volume) | B47: Montant réglé | C47: Délai (jours) | D47: Nb
A48: Coworking Atelier 9 | B48: 334739 | C48: 54 | D48: 10
A49: Agence Mobilis | B49: 245110 | C49: 47 | D49: 6
A50: Hotel Les Tilleuls | B50: 204378 | C50: 65 | D50: 6
A51: Boutique Hetre et Chene | B51: 188709 | C51: 65 | D51: 7
A52: Residence Bel Air | B52: 165990 | C52: 50 | D52: 4
A53: Cabinet Varenne Associes | B53: 155041 | C53: 51 | D53: 6
A54: Restaurant Le Comptoir | B54: 152247 | C54: 62 | D54: 3
A55: Clinique du Parc | B55: 120567 | C55: 47 | D55: 4
A58: 2025 — Fournisseurs : délai de paiement : 52 jours en moyenne pondérée (74 lettrages, 982 821 €)
A59: Trimestre de règlement | B59: Délai moyen (jours) | C59: Montant réglé
A60: 2025-T1 | B60: 35 | C60: 248181
A61: 2025-T2 | B61: 57 | C61: 202556
A62: 2025-T3 | B62: 58 | C62: 316768
A63: 2025-T4 | B63: 55 | C63: 215316
A65: Tiers (15 premiers en volume) | B65: Montant réglé | C65: Délai (jours) | D65: Nb
A66: Quincaillerie Pro Est | B66: 307497 | C66: 49 | D66: 10
A67: Scierie du Nord | B67: 253781 | C67: 62 | D67: 11
A68: Vernis et Finitions | B68: 209076 | C68: 66 | D68: 9
A69: SCI Les Halles | B69: 122400 | C69: 28 | D69: 12
A70: Energie Plus | B70: 42355 | C70: 28 | D70: 12
A71: Cabinet Comptable Exemple | B71: 28800 | C71: 25 | D71: 4
A72: Assurances Mutuelles Exemple | B72: 12000 | C72: 30 | D72: 4
A73: Telecom Pro | B73: 6912 | C73: 28 | D73: 12

Sheet Recurrences
A1: Décaissements récurrents — 12 derniers mois de 2025
A2: Base du calendrier des décaissements du prévisionnel. Jour type = jour du mois qui concentre le plus de montants. Valeurs calculées par l'application.
A4: Nature ou tiers | B4: Type | C4: Mois avec flux | D4: Moyenne mensuelle (sur 12 mois) | E4: Jour type | F4: Dernier montant | G4: Dernière date
A5: Salaires et personnel | B5: nature | C5: 12 / 12 | D5: -39098.84 | E5: 31 | F5: -38416.44 | G5: 46022
A6: Charges sociales | B6: nature | C6: 9 / 12 | D6: -24164.07 | E6: 15 | F6: -31562.21 | G6: 45915
A7: TVA | B7: nature | C7: 12 / 12 | D7: -10646.02 | E7: 20 | F7: -11227.16 | G7: 46011
A8: Impôt sur les sociétés | B8: nature | C8: 1 / 12 | D8: -755.59 | E8: 15 | F8: -9067.03 | G8: 45762
A9: Emprunts - capital | B9: nature | C9: 12 / 12 | D9: -2000 | E9: 10 | F9: -2000 | G9: 46001
A10: Intérêts et charges financières | B10: nature | C10: 12 / 12 | D10: -183.33 | E10: 10 | F10: -146.67 | G10: 46001
A11: Quincaillerie Pro Est | B11: tiers | C11: 7 / 12 | D11: -25624.73 | E11: 14 | F11: -26072.11 | G11: 46020
A12: Scierie du Nord | B12: tiers | C12: 7 / 12 | D12: -21148.4 | E12: 11 | F12: -15005.32 | G12: 46006
A13: Vernis et Finitions | B13: tiers | C13: 8 / 12 | D13: -17423.02 | E13: 24 | F13: -25951.42 | G13: 45993
A14: SCI Les Halles | B14: tiers | C14: 12 / 12 | D14: -10200 | E14: 4 | F14: -10200 | G14: 45996
A15: Energie Plus | B15: tiers | C15: 12 / 12 | D15: -3529.57 | E15: 4 | F15: -3481.04 | G15: 45996
A16: Telecom Pro | B16: tiers | C16: 12 / 12 | D16: -576 | E16: 4 | F16: -576 | G16: 45996

Sheet Categories
A1: Catégories de flux
A2: Bloc de chaque catégorie. Pour reclasser un flux, utiliser la colonne « Surcharge » de Flux_detail (liste ci-dessous).
A4: Catégorie | B4: Bloc | C4: Libellé du bloc
A5: Clients | B5: EXPL | C5: Flux d'exploitation
A6: Clients - avances et avoirs | B6: EXPL | C6: Flux d'exploitation
A7: Subventions et autres produits | B7: EXPL | C7: Flux d'exploitation
A8: Produits exceptionnels | B8: EXPL | C8: Flux d'exploitation
A9: Fournisseurs et charges externes | B9: EXPL | C9: Flux d'exploitation
A10: Frais bancaires | B10: EXPL | C10: Flux d'exploitation
A11: Salaires et personnel | B11: EXPL | C11: Flux d'exploitation
A12: Prélèvement à la source | B12: EXPL | C12: Flux d'exploitation
A13: Charges sociales | B13: EXPL | C13: Flux d'exploitation
A14: TVA | B14: EXPL | C14: Flux d'exploitation
A15: Impôt sur les sociétés | B15: EXPL | C15: Flux d'exploitation
... A35: Virements internes (transit groupé) | B35: INT | C35: Virements internes
A37: Règles d'affectation (compte de contrepartie de l'écriture de banque, racine la plus longue)
A38: Racine | B38: Catégorie | C38: Bloc
A39: 1 | B39: Autres financements | C39: FIN
A40: 10 | B40: Capital et subventions d'investissement | C40: FIN
A41: 13 | B41: Capital et subventions d'investissement | C41: FIN
A42: 16 | B42: Emprunts - capital | C42: FIN
A43: 17 | B43: Emprunts - capital | C43: FIN
A44: 2 | B44: Investissements | C44: INV
A45: 3 | B45: Autres | C45: NA
A46: 40 | B46: Fournisseurs et charges externes | C46: EXPL
A47: 404 | B47: Investissements | C47: INV
A48: 405 | B48: Investissements | C48: INV
A49: 41 | B49: Clients | C49: EXPL
... A88: 79 | B88: Subventions et autres produits | C88: EXPL
A90: Compte dont le libellé contient FACTOR, AFFACTURAGE, COFACREDIT ou EUROFACTOR → « Encaissements via le factor » (bloc exploitation : ce sont les créances cédées, avancées par le factor). Les comptes courants du factor tenus en 51x sont exclus de la trésorerie bancaire.
A91: Compte 58 : apparié à l'autre banque (virement interne), sinon à l'écriture hors banque qui le solde (catégorie de ses contreparties), sinon « Transit 58 non rapproché ».
A92: Écriture de banque à plusieurs contreparties : chaque contrepartie donne un flux de son propre montant (la somme égale le mouvement de banque).

Sheet Flux_detail
A1: Date | B1: Semaine | C1: Mois | D1: Exercice | E1: Banque | F1: Journal | G1: N° écriture | H1: Contrepartie | I1: Libellé | J1: Tiers | K1: Montant | L1: Catégorie proposée | M1: Surcharge | N1: Catégorie retenue | O1: Bloc
A2: 45301 | B2: 2024-S02 | C2: 2024-01 | D2: 2024 | E2: 512000 | F2: BQ | G2: BQ00002 | H2: 164000 | I2: Echeance emprunt 01/2024 | K2: -2000 | L2: Emprunts - capital | N2: =IF(M2<>"",M2,L2) | O2: =IFERROR(INDEX(Categories!$B$5:$B$35,MATCH(N2,Categories!$A$5:$A$35,0)),"NA")
A3: 45301 | B3: 2024-S02 | C3: 2024-01 | D3: 2024 | E3: 512000 | F3: BQ | G3: BQ00002 | H3: 661100 | I3: Echeance emprunt 01/2024 | K3: -300 | L3: Intérêts et charges financières | N3: =IF(M3<>"",M3,L3) | O3: =IFERROR(INDEX(Categories!$B$5:$B$35,MATCH(N3,Categories!$A$5:$A$35,0)),"NA")
A4: 45301 | B4: 2024-S02 | C4: 2024-01 | D4: 2024 | E4: 512000 | F4: BQ | G4: BQ00120 | H4: 401000 | I4: Reglement fournisseur Scierie du Nord AN2024 | J4: Scierie du Nord | K4: -28000 | L4: Fournisseurs et charges externes | N4: =IF(M4<>"",M4,L4) | O4: =IFERROR(INDEX(Categories!$B$5:$B$35,MATCH(N4,Categories!$A$5:$A$35,0)),"NA")
A5: 45306 | B5: 2024-S03 | C5: 2024-01 | D5: 2024 | E5: 512000 | F5: BQ | G5: BQ00037 | H5: 431000 | I5: Reglement URSSAF 12/2023 | K5: -18000 | L5: Charges sociales | N5: =IF(M5<>"",M5,L5) | O5: =IFERROR(INDEX(Categories!$B$5:$B$35,MATCH(N5,Categories!$A$5:$A$35,0)),"NA")
A6: 45306 | B6: 2024-S03 | C6: 2024-01 | D6: 2024 | E6: 512000 | F6: BQ | G6: BQ00061 | H6: 411000 | I6: Reglement client Hotel Les Tilleuls AN2024 | J6: Hotel Les Tilleuls | K6: 30000 | L6: Clients | N6: =IF(M6<>"",M6,L6) | O6: =IFERROR(INDEX(Categories!$B$5:$B$35,MATCH(N6,Categories!$A$5:$A$35,0)),"NA")
A7: 45306 | B7: 2024-S03 | C7: 2024-01 | D7: 2024 | E7: 512000 | F7: BQ | G7: BQ00121 | H7: 401000 | I7: Reglement fournisseur Quincaillerie Pro Est AN2024 | J7: Quincaillerie Pro Est | K7: -12000 | L7: Fournisseurs et charges externes | N7: =IF(M7<>"",M7,L7) | O7: =IFERROR(INDEX(Categories!$B$5:$B$35,MATCH(N7,Categories!$A$5:$A$35,0)),"NA")
A8: 45309 | B8: 2024-S03 | C8: 2024-01 | D8: 2024 | E8: 512000 | F8: BQ | G8: BQ00062 | H8: 411000 | I8: Reglement client Residence Bel Air AN2024 | J8: Residence Bel Air | K8: 26000 | L8: Clients | N8: =IF(M8<>"",M8,L8) | O8: =IFERROR(INDEX(Categories!$B$5:$B$35,MATCH(N8,Categories!$A$5:$A$35,0)),"NA")
A9: 45309 | B9: 2024-S03 | C9: 2024-01 | D9: 2024 | E9: 512000 | F9: BQ | G9: BQ00122 | H9: 401000 | I9: Reglement fournisseur Vernis et Finitions AN2024 | J9: Vernis et Finitions | K9: -9000 | L9: Fournisseurs et charges externes | N9: =IF(M9<>"",M9,L9) | O9: =IFERROR(INDEX(Categories!$B$5:$B$35,MATCH(N9,Categories!$A$5:$A$35,0)),"NA")
A10: 45311 | B10: 2024-S03 | C10: 2024-01 | D10: 2024 | E10: 512000 | F10: BQ | G10: BQ00038 | H10: 445510 | I10: Reglement TVA 12/2023 | K10: -12000 | L10: TVA | N10: =IF(M10<>"",M10,L10) | O10: =IFERROR(INDEX(Categories!$B$5:$B$35,MATCH(N10,Categories!$A$5:$A$35,0)),"NA")
A11: 45313 | B11: 2024-S04 | C11: 2024-01 | D11: 2024 | E11: 512000 | F11: BQ | G11: BQ00063 | H11: 411000 | I11: Reglement client Cabinet Varenne Associes AN2024 | J11: Cabinet Varenne Associes | K11: 22000 | L11: Clients | N11: =IF(M11<>"",M11,L11) | O11: =IFERROR(INDEX(Categories!$B$5:$B$35,MATCH(N11,Categories!$A$5:$A$35,0)),"NA")
A12: 45313 | B12: 2024-S04 | C12: 2024-01 | D12: 2024 | E12: 512000 | F12: BQ | G12: BQ00123 | H12: 401000 | I12: Reglement fournisseur Energie Plus AN2024 | J12: Energie Plus | K12: -4000 | L12: Fournisseurs et charges externes | N12: =IF(M12<>"",M12,L12) | O12: =IFERROR(INDEX(Categories!$B$5:$B$35,MATCH(N12,Categories!$A$5:$A$35,0)),"NA")
A13: 45315 | B13: 2024-S04 | C13: 2024-01 | D13: 2024 | E13: 512000 | F13: BQ | G13: BQ00064 | H13: 411000 | I13: Reglement client Clinique du Parc AN2024 | J13: Clinique du Parc | K13: 24000 | L13: Clients | N13: =IF(M13<>"",M13,L13) | O13: =IFERROR(INDEX(Categories!$B$5:$B$35,MATCH(N13,Categories!$A$5:$A$35,0)),"NA")
A14: 45317 | B14: 2024-S04 | C14: 2024-01 | D14: 2024 | E14: 512000 | F14: BQ | G14: BQ00124 | H14: 401000 | I14: Reglement fournisseur SCI Les Halles AN2024 | J14: SCI Les Halles | K14: -7000 | L14: Fournisseurs et charges externes | N14: =IF(M14<>"",M14,L14) | O14: =IFERROR(INDEX(Categories!$B$5:$B$35,MATCH(N14,Categories!$A$5:$A$35,0)),"NA")
A15: 45320 | B15: 2024-S05 | C15: 2024-01 | D15: 2024 | E15: 512000 | F15: BQ | G15: BQ00065 | H15: 411000 | I15: Reglement client Coworking Atelier 9 AN2024 | J15: Coworking Atelier 9 | K15: 18000 | L15: Clients | N15: =IF(M15<>"",M15,L15) | O15: =IFERROR(INDEX(Categories!$B$5:$B$35,MATCH(N15,Categories!$A$5:$A$35,0)),"NA")
A16: 45320 | B16: 2024-S05 | C16: 2024-01 | D16: 2024 | E16: 512000 | F16: BQ | G16: BQ00067 | H16: 411000 | I16: Reglement client Hotel Les Tilleuls FA2024-0002 | J16: Hotel Les Tilleuls | K16: 38532.72 | L16: Clients | N16: =IF(M16<>"",M16,L16) | O16: =IFERROR(INDEX(Categories!$B$5:$B$35,MATCH(N16,Categories!$A$5:$A$35,0)),"NA")
A17: 45322 | B17: 2024-S05 | C17: 2024-01 | D17: 2024 | E17: 512000 | F17: BQ | G17: BQ00001 | H17: 421000 | I17: Virement salaires 01/2024 | K17: -41123.78 | L17: Salaires et personnel | N17: =IF(M17<>"",M17,L17) | O17: =IFERROR(INDEX(Categories!$B$5:$B$35,MATCH(N17,Categories!$A$5:$A$35,0)),"NA")
A18: 45322 | B18: 2024-S05 | C18: 2024-01 | D18: 2024 | E18: 512000 | F18: BQ | G18: BQ00003 | H18: 627000 | I18: Frais bancaires 01/2024 | K18: -85 | L18: Frais bancaires | N18: =IF(M18<>"",M18,L18) | O18: =IFERROR(INDEX(Categories!$B$5:$B$35,MATCH(N18,Categories!$A$5:$A$35,0)),"NA")
A19: 45327 | B19: 2024-S06 | C19: 2024-02 | D19: 2024 | E19: 512000 | F19: BQ | G19: BQ00127 | H19: 401000 | I19: Reglement fournisseur SCI Les Halles F004-202401 | J19: SCI Les Halles | K19: -10200 | L19: Fournisseurs et charges externes | N19: =IF(M19<>"",M19,L19) | O19: =IFERROR(INDEX(Categories!$B$5:$B$35,MATCH(N19,Categories!$A$5:$A$35,0)),"NA")
A20: 45327 | B20: 2024-S06 | C20: 2024-02 | D20: 2024 | E20: 512000 | F20: BQ | G20: BQ00128 | H20: 401000 | I20: Reglement fournisseur Energie Plus F005-202401 | J20: Energie Plus | K20: -3036.68 | L20: Fournisseurs et charges externes | N20: =IF(M20<>"",M20,L20) | O20: =IFERROR(INDEX(Categories!$B$5:$B$35,MATCH(N20,Categories!$A$5:$A$35,0)),"NA")
A21: 45327 | B21: 2024-S06 | C21: 2024-02 | D21: 2024 | E21: 512000 | F21: BQ | G21: BQ00129 | H21: 401000 | I21: Reglement fournisseur Telecom Pro F008-202401 | J21: Telecom Pro | K21: -576 | L21: Fournisseurs et charges externes | N21: =IF(M21<>"",M21,L21) | O21: =IFERROR(INDEX(Categories!$B$5:$B$35,MATCH(N21,Categories!$A$5:$A$35,0)),"NA")
A22: 45327 | B22: 2024-S06 | C22: 2024-02 | D22: 2024 | E22: 512000 | F22: BQ | G22: BQ00130 | H22: 401000 | I22: Reglement fournisseur Assurances Mutuelles Exemple F006-202401 | J22: Assurances Mutuelles Exemple | K22: -3000 | L22: Fournisseurs et charges externes | N22: =IF(M22<>"",M22,L22) | O22: =IFERROR(INDEX(Categories!$B$5:$B$35,MATCH(N22,Categories!$A$5:$A$35,0)),"NA")
A23: 45332 | B23: 2024-S06 | C23: 2024-02 | D23: 2024 | E23: 512000 | F23: BQ | G23: BQ00005 | H23: 164000 | I23: Echeance emprunt 02/2024 | K23: -2000 | L23: Emprunts - capital | N23: =IF(M23<>"",M23,L23) | O23: =IFERROR(INDEX(Categories!$B$5:$B$35,MATCH(N23,Categories!$A$5:$A$35,0)),"NA")
A24: 45332 | B24: 2024-S06 | C24: 2024-02 | D24: 2024 | E24: 512000 | F24: BQ | G24: BQ00005 | H24: 661100 | I24: Echeance emprunt 02/2024 | K24: -293.33 | L24: Intérêts et charges financières | N24: =IF(M24<>"",M24,L24) | O24: =IFERROR(INDEX(Categories!$B$5:$B$35,MATCH(N24,Categories!$A$5:$A$35,0)),"NA")
A25: 45337 | B25: 2024-S07 | C25: 2024-02 | D25: 2024 | E25: 512000 | F25: BQ | G25: BQ00039 | H25: 431000 | I25: Reglement URSSAF 01/2024 | K25: -33742.58 | L25: Charges sociales | N25: =IF(M25<>"",M25,L25) | O25: =IFERROR(INDEX(Categories!$B$5:$B$35,MATCH(N25,Categories!$A$5:$A$35,0)),"NA")
A26: 45338 | B26: 2024-S07 | C26: 2024-02 | D26: 2024 | E26: 512000 | F26: BQ | G26: BQ00070 | H26: 411000 | I26: Reglement client Boutique Hetre et Chene FA2024-0005 | J26: Boutique Hetre et Chene | K26: 22023.36 | L26: Clients | N26: =IF(M26<>"",M26,L26) | O26: =IFERROR(INDEX(Categories!$B$5:$B$35,MATCH(N26,Categories!$A$5:$A$35,0)),"NA")
A27: 45341 | B27: 2024-S08 | C27: 2024-02 | D27: 2024 | E27: 512000 | F27: BQ | G27: BQ00068 | H27: 411000 | I27: Reglement client Cabinet Varenne Associes FA2024-0003 | J27: Cabinet Varenne Associes | K27: 25702.04 | L27: Clients | N27: =IF(M27<>"",M27,L27) | O27: =IFERROR(INDEX(Categories!$B$5:$B$35,MATCH(N27,Categories!$A$5:$A$35,0)),"NA")
A28: 45341 | B28: 2024-S08 | C28: 2024-02 | D28: 2024 | E28: 512000 | F28: BQ | G28: BQ00069 | H28: 411000 | I28: Reglement client Hotel Les Tilleuls FA2024-0004 | J28: Hotel Les Tilleuls | K28: 22980.32 | L28: Clients | N28: =IF(M28<>"",M28,L28) | O28: =IFERROR(INDEX(Categories!$B$5:$B$35,MATCH(N28,Categories!$A$5:$A$35,0)),"NA")
A29: 45342 | B29: 2024-S08 | C29: 2024-02 | D29: 2024 | E29: 512000 | F29: BQ | G29: BQ00040 | H29: 445510 | I29: Reglement TVA 01/2024 | K29: -14131.22 | L29: TVA | N29: =IF(M29<>"",M29,L29) | O29: =IFERROR(INDEX(Categories!$B$5:$B$35,MATCH(N29,Categories!$A$5:$A$35,0)),"NA")
A30: 45342 | B30: 2024-S08 | C30: 2024-02 | D30: 2024 | E30: 512000 | F30: BQ | G30: BQ00071 | H30: 411000 | I30: Reglement client Restaurant Le Comptoir FA2024-0006 | J30: Restaurant Le Comptoir | K30: 38509.92 | L30: Clients | N30: =IF(M30<>"",M30,L30) | O30: =IFERROR(INDEX(Categories!$B$5:$B$35,MATCH(N30,Categories!$A$5:$A$35,0)),"NA")
A31: 45348 | B31: 2024-S09 | C31: 2024-02 | D31: 2024 | E31: 512000 | F31: BQ | G31: BQ00066 | H31: 411000 | I31: Reglement client Agence Mobilis FA2024-0001 | J31: Agence Mobilis | K31: 22251.64 | L31: Clients | N31: =IF(M31<>"",M31,L31) | O31: =IFERROR(INDEX(Categories!$B$5:$B$35,MATCH(N31,Categories!$A$5:$A$35,0)),"NA")
A32: 45351 | B32: 2024-S09 | C32: 2024-02 | D32: 2024 | E32: 512000 | F32: BQ | G32: BQ00004 | H32: 421000 | I32: Virement salaires 02/2024 | K32: -40186.76 | L32: Salaires et personnel | N32: =IF(M32<>"",M32,L32) | O32: =IFERROR(INDEX(Categories!$B$5:$B$35,MATCH(N32,Categories!$A$5:$A$35,0)),"NA")
A33: 45351 | B33: 2024-S09 | C33: 2024-02 | D33: 2024 | E33: 512000 | F33: BQ | G33: BQ00006 | H33: 627000 | I33: Frais bancaires 02/2024 | K33: -85 | L33: Frais bancaires | N33: =IF(M33<>"",M33,L33) | O33: =IFERROR(INDEX(Categories!$B$5:$B$35,MATCH(N33,Categories!$A$5:$A$35,0)),"NA")
A34: 45351 | B34: 2024-S09 | C34: 2024-02 | D34: 2024 | E34: 512000 | F34: BQ | G34: BQ00126 | H34: 401000 | I34: Reglement fournisseur Scierie du Nord F001-2024012 | J34: Scierie du Nord | K34: -31910.65 | L34: Fournisseurs et charges externes | N34: =IF(M34<>"",M34,L34) | O34: =IFERROR(INDEX(Categories!$B$5:$B$35,MATCH(N34,Categories!$A$5:$A$35,0)),"NA")
A35: 45357 | B35: 2024-S10 | C35: 2024-03 | D35: 2024 | E35: 512000 | F35: BQ | G35: BQ00133 | H35: 401000 | I35: Reglement fournisseur SCI Les Halles F004-202402 | J35: SCI Les Halles | K35: -10200 | L35: Fournisseurs et charges externes | N35: =IF(M35<>"",M35,L35) | O35: =IFERROR(INDEX(Categories!$B$5:$B$35,MATCH(N35,Categories!$A$5:$A$35,0)),"NA")
A36: 45357 | B36: 2024-S10 | C36: 2024-03 | D36: 2024 | E36: 512000 | F36: BQ | G36: BQ00134 | H36: 401000 | I36: Reglement fournisseur Energie Plus F005-202402 | J36: Energie Plus | K36: -3628.86 | L36: Fournisseurs et charges externes | N36: =IF(M36<>"",M36,L36) | O36: =IFERROR(INDEX(Categories!$B$5:$B$35,MATCH(N36,Categories!$A$5:$A$35,0)),"NA")
A37: 45357 | B37: 2024-S10 | C37: 2024-03 | D37: 2024 | E37: 512000 | F37: BQ | G37: BQ00135 | H37: 401000 | I37: Reglement fournisseur Telecom Pro F008-202402 | J37: Telecom Pro | K37: -576 | L37: Fournisseurs et charges externes | N37: =IF(M37<>"",M37,L37) | O37: =IFERROR(INDEX(Categories!$B$5:$B$35,MATCH(N37,Categories!$A$5:$A$35,0)),"NA")
A38: 45361 | B38: 2024-S10 | C38: 2024-03 | D38: 2024 | E38: 512000 | F38: BQ | G38: BQ00008 | H38: 164000 | I38: Echeance emprunt 03/2024 | K38: -2000 | L38: Emprunts - capital | N38: =IF(M38<>"",M38,L38) | O38: =IFERROR(INDEX(Categories!$B$5:$B$35,MATCH(N38,Categories!$A$5:$A$35,0)),"NA")
A39: 45361 | B39: 2024-S10 | C39: 2024-03 | D39: 2024 | E39: 512000 | F39: BQ | G39: BQ00008 | H39: 661100 | I39: Echeance emprunt 03/2024 | K39: -286.67 | L39: Intérêts et charges financières | N39: =IF(M39<>"",M39,L39) | O39: =IFERROR(INDEX(Categories!$B$5:$B$35,MATCH(N39,Categories!$A$5:$A$35,0)),"NA")
A40: 45366 | B40: 2024-S11 | C40: 2024-03 | D40: 2024 | E40: 512000 | F40: BQ | G40: BQ00041 | H40: 431000 | I40: Reglement URSSAF 02/2024 | K40: -32973.76 | L40: Charges sociales | N40: =IF(M40<>"",M40,L40) | O40: =IFERROR(INDEX(Categories!$B$5:$B$35,MATCH(N40,Categories!$A$5:$A$35,0)),"NA")
A41: 45369 | B41: 2024-S12 | C41: 2024-03 | D41: 2024 | E41: 512000 | F41: BQ | G41: BQ00076 | H41: 411000 | I41: Reglement client Agence Mobilis FA2024-0011 | J41: Agence Mobilis | K41: 47082.47 | L41: Clients | N41: =IF(M41<>"",M41,L41) | O41: =IFERROR(INDEX(Categories!$B$5:$B$35,MATCH(N41,Categories!$A$5:$A$35,0)),"NA")
A42: 45370 | B42: 2024-S12 | C42: 2024-03 | D42: 2024 | E42: 512000 | F42: BQ | G42: BQ00074 | H42: 411000 | I42: Reglement client Agence Mobilis FA2024-0009 | J42: Agence Mobilis | K42: 34050.62 | L42: Clients | N42: =IF(M42<>"",M42,L42) | O42: =IFERROR(INDEX(Categories!$B$5:$B$35,MATCH(N42,Categories!$A$5:$A$35,0)),"NA")
A43: 45371 | B43: 2024-S12 | C43: 2024-03 | D43: 2024 | E43: 512000 | F43: BQ | G43: BQ00042 | H43: 445510 | I43: Reglement TVA 02/2024 | K43: -14999.19 | L43: TVA | N43: =IF(M43<>"",M43,L43) | O43: =IFERROR(INDEX(Categories!$B$5:$B$35,MATCH(N43,Categories!$A$5:$A$35,0)),"NA")
A44: 45372 | B44: 2024-S12 | C44: 2024-03 | D44: 2024 | E44: 512000 | F44: BQ | G44: BQ00073 | H44: 411000 | I44: Reglement client Clinique du Parc FA2024-0008 | J44: Clinique du Parc | K44: 22339.12 | L44: Clients | N44: =IF(M44<>"",M44,L44) | O44: =IFERROR(INDEX(Categories!$B$5:$B$35,MATCH(N44,Categories!$A$5:$A$35,0)),"NA")
A45: 45377 | B45: 2024-S13 | C45: 2024-03 | D45: 2024 | E45: 512000 | F45: BQ | G45: BQ00125 | H45: 401000 | I45: Reglement fournisseur Scierie du Nord F001-2024011 | J45: Scierie du Nord | K45: -39489.35 | L45: Fournisseurs et charges externes | N45: =IF(M45<>"",M45,L45) | O45: =IFERROR(INDEX(Categories!$B$5:$B$35,MATCH(N45,Categories!$A$5:$A$35,0)),"NA")
A46: 45379 | B46: 2024-S13 | C46: 2024-03 | D46: 2024 | E46: 512000 | F46: BQ | G46: BQ00077 | H46: 411000 | I46: Reglement client Coworking Atelier 9 FA2024-0012 | J46: Coworking Atelier 9 | K46: 23334.37 | L46: Clients | N46: =IF(M46<>"",M46,L46) | O46: =IFERROR(INDEX(Categories!$B$5:$B$35,MATCH(N46,Categories!$A$5:$A$35,0)),"NA")
A47: 45380 | B47: 2024-S13 | C47: 2024-03 | D47: 2024 | E47: 512000 | F47: BQ | G47: BQ00132 | H47: 401000 | I47: Reglement fournisseur Scierie du Nord F001-2024022 | J47: Scierie du Nord | K47: -35715.06 | L47: Fournisseurs et charges externes | N47: =IF(M47<>"",M47,L47) | O47: =IFERROR(INDEX(Categories!$B$5:$B$35,MATCH(N47,Categories!$A$5:$A$35,0)),"NA")
A48: 45382 | B48: 2024-S13 | C48: 2024-03 | D48: 2024 | E48: 512000 | F48: BQ | G48: BQ00007 | H48: 421000 | I48: Virement salaires 03/2024 | K48: -40433.71 | L48: Salaires et personnel | N48: =IF(M48<>"",M48,L48) | O48: =IFERROR(INDEX(Categories!$B$5:$B$35,MATCH(N48,Categories!$A$5:$A$35,0)),"NA")
A49: 45382 | B49: 2024-S13 | C49: 2024-03 | D49: 2024 | E49: 512000 | F49: BQ | G49: BQ00009 | H49: 627000 | I49: Frais bancaires 03/2024 | K49: -85 | L49: Frais bancaires | N49: =IF(M49<>"",M49,L49) | O49: =IFERROR(INDEX(Categories!$B$5:$B$35,MATCH(N49,Categories!$A$5:$A$35,0)),"NA")
A50: 45383 | B50: 2024-S14 | C50: 2024-04 | D50: 2024 | E50: 512000 | F50: BQ | G50: BQ00075 | H50: 411000 | I50: Reglement client Cabinet Varenne Associes FA2024-0010 | J50: Cabinet Varenne Associes | K50: 24630.2 | L50: Clients | N50: =IF(M50<>"",M50,L50) | O50: =IFERROR(INDEX(Categories!$B$5:$B$35,MATCH(N50,Categories!$A$5:$A$35,0)),"NA")
A51: 45386 | B51: 2024-S14 | C51: 2024-04 | D51: 2024 | E51: 512000 | F51: BQ | G51: BQ00139 | H51: 401000 | I51: Reglement fournisseur SCI Les Halles F004-202403 | J51: SCI Les Halles | K51: -10200 | L51: Fournisseurs et charges externes | N51: =IF(M51<>"",M51,L51) | O51: =IFERROR(INDEX(Categories!$B$5:$B$35,MATCH(N51,Categories!$A$5:$A$35,0)),"NA")
A52: 45386 | B52: 2024-S14 | C52: 2024-04 | D52: 2024 | E52: 512000 | F52: BQ | G52: BQ00140 | H52: 401000 | I52: Reglement fournisseur Energie Plus F005-202403 | J52: Energie Plus | K52: -4163.17 | L52: Fournisseurs et charges externes | N52: =IF(M52<>"",M52,L52) | O52: =IFERROR(INDEX(Categories!$B$5:$B$35,MATCH(N52,Categories!$A$5:$A$35,0)),"NA")
A53: 45386 | B53: 2024-S14 | C53: 2024-04 | D53: 2024 | E53: 512000 | F53: BQ | G53: BQ00141 | H53: 401000 | I53: Reglement fournisseur Telecom Pro F008-202403 | J53: Telecom Pro | K53: -576 | L53: Fournisseurs et charges externes | N53: =IF(M53<>"",M53,L53) | O53: =IFERROR(INDEX(Categories!$B$5:$B$35,MATCH(N53,Categories!$A$5:$A$35,0)),"NA")
A54: 45386 | B54: 2024-S14 | C54: 2024-04 | D54: 2024 | E54: 512000 | F54: BQ | G54: BQ00142 | H54: 401000 | I54: Reglement fournisseur Cabinet Comptable Exemple F007-202403 | J54: Cabinet Comptable Exemple | K54: -7200 | L54: Fournisseurs et charges externes | N54: =IF(M54<>"",M54,L54) | O54: =IFERROR(INDEX(Categories!$B$5:$B$35,MATCH(N54,Categories!$A$5:$A$35,0)),"NA")
A55: 45390 | B55: 2024-S15 | C55: 2024-04 | D55: 2024 | E55: 512000 | F55: BQ | G55: BQ00082 | H55: 411000 | I55: Reglement client Coworking Atelier 9 FA2024-0017 | J55: Coworking Atelier 9 | K55: 22939.06 | L55: Clients | N55: =IF(M55<>"",M55,L55) | O55: =IFERROR(INDEX(Categories!$B$5:$B$35,MATCH(N55,Categories!$A$5:$A$35,0)),"NA")
A56: 45392 | B56: 2024-S15 | C56: 2024-04 | D56: 2024 | E56: 512000 | F56: BQ | G56: BQ00011 | H56: 164000 | I56: Echeance emprunt 04/2024 | K56: -2000 | L56: Emprunts - capital | N56: =IF(M56<>"",M56,L56) | O56: =IFERROR(INDEX(Categories!$B$5:$B$35,MATCH(N56,Categories!$A$5:$A$35,0)),"NA")
A57: 45392 | B57: 2024-S15 | C57: 2024-04 | D57: 2024 | E57: 512000 | F57: BQ | G57: BQ00011 | H57: 661100 | I57: Echeance emprunt 04/2024 | K57: -280 | L57: Intérêts et charges financières | N57: =IF(M57<>"",M57,L57) | O57: =IFERROR(INDEX(Categories!$B$5:$B$35,MATCH(N57,Categories!$A$5:$A$35,0)),"NA")
A58: 45392 | B58: 2024-S15 | C58: 2024-04 | D58: 2024 | E58: 512000 | F58: BQ | G58: BQ00131 | H58: 401000 | I58: Reglement fournisseur Quincaillerie Pro Est F002-2024021 | J58: Quincaillerie Pro Est | K58: -39884.94 | L58: Fournisseurs et charges externes | N58: =IF(M58<>"",M58,L58) | O58: =IFERROR(INDEX(Categories!$B$5:$B$35,MATCH(N58,Categories!$A$5:$A$35,0)),"NA")
A59: 45394 | B59: 2024-S15 | C59: 2024-04 | D59: 2024 | E59: 512000 | F59: BQ | G59: BQ00072 | H59: 411000 | I59: Reglement client Restaurant Le Comptoir FA2024-0007 | J59: Restaurant Le Comptoir | K59: 28563.22 | L59: Clients | N59: =IF(M59<>"",M59,L59) | O59: =IFERROR(INDEX(Categories!$B$5:$B$35,MATCH(N59,Categories!$A$5:$A$35,0)),"NA")
A60: 45397 | B60: 2024-S16 | C60: 2024-04 | D60: 2024 | E60: 512000 | F60: BQ | G60: BQ00043 | H60: 431000 | I60: Reglement URSSAF 03/2024 | K60: -33176.38 | L60: Charges sociales | N60: =IF(M60<>"",M60,L60) | O60: =IFERROR(INDEX(Categories!$B$5:$B$35,MATCH(N60,Categories!$A$5:$A$35,0)),"NA")
A61: 45397 | B61: 2024-S16 | C61: 2024-04 | D61: 2024 | E61: 512000 | F61: BQ | G61: BQ00078 | H61: 411000 | I61: Reglement client Clinique du Parc FA2024-0013 | J61: Clinique du Parc | K61: 40933.76 | L61: Clients | N61: =IF(M61<>"",M61,L61) | O61: =IFERROR(INDEX(Categories!$B$5:$B$35,MATCH(N61,Categories!$A$5:$A$35,0)),"NA")
A62: 45401 | B62: 2024-S16 | C62: 2024-04 | D62: 2024 | E62: 512000 | F62: BQ | G62: BQ00079 | H62: 411000 | I62: Reglement client Agence Mobilis FA2024-0014 | J62: Agence Mobilis | K62: 27597.73 | L62: Clients | N62: =IF(M62<>"",M62,L62) | O62: =IFERROR(INDEX(Categories!$B$5:$B$35,MATCH(N62,Categories!$A$5:$A$35,0)),"NA")
A63: 45402 | B63: 2024-S16 | C63: 2024-04 | D63: 2024 | E63: 512000 | F63: BQ | G63: BQ00044 | H63: 445510 | I63: Reglement TVA 03/2024 | K63: -16610.13 | L63: TVA | N63: =IF(M63<>"",M63,L63) | O63: =IFERROR(INDEX(Categories!$B$5:$B$35,MATCH(N63,Categories!$A$5:$A$35,0)),"NA")
A64: 45404 | B64: 2024-S17 | C64: 2024-04 | D64: 2024 | E64: 512000 | F64: BQ | G64: BQ00080 | H64: 411000 | I64: Reglement client Clinique du Parc FA2024-0015 | J64: Clinique du Parc | K64: 30576.84 | L64: Clients | N64: =IF(M64<>"",M64,L64) | O64: =IFERROR(INDEX(Categories!$B$5:$B$35,MATCH(N64,Categories!$A$5:$A$35,0)),"NA")
A65: 45406 | B65: 2024-S17 | C65: 2024-04 | D65: 2024 | E65: 512000 | F65: BQ | G65: BQ00138 | H65: 401000 | I65: Reglement fournisseur Scierie du Nord F001-2024033 | J65: Scierie du Nord | K65: -29353.14 | L65: Fournisseurs et charges externes | N65: =IF(M65<>"",M65,L65) | O65: =IFERROR(INDEX(Categories!$B$5:$B$35,MATCH(N65,Categories!$A$5:$A$35,0)),"NA")
A66: 45407 | B66: 2024-S17 | C66: 2024-04 | D66: 2024 | E66: 512000 | F66: BQ | G66: BQ00083 | H66: 411000 | I66: Reglement client Residence Bel Air FA2024-0018 | J66: Residence Bel Air | K66: 44737.52 | L66: Clients | N66: =IF(M66<>"",M66,L66) | O66: =IFERROR(INDEX(Categories!$B$5:$B$35,MATCH(N66,Categories!$A$5:$A$35,0)),"NA")
A67: 45408 | B67: 2024-S17 | C67: 2024-04 | D67: 2024 | E67: 512000 | F67: BQ | G67: BQ00136 | H67: 401000 | I67: Reglement fournisseur Quincaillerie Pro Est F002-2024031 | J67: Quincaillerie Pro Est | K67: -32094.94 | L67: Fournisseurs et charges externes | N67: =IF(M67<>"",M67,L67) | O67: =IFERROR(INDEX(Categories!$B$5:$B$35,MATCH(N67,Categories!$A$5:$A$35,0)),"NA")
A68: 45411 | B68: 2024-S18 | C68: 2024-04 | D68: 2024 | E68: 512000 | F68: BQ | G68: BQ00081 | H68: 411000 | I68: Reglement client Coworking Atelier 9 FA2024-0016 | J68: Coworking Atelier 9 | K68: 43215.08 | L68: Clients | N68: =IF(M68<>"",M68,L68) | O68: =IFERROR(INDEX(Categories!$B$5:$B$35,MATCH(N68,Categories!$A$5:$A$35,0)),"NA")
A69: 45412 | B69: 2024-S18 | C69: 2024-04 | D69: 2024 | E69: 512000 | F69: BQ | G69: BQ00010 | H69: 421000 | I69: Virement salaires 04/2024 | K69: -41012.04 | L69: Salaires et personnel | N69: =IF(M69<>"",M69,L69) | O69: =IFERROR(INDEX(Categories!$B$5:$B$35,MATCH(N69,Categories!$A$5:$A$35,0)),"NA")
A70: 45412 | B70: 2024-S18 | C70: 2024-04 | D70: 2024 | E70: 512000 | F70: BQ | G70: BQ00012 | H70: 627000 | I70: Frais bancaires 04/2024 | K70: -85 | L70: Frais bancaires | N70: =IF(M70<>"",M70,L70) | O70: =IFERROR(INDEX(Categories!$B$5:$B$35,MATCH(N70,Categories!$A$5:$A$35,0)),"NA")
A71: 45418 | B71: 2024-S19 | C71: 2024-05 | D71: 2024 | E71: 512000 | F71: BQ | G71: BQ00146 | H71: 401000 | I71: Reglement fournisseur SCI Les Halles F004-202404 | J71: SCI Les Halles | K71: -10200 | L71: Fournisseurs et charges externes | N71: =IF(M71<>"",M71,L71) | O71: =IFERROR(INDEX(Categories!$B$5:$B$35,MATCH(N71,Categories!$A$5:$A$35,0)),"NA")
A72: 45418 | B72: 2024-S19 | C72: 2024-05 | D72: 2024 | E72: 512000 | F72: BQ | G72: BQ00147 | H72: 401000 | I72: Reglement fournisseur Energie Plus F005-202404 | J72: Energie Plus | K72: -3753.79 | L72: Fournisseurs et charges externes | N72: =IF(M72<>"",M72,L72) | O72: =IFERROR(INDEX(Categories!$B$5:$B$35,MATCH(N72,Categories!$A$5:$A$35,0)),"NA")
A73: 45418 | B73: 2024-S19 | C73: 2024-05 | D73: 2024 | E73: 512000 | F73: BQ | G73: BQ00148 | H73: 401000 | I73: Reglement fournisseur Telecom Pro F008-202404 | J73: Telecom Pro | K73: -576 | L73: Fournisseurs et charges externes | N73: =IF(M73<>"",M73,L73) | O73: =IFERROR(INDEX(Categories!$B$5:$B$35,MATCH(N73,Categories!$A$5:$A$35,0)),"NA")
A74: 45418 | B74: 2024-S19 | C74: 2024-05 | D74: 2024 | E74: 512000 | F74: BQ | G74: BQ00149 | H74: 401000 | I74: Reglement fournisseur Assurances Mutuelles Exemple F006-202404 | J74: Assurances Mutuelles Exemple | K74: -3000 | L74: Fournisseurs et charges externes | N74: =IF(M74<>"",M74,L74) | O74: =IFERROR(INDEX(Categories!$B$5:$B$35,MATCH(N74,Categories!$A$5:$A$35,0)),"NA")
A75: 45420 | B75: 2024-S19 | C75: 2024-05 | D75: 2024 | E75: 512000 | F75: BQ | G75: BQ00087 | H75: 411000 | I75: Reglement client Clinique du Parc FA2024-0022 | J75: Clinique du Parc | K75: 44742.9 | L75: Clients | N75: =IF(M75<>"",M75,L75) | O75: =IFERROR(INDEX(Categories!$B$5:$B$35,MATCH(N75,Categories!$A$5:$A$35,0)),"NA")
A76: 45422 | B76: 2024-S19 | C76: 2024-05 | D76: 2024 | E76: 512000 | F76: BQ | G76: BQ00014 | H76: 164000 | I76: Echeance emprunt 05/2024 | K76: -2000 | L76: Emprunts - capital | N76: =IF(M76<>"",M76,L76) | O76: =IFERROR(INDEX(Categories!$B$5:$B$35,MATCH(N76,Categories!$A$5:$A$35,0)),"NA")
A77: 45422 | B77: 2024-S19 | C77: 2024-05 | D77: 2024 | E77: 512000 | F77: BQ | G77: BQ00014 | H77: 661100 | I77: Echeance emprunt 05/2024 | K77: -273.33 | L77: Intérêts et charges financières | N77: =IF(M77<>"",M77,L77) | O77: =IFERROR(INDEX(Categories!$B$5:$B$35,MATCH(N77,Categories!$A$5:$A$35,0)),"NA")
A78: 45422 | B78: 2024-S19 | C78: 2024-05 | D78: 2024 | E78: 512000 | F78: BQ | G78: BQ00137 | H78: 401000 | I78: Reglement fournisseur Vernis et Finitions F003-2024032 | J78: Vernis et Finitions | K78: -26751.92 | L78: Fournisseurs et charges externes | N78: =IF(M78<>"",M78,L78) | O78: =IFERROR(INDEX(Categories!$B$5:$B$35,MATCH(N78,Categories!$A$5:$A$35,0)),"NA")
A79: 45427 | B79: 2024-S20 | C79: 2024-05 | D79: 2024 | E79: 512000 | F79: BQ | G79: BQ00045 | H79: 431000 | I79: Reglement URSSAF 04/2024 | K79: -33650.91 | L79: Charges sociales | N79: =IF(M79<>"",M79,L79) | O79: =IFERROR(INDEX(Categories!$B$5:$B$35,MATCH(N79,Categories!$A$5:$A$35,0)),"NA")
A80: 45432 | B80: 2024-S21 | C80: 2024-05 | D80: 2024 | E80: 512000 | F80: BQ | G80: BQ00046 | H80: 445510 | I80: Reglement TVA 04/2024 | K80: -17878.37 | L80: TVA | N80: =IF(M80<>"",M80,L80) | O80: =IFERROR(INDEX(Categories!$B$5:$B$35,MATCH(N80,Categories!$A$5:$A$35,0)),"NA")
A81: 45443 | B81: 2024-S22 | C81: 2024-05 | D81: 2024 | E81: 512000 | F81: BQ | G81: BQ00013 | H81: 421000 | I81: Virement salaires 05/2024 | K81: -40113.35 | L81: Salaires et personnel | N81: =IF(M81<>"",M81,L81) | O81: =IFERROR(INDEX(Categories!$B$5:$B$35,MATCH(N81,Categories!$A$5:$A$35,0)),"NA")
A82: 45443 | B82: 2024-S22 | C82: 2024-05 | D82: 2024 | E82: 512000 | F82: BQ | G82: BQ00015 | H82: 627000 | I82: Frais bancaires 05/2024 | K82: -85 | L82: Frais bancaires | N82: =IF(M82<>"",M82,L82) | O82: =IFERROR(INDEX(Categories!$B$5:$B$35,MATCH(N82,Categories!$A$5:$A$35,0)),"NA")
A83: 45443 | B83: 2024-S22 | C83: 2024-05 | D83: 2024 | E83: 512000 | F83: BQ | G83: BQ00144 | H83: 401000 | I83: Reglement fournisseur Scierie du Nord F001-2024042 | J83: Scierie du Nord | K83: -23539.72 | L83: Fournisseurs et charges externes | N83: =IF(M83<>"",M83,L83) | O83: =IFERROR(INDEX(Categories!$B$5:$B$35,MATCH(N83,Categories!$A$5:$A$35,0)),"NA")
A84: 45446 | B84: 2024-S23 | C84: 2024-06 | D84: 2024 | E84: 512000 | F84: BQ | G84: BQ00085 | H84: 411000 | I84: Reglement client Agence Mobilis FA2024-0020 | J84: Agence Mobilis | K84: 60133.91 | L84: Clients | N84: =IF(M84<>"",M84,L84) | O84: =IFERROR(INDEX(Categories!$B$5:$B$35,MATCH(N84,Categories!$A$5:$A$35,0)),"NA")
A85: 45446 | B85: 2024-S23 | C85: 2024-06 | D85: 2024 | E85: 512000 | F85: BQ | G85: BQ00088 | H85: 411000 | I85: Reglement client Restaurant Le Comptoir FA2024-0023 | J85: Restaurant Le Comptoir | K85: 46078.18 | L85: Clients | N85: =IF(M85<>"",M85,L85) | O85: =IFERROR(INDEX(Categories!$B$5:$B$35,MATCH(N85,Categories!$A$5:$A$35,0)),"NA")
A86: 45446 | B86: 2024-S23 | C86: 2024-06 | D86: 2024 | E86: 512000 | F86: BQ | G86: BQ00145 | H86: 401000 | I86: Reglement fournisseur Scierie du Nord F001-2024043 | J86: Scierie du Nord | K86: -38003.58 | L86: Fournisseurs et charges externes | N86: =IF(M86<>"",M86,L86) | O86: =IFERROR(INDEX(Categories!$B$5:$B$35,MATCH(N86,Categories!$A$5:$A$35,0)),"NA")
A87: 45447 | B87: 2024-S23 | C87: 2024-06 | D87: 2024 | E87: 512000 | F87: BQ | G87: BQ00153 | H87: 401000 | I87: Reglement fournisseur SCI Les Halles F004-202405 | J87: SCI Les Halles | K87: -10200 | L87: Fournisseurs et charges externes | N87: =IF(M87<>"",M87,L87) | O87: =IFERROR(INDEX(Categories!$B$5:$B$35,MATCH(N87,Categories!$A$5:$A$35,0)),"NA")
A88: 45447 | B88: 2024-S23 | C88: 2024-06 | D88: 2024 | E88: 512000 | F88: BQ | G88: BQ00154 | H88: 401000 | I88: Reglement fournisseur Energie Plus F005-202405 | J88: Energie Plus | K88: -3076.03 | L88: Fournisseurs et charges externes | N88: =IF(M88<>"",M88,L88) | O88: =IFERROR(INDEX(Categories!$B$5:$B$35,MATCH(N88,Categories!$A$5:$A$35,0)),"NA")
A89: 45447 | B89: 2024-S23 | C89: 2024-06 | D89: 2024 | E89: 512000 | F89: BQ | G89: BQ00155 | H89: 401000 | I89: Reglement fournisseur Telecom Pro F008-202405 | J89: Telecom Pro | K89: -576 | L89: Fournisseurs et charges externes | N89: =IF(M89<>"",M89,L89) | O89: =IFERROR(INDEX(Categories!$B$5:$B$35,MATCH(N89,Categories!$A$5:$A$35,0)),"NA")
A90: 45449 | B90: 2024-S23 | C90: 2024-06 | D90: 2024 | E90: 512000 | F90: BQ | G90: BQ00143 | H90: 401000 | I90: Reglement fournisseur Quincaillerie Pro Est F002-2024041 | J90: Quincaillerie Pro Est | K90: -26656.7 | L90: Fournisseurs et charges externes | N90: =IF(M90<>"",M90,L90) | O90: =IFERROR(INDEX(Categories!$B$5:$B$35,MATCH(N90,Categories!$A$5:$A$35,0)),"NA")
A91: 45453 | B91: 2024-S24 | C91: 2024-06 | D91: 2024 | E91: 512000 | F91: BQ | G91: BQ00017 | H91: 164000 | I91: Echeance emprunt 06/2024 | K91: -2000 | L91: Emprunts - capital | N91: =IF(M91<>"",M91,L91) | O91: =IFERROR(INDEX(Categories!$B$5:$B$35,MATCH(N91,Categories!$A$5:$A$35,0)),"NA")
A92: 45453 | B92: 2024-S24 | C92: 2024-06 | D92: 2024 | E92: 512000 | F92: BQ | G92: BQ00017 | H92: 661100 | I92: Echeance emprunt 06/2024 | K92: -266.67 | L92: Intérêts et charges financières | N92: =IF(M92<>"",M92,L92) | O92: =IFERROR(INDEX(Categories!$B$5:$B$35,MATCH(N92,Categories!$A$5:$A$35,0)),"NA")
A93: 45453 | B93: 2024-S24 | C93: 2024-06 | D93: 2024 | E93: 512000 | F93: BQ | G93: BQ00084 | H93: 411000 | I93: Reglement client Hotel Les Tilleuls FA2024-0019 | J93: Hotel Les Tilleuls | K93: 50701.08 | L93: Clients | N93: =IF(M93<>"",M93,L93) | O93: =IFERROR(INDEX(Categories!$B$5:$B$35,MATCH(N93,Categories!$A$5:$A$35,0)),"NA")
A94: 45453 | B94: 2024-S24 | C94: 2024-06 | D94: 2024 | E94: 512000 | F94: BQ | G94: BQ00086 | H94: 411000 | I94: Reglement client Restaurant Le Comptoir FA2024-0021 | J94: Restaurant Le Comptoir | K94: 54422.12 | L94: Clients | N94: =IF(M94<>"",M94,L94) | O94: =IFERROR(INDEX(Categories!$B$5:$B$35,MATCH(N94,Categories!$A$5:$A$35,0)),"NA")
A95: 45458 | B95: 2024-S24 | C95: 2024-06 | D95: 2024 | E95: 512000 | F95: BQ | G95: BQ00047 | H95: 431000 | I95: Reglement URSSAF 05/2024 | K95: -32913.52 | L95: Charges sociales | N95: =IF(M95<>"",M95,L95) | O95: =IFERROR(INDEX(Categories!$B$5:$B$35,MATCH(N95,Categories!$A$5:$A$35,0)),"NA")
A96: 45462 | B96: 2024-S25 | C96: 2024-06 | D96: 2024 | E96: 512000 | F96: BQ | G96: BQ00093 | H96: 411000 | I96: Reglement client Residence Bel Air FA2024-0028 | J96: Residence Bel Air | K96: 47923.73 | L96: Clients | N96: =IF(M96<>"",M96,L96) | O96: =IFERROR(INDEX(Categories!$B$5:$B$35,MATCH(N96,Categories!$A$5:$A$35,0)),"NA")
A97: 45463 | B97: 2024-S25 | C97: 2024-06 | D97: 2024 | E97: 512000 | F97: BQ | G97: BQ00048 | H97: 445510 | I97: Reglement TVA 05/2024 | K97: -18958.01 | L97: TVA | N97: =IF(M97<>"",M97,L97) | O97: =IFERROR(INDEX(Categories!$B$5:$B$35,MATCH(N97,Categories!$A$5:$A$35,0)),"NA")
A98: 45463 | B98: 2024-S25 | C98: 2024-06 | D98: 2024 | E98: 512000 | F98: BQ | G98: BQ00090 | H98: 411000 | I98: Reglement client Agence Mobilis FA2024-0025 | J98: Agence Mobilis | K98: 34206.12 | L98: Clients | N98: =IF(M98<>"",M98,L98) | O98: =IFERROR(INDEX(Categories!$B$5:$B$35,MATCH(N98,Categories!$A$5:$A$35,0)),"NA")
A99: 45467 | B99: 2024-S26 | C99: 2024-06 | D99: 2024 | E99: 512000 | F99: BQ | G99: BQ00091 | H99: 411000 | I99: Reglement client Coworking Atelier 9 FA2024-0026 | J99: Coworking Atelier 9 | K99: 23801.88 | L99: Clients | N99: =IF(M99<>"",M99,L99) | O99: =IFERROR(INDEX(Categories!$B$5:$B$35,MATCH(N99,Categories!$A$5:$A$35,0)),"NA")
A100: 45473 | B100: 2024-S26 | C100: 2024-06 | D100: 2024 | E100: 512000 | F100: BQ | G100: BQ00016 | H100: 421000 | I100: Virement salaires 06/2024 | K100: -39926.08 | L100: Salaires et personnel | N100: =IF(M100<>"",M100,L100) | O100: =IFERROR(INDEX(Categories!$B$5:$B$35,MATCH(N100,Categories!$A$5:$A$35,0)),"NA")
...
